src/tests/resources/operation/comb/parity/parity.sv
// Generated by CIRCT firtool-1.71.0
module Foo(	// comb/parity/parity.generic.mlir:3:3
  input  [7:0] a,	// comb/parity/parity.generic.mlir:4:8
  output       res	// comb/parity/parity.mlir:1:31
);

  assign res = ^a;	// comb/parity/parity.generic.mlir:5:10, :6:5
endmodule

src/tests/resources/operation/comb/parity/test.vcd
$version Generated by KCIRCT $end
$timescale 1s $end
 $scope module Foo $end
  $var wire 8 $ a [7:0] $end
  $var wire 1 % res $end
  $scope module Foo $end
   $var wire 8 $ a [7:0] $end
   $var wire 1 % res $end
  $upscope $end
 $upscope $end
$enddefinitions $end

#0
b10011111 $
0%

#1
b10110111 $
0%

#2
b10101001 $
0%

#3
b11010011 $
1%

#4
b00011100 $
1%

#5
b00110010 $
1%

#6
b11111011 $
1%

#7
b11011000 $
0%

#8
b11001110 $
1%

#9
b11001010 $
0%

#10
b11010100 $
0%

#11
b11100011 $
1%

#12
b01001111 $
1%

#13
b11110111 $
1%

#14
b10111101 $
0%

#15
b01010111 $
1%

#16
b11000101 $
0%

#17
b10011111 $
0%

#18
b11001000 $
1%

#19
b11011001 $
1%

#20
b10001001 $
1%

#21
b11010001 $
0%

#22
b11001010 $
0%

#23
b01011010 $
0%

#24
b11100001 $
0%

#25
b11111000 $
1%

#26
b10010011 $
0%

#27
b11110101 $
0%

#28
b10010100 $
1%

#29
b00010000 $
1%

#30
b11111101 $
1%

#31
b10010010 $
1%

#32
b10000001 $
0%

#33
b10001111 $
1%

#34
b10101000 $
1%

#35
b01100101 $
0%

#36
b10011100 $
0%

#37
b11110010 $
1%

#38
b11000111 $
1%

#39
b11001110 $
1%

#40
b00111000 $
1%

#41
b01101011 $
1%

#42
b00001001 $
0%

#43
b00001000 $
1%

#44
b00011011 $
0%

#45
b00101100 $
1%

#46
b01000111 $
0%

#47
b11101101 $
0%

#48
b11101011 $
0%

#49
b10110001 $
0%

#50
b11100000 $
1%

#51
b10100100 $
1%

#52
b10010001 $
1%

#53
b01011101 $
1%

#54
b11101111 $
1%

#55
b11011110 $
0%

#56
b01001011 $
0%

#57
b00111011 $
1%

#58
b00100101 $
1%

#59
b11101101 $
0%

#60
b11101001 $
1%

#61
b01011111 $
0%

#62
b00001000 $
1%

#63
b11001001 $
0%

#64
b00010111 $
0%

#65
b10011010 $
0%

#66
b11110010 $
1%

#67
b11010000 $
1%

#68
b00000100 $
1%

#69
b10000000 $
1%

#70
b00101100 $
1%

#71
b11100011 $
1%

#72
b11111001 $
0%

#73
b01101110 $
1%

#74
b01011011 $
1%

#75
b00011010 $
1%

#76
b00110101 $
0%

#77
b11010010 $
0%

#78
b11110110 $
0%

#79
b00001101 $
1%

#80
b01110001 $
0%

#81
b11000011 $
0%

#82
b10010110 $
0%

#83
b10111110 $
0%

#84
b01000010 $
0%

#85
b10101001 $
0%

#86
b11010011 $
1%

#87
b10010111 $
1%

#88
b11101010 $
1%

#89
b11100000 $
1%

#90
b00111010 $
0%

#91
b10010000 $
0%

#92
b11111101 $
1%

#93
b00000110 $
0%

#94
b10000000 $
1%

#95
b10110000 $
1%

#96
b11110111 $
1%

#97
b10110011 $
1%

#98
b01100100 $
1%

#99
b11001010 $
0%

#100
b00010100 $
0%

#101
b11110001 $
1%

#102
b11111100 $
0%

#103
b01110101 $
1%

#104
b10111010 $
1%

#105
b10001001 $
1%

#106
b11000010 $
1%

#107
b10100001 $
1%

#108
b11000111 $
1%

#109
b10001001 $
1%

#110
b01001000 $
0%

#111
b01010100 $
1%

#112
b10110111 $
0%

#113
b10111011 $
0%

#114
b10100010 $
1%

#115
b00011110 $
0%

#116
b01001100 $
1%

#117
b00101011 $
0%

#118
b11010111 $
0%

#119
b01001010 $
1%

#120
b00010000 $
1%

#121
b00101011 $
0%

#122
b11110010 $
1%

#123
b10110111 $
0%

#124
b11000010 $
1%

#125
b10010010 $
1%

#126
b11001111 $
0%

#127
b10101100 $
0%

#128
b10000000 $
1%

#129
b00111001 $
0%

#130
b10001100 $
1%

#131
b10111101 $
0%

#132
b01100110 $
0%

#133
b11100100 $
0%

#134
b01000011 $
1%

#135
b10110101 $
1%

#136
b01110101 $
1%

#137
b10100101 $
0%

#138
b10010111 $
1%

#139
b11000111 $
1%

#140
b01100000 $
0%

#141
b10010000 $
0%

#142
b00100100 $
0%

#143
b01010111 $
1%

#144
b11110111 $
1%

#145
b01000011 $
1%

#146
b11011010 $
1%

#147
b10100001 $
1%

#148
b00010101 $
1%

#149
b00011100 $
1%

#150
b01110101 $
1%

#151
b10110110 $
1%

#152
b10100011 $
0%

#153
b11010101 $
1%

#154
b10101011 $
1%

#155
b10111000 $
0%

#156
b10011001 $
0%

#157
b11011011 $
0%

#158
b10110001 $
0%

#159
b00100000 $
1%

#160
b10010101 $
0%

#161
b00010010 $
0%

#162
b11100100 $
0%

#163
b10110110 $
1%

#164
b00100001 $
0%

#165
b00001111 $
0%

#166
b00101001 $
1%

#167
b00101011 $
0%

#168
b10110110 $
1%

#169
b01110111 $
0%

#170
b10110011 $
1%

#171
b10100100 $
1%

#172
b11100001 $
0%

#173
b00101010 $
1%

#174
b10110010 $
0%

#175
b00011000 $
0%

#176
b11011111 $
1%

#177
b10100111 $
1%

#178
b10010100 $
1%

#179
b01010011 $
0%

#180
b01100011 $
0%

#181
b11101111 $
1%

#182
b11000001 $
1%

#183
b01110110 $
1%

#184
b10100000 $
0%

#185
b10100000 $
0%

#186
b00100001 $
0%

#187
b11111000 $
1%

#188
b11111000 $
1%

#189
b11110101 $
0%

#190
b11110001 $
1%

#191
b10011011 $
1%

#192
b11001010 $
0%

#193
b10101100 $
0%

#194
b00010100 $
0%

#195
b01110110 $
1%

#196
b10100101 $
0%

#197
b00101001 $
1%

#198
b01010001 $
1%

#199
b11000010 $
1%

#200
b10011100 $
0%

#201
b00010110 $
1%

#202
b00010011 $
1%

#203
b01001011 $
0%

#204
b11001110 $
1%

#205
b00001101 $
1%

#206
b10011110 $
1%

#207
b01111010 $
1%

#208
b00001011 $
1%

#209
b10011101 $
1%

#210
b11101110 $
0%

#211
b10111111 $
1%

#212
b10011010 $
0%

#213
b00000110 $
0%

#214
b00011111 $
1%

#215
b10100100 $
1%

#216
b00001100 $
0%

#217
b11000000 $
0%

#218
b10100100 $
1%

#219
b00001110 $
1%

#220
b10001011 $
0%

#221
b00000111 $
1%

#222
b00110001 $
1%

#223
b01001001 $
1%

#224
b00000011 $
0%

#225
b11011011 $
0%

#226
b01110110 $
1%

#227
b01101100 $
0%

#228
b10111100 $
1%

#229
b10101100 $
0%

#230
b11100100 $
0%

#231
b01000011 $
1%

#232
b11001000 $
1%

#233
b10001010 $
1%

#234
b10100000 $
0%

#235
b00100111 $
0%

#236
b10100000 $
0%

#237
b10100100 $
1%

#238
b11110101 $
0%

#239
b11000011 $
0%

#240
b11000111 $
1%

#241
b00101111 $
1%

#242
b10100001 $
1%

#243
b11011111 $
1%

#244
b10111110 $
0%

#245
b10100110 $
0%

#246
b10101000 $
1%

#247
b10110011 $
1%

#248
b00001111 $
0%

#249
b11100001 $
0%

#250
b10100010 $
1%

#251
b00010100 $
0%

#252
b10000001 $
0%

#253
b11011010 $
1%

#254
b01100000 $
0%

#255
b10101101 $
1%

#256
b11000100 $
1%

#257
b01100001 $
1%

#258
b01011011 $
1%

#259
b00111000 $
1%

#260
b01100010 $
1%

#261
b00010001 $
0%

#262
b11001100 $
0%

#263
b10001000 $
0%

#264
b01100100 $
1%

#265
b11101001 $
1%

#266
b10010011 $
0%

#267
b10000001 $
0%

#268
b11110010 $
1%

#269
b10111011 $
0%

#270
b11100110 $
1%

#271
b10100000 $
0%

#272
b01011011 $
1%

#273
b11111011 $
1%

#274
b10100110 $
0%

#275
b10010000 $
0%

#276
b10100110 $
0%

#277
b00100011 $
1%

#278
b11010011 $
1%

#279
b01010100 $
1%

#280
b11110110 $
0%

#281
b00001101 $
1%

#282
b11101001 $
1%

#283
b10100011 $
0%

#284
b10001110 $
0%

#285
b10001010 $
1%

#286
b01100001 $
1%

#287
b10001011 $
0%

#288
b10011111 $
0%

#289
b00100101 $
1%

#290
b11001010 $
0%

#291
b00110101 $
0%

#292
b11001010 $
0%

#293
b00001001 $
0%

#294
b10110001 $
0%

#295
b01001111 $
1%

#296
b10110101 $
1%

#297
b00111000 $
1%

#298
b11001011 $
1%

#299
b01110010 $
0%

#300
b10011111 $
0%

#301
b00000110 $
0%

#302
b11111100 $
0%

#303
b11111110 $
1%

#304
b01110110 $
1%

#305
b10110010 $
0%

#306
b10110111 $
0%

#307
b10110101 $
1%

#308
b10100110 $
0%

#309
b11011101 $
0%

#310
b10110010 $
0%

#311
b01001001 $
1%

#312
b10000101 $
1%

#313
b10101010 $
0%

#314
b01101000 $
1%

#315
b01000000 $
1%

#316
b10001110 $
0%

#317
b11000011 $
0%

#318
b10010000 $
0%

#319
b11010101 $
1%

#320
b01110101 $
1%

#321
b10100110 $
0%

#322
b11110110 $
0%

#323
b01011111 $
0%

#324
b11001000 $
1%

#325
b11101011 $
0%

#326
b00111100 $
0%

#327
b11111101 $
1%

#328
b11101001 $
1%

#329
b01011011 $
1%

#330
b10010110 $
0%

#331
b00111001 $
0%

#332
b11110111 $
1%

#333
b11111111 $
0%

#334
b00001001 $
0%

#335
b00010110 $
1%

#336
b11110100 $
1%

#337
b01101110 $
1%

#338
b10100001 $
1%

#339
b10011101 $
1%

#340
b10000111 $
0%

#341
b00110111 $
1%

#342
b01000101 $
1%

#343
b10110011 $
1%

#344
b11101111 $
1%

#345
b11010111 $
0%

#346
b10001111 $
1%

#347
b11101110 $
0%

#348
b10001011 $
0%

#349
b01011111 $
0%

#350
b00011111 $
1%

#351
b11111000 $
1%

#352
b10101110 $
1%

#353
b00100111 $
0%

#354
b10101001 $
0%

#355
b11010000 $
1%

#356
b11001010 $
0%

#357
b01100010 $
1%

#358
b10111011 $
0%

#359
b00001011 $
1%

#360
b10001101 $
0%

#361
b11010101 $
1%

#362
b11001100 $
0%

#363
b11010010 $
0%

#364
b11001001 $
0%

#365
b01011000 $
1%

#366
b11000010 $
1%

#367
b01010111 $
1%

#368
b01110100 $
0%

#369
b11100100 $
0%
