src/tests/resources/operation/hw/array_get/array_get.sv
// Generated by CIRCT firtool-1.71.0
module Foo(	// hw/array_get/array_get.generic.mlir:3:3
  input  [7:0] a,	// hw/array_get/array_get.generic.mlir:4:8
               b,	// hw/array_get/array_get.generic.mlir:4:19
  output [7:0] res	// hw/array_get/array_get.mlir:1:42
);

  assign res = b - a;	// hw/array_get/array_get.generic.mlir:10:10, :11:5
endmodule

src/tests/resources/operation/hw/array_get/test.vcd
$version Generated by KCIRCT $end
$timescale 1s $end
 $scope module Foo $end
  $var wire 8 % a [7:0] $end
  $var wire 8 & b [7:0] $end
  $var wire 8 ' res [7:0] $end
  $scope module Foo $end
   $var wire 8 % a [7:0] $end
   $var wire 8 & b [7:0] $end
   $var wire 8 ' res [7:0] $end
  $upscope $end
 $upscope $end
$enddefinitions $end

#0
b00000001 %
b01000101 &
b01000100 '

#1
b01000101 %
b11001011 &
b10000110 '

#2
b01011011 %
b11011001 &
b01111110 '

#3
b11101100 %
b11111101 &
b00010001 '

#4
b10000001 %
b01001001 &
b11001000 '

#5
b00010110 %
b00010100 &
b11111110 '

#6
b00001011 %
b00100011 &
b00011000 '

#7
b00011101 %
b10100011 &
b10000110 '

#8
b01010101 %
b01001111 &
b11111010 '

#9
b00111100 %
b01110111 &
b00111011 '

#10
b00010111 %
b01011000 &
b01000001 '

#11
b10011100 %
b11000000 &
b00100100 '

#12
b10011111 %
b10011110 &
b11111111 '

#13
b01110101 %
b11110101 &
b10000000 '

#14
b10111101 %
b11110010 &
b00110101 '

#15
b10011000 %
b11100100 &
b01001100 '

#16
b00000000 %
b00101010 &
b00101010 '

#17
b00011011 %
b11000010 &
b10100111 '

#18
b11001010 %
b11100111 &
b00011101 '

#19
b00010110 %
b00001000 &
b11110010 '

#20
b11011111 %
b10100001 &
b11000010 '

#21
b10000101 %
b01000000 &
b10111011 '

#22
b01000110 %
b00000011 &
b10111101 '

#23
b01100100 %
b11010110 &
b01110010 '

#24
b01101110 %
b10001010 &
b00011100 '

#25
b10000010 %
b00001010 &
b10001000 '

#26
b01100000 %
b01010110 &
b11110110 '

#27
b01010011 %
b11000110 &
b01110011 '

#28
b11100010 %
b11101011 &
b00001001 '

#29
b11101001 %
b00100000 &
b00110111 '

#30
b10111101 %
b01110001 &
b10110100 '

#31
b10010100 %
b00010110 &
b10000010 '

#32
b10011000 %
b01111101 &
b11100101 '

#33
b01000110 %
b10011001 &
b01010011 '

#34
b00000101 %
b00100100 &
b00011111 '

#35
b01000001 %
b00010100 &
b11010011 '

#36
b11110111 %
b11101000 &
b11110001 '

#37
b01011101 %
b11010001 &
b01110100 '

#38
b01111110 %
b11000011 &
b01000101 '

#39
b10001010 %
b01000100 &
b10111010 '

#40
b11001001 %
b01110101 &
b10101100 '

#41
b01011010 %
b00111110 &
b11100100 '

#42
b00100011 %
b01000010 &
b00011111 '

#43
b00111011 %
b10101000 &
b01101101 '

#44
b01010110 %
b01101010 &
b00010100 '

#45
b00000001 %
b01001010 &
b01001001 '

#46
b11100110 %
b00000001 &
b00011011 '

#47
b00010011 %
b11011000 &
b11000101 '

#48
b10000110 %
b11011111 &
b01011001 '

#49
b10010011 %
b11101011 &
b01011000 '

#50
b00001000 %
b11001010 &
b11000010 '

#51
b11010011 %
b00111101 &
b01101010 '

#52
b01010001 %
b01010100 &
b00000011 '

#53
b00101011 %
b00010010 &
b11100111 '

#54
b01110010 %
b00001000 &
b10010110 '

#55
b10100001 %
b01111111 &
b11011110 '

#56
b00010000 %
b11101110 &
b11011110 '

#57
b10001011 %
b00111111 &
b10110100 '

#58
b10010000 %
b10000000 &
b11110000 '

#59
b00011001 %
b01100101 &
b01001100 '

#60
b01000001 %
b00110010 &
b11110001 '

#61
b01111000 %
b01011101 &
b11100101 '

#62
b10010110 %
b11000001 &
b00101011 '

#63
b01011010 %
b00001110 &
b10110100 '

#64
b00000001 %
b00111101 &
b00111100 '

#65
b01001010 %
b11011110 &
b10010100 '

#66
b00001001 %
b00010110 &
b00001101 '

#67
b10100001 %
b11000011 &
b00100010 '

#68
b00100011 %
b01100100 &
b01000001 '

#69
b10101001 %
b11011011 &
b00110010 '

#70
b01010100 %
b00000000 &
b10101100 '

#71
b01100100 %
b10011010 &
b00110110 '

#72
b01100010 %
b11100111 &
b10000101 '

#73
b11001011 %
b11010010 &
b00000111 '

#74
b10001110 %
b11011010 &
b01001100 '

#75
b11000101 %
b10110101 &
b11110000 '

#76
b11101001 %
b01010111 &
b01101110 '

#77
b10111100 %
b01111101 &
b11000001 '

#78
b01011111 %
b11111101 &
b10011110 '

#79
b11010111 %
b10110110 &
b11011111 '

#80
b00111011 %
b00111011 &
b00000000 '

#81
b10110001 %
b01101000 &
b10110111 '

#82
b01010110 %
b00000011 &
b10101101 '

#83
b00011011 %
b00001000 &
b11101101 '

#84
b00101100 %
b00110110 &
b00001010 '

#85
b10011111 %
b00000101 &
b01100110 '

#86
b01010001 %
b01001011 &
b11111010 '

#87
b10101100 %
b10101001 &
b11111101 '

#88
b10011001 %
b11010100 &
b00111011 '

#89
b01010110 %
b01011101 &
b00000111 '

#90
b11101111 %
b01011000 &
b01101001 '

#91
b00111110 %
b10000010 &
b01000100 '

#92
b11100101 %
b00100110 &
b01000001 '

#93
b00001000 %
b00011110 &
b00010110 '

#94
b00101111 %
b11100010 &
b10110011 '

#95
b00111101 %
b11111100 &
b10111111 '

#96
b00100001 %
b01000010 &
b00100001 '

#97
b00100100 %
b00010010 &
b11101110 '

#98
b10011000 %
b01100010 &
b11001010 '

#99
b10011011 %
b10100010 &
b00000111 '

#100
b10000100 %
b10001101 &
b00001001 '

#101
b11110101 %
b11110010 &
b11111101 '

#102
b10101110 %
b01111000 &
b11001010 '

#103
b11001111 %
b11011110 &
b00001111 '

#104
b11101010 %
b10001101 &
b10100011 '

#105
b01100011 %
b01011010 &
b11110111 '

#106
b01110101 %
b10011011 &
b00100110 '

#107
b00011100 %
b11001111 &
b10110011 '

#108
b11100011 %
b00010001 &
b00101110 '

#109
b10000011 %
b00000011 &
b10000000 '

#110
b00010100 %
b10011000 &
b10000100 '

#111
b00011100 %
b10011101 &
b10000001 '

#112
b01111011 %
b00111001 &
b10111110 '

#113
b11110000 %
b01000010 &
b01010010 '

#114
b01110110 %
b11000001 &
b01001011 '

#115
b10011111 %
b00000000 &
b01100001 '

#116
b00010010 %
b01101111 &
b01011101 '

#117
b01111110 %
b10111100 &
b00111110 '

#118
b00011010 %
b10101000 &
b10001110 '

#119
b11010110 %
b00010011 &
b00111101 '

#120
b00010011 %
b11011011 &
b11001000 '

#121
b01001011 %
b01111010 &
b00101111 '

#122
b10011101 %
b00001011 &
b01101110 '

#123
b00001010 %
b00001001 &
b11111111 '

#124
b10101001 %
b01001110 &
b10100101 '

#125
b10000011 %
b01011100 &
b11011001 '

#126
b00101010 %
b11101101 &
b11000011 '

#127
b01001101 %
b11001010 &
b01111101 '

#128
b10101000 %
b01110011 &
b11001011 '

#129
b00111101 %
b11010101 &
b10011000 '

#130
b10101000 %
b11001101 &
b00100101 '

#131
b10111001 %
b10000010 &
b11001001 '

#132
b11101000 %
b01100001 &
b01111001 '

#133
b01111001 %
b00110011 &
b10111010 '

#134
b01111011 %
b10001000 &
b00001101 '

#135
b01101110 %
b11001110 &
b01100000 '

#136
b10000111 %
b11001011 &
b01000100 '

#137
b11000010 %
b10000110 &
b11000100 '

#138
b01111010 %
b10100101 &
b00101011 '

#139
b10001010 %
b10100101 &
b00011011 '

#140
b11001110 %
b11100111 &
b00011001 '

#141
b00100100 %
b11001100 &
b10101000 '

#142
b01110100 %
b10001010 &
b00010110 '

#143
b11101000 %
b01100110 &
b01111110 '

#144
b11110111 %
b00111000 &
b01000001 '

#145
b01110000 %
b01010010 &
b11100010 '

#146
b01010000 %
b01101100 &
b00011100 '

#147
b01010000 %
b11111001 &
b10101001 '

#148
b11110000 %
b11001001 &
b11011001 '

#149
b10100000 %
b01111111 &
b11011111 '

#150
b10101111 %
b00111010 &
b10001011 '

#151
b00001001 %
b11101110 &
b11100101 '

#152
b01001010 %
b11011011 &
b10010001 '

#153
b00100010 %
b00011010 &
b11111000 '

#154
b10011011 %
b01001011 &
b10110000 '

#155
b01010011 %
b10100111 &
b01010100 '

#156
b00011011 %
b10011111 &
b10000100 '

#157
b11010111 %
b00010010 &
b00111011 '

#158
b11001011 %
b11111000 &
b00101101 '

#159
b11011111 %
b11111111 &
b00100000 '

#160
b00100110 %
b11011100 &
b10110110 '

#161
b01111001 %
b10110100 &
b00111011 '

#162
b01101011 %
b00111010 &
b11001111 '

#163
b10001000 %
b10101010 &
b00100010 '

#164
b10010000 %
b11100010 &
b01010010 '

#165
b00000011 %
b01011011 &
b01011000 '

#166
b00110010 %
b10001011 &
b01011001 '

#167
b01101011 %
b00111011 &
b11010000 '

#168
b10110001 %
b00111011 &
b10001010 '

#169
b11010000 %
b10101010 &
b11011010 '

#170
b11011101 %
b10110000 &
b11010011 '

#171
b01011011 %
b10000000 &
b00100101 '

#172
b10010110 %
b11111101 &
b01100111 '

#173
b01111001 %
b10110110 &
b00111101 '

#174
b11001001 %
b00100010 &
b01011001 '

#175
b11010111 %
b01001111 &
b01111000 '

#176
b01110111 %
b11010010 &
b01011011 '

#177
b10100101 %
b10100110 &
b00000001 '

#178
b10110001 %
b11100111 &
b00110110 '

#179
b10101110 %
b11101000 &
b00111010 '

#180
b01011111 %
b10011101 &
b00111110 '

#181
b10011101 %
b11110011 &
b01010110 '

#182
b10010101 %
b01000101 &
b10110000 '

#183
b01001100 %
b11001000 &
b01111100 '

#184
b11010100 %
b11000101 &
b11110001 '

#185
b10000010 %
b01011101 &
b11011011 '

#186
b11110110 %
b00111011 &
b01000101 '

#187
b10000011 %
b00011001 &
b10010110 '

#188
b00101000 %
b00010101 &
b11101101 '

#189
b11010100 %
b10011011 &
b11000111 '

#190
b10101110 %
b10010110 &
b11101000 '

#191
b00110101 %
b00011111 &
b11101010 '

#192
b01001100 %
b01000100 &
b11111000 '

#193
b10100011 %
b01101110 &
b11001011 '

#194
b00100001 %
b11010100 &
b10110011 '

#195
b10000111 %
b10111001 &
b00110010 '

#196
b01110010 %
b10111111 &
b01001101 '

#197
b10110000 %
b00110000 &
b10000000 '

#198
b10110001 %
b11000111 &
b00010110 '

#199
b01101000 %
b00011100 &
b10110100 '

#200
b10011001 %
b01011001 &
b11000000 '

#201
b11001010 %
b00101110 &
b01100100 '

#202
b00100000 %
b00001111 &
b11101111 '

#203
b00001000 %
b10111000 &
b10110000 '

#204
b10010001 %
b11110101 &
b01100100 '

#205
b00101101 %
b11000100 &
b10010111 '

#206
b01111111 %
b00111001 &
b10111010 '

#207
b11000110 %
b01010001 &
b10001011 '

#208
b00010100 %
b00111111 &
b00101011 '

#209
b11000100 %
b00111101 &
b01111001 '

#210
b00110011 %
b11000010 &
b10001111 '

#211
b10000000 %
b00111010 &
b10111010 '

#212
b10101010 %
b10110011 &
b00001001 '

#213
b11110100 %
b01000111 &
b01010011 '

#214
b11001011 %
b10101000 &
b11011101 '

#215
b00111001 %
b11010101 &
b10011100 '

#216
b00001110 %
b10010110 &
b10001000 '

#217
b10011011 %
b11101101 &
b01010010 '

#218
b00101011 %
b10100000 &
b01110101 '

#219
b01000110 %
b01100101 &
b00011111 '

#220
b11111100 %
b01011100 &
b01100000 '

#221
b11001000 %
b00001101 &
b01000101 '

#222
b00101011 %
b01100101 &
b00111010 '

#223
b10110011 %
b10110011 &
b00000000 '

#224
b01111010 %
b01110010 &
b11111000 '

#225
b11001010 %
b10001011 &
b11000001 '

#226
b00001000 %
b00010001 &
b00001001 '

#227
b11001000 %
b11111011 &
b00110011 '

#228
b00000000 %
b11110000 &
b11110000 '

#229
b01011010 %
b10001010 &
b00110000 '

#230
b01011011 %
b01111110 &
b00100011 '

#231
b01110110 %
b11110111 &
b10000001 '

#232
b00110101 %
b00011111 &
b11101010 '

#233
b00100101 %
b01101010 &
b01000101 '

#234
b01110111 %
b10000001 &
b00001010 '

#235
b00100010 %
b01100100 &
b01000010 '

#236
b11111110 %
b10000010 &
b10000100 '

#237
b11011011 %
b01100001 &
b10000110 '

#238
b11110000 %
b00001011 &
b00011011 '

#239
b10110011 %
b01000110 &
b10010011 '

#240
b01001010 %
b11101111 &
b10100101 '

#241
b01111011 %
b10101011 &
b00110000 '

#242
b11110001 %
b10100100 &
b10110011 '

#243
b00000001 %
b10000100 &
b10000011 '

#244
b01100010 %
b01110011 &
b00010001 '

#245
b10111100 %
b01011101 &
b10100001 '

#246
b00010001 %
b11101001 &
b11011000 '

#247
b00111100 %
b00000100 &
b11001000 '

#248
b01010100 %
b10110111 &
b01100011 '

#249
b01110001 %
b10111111 &
b01001110 '

#250
b11110001 %
b00100111 &
b00110110 '

#251
b01100000 %
b10101011 &
b01001011 '

#252
b01111000 %
b01001011 &
b11010011 '

#253
b00000101 %
b01000111 &
b01000010 '

#254
b11111001 %
b01000100 &
b01001011 '

#255
b01001110 %
b00101010 &
b11011100 '

#256
b10010111 %
b11011001 &
b01000010 '

#257
b10010111 %
b00101101 &
b10010110 '

#258
b10100000 %
b00010001 &
b01110001 '

#259
b10111010 %
b10010111 &
b11011101 '

#260
b00110001 %
b10001110 &
b01011101 '

#261
b00110101 %
b11001000 &
b10010011 '

#262
b01110111 %
b11110001 &
b01111010 '

#263
b11101010 %
b00111111 &
b01010101 '

#264
b00001011 %
b01100110 &
b01011011 '

#265
b01101010 %
b10100010 &
b00111000 '

#266
b11001110 %
b10101100 &
b11011110 '

#267
b00111101 %
b01010100 &
b00010111 '

#268
b00101111 %
b10101000 &
b01111001 '

#269
b10001110 %
b00000010 &
b01110100 '

#270
b10001101 %
b00111001 &
b10101100 '

#271
b01100110 %
b10001010 &
b00100100 '

#272
b10111100 %
b10100101 &
b11101001 '

#273
b01100011 %
b10111101 &
b01011010 '

#274
b11100110 %
b10100000 &
b10111010 '

#275
b10111001 %
b10100000 &
b11100111 '

#276
b01110111 %
b10111011 &
b01000100 '

#277
b11111111 %
b01011000 &
b01011001 '

#278
b01011001 %
b11100011 &
b10001010 '

#279
b01001100 %
b10110100 &
b01101000 '

#280
b01010010 %
b10011110 &
b01001100 '

#281
b01001110 %
b11111001 &
b10101011 '

#282
b10111110 %
b11110000 &
b00110010 '

#283
b01010100 %
b01111011 &
b00100111 '

#284
b01111010 %
b10111111 &
b01000101 '

#285
b11100010 %
b10111101 &
b11011011 '

#286
b10011010 %
b01001010 &
b10110000 '

#287
b01001011 %
b00101000 &
b11011101 '

#288
b00110111 %
b10111110 &
b10000111 '

#289
b10011110 %
b10000111 &
b11101001 '

#290
b01100101 %
b00001011 &
b10100110 '

#291
b11111000 %
b00010111 &
b00011111 '

#292
b01110101 %
b11110010 &
b01111101 '

#293
b00011111 %
b10000100 &
b01100101 '

#294
b00011100 %
b01011001 &
b00111101 '

#295
b00110101 %
b01001100 &
b00010111 '

#296
b10111011 %
b10010010 &
b11010111 '

#297
b10000010 %
b00010111 &
b10010101 '

#298
b11110000 %
b01101011 &
b01111011 '

#299
b11110110 %
b01111001 &
b10000011 '

#300
b00110110 %
b00010011 &
b11011101 '

#301
b11100011 %
b01011010 &
b01110111 '

#302
b00010010 %
b00000111 &
b11110101 '

#303
b00010101 %
b00000111 &
b11110010 '

#304
b01011010 %
b00111011 &
b11100001 '

#305
b10010011 %
b11101111 &
b01011100 '

#306
b11001000 %
b10011110 &
b11010110 '

#307
b00001000 %
b00000011 &
b11111011 '

#308
b11001011 %
b10011011 &
b11010000 '

#309
b01111100 %
b10110001 &
b00110101 '

#310
b01101111 %
b11110000 &
b10000001 '

#311
b01001010 %
b10010001 &
b01000111 '

#312
b00010110 %
b00110011 &
b00011101 '

#313
b01011111 %
b00100111 &
b11001000 '

#314
b01011010 %
b10011111 &
b01000101 '

#315
b11000001 %
b01111110 &
b10111101 '

#316
b00111100 %
b10111100 &
b10000000 '

#317
b00001110 %
b11000100 &
b10110110 '

#318
b01000010 %
b00110011 &
b11110001 '

#319
b11010100 %
b10100111 &
b11010011 '

#320
b01001011 %
b01001101 &
b00000010 '

#321
b01001100 %
b10001100 &
b01000000 '

#322
b01010111 %
b00011010 &
b11000011 '

#323
b10111011 %
b10011110 &
b11100011 '

#324
b01101111 %
b11001010 &
b01011011 '

#325
b11101110 %
b01110001 &
b10000011 '

#326
b00100000 %
b10111011 &
b10011011 '

#327
b00011101 %
b00001101 &
b11110000 '

#328
b00000100 %
b11100100 &
b11100000 '

#329
b11100101 %
b10111101 &
b11011000 '

#330
b11011011 %
b10110110 &
b11011011 '

#331
b01101100 %
b11000111 &
b01011011 '

#332
b10100011 %
b10011000 &
b11110101 '

#333
b10001110 %
b11100011 &
b01010101 '

#334
b00000011 %
b01000000 &
b00111101 '

#335
b01111101 %
b10001100 &
b00001111 '

#336
b11001010 %
b01110111 &
b10101101 '

#337
b10000011 %
b01100000 &
b11011101 '

#338
b10100011 %
b11011000 &
b00110101 '

#339
b10110011 %
b10111100 &
b00001001 '

#340
b01110111 %
b00100001 &
b10101010 '

#341
b10001010 %
b10000101 &
b11111011 '

#342
b11010110 %
b01010110 &
b10000000 '

#343
b00011110 %
b11011110 &
b11000000 '

#344
b10101000 %
b11101101 &
b01000101 '

#345
b00011110 %
b01011100 &
b00111110 '

#346
b01101100 %
b00111101 &
b11010001 '

#347
b01000100 %
b00100111 &
b11100011 '

#348
b11001100 %
b11111111 &
b00110011 '

#349
b11011100 %
b11100000 &
b00000100 '

#350
b01111100 %
b10110010 &
b00110110 '

#351
b10101001 %
b10001111 &
b11100110 '

#352
b00001111 %
b00000100 &
b11110101 '

#353
b10100001 %
b11010111 &
b00110110 '

#354
b11011111 %
b00011111 &
b01000000 '

#355
b01010110 %
b11111111 &
b10101001 '

#356
b00100100 %
b00001110 &
b11101010 '

#357
b01111111 %
b11001110 &
b01001111 '

#358
b11010111 %
b11001110 &
b11110111 '

#359
b00010011 %
b11001011 &
b10111000 '

#360
b00001100 %
b11001001 &
b10111101 '

#361
b11100001 %
b10100000 &
b10111111 '

#362
b01101011 %
b10111001 &
b01001110 '

#363
b10101001 %
b01000000 &
b10010111 '

#364
b10110000 %
b11000000 &
b00010000 '

#365
b01101110 %
b10000100 &
b00010110 '

#366
b01001110 %
b01110001 &
b00100011 '

#367
b11010010 %
b11101010 &
b00011000 '

#368
b11001010 %
b00010000 &
b01000110 '

#369
b00001101 %
b10010000 &
b10000011 '

#370
b10010110 %
b01101110 &
b11011000 '

#371
b01110100 %
b00010101 &
b10100001 '

#372
b01100001 %
b10101010 &
b01001001 '

#373
b10011100 %
b10000110 &
b11101010 '

#374
b11001101 %
b11010001 &
b00000100 '

#375
b11101100 %
b10000110 &
b10011010 '

#376
b00101110 %
b01101101 &
b00111111 '

#377
b01000110 %
b01100001 &
b00011011 '

#378
b01011001 %
b11100000 &
b10000111 '

#379
b01000111 %
b01101011 &
b00100100 '

#380
b10010011 %
b11110000 &
b01011101 '

#381
b11100100 %
b11110100 &
b00010000 '

#382
b10101000 %
b11111101 &
b01010101 '

#383
b00001100 %
b10101001 &
b10011101 '

#384
b01101101 %
b00010001 &
b10100100 '

#385
b10111011 %
b10011101 &
b11100010 '

#386
b11101110 %
b00000010 &
b00010100 '

#387
b11111000 %
b01000010 &
b01001010 '

#388
b10010111 %
b10000111 &
b11110000 '

#389
b01111011 %
b10010110 &
b00011011 '

#390
b10100010 %
b11110101 &
b01010011 '

#391
b01101110 %
b11111111 &
b10010001 '

#392
b11011001 %
b11010010 &
b11111001 '

#393
b00110011 %
b01010011 &
b00100000 '

#394
b11011001 %
b11111011 &
b00100010 '

#395
b11010011 %
b00111101 &
b01101010 '

#396
b01100010 %
b01110101 &
b00010011 '

#397
b11011110 %
b01001000 &
b01101010 '

#398
b01111011 %
b01111000 &
b11111101 '

#399
b00101100 %
b01001111 &
b00100011 '

#400
b01011001 %
b01011100 &
b00000011 '

#401
b01110111 %
b01000001 &
b11001010 '

#402
b10001000 %
b01000111 &
b10111111 '

#403
b11011100 %
b10100010 &
b11000110 '

#404
b01111111 %
b00111111 &
b11000000 '

#405
b01111111 %
b11001100 &
b01001101 '

#406
b00010110 %
b10000010 &
b01101100 '

#407
b00111110 %
b10110001 &
b01110011 '

#408
b01010011 %
b10001001 &
b00110110 '

#409
b11100101 %
b01111110 &
b10011001 '

#410
b11101010 %
b00101101 &
b01000011 '

#411
b11010111 %
b00111100 &
b01100101 '

#412
b10110010 %
b00010101 &
b01100011 '

#413
b10100000 %
b01111110 &
b11011110 '

#414
b00011100 %
b11011011 &
b10111111 '

#415
b00000110 %
b10111111 &
b10111001 '

#416
b00010101 %
b11011100 &
b11000111 '

#417
b01001100 %
b10101110 &
b01100010 '

#418
b01010111 %
b10010101 &
b00111110 '

#419
b00110111 %
b01110110 &
b00111111 '

#420
b00001100 %
b10001010 &
b01111110 '

#421
b01110010 %
b00000010 &
b10010000 '

#422
b11010100 %
b00010110 &
b01000010 '

#423
b01011101 %
b10010100 &
b00110111 '

#424
b01011011 %
b01110001 &
b00010110 '

#425
b00110101 %
b11001110 &
b10011001 '

#426
b01000000 %
b10010011 &
b01010011 '

#427
b11100011 %
b01011100 &
b01111001 '

#428
b10101011 %
b00001100 &
b01100001 '

#429
b00111100 %
b01111100 &
b01000000 '

#430
b11110001 %
b11101011 &
b11111010 '

#431
b10010111 %
b01011000 &
b11000001 '

#432
b01011101 %
b01010101 &
b11111000 '

#433
b01100000 %
b00001110 &
b10101110 '

#434
b00000111 %
b00100110 &
b00011111 '

#435
b01111100 %
b00100001 &
b10100101 '

#436
b00101010 %
b10000011 &
b01011001 '

#437
b01011110 %
b10101011 &
b01001101 '

#438
b10100100 %
b00011100 &
b01111000 '

#439
b00011111 %
b10100011 &
b10000100 '

#440
b11111110 %
b01010011 &
b01010101 '

#441
b10001101 %
b10100011 &
b00010110 '

#442
b10011011 %
b11011010 &
b00111111 '

#443
b10110111 %
b10111011 &
b00000100 '

#444
b00011111 %
b11001100 &
b10101101 '

#445
b00011010 %
b10001000 &
b01101110 '

#446
b11010011 %
b00110001 &
b01011110 '

#447
b11111110 %
b10101110 &
b10110000 '

#448
b10001000 %
b10101001 &
b00100001 '

#449
b00011011 %
b10111001 &
b10011110 '

#450
b00111000 %
b11101001 &
b10110001 '

#451
b10110110 %
b00100010 &
b01101100 '

#452
b00000001 %
b10010001 &
b10010000 '

#453
b10000111 %
b11001000 &
b01000001 '

#454
b10010001 %
b11111010 &
b01101001 '

#455
b00100011 %
b10011110 &
b01111011 '

#456
b00001010 %
b11000010 &
b10111000 '

#457
b01001100 %
b11000000 &
b01110100 '

#458
b10101010 %
b00001110 &
b01100100 '

#459
b01011110 %
b01001001 &
b11101011 '

#460
b11100000 %
b11101100 &
b00001100 '

#461
b01100111 %
b11111010 &
b10010011 '

#462
b10010000 %
b00101010 &
b10011010 '

#463
b01001010 %
b01011101 &
b00010011 '

#464
b11001001 %
b10111100 &
b11110011 '

#465
b01111010 %
b11010100 &
b01011010 '

#466
b11101101 %
b00100000 &
b00110011 '

#467
b11111110 %
b00110111 &
b00111001 '

#468
b10100111 %
b11010101 &
b00101110 '

#469
b00000101 %
b01100001 &
b01011100 '

#470
b01100100 %
b01110010 &
b00001110 '

#471
b00011010 %
b01001110 &
b00110100 '

#472
b10110001 %
b10001011 &
b11011010 '

#473
b01101101 %
b10110000 &
b01000011 '

#474
b01011111 %
b00111101 &
b11011110 '

#475
b11111101 %
b00100011 &
b00100110 '

#476
b00000001 %
b00111110 &
b00111101 '

#477
b01000011 %
b10011101 &
b01011010 '

#478
b01010000 %
b01000001 &
b11110001 '

#479
b01000011 %
b01111110 &
b00111011 '

#480
b10001001 %
b01100110 &
b11011101 '

#481
b01100101 %
b00001101 &
b10101000 '

#482
b00101011 %
b01101111 &
b01000100 '

#483
b11010001 %
b10011001 &
b11001000 '

#484
b00000011 %
b11011001 &
b11010110 '

#485
b00111111 %
b00000000 &
b11000001 '

#486
b01101010 %
b11110010 &
b10001000 '

#487
b00101111 %
b00011001 &
b11101010 '

#488
b11101011 %
b00000100 &
b00011001 '

#489
b10000010 %
b11001111 &
b01001101 '

#490
b00011010 %
b10001000 &
b01101110 '

#491
b11100101 %
b00011011 &
b00110110 '

#492
b01011110 %
b01010110 &
b11111000 '

#493
b00110110 %
b01100001 &
b00101011 '

#494
b11100010 %
b10000101 &
b10100011 '

#495
b11011101 %
b00001101 &
b00110000 '

#496
b01001110 %
b00111111 &
b11110001 '

#497
b01100010 %
b01001111 &
b11101101 '

#498
b01101010 %
b01010100 &
b11101010 '

#499
b10110010 %
b11101110 &
b00111100 '

#500
b10011111 %
b00111001 &
b10011010 '

#501
b01011010 %
b11100101 &
b10001011 '

#502
b11010011 %
b00111001 &
b01100110 '

#503
b01001000 %
b11101011 &
b10100011 '

#504
b11000000 %
b01110010 &
b10110010 '

#505
b10110001 %
b10010111 &
b11100110 '

#506
b11110111 %
b00000010 &
b00001011 '

#507
b10111000 %
b11110010 &
b00111010 '

#508
b10110111 %
b11011011 &
b00100100 '

#509
b10011000 %
b11101011 &
b01010011 '

#510
b00000000 %
b11010111 &
b11010111 '

#511
b00011010 %
b01111100 &
b01100010 '

#512
b11001100 %
b01101110 &
b10100010 '

#513
b11101000 %
b00111000 &
b01010000 '

#514
b01101001 %
b01001011 &
b11100010 '

#515
b01011111 %
b11000010 &
b01100011 '

#516
b00011101 %
b11011001 &
b10111100 '

#517
b11011011 %
b00111011 &
b01100000 '

#518
b11001101 %
b11001101 &
b00000000 '

#519
b10110110 %
b11000100 &
b00001110 '

#520
b10001110 %
b10101001 &
b00011011 '

#521
b01001001 %
b01011001 &
b00010000 '

#522
b11111000 %
b01110101 &
b01111101 '

#523
b10101101 %
b11101010 &
b00111101 '

#524
b01110001 %
b00110101 &
b11000100 '

#525
b10000010 %
b11000101 &
b01000011 '

#526
b01110010 %
b00001111 &
b10011101 '

#527
b10001001 %
b00100010 &
b10011001 '

#528
b10011111 %
b11011101 &
b00111110 '

#529
b01100000 %
b11000101 &
b01100101 '

#530
b01001101 %
b11010011 &
b10000110 '

#531
b10011011 %
b11010111 &
b00111100 '

#532
b00111001 %
b10110101 &
b01111100 '

#533
b00010100 %
b00001011 &
b11110111 '

#534
b10100111 %
b10000100 &
b11011101 '

#535
b01010101 %
b00011001 &
b11000100 '

#536
b01110111 %
b11001101 &
b01010110 '

#537
b11011001 %
b11001001 &
b11110000 '

#538
b10010111 %
b00001011 &
b01110100 '

#539
b00111001 %
b11100001 &
b10101000 '

#540
b00110000 %
b11000011 &
b10010011 '

#541
b01111001 %
b01001000 &
b11001111 '

#542
b01011011 %
b10111111 &
b01100100 '

#543
b01010101 %
b01000110 &
b11110001 '

#544
b00110011 %
b01100110 &
b00110011 '

#545
b11001111 %
b10111100 &
b11101101 '

#546
b11011001 %
b10011111 &
b11000110 '

#547
b10010000 %
b01111000 &
b11101000 '

#548
b10101110 %
b11101000 &
b00111010 '

#549
b11001101 %
b10111010 &
b11101101 '

#550
b01010100 %
b00101011 &
b11010111 '

#551
b11011100 %
b01000111 &
b01101011 '

#552
b00110101 %
b10001100 &
b01010111 '

#553
b00010101 %
b00000101 &
b11110000 '

#554
b11001011 %
b11101010 &
b00011111 '

#555
b11001011 %
b00101101 &
b01100010 '

#556
b00100000 %
b10010111 &
b01110111 '

#557
b00001001 %
b01000000 &
b00110111 '

#558
b10111000 %
b00000110 &
b01001110 '

#559
b11010101 %
b10100101 &
b11010000 '

#560
b01000110 %
b01000100 &
b11111110 '

#561
b00100000 %
b11110010 &
b11010010 '

#562
b01000111 %
b01110010 &
b00101011 '

#563
b00100110 %
b00111000 &
b00010010 '

#564
b00010101 %
b01110011 &
b01011110 '

#565
b00101010 %
b11000110 &
b10011100 '

#566
b10111100 %
b01100001 &
b10100101 '

#567
b00101100 %
b00010100 &
b11101000 '

#568
b00001010 %
b10110000 &
b10100110 '

#569
b01100010 %
b00111101 &
b11011011 '

#570
b10010000 %
b11010011 &
b01000011 '

#571
b11111011 %
b10000101 &
b10001010 '

#572
b01101000 %
b11111010 &
b10010010 '

#573
b11111000 %
b00110100 &
b00111100 '

#574
b00000110 %
b00011011 &
b00010101 '

#575
b01111111 %
b10110001 &
b00110010 '

#576
b10101110 %
b11010000 &
b00100010 '

#577
b10010011 %
b01001011 &
b10111000 '

#578
b01101010 %
b11110011 &
b10001001 '

#579
b11000111 %
b10000110 &
b10111111 '

#580
b11111000 %
b01011001 &
b01100001 '

#581
b10000111 %
b10011101 &
b00010110 '

#582
b00110101 %
b11010101 &
b10100000 '

#583
b01010000 %
b00011011 &
b11001011 '

#584
b00110111 %
b00000111 &
b11010000 '

#585
b01101110 %
b10100101 &
b00110111 '

#586
b10010111 %
b10101101 &
b00010110 '

#587
b00011000 %
b10110111 &
b10011111 '

#588
b10100100 %
b11010011 &
b00101111 '

#589
b10111111 %
b01001010 &
b10001011 '

#590
b00110001 %
b10011100 &
b01101011 '

#591
b01101001 %
b11100011 &
b01111010 '

#592
b00100011 %
b01111010 &
b01010111 '

#593
b11110000 %
b11100001 &
b11110001 '

#594
b00111111 %
b01011101 &
b00011110 '

#595
b00000101 %
b00010011 &
b00001110 '

#596
b00001110 %
b11011010 &
b11001100 '

#597
b10001110 %
b10100110 &
b00011000 '

#598
b01110100 %
b00101011 &
b10110111 '

#599
b10010010 %
b11010110 &
b01000100 '

#600
b00001010 %
b01111000 &
b01101110 '

#601
b00110101 %
b10111011 &
b10000110 '

#602
b10100101 %
b00101000 &
b10000011 '

#603
b00111111 %
b01010011 &
b00010100 '

#604
b11101101 %
b10010111 &
b10101010 '

#605
b00110101 %
b01011000 &
b00100011 '

#606
b00101101 %
b01100111 &
b00111010 '

