src/tests/resources/operation/seq/firmem/firmem.sv
// Generated by CIRCT firtool-1.71.0
// VCS coverage exclude_file
module memory_4x8(	// seq/firmem/firmem.generic.mlir:4:14
  input  [1:0] R0_addr,
  input        R0_en,
               R0_clk,
  output [7:0] R0_data,
  input  [1:0] W0_addr,
  input        W0_en,
               W0_clk,
  input  [7:0] W0_data
);

  reg [7:0] Memory[0:3];	// seq/firmem/firmem.generic.mlir:4:14
  reg       _R0_en_d0;	// seq/firmem/firmem.generic.mlir:4:14
  reg       _R0_en_d1;	// seq/firmem/firmem.generic.mlir:4:14
  reg       _R0_en_d2;	// seq/firmem/firmem.generic.mlir:4:14
  reg [1:0] _R0_addr_d0;	// seq/firmem/firmem.generic.mlir:4:14
  reg [1:0] _R0_addr_d1;	// seq/firmem/firmem.generic.mlir:4:14
  reg [1:0] _R0_addr_d2;	// seq/firmem/firmem.generic.mlir:4:14
  always @(posedge R0_clk) begin	// seq/firmem/firmem.generic.mlir:4:14
    _R0_en_d0 <= R0_en;	// seq/firmem/firmem.generic.mlir:4:14
    _R0_en_d1 <= _R0_en_d0;	// seq/firmem/firmem.generic.mlir:4:14
    _R0_en_d2 <= _R0_en_d1;	// seq/firmem/firmem.generic.mlir:4:14
    _R0_addr_d0 <= R0_addr;	// seq/firmem/firmem.generic.mlir:4:14
    _R0_addr_d1 <= _R0_addr_d0;	// seq/firmem/firmem.generic.mlir:4:14
    _R0_addr_d2 <= _R0_addr_d1;	// seq/firmem/firmem.generic.mlir:4:14
  end // always @(posedge)
  always @(posedge W0_clk) begin	// seq/firmem/firmem.generic.mlir:4:14
    if (W0_en & 1'h1)	// seq/firmem/firmem.generic.mlir:4:14
      Memory[W0_addr] <= W0_data;	// seq/firmem/firmem.generic.mlir:4:14
  end // always @(posedge)
  `ifdef ENABLE_INITIAL_MEM_	// seq/firmem/firmem.generic.mlir:4:14
    `ifdef RANDOMIZE_REG_INIT	// seq/firmem/firmem.generic.mlir:4:14
      reg [31:0] _RANDOM;	// seq/firmem/firmem.generic.mlir:4:14
    `endif // RANDOMIZE_REG_INIT
    reg [31:0] _RANDOM_MEM;	// seq/firmem/firmem.generic.mlir:4:14
    initial begin	// seq/firmem/firmem.generic.mlir:4:14
      `INIT_RANDOM_PROLOG_	// seq/firmem/firmem.generic.mlir:4:14
      `ifdef RANDOMIZE_MEM_INIT	// seq/firmem/firmem.generic.mlir:4:14
        for (logic [2:0] i = 3'h0; i < 3'h4; i += 3'h1) begin
          _RANDOM_MEM = `RANDOM;	// seq/firmem/firmem.generic.mlir:4:14
          Memory[i[1:0]] = _RANDOM_MEM[7:0];	// seq/firmem/firmem.generic.mlir:4:14
        end
      `endif // RANDOMIZE_MEM_INIT
      `ifdef RANDOMIZE_REG_INIT	// seq/firmem/firmem.generic.mlir:4:14
        _RANDOM = {`RANDOM};	// seq/firmem/firmem.generic.mlir:4:14
        _R0_en_d0 = _RANDOM[0];	// seq/firmem/firmem.generic.mlir:4:14
        _R0_en_d1 = _RANDOM[1];	// seq/firmem/firmem.generic.mlir:4:14
        _R0_en_d2 = _RANDOM[2];	// seq/firmem/firmem.generic.mlir:4:14
        _R0_addr_d0 = _RANDOM[4:3];	// seq/firmem/firmem.generic.mlir:4:14
        _R0_addr_d1 = _RANDOM[6:5];	// seq/firmem/firmem.generic.mlir:4:14
        _R0_addr_d2 = _RANDOM[8:7];	// seq/firmem/firmem.generic.mlir:4:14
      `endif // RANDOMIZE_REG_INIT
    end // initial
  `endif // ENABLE_INITIAL_MEM_
  assign R0_data = _R0_en_d2 ? Memory[_R0_addr_d2] : 8'bx;	// seq/firmem/firmem.generic.mlir:4:14
endmodule

// Standard header to adapt well known macros for register randomization.

// RANDOM may be set to an expression that produces a 32-bit random unsigned value.
`ifndef RANDOM
  `define RANDOM $random
`endif // not def RANDOM

// Users can define INIT_RANDOM as general code that gets injected into the
// initializer block for modules with registers.
`ifndef INIT_RANDOM
  `define INIT_RANDOM
`endif // not def INIT_RANDOM

// If using random initialization, you can also define RANDOMIZE_DELAY to
// customize the delay used, otherwise 0.002 is used.
`ifndef RANDOMIZE_DELAY
  `define RANDOMIZE_DELAY 0.002
`endif // not def RANDOMIZE_DELAY

// Define INIT_RANDOM_PROLOG_ for use in our modules below.
`ifndef INIT_RANDOM_PROLOG_
  `ifdef RANDOMIZE
    `ifdef VERILATOR
      `define INIT_RANDOM_PROLOG_ `INIT_RANDOM
    `else  // VERILATOR
      `define INIT_RANDOM_PROLOG_ `INIT_RANDOM #`RANDOMIZE_DELAY begin end
    `endif // VERILATOR
  `else  // RANDOMIZE
    `define INIT_RANDOM_PROLOG_
  `endif // RANDOMIZE
`endif // not def INIT_RANDOM_PROLOG_

// Include rmemory initializers in init blocks unless synthesis is set
`ifndef RANDOMIZE
  `ifdef RANDOMIZE_MEM_INIT
    `define RANDOMIZE
  `endif // RANDOMIZE_MEM_INIT
`endif // not def RANDOMIZE
`ifndef SYNTHESIS
  `ifndef ENABLE_INITIAL_MEM_
    `define ENABLE_INITIAL_MEM_
  `endif // not def ENABLE_INITIAL_MEM_
`endif // not def SYNTHESIS

module Foo(	// seq/firmem/firmem.generic.mlir:2:3
  input        clk,	// seq/firmem/firmem.generic.mlir:3:10
  input  [7:0] data_in_w,	// seq/firmem/firmem.generic.mlir:3:28
               data_in_rw,	// seq/firmem/firmem.generic.mlir:3:44
  input  [1:0] addr_r,	// seq/firmem/firmem.generic.mlir:3:62
               addr_w,	// seq/firmem/firmem.generic.mlir:3:76
               addr_rw,	// seq/firmem/firmem.generic.mlir:3:90
  input        mode,	// seq/firmem/firmem.generic.mlir:3:105
               enable_r,	// seq/firmem/firmem.generic.mlir:3:117
               enable_w,	// seq/firmem/firmem.generic.mlir:3:132
               enable_rw,	// seq/firmem/firmem.generic.mlir:3:148
  output [7:0] read_out
);

  memory_4x8 memory_ext (	// seq/firmem/firmem.generic.mlir:4:14
    .R0_addr (addr_r),
    .R0_en   (enable_r),
    .R0_clk  (clk),
    .R0_data (read_out),
    .W0_addr (addr_w),
    .W0_en   (enable_w),
    .W0_clk  (clk),
    .W0_data (data_in_w)
  );	// seq/firmem/firmem.generic.mlir:4:14
endmodule

src/tests/resources/operation/seq/firmem/trace_vtor.vcd
$version Generated by VerilatedVcd $end
$date Thu Mar 13 14:48:55 2025
 $end
$timescale   1ps $end

 $scope module Foo $end
  $var wire  2 * addr_r [1:0] $end
  $var wire  2 , addr_rw [1:0] $end
  $var wire  2 + addr_w [1:0] $end
  $var wire  1 ' clk $end
  $var wire  8 ) data_in_rw [7:0] $end
  $var wire  8 ( data_in_w [7:0] $end
  $var wire  1 . enable_r $end
  $var wire  1 0 enable_rw $end
  $var wire  1 / enable_w $end
  $var wire  1 - mode $end
  $var wire  8 1 read_out [7:0] $end
  $scope module Foo $end
   $var wire  2 * addr_r [1:0] $end
   $var wire  2 , addr_rw [1:0] $end
   $var wire  2 + addr_w [1:0] $end
   $var wire  1 ' clk $end
   $var wire  8 ) data_in_rw [7:0] $end
   $var wire  8 ( data_in_w [7:0] $end
   $var wire  1 . enable_r $end
   $var wire  1 0 enable_rw $end
   $var wire  1 / enable_w $end
   $var wire  1 - mode $end
   $var wire  8 1 read_out [7:0] $end
   $scope module memory_ext $end
    $var wire  8 # Memory(0) [7:0] $end
    $var wire  8 $ Memory(1) [7:0] $end
    $var wire  8 % Memory(2) [7:0] $end
    $var wire  8 & Memory(3) [7:0] $end
    $var wire  2 * R0_addr [1:0] $end
    $var wire  1 ' R0_clk $end
    $var wire  8 1 R0_data [7:0] $end
    $var wire  1 . R0_en $end
    $var wire  2 + W0_addr [1:0] $end
    $var wire  1 ' W0_clk $end
    $var wire  8 ( W0_data [7:0] $end
    $var wire  1 / W0_en $end
   $upscope $end
  $upscope $end
 $upscope $end
$enddefinitions $end


#0
b00000000 #
b00101101 $
b00000000 %
b00000000 &
1'
b00101101 (
b01000010 )
b00 *
b01 +
b10 ,
1-
0.
1/
10
b00000000 1
#1
0'
b00000000 (
b00000000 )
b00 +
b00 ,
0-
0/
00
#2
1'
b10 *
b11 ,
1.
10
#3
0'
b00 *
b00 ,
0.
00
#4
b01010100 $
1'
b01010100 (
b11111001 )
b01 +
b10 ,
1-
1/
10
#5
0'
b00000000 (
b00000000 )
b00 +
b00 ,
0-
0/
00
#6
1'
b01 ,
1.
10
#7
0'
b00 ,
0.
00
#8
b01001010 $
1'
b01001010 (
b10010011 )
b01 +
b10 ,
1-
1/
10
#9
0'
b00000000 (
b00000000 )
b00 +
b00 ,
0-
0/
00
#10
1'
b01 *
b10 ,
1.
10
b01001010 1
#11
0'
b00 *
b00 ,
0.
00
#12
b11110010 #
1'
b11110010 (
b00110011 )
b01 ,
1-
1/
10
b00000000 1
#13
0'
b00000000 (
b00000000 )
b00 ,
0-
0/
00
#14
1'
b11 *
1.
10
#15
0'
b00 *
0.
00
#16
b01010111 &
1'
b01010111 (
b11001110 )
b11 +
1-
1/
10
#17
0'
b00000000 (
b00000000 )
b00 +
0-
0/
00
#18
1'
b11 *
1.
10
b01010111 1
#19
0'
b00 *
0.
00
#20
b11011000 $
1'
b11011000 (
b11111110 )
b01 +
b10 ,
1-
1/
10
b00000000 1
#21
0'
b00000000 (
b00000000 )
b00 +
b00 ,
0-
0/
00
#22
1'
b01 *
b10 ,
1.
10
b11011000 1
#23
0'
b00 *
b00 ,
0.
00
#24
b11111101 $
1'
b11111101 (
b10011100 )
b01 +
b10 ,
1-
1/
10
b00000000 1
#25
0'
b00000000 (
b00000000 )
b00 +
b00 ,
0-
0/
00
#26
1'
b10 *
b11 ,
1.
10
#27
0'
b00 *
b00 ,
0.
00
#28
b10110101 &
1'
b10110101 (
b10010001 )
b11 +
1-
1/
10
#29
0'
b00000000 (
b00000000 )
b00 +
0-
0/
00
#30
1'
b01 ,
1.
10
b11110010 1
#31
0'
b00 ,
0.
00
#32
b00001101 $
1'
b00001101 (
b01000101 )
b01 +
b10 ,
1-
1/
10
b00000000 1
#33
0'
b00000000 (
b00000000 )
b00 +
b00 ,
0-
0/
00
#34
1'
b01 *
b10 ,
1.
10
b00001101 1
#35
0'
b00 *
b00 ,
0.
00
#36
b00000100 %
1'
b00000100 (
b01101011 )
b10 +
b11 ,
1-
1/
10
b00000000 1
#37
0'
b00000000 (
b00000000 )
b00 +
b00 ,
0-
0/
00
#38
1'
b10 *
b11 ,
1.
10
b00000100 1
#39
0'
b00 *
b00 ,
0.
00
#40
b00001011 #
1'
b00001011 (
b00010111 )
b01 ,
1-
1/
10
b00000000 1
#41
0'
b00000000 (
b00000000 )
b00 ,
0-
0/
00
#42
1'
b01 *
b10 ,
1.
10
b00001101 1
#43
0'
b00 *
b00 ,
0.
00
#44
b11010001 $
1'
b11010001 (
b11001101 )
b01 +
b10 ,
1-
1/
10
b00000000 1
#45
0'
b00000000 (
b00000000 )
b00 +
b00 ,
0-
0/
00
#46
1'
b11 *
1.
10
b10110101 1
#47
0'
b00 *
0.
00
#48
b00100111 #
1'
b00100111 (
b01111101 )
b01 ,
1-
1/
10
b00000000 1
#49
0'
b00000000 (
b00000000 )
b00 ,
0-
0/
00
#50
1'
b10 *
b11 ,
1.
10
b00000100 1
#51
0'
b00 *
b00 ,
0.
00
#52
b10100110 %
1'
b10100110 (
b11101111 )
b10 +
b11 ,
1-
1/
10
b00000000 1
#53
0'
b00000000 (
b00000000 )
b00 +
b00 ,
0-
0/
00
#54
1'
b01 ,
1.
10
b00100111 1
#55
0'
b00 ,
0.
00
#56
b11011110 %
1'
b11011110 (
b10100011 )
b10 +
b11 ,
1-
1/
10
b00000000 1
#57
0'
b00000000 (
b00000000 )
b00 +
b00 ,
0-
0/
00
#58
1'
b11 *
1.
10
b10110101 1
#59
0'
b00 *
0.
00
#60
b01111110 $
1'
b01111110 (
b10110000 )
b01 +
b10 ,
1-
1/
10
b00000000 1
#61
0'
b00000000 (
b00000000 )
b00 +
b00 ,
0-
0/
00
#62
1'
b10 *
b11 ,
1.
10
b11011110 1
#63
0'
b00 *
b00 ,
0.
00
#64
b11100111 #
1'
b11100111 (
b11000000 )
b01 ,
1-
1/
10
b00000000 1
#65
0'
b00000000 (
b00000000 )
b00 ,
0-
0/
00
#66
1'
b11 *
1.
10
b10110101 1
#67
0'
b00 *
0.
00
#68
b10101110 $
1'
b10101110 (
b01100011 )
b01 +
b10 ,
1-
1/
10
b00000000 1
#69
0'
b00000000 (
b00000000 )
b00 +
b00 ,
0-
0/
00
#70
1'
b10 *
b11 ,
1.
10
b11011110 1
#71
0'
b00 *
b00 ,
0.
00
#72
b01000011 $
1'
b01000011 (
b01000110 )
b01 +
b10 ,
1-
1/
10
b00000000 1
#73
0'
b00000000 (
b00000000 )
b00 +
b00 ,
0-
0/
00
#74
1'
b01 ,
1.
10
b11100111 1
#75
0'
b00 ,
0.
00
#76
b00010000 %
1'
b00010000 (
b00011011 )
b10 +
b11 ,
1-
1/
10
b00000000 1
#77
0'
b00000000 (
b00000000 )
b00 +
b00 ,
0-
0/
00
#78
1'
b01 *
b10 ,
1.
10
b01000011 1
#79
0'
b00 *
b00 ,
0.
00
#80
b10010101 %
1'
b10010101 (
b01010110 )
b10 +
b11 ,
1-
1/
10
b00000000 1
#81
0'
b00000000 (
b00000000 )
b00 +
b00 ,
0-
0/
00
#82
1'
b10 *
b11 ,
1.
10
b10010101 1
#83
0'
b00 *
b00 ,
0.
00
#84
b11101010 #
1'
b11101010 (
b11100010 )
b01 ,
1-
1/
10
b00000000 1
#85
0'
b00000000 (
b00000000 )
b00 ,
0-
0/
00
#86
1'
b01 *
b10 ,
1.
10
b01000011 1
#87
0'
b00 *
b00 ,
0.
00
#88
b10111011 $
1'
b10111011 (
b00100000 )
b01 +
b10 ,
1-
1/
10
b00000000 1
#89
0'
b00000000 (
b00000000 )
b00 +
b00 ,
0-
0/
00
#90
1'
b10 *
b11 ,
1.
10
b10010101 1
#91
0'
b00 *
b00 ,
0.
00
#92
b01011011 %
1'
b01011011 (
b11001011 )
b10 +
b11 ,
1-
1/
10
b00000000 1
#93
0'
b00000000 (
b00000000 )
b00 +
b00 ,
0-
0/
00
#94
1'
b11 *
1.
10
b10110101 1
#95
0'
b00 *
0.
00
#96
b11000111 %
1'
b11000111 (
b11011010 )
b10 +
b11 ,
1-
1/
10
b00000000 1
#97
0'
b00000000 (
b00000000 )
b00 +
b00 ,
0-
0/
00
#98
1'
b10 *
b11 ,
1.
10
b11000111 1
#99
0'
b00 *
b00 ,
0.
00
#100
b11000001 %
1'
b11000001 (
b11110111 )
b10 +
b11 ,
1-
1/
10
b00000000 1
#101
0'
b00000000 (
b00000000 )
b00 +
b00 ,
0-
0/
00
#102
1'
b01 ,
1.
10
b11101010 1
#103
0'
b00 ,
0.
00
#104
b10110100 %
1'
b10110100 (
b00001111 )
b10 +
b11 ,
1-
1/
10
b00000000 1
#105
0'
b00000000 (
b00000000 )
b00 +
b00 ,
0-
0/
00
#106
1'
b01 *
b10 ,
1.
10
b10111011 1
#107
0'
b00 *
b00 ,
0.
00
#108
b10000010 #
1'
b10000010 (
b11011100 )
b01 ,
1-
1/
10
b00000000 1
#109
0'
b00000000 (
b00000000 )
b00 ,
0-
0/
00
#110
1'
b01 *
b10 ,
1.
10
b10111011 1
#111
0'
b00 *
b00 ,
0.
00
#112
b01011101 $
1'
b01011101 (
b01111011 )
b01 +
b10 ,
1-
1/
10
b00000000 1
#113
0'
b00000000 (
b00000000 )
b00 +
b00 ,
0-
0/
00
#114
1'
b01 ,
1.
10
b10000010 1
#115
0'
b00 ,
0.
00
#116
b10110111 &
1'
b10110111 (
b01111111 )
b11 +
1-
1/
10
b00000000 1
#117
0'
b00000000 (
b00000000 )
b00 +
0-
0/
00
#118
1'
b11 *
1.
10
b10110111 1
#119
0'
b00 *
0.
00
#120
b10011001 $
1'
b10011001 (
b01111100 )
b01 +
b10 ,
1-
1/
10
b00000000 1
#121
0'
b00000000 (
b00000000 )
b00 +
b00 ,
0-
0/
00
#122
1'
b11 *
1.
10
b10110111 1
#123
0'
b00 *
0.
00
#124
b00101001 %
1'
b00101001 (
b00010000 )
b10 +
b11 ,
1-
1/
10
b00000000 1
#125
0'
b00000000 (
b00000000 )
b00 +
b00 ,
0-
0/
00
#126
1'
b11 *
1.
10
b10110111 1
#127
0'
b00 *
0.
00
#128
b01110110 #
1'
b01110110 (
b00111101 )
b01 ,
1-
1/
10
b00000000 1
#129
0'
b00000000 (
b00000000 )
b00 ,
0-
0/
00
#130
1'
b01 *
b10 ,
1.
10
b10011001 1
#131
0'
b00 *
b00 ,
0.
00
#132
b01000011 %
1'
b01000011 (
b10000010 )
b10 +
b11 ,
1-
1/
10
b00000000 1
#133
0'
b00000000 (
b00000000 )
b00 +
b00 ,
0-
0/
00
#134
1'
b11 *
1.
10
b10110111 1
#135
0'
b00 *
0.
00
#136
b11001011 &
1'
b11001011 (
b10110100 )
b11 +
1-
1/
10
b00000000 1
#137
0'
b00000000 (
b00000000 )
b00 +
0-
0/
00
#138
1'
b01 ,
1.
10
b01110110 1
#139
0'
b00 ,
0.
00
#140
b11001010 %
1'
b11001010 (
b01110001 )
b10 +
b11 ,
1-
1/
10
b00000000 1
#141
0'
b00000000 (
b00000000 )
b00 +
b00 ,
0-
0/
00
#142
1'
b10 *
b11 ,
1.
10
b11001010 1
#143
0'
b00 *
b00 ,
0.
00
#144
b00101101 $
1'
b00101101 (
b10111100 )
b01 +
b10 ,
1-
1/
10
b00000000 1
#145
0'
b00000000 (
b00000000 )
b00 +
b00 ,
0-
0/
00
#146
1'
b10 *
b11 ,
1.
10
b11001010 1
#147
0'
b00 *
b00 ,
0.
00
#148
b11111000 #
1'
b11111000 (
b01111010 )
b01 ,
1-
1/
10
b00000000 1
#149
0'
b00000000 (
b00000000 )
b00 ,
0-
0/
00
#150
1'
b01 *
b10 ,
1.
10
b00101101 1
#151
0'
b00 *
b00 ,
0.
00
#152
b01011110 #
1'
b01011110 (
b11011001 )
b01 ,
1-
1/
10
b00000000 1
#153
0'
b00000000 (
b00000000 )
b00 ,
0-
0/
00
#154
1'
b01 ,
1.
10
b01011110 1
#155
0'
b00 ,
0.
00
#156
b11000111 #
1'
b11000111 (
b11100010 )
b01 ,
1-
1/
10
b00000000 1
#157
0'
b00000000 (
b00000000 )
b00 ,
0-
0/
00
#158
1'
b10 *
b11 ,
1.
10
b11001010 1
#159
0'
b00 *
b00 ,
0.
00
#160
b10011000 %
1'
b10011000 (
b01010000 )
b10 +
b11 ,
1-
1/
10
b00000000 1
#161
0'
b00000000 (
b00000000 )
b00 +
b00 ,
0-
0/
00
#162
1'
b11 *
1.
10
b11001011 1
#163
0'
b00 *
0.
00
#164
b10111100 &
1'
b10111100 (
b01111100 )
b11 +
1-
1/
10
b00000000 1
#165
0'
b00000000 (
b00000000 )
b00 +
0-
0/
00
#166
1'
b01 ,
1.
10
b11000111 1
#167
0'
b00 ,
0.
00
#168
b11111010 %
1'
b11111010 (
b00111111 )
b10 +
b11 ,
1-
1/
10
b00000000 1
#169
0'
b00000000 (
b00000000 )
b00 +
b00 ,
0-
0/
00
#170
1'
b11 *
1.
10
b10111100 1
#171
0'
b00 *
0.
00
#172
b01110100 &
1'
b01110100 (
b10111100 )
b11 +
1-
1/
10
b00000000 1
#173
0'
b00000000 (
b00000000 )
b00 +
0-
0/
00
#174
1'
b01 ,
1.
10
b11000111 1
#175
0'
b00 ,
0.
00
#176
b00100111 &
1'
b00100111 (
b10011111 )
b11 +
1-
1/
10
b00000000 1
#177
0'
b00000000 (
b00000000 )
b00 +
0-
0/
00
#178
1'
b11 *
1.
10
b00100111 1
#179
0'
b00 *
0.
00
#180
b11101101 &
1'
b11101101 (
b01010010 )
b11 +
1-
1/
10
b00000000 1
#181
0'
b00000000 (
b00000000 )
b00 +
0-
0/
00
#182
1'
b10 *
b11 ,
1.
10
b11111010 1
#183
0'
b00 *
b00 ,
0.
00
#184
b00011100 #
1'
b00011100 (
b10011001 )
b01 ,
1-
1/
10
b00000000 1
#185
0'
b00000000 (
b00000000 )
b00 ,
0-
0/
00
#186
1'
b01 *
b10 ,
1.
10
b00101101 1
#187
0'
b00 *
b00 ,
0.
00
#188
b11011110 %
1'
b11011110 (
b01000101 )
b10 +
b11 ,
1-
1/
10
b00000000 1
#189
0'
b00000000 (
b00000000 )
b00 +
b00 ,
0-
0/
00
#190
1'
b10 *
b11 ,
1.
10
b11011110 1
#191
0'
b00 *
b00 ,
0.
00
#192
b01100001 $
1'
b01100001 (
b11001001 )
b01 +
b10 ,
1-
1/
10
b00000000 1
#193
0'
b00000000 (
b00000000 )
b00 +
b00 ,
0-
0/
00
#194
1'
b11 *
1.
10
b11101101 1
#195
0'
b00 *
0.
00
#196
b00100111 %
1'
b00100111 (
b01101111 )
b10 +
b11 ,
1-
1/
10
b00000000 1
#197
0'
b00000000 (
b00000000 )
b00 +
b00 ,
0-
0/
00
#198
1'
b11 *
1.
10
b11101101 1
#199
0'
b00 *
0.
00
#200
b00100111 #
1'
b00100111 (
b01001010 )
b01 ,
1-
1/
10
b00000000 1
#201
0'
b00000000 (
b00000000 )
b00 ,
0-
0/
00
#202
1'
b01 ,
1.
10
b00100111 1
#203
0'
b00 ,
0.
00
#204
b00101111 #
1'
b00101111 (
b01110011 )
b01 ,
1-
1/
10
b00000000 1
#205
0'
b00000000 (
b00000000 )
b00 ,
0-
0/
00
#206
1'
b10 *
b11 ,
1.
10
b00100111 1
#207
0'
b00 *
b00 ,
0.
00
#208
b11000010 #
1'
b11000010 (
b10010100 )
b01 ,
1-
1/
10
b00000000 1
#209
0'
b00000000 (
b00000000 )
b00 ,
0-
0/
00
#210
1'
b01 *
b10 ,
1.
10
b01100001 1
#211
0'
b00 *
b00 ,
0.
00
#212
b00100111 #
1'
b00100111 (
b00110011 )
b01 ,
1-
1/
10
b00000000 1
#213
0'
b00000000 (
b00000000 )
b00 ,
0-
0/
00
#214
1'
b01 ,
1.
10
b00100111 1
#215
0'
b00 ,
0.
00
#216
b01000011 $
1'
b01000011 (
b01010000 )
b01 +
b10 ,
1-
1/
10
b00000000 1
#217
0'
b00000000 (
b00000000 )
b00 +
b00 ,
0-
0/
00
#218
1'
b11 *
1.
10
b11101101 1
#219
0'
b00 *
0.
00
#220
b01110110 $
1'
b01110110 (
b11110110 )
b01 +
b10 ,
1-
1/
10
b00000000 1
#221
0'
b00000000 (
b00000000 )
b00 +
b00 ,
0-
0/
00
#222
1'
b10 *
b11 ,
1.
10
b00100111 1
#223
0'
b00 *
b00 ,
0.
00
#224
b11101100 &
1'
b11101100 (
b01110100 )
b11 +
1-
1/
10
b00000000 1
#225
0'
b00000000 (
b00000000 )
b00 +
0-
0/
00
#226
1'
b01 *
b10 ,
1.
10
b01110110 1
#227
0'
b00 *
b00 ,
0.
00
#228
b00110100 &
1'
b00110100 (
b11000111 )
b11 +
1-
1/
10
b00000000 1
#229
0'
b00000000 (
b00000000 )
b00 +
0-
0/
00
#230
1'
b10 *
b11 ,
1.
10
b00100111 1
#231
0'
b00 *
b00 ,
0.
00
#232
b00110001 %
1'
b00110001 (
b00110011 )
b10 +
b11 ,
1-
1/
10
b00000000 1
#233
0'
b00000000 (
b00000000 )
b00 +
b00 ,
0-
0/
00
#234
1'
b10 *
b11 ,
1.
10
b00110001 1
#235
0'
b00 *
b00 ,
0.
00
#236
b01010110 &
1'
b01010110 (
b10010001 )
b11 +
1-
1/
10
b00000000 1
#237
0'
b00000000 (
b00000000 )
b00 +
0-
0/
00
#238
1'
b10 *
b11 ,
1.
10
b00110001 1
#239
0'
b00 *
b00 ,
0.
00
#240
b01001101 $
1'
b01001101 (
b01011100 )
b01 +
b10 ,
1-
1/
10
b00000000 1
#241
0'
b00000000 (
b00000000 )
b00 +
b00 ,
0-
0/
00
#242
1'
b01 *
b10 ,
1.
10
b01001101 1
#243
0'
b00 *
b00 ,
0.
00
#244
b10011011 %
1'
b10011011 (
b00010100 )
b10 +
b11 ,
1-
1/
10
b00000000 1
#245
0'
b00000000 (
b00000000 )
b00 +
b00 ,
0-
0/
00
#246
1'
b01 *
b10 ,
1.
10
b01001101 1
#247
0'
b00 *
b00 ,
0.
00
#248
b01111100 %
1'
b01111100 (
b00001000 )
b10 +
b11 ,
1-
1/
10
b00000000 1
#249
0'
b00000000 (
b00000000 )
b00 +
b00 ,
0-
0/
00
#250
1'
b01 ,
1.
10
b00100111 1
#251
0'
b00 ,
0.
00
#252
1'
b01010110 (
b01001100 )
b11 +
1-
1/
10
b00000000 1
#253
0'
b00000000 (
b00000000 )
b00 +
0-
0/
00
#254
1'
b01 ,
1.
10
b00100111 1
#255
0'
b00 ,
0.
00
#256
b10011011 #
1'
b10011011 (
b11110001 )
b01 ,
1-
1/
10
b00000000 1
#257
0'
b00000000 (
b00000000 )
b00 ,
0-
0/
00
#258
1'
b01 *
b10 ,
1.
10
b01001101 1
#259
0'
b00 *
b00 ,
0.
00
#260
b01011101 %
1'
b01011101 (
b01111001 )
b10 +
b11 ,
1-
1/
10
b00000000 1
#261
0'
b00000000 (
b00000000 )
b00 +
b00 ,
0-
0/
00
#262
1'
b01 ,
1.
10
b10011011 1
#263
0'
b00 ,
0.
00
#264
b10111010 $
1'
b10111010 (
b11100101 )
b01 +
b10 ,
1-
1/
10
b00000000 1
#265
0'
b00000000 (
b00000000 )
b00 +
b00 ,
0-
0/
00
#266
1'
b01 ,
1.
10
b10011011 1
#267
0'
b00 ,
0.
00
#268
b11010000 #
1'
b11010000 (
b11100011 )
b01 ,
1-
1/
10
b00000000 1
#269
0'
b00000000 (
b00000000 )
b00 ,
0-
0/
00
#270
1'
b01 ,
1.
10
b11010000 1
#271
0'
b00 ,
0.
00
#272
b11001110 $
1'
b11001110 (
b01010011 )
b01 +
b10 ,
1-
1/
10
b00000000 1
#273
0'
b00000000 (
b00000000 )
b00 +
b00 ,
0-
0/
00
#274
1'
b11 *
1.
10
b01010110 1
#275
0'
b00 *
0.
00
#276
b00010011 #
1'
b00010011 (
b11101010 )
b01 ,
1-
1/
10
b00000000 1
#277
0'
b00000000 (
b00000000 )
b00 ,
0-
0/
00
#278
1'
b01 ,
1.
10
b00010011 1
#279
0'
b00 ,
0.
00
#280
b11110111 &
1'
b11110111 (
b11101010 )
b11 +
1-
1/
10
b00000000 1
#281
0'
b00000000 (
b00000000 )
b00 +
0-
0/
00
#282
1'
b01 *
b10 ,
1.
10
b11001110 1
#283
0'
b00 *
b00 ,
0.
00
#284
b00011001 $
1'
b00011001 (
b11101111 )
b01 +
b10 ,
1-
1/
10
b00000000 1
#285
0'
b00000000 (
b00000000 )
b00 +
b00 ,
0-
0/
00
#286
1'
b01 *
b10 ,
1.
10
b00011001 1
#287
0'
b00 *
b00 ,
0.
00
#288
b00100101 %
1'
b00100101 (
b11001111 )
b10 +
b11 ,
1-
1/
10
b00000000 1
#289
0'
b00000000 (
b00000000 )
b00 +
b00 ,
0-
0/
00
#290
1'
b10 *
b11 ,
1.
10
b00100101 1
#291
0'
b00 *
b00 ,
0.
00
#292
b10101011 $
1'
b10101011 (
b00111100 )
b01 +
b10 ,
1-
1/
10
b00000000 1
#293
0'
b00000000 (
b00000000 )
b00 +
b00 ,
0-
0/
00
#294
1'
b01 *
b10 ,
1.
10
b10101011 1
#295
0'
b00 *
b00 ,
0.
00
#296
b11101111 &
1'
b11101111 (
b11001011 )
b11 +
1-
1/
10
b00000000 1
#297
0'
b00000000 (
b00000000 )
b00 +
0-
0/
00
#298
1'
b01 *
b10 ,
1.
10
b10101011 1
#299
0'
b00 *
b00 ,
0.
00
#300
b00110000 #
1'
b00110000 (
b00001101 )
b01 ,
1-
1/
10
b00000000 1
#301
0'
b00000000 (
b00000000 )
b00 ,
0-
0/
00
#302
1'
b01 *
b10 ,
1.
10
b10101011 1
#303
0'
b00 *
b00 ,
0.
00
#304
b11010010 %
1'
b11010010 (
b10110001 )
b10 +
b11 ,
1-
1/
10
b00000000 1
#305
0'
b00000000 (
b00000000 )
b00 +
b00 ,
0-
0/
00
#306
1'
b01 ,
1.
10
b00110000 1
#307
0'
b00 ,
0.
00
#308
b10111000 %
1'
b10111000 (
b11110100 )
b10 +
b11 ,
1-
1/
10
b00000000 1
#309
0'
b00000000 (
b00000000 )
b00 +
b00 ,
0-
0/
00
#310
1'
b01 ,
1.
10
b00110000 1
#311
0'
b00 ,
0.
00
#312
b10001001 &
1'
b10001001 (
b00010001 )
b11 +
1-
1/
10
b00000000 1
#313
0'
b00000000 (
b00000000 )
b00 +
0-
0/
00
#314
1'
b11 *
1.
10
b10001001 1
#315
0'
b00 *
0.
00
#316
b10110000 #
1'
b10110000 (
b00001110 )
b01 ,
1-
1/
10
b00000000 1
#317
0'
b00000000 (
b00000000 )
b00 ,
0-
0/
00
#318
1'
b10 *
b11 ,
1.
10
b10111000 1
#319
0'
b00 *
b00 ,
0.
00
#320
b01101011 #
1'
b01101011 (
b11101111 )
b01 ,
1-
1/
10
b00000000 1
#321
0'
b00000000 (
b00000000 )
b00 ,
0-
0/
00
#322
1'
b01 ,
1.
10
b01101011 1
#323
0'
b00 ,
0.
00
#324
b11110000 %
1'
b11110000 (
b11111101 )
b10 +
b11 ,
1-
1/
10
b00000000 1
#325
0'
b00000000 (
b00000000 )
b00 +
b00 ,
0-
0/
00
#326
1'
b01 ,
1.
10
b01101011 1
#327
0'
b00 ,
0.
00
#328
b10001001 %
1'
b10001001 (
b10001000 )
b10 +
b11 ,
1-
1/
10
b00000000 1
#329
0'
b00000000 (
b00000000 )
b00 +
b00 ,
0-
0/
00
#330
1'
b01 *
b10 ,
1.
10
b10101011 1
#331
0'
b00 *
b00 ,
0.
00
