src/tests/resources/operation/hw/module/module.sv
// Generated by CIRCT firtool-1.71.0
module Foo(	// hw/module/module.generic.mlir:3:3
  input  [7:0] a,	// hw/module/module.generic.mlir:4:8
               b,	// hw/module/module.generic.mlir:4:19
  output [7:0] res	// hw/module/module.mlir:1:42
);

  assign res = a + b;	// hw/module/module.generic.mlir:5:10, :6:5
endmodule

src/tests/resources/operation/hw/module/test.vcd
$version Generated by KCIRCT $end
$timescale 1s $end
 $scope module Foo $end
  $var wire 8 % a [7:0] $end
  $var wire 8 & b [7:0] $end
  $var wire 8 ' res [7:0] $end
  $scope module Foo $end
   $var wire 8 % a [7:0] $end
   $var wire 8 & b [7:0] $end
   $var wire 8 ' res [7:0] $end
  $upscope $end
 $upscope $end
$enddefinitions $end

#0
b01101111 %
b10101111 &
b00011110 '

#1
b00001001 %
b01010000 &
b01011001 '

#2
b00011000 %
b10001010 &
b10100010 '

#3
b00110110 %
b00111100 &
b01110010 '

#4
b00010001 %
b00100000 &
b00110001 '

#5
b11111011 %
b01101011 &
b01100110 '

#6
b01100110 %
b00010101 &
b01111011 '

#7
b10110100 %
b01110000 &
b00100100 '

#8
b10010111 %
b11001000 &
b01011111 '

#9
b11001010 %
b11100001 &
b10101011 '

#10
b11101010 %
b10001010 &
b01110100 '

#11
b11000011 %
b10101110 &
b01110001 '

#12
b10000011 %
b00101001 &
b10101100 '

#13
b00100101 %
b10000000 &
b10100101 '

#14
b11010111 %
b11010011 &
b10101010 '

#15
b01011010 %
b00010100 &
b01101110 '

#16
b10000110 %
b01110000 &
b11110110 '

#17
b01000111 %
b10001000 &
b11001111 '

#18
b00001000 %
b01011101 &
b01100101 '

#19
b00001101 %
b11001100 &
b11011001 '

#20
b10001010 %
b11100111 &
b01110001 '

#21
b11011110 %
b10100110 &
b10000100 '

#22
b01000000 %
b10100101 &
b11100101 '

#23
b00110110 %
b11100110 &
b00011100 '

#24
b10010111 %
b01010111 &
b11101110 '

#25
b00110001 %
b01101010 &
b10011011 '

#26
b11101011 %
b00011000 &
b00000011 '

#27
b00111111 %
b00001111 &
b01001110 '

#28
b00000100 %
b11110111 &
b11111011 '

#29
b11011000 %
b10011100 &
b01110100 '

#30
b00110011 %
b10100110 &
b11011001 '

#31
b01110010 %
b10101111 &
b00100001 '

#32
b11010010 %
b01000100 &
b00010110 '

#33
b00101111 %
b11010101 &
b00000100 '

#34
b01010010 %
b10100011 &
b11110101 '

#35
b11101110 %
b11011011 &
b11001001 '

#36
b10001011 %
b10110000 &
b00111011 '

#37
b00111101 %
b10110101 &
b11110010 '

#38
b11111111 %
b00010101 &
b00010100 '

#39
b10100001 %
b10100001 &
b01000010 '

#40
b10001111 %
b11101100 &
b01111011 '

#41
b01110010 %
b11000101 &
b00110111 '

#42
b00111100 %
b00110011 &
b01101111 '

#43
b11000101 %
b01111110 &
b01000011 '

#44
b10100011 %
b01110111 &
b00011010 '

#45
b11111001 %
b10010001 &
b10001010 '

#46
b11001100 %
b01011010 &
b00100110 '

#47
b10110011 %
b01111101 &
b00110000 '

#48
b11011001 %
b11001110 &
b10100111 '

#49
b01010111 %
b11110110 &
b01001101 '

#50
b00101011 %
b10011101 &
b11001000 '

#51
b10110001 %
b00100111 &
b11011000 '

#52
b01100101 %
b01010011 &
b10111000 '

#53
b00101110 %
b01101001 &
b10010111 '

#54
b01110011 %
b11010101 &
b01001000 '

#55
b11011011 %
b00111101 &
b00011000 '

#56
b10110000 %
b10000001 &
b00110001 '

#57
b11101100 %
b00000010 &
b11101110 '

#58
b11011000 %
b10110111 &
b10001111 '

#59
b01111111 %
b01000110 &
b11000101 '

#60
b01010001 %
b11000101 &
b00010110 '

#61
b00011000 %
b10100101 &
b10111101 '

#62
b10000101 %
b00110101 &
b10111010 '

#63
b01010110 %
b01000101 &
b10011011 '

#64
b10111000 %
b01111000 &
b00110000 '

#65
b00111011 %
b01101010 &
b10100101 '

#66
b01100001 %
b11111011 &
b01011100 '

#67
b11000011 %
b00000010 &
b11000101 '

#68
b01001011 %
b11001110 &
b00011001 '

#69
b10100101 %
b11010111 &
b01111100 '

#70
b01001100 %
b11011011 &
b00100111 '

#71
b11110001 %
b01010110 &
b01000111 '

#72
b00110111 %
b10111100 &
b11110011 '

#73
b10100111 %
b11100100 &
b10001011 '

#74
b10011001 %
b00111110 &
b11010111 '

#75
b11110010 %
b11011111 &
b11010001 '

#76
b00010101 %
b00001111 &
b00100100 '

#77
b00101000 %
b01101000 &
b10010000 '

#78
b00100111 %
b11111000 &
b00011111 '

#79
b10001010 %
b11111110 &
b10001000 '

#80
b01101101 %
b10110001 &
b00011110 '

#81
b10100101 %
b00110010 &
b11010111 '

#82
b11110001 %
b00000100 &
b11110101 '

#83
b11000000 %
b10011110 &
b01011110 '

#84
b01111111 %
b10100010 &
b00100001 '

#85
b00111110 %
b00000101 &
b01000011 '

#86
b00110110 %
b11101000 &
b00011110 '

#87
b11010001 %
b01011011 &
b00101100 '

#88
b11111110 %
b00001011 &
b00001001 '

#89
b00111011 %
b11100101 &
b00100000 '

#90
b01100001 %
b01100001 &
b11000010 '

#91
b00011000 %
b00100001 &
b00111001 '

#92
b11111111 %
b10111000 &
b10110111 '

#93
b01101100 %
b00001010 &
b01110110 '

#94
b10011110 %
b11100010 &
b10000000 '

#95
b11100111 %
b01010110 &
b00111101 '

#96
b00111100 %
b01000011 &
b01111111 '

#97
b00100000 %
b10101101 &
b11001101 '

#98
b01001011 %
b00001110 &
b01011001 '

#99
b11100000 %
b01100110 &
b01000110 '

#100
b01101101 %
b11000001 &
b00101110 '

#101
b10110010 %
b01001001 &
b11111011 '

#102
b10011100 %
b10010100 &
b00110000 '

#103
b00100000 %
b11100001 &
b00000001 '

#104
b10100010 %
b00111110 &
b11100000 '

#105
b11011011 %
b11010001 &
b10101100 '

#106
b01111010 %
b11010101 &
b01001111 '

#107
b11101100 %
b10110101 &
b10100001 '

#108
b11110001 %
b11100011 &
b11010100 '

#109
b01110100 %
b11111000 &
b01101100 '

#110
b11010111 %
b10100011 &
b01111010 '

#111
b10010010 %
b11011001 &
b01101011 '

#112
b10010010 %
b00111000 &
b11001010 '

#113
b00101010 %
b10011100 &
b11000110 '

#114
b10001101 %
b11101001 &
b01110110 '

#115
b00101111 %
b00110100 &
b01100011 '

#116
b10001111 %
b11101010 &
b01111001 '

#117
b11000001 %
b01100000 &
b00100001 '

#118
b00100001 %
b00100000 &
b01000001 '

#119
b11000110 %
b10001010 &
b01010000 '

#120
b11010000 %
b01100000 &
b00110000 '

#121
b11100000 %
b01111100 &
b01011100 '

#122
b11100110 %
b00110110 &
b00011100 '

#123
b00100101 %
b10000110 &
b10101011 '

#124
b00010000 %
b11111010 &
b00001010 '

#125
b00001101 %
b00001111 &
b00011100 '

#126
b11101011 %
b01111110 &
b01101001 '

#127
b10001101 %
b01010010 &
b11011111 '

#128
b00100100 %
b10001011 &
b10101111 '

#129
b01101101 %
b10000011 &
b11110000 '

#130
b00000010 %
b11011001 &
b11011011 '

#131
b11111011 %
b01101100 &
b01100111 '

#132
b00000110 %
b11111001 &
b11111111 '

#133
b10001111 %
b11110001 &
b10000000 '

#134
b10111000 %
b00101011 &
b11100011 '

#135
b10010001 %
b01000110 &
b11010111 '

#136
b01001111 %
b10010110 &
b11100101 '

#137
b01001100 %
b11010110 &
b00100010 '

#138
b00011111 %
b10100001 &
b11000000 '

#139
b10001001 %
b01010111 &
b11100000 '

#140
b00010010 %
b00001011 &
b00011101 '

#141
b11011010 %
b10011001 &
b01110011 '

#142
b10011101 %
b10110010 &
b01001111 '

#143
b01110111 %
b00011100 &
b10010011 '

#144
b01010010 %
b01101000 &
b10111010 '

#145
b10101011 %
b10101000 &
b01010011 '

#146
b10011101 %
b01011000 &
b11110101 '

#147
b01010011 %
b01000011 &
b10010110 '

#148
b10110001 %
b10001111 &
b01000000 '

#149
b10101000 %
b00111000 &
b11100000 '

#150
b11111000 %
b11001100 &
b11000100 '

#151
b10000111 %
b00110100 &
b10111011 '

#152
b01000011 %
b00110110 &
b01111001 '

#153
b00011101 %
b10010110 &
b10110011 '

#154
b01101111 %
b10000100 &
b11110011 '

#155
b10101101 %
b00010001 &
b10111110 '

#156
b10001100 %
b10000110 &
b00010010 '

#157
b01011100 %
b00010001 &
b01101101 '

#158
b10011101 %
b10101001 &
b01000110 '

#159
b10101100 %
b01000011 &
b11101111 '

#160
b01011000 %
b10010110 &
b11101110 '

#161
b01110101 %
b01000101 &
b10111010 '

#162
b11100000 %
b01111111 &
b01011111 '

#163
b01010101 %
b00110110 &
b10001011 '

#164
b11001111 %
b00010111 &
b11100110 '

#165
b00001111 %
b00100011 &
b00110010 '

#166
b11101011 %
b01010110 &
b01000001 '

#167
b01111001 %
b11001100 &
b01000101 '

#168
b11001110 %
b11010010 &
b10100000 '

#169
b10001100 %
b11100111 &
b01110011 '

#170
b00010100 %
b11010110 &
b11101010 '

#171
b00001000 %
b11111000 &
b00000000 '

#172
b11011001 %
b00101110 &
b00000111 '

#173
b10111010 %
b10011101 &
b01010111 '

#174
b01000101 %
b11101101 &
b00110010 '

#175
b01011100 %
b00110000 &
b10001100 '

#176
b10111101 %
b00111110 &
b11111011 '

#177
b01011000 %
b11001101 &
b00100101 '

#178
b01110000 %
b01110011 &
b11100011 '

#179
b01011111 %
b00101101 &
b10001100 '

#180
b11110011 %
b01110001 &
b01100100 '

#181
b10001011 %
b00001011 &
b10010110 '

#182
b00110001 %
b00011110 &
b01001111 '

#183
b00100101 %
b11111000 &
b00011101 '

#184
b10100111 %
b01101011 &
b00010010 '

#185
b10010100 %
b01111100 &
b00010000 '

#186
b11111111 %
b00000010 &
b00000001 '

#187
b00110000 %
b00100111 &
b01010111 '

#188
b10101111 %
b01000110 &
b11110101 '

#189
b01100010 %
b11111011 &
b01011101 '

#190
b10100011 %
b01011011 &
b11111110 '

#191
b10011001 %
b00110110 &
b11001111 '

#192
b10110001 %
b01001001 &
b11111010 '

#193
b10001001 %
b00010011 &
b10011100 '

#194
b01000110 %
b01000101 &
b10001011 '

#195
b00100011 %
b01101010 &
b10001101 '

#196
b10100000 %
b01000011 &
b11100011 '

#197
b11110001 %
b01101001 &
b01011010 '

#198
b10101110 %
b10111011 &
b01101001 '

#199
b10110011 %
b00101011 &
b11011110 '

#200
b00011000 %
b01101011 &
b10000011 '

#201
b00111110 %
b00010111 &
b01010101 '

#202
b11010011 %
b01111101 &
b01010000 '

#203
b00011111 %
b11010011 &
b11110010 '

#204
b11110101 %
b00011000 &
b00001101 '

#205
b11100111 %
b00011111 &
b00000110 '

#206
b10100110 %
b00000100 &
b10101010 '

#207
b01010101 %
b01011000 &
b10101101 '

#208
b10000001 %
b01011111 &
b11100000 '

#209
b01100111 %
b11110100 &
b01011011 '

#210
b01110011 %
b01111111 &
b11110010 '

#211
b00111000 %
b10001110 &
b11000110 '

#212
b10110110 %
b00101010 &
b11100000 '

#213
b00000101 %
b01011110 &
b01100011 '

#214
b10011001 %
b00110101 &
b11001110 '

#215
b11100011 %
b10011100 &
b01111111 '

#216
b00101000 %
b00010110 &
b00111110 '

#217
b01110100 %
b10010000 &
b00000100 '

#218
b00011100 %
b00111111 &
b01011011 '

#219
b00010111 %
b10100100 &
b10111011 '

#220
b00010110 %
b01001010 &
b01100000 '

#221
b10000010 %
b11100011 &
b01100101 '

#222
b01001010 %
b10011000 &
b11100010 '

#223
b01001110 %
b01100010 &
b10110000 '

#224
b10011110 %
b10000010 &
b00100000 '

#225
b11111110 %
b00100100 &
b00100010 '

#226
b01001011 %
b10010001 &
b11011100 '

#227
b00000101 %
b00101011 &
b00110000 '

#228
b01000000 %
b01111010 &
b10111010 '

#229
b10010001 %
b01011010 &
b11101011 '

#230
b10011011 %
b00010101 &
b10110000 '

#231
b01101101 %
b01000001 &
b10101110 '

#232
b10100010 %
b00111001 &
b11011011 '

#233
b11100110 %
b01001110 &
b00110100 '

#234
b10110100 %
b00010001 &
b11000101 '

#235
b00010100 %
b10110001 &
b11000101 '

#236
b10110000 %
b11111001 &
b10101001 '

#237
b01100000 %
b11001011 &
b00101011 '

#238
b11110100 %
b10100001 &
b10010101 '

#239
b01101100 %
b10000110 &
b11110010 '

#240
b11111000 %
b10001001 &
b10000001 '

#241
b01001100 %
b11110011 &
b00111111 '

#242
b00010011 %
b00110101 &
b01001000 '

#243
b01111010 %
b01000001 &
b10111011 '

#244
b00101100 %
b10101010 &
b11010110 '

#245
b10011110 %
b01101000 &
b00000110 '

#246
b01001010 %
b00110101 &
b01111111 '

#247
b01001010 %
b11001011 &
b00010101 '

#248
b10110110 %
b10011110 &
b01010100 '

#249
b01011101 %
b00111100 &
b10011001 '

#250
b00101011 %
b10011001 &
b11000100 '

#251
b00100111 %
b10111010 &
b11100001 '

#252
b01111000 %
b11000000 &
b00111000 '

#253
b00100101 %
b10001100 &
b10110001 '

#254
b10110010 %
b11000111 &
b01111001 '

#255
b00110110 %
b00110010 &
b01101000 '

#256
b10111011 %
b01011101 &
b00011000 '

#257
b01001011 %
b00010011 &
b01011110 '

#258
b01010000 %
b11010011 &
b00100011 '

#259
b10110010 %
b11000001 &
b01110011 '

#260
b01101011 %
b11100100 &
b01001111 '

#261
b11010000 %
b00010111 &
b11100111 '

#262
b11001011 %
b00101100 &
b11110111 '

#263
b00011011 %
b10010000 &
b10101011 '

#264
b10001011 %
b10011010 &
b00100101 '

#265
b11001111 %
b10100000 &
b01101111 '

#266
b11100111 %
b01001110 &
b00110101 '

#267
b11110011 %
b00111010 &
b00101101 '

#268
b11011010 %
b00000110 &
b11100000 '

#269
b00100011 %
b00001110 &
b00110001 '

#270
b10001011 %
b10001111 &
b00011010 '

#271
b00010110 %
b01001000 &
b01011110 '

#272
b01010100 %
b01001100 &
b10100000 '

#273
b10010000 %
b00111010 &
b11001010 '

#274
b01100111 %
b10100110 &
b00001101 '

#275
b00111110 %
b10101111 &
b11101101 '

#276
b10001111 %
b01110101 &
b00000100 '

#277
b00001111 %
b00001111 &
b00011110 '

#278
b01110100 %
b10111111 &
b00110011 '

#279
b10010111 %
b11100101 &
b01111100 '

#280
b10110000 %
b01110001 &
b00100001 '

#281
b11110100 %
b00011001 &
b00001101 '

#282
b01000000 %
b01011001 &
b10011001 '

#283
b01101011 %
b10111001 &
b00100100 '

#284
b11001001 %
b00011100 &
b11100101 '

#285
b11000101 %
b11111010 &
b10111111 '

#286
b00101010 %
b10011100 &
b11000110 '

#287
b00110111 %
b01111010 &
b10110001 '

#288
b11001100 %
b11101000 &
b10110100 '

#289
b10110111 %
b10110111 &
b01101110 '

#290
b10101010 %
b01100111 &
b00010001 '

#291
b11111010 %
b01000010 &
b00111100 '

#292
b10110111 %
b01001001 &
b00000000 '

#293
b10100000 %
b10110011 &
b01010011 '

#294
b01100000 %
b10100110 &
b00000110 '

#295
b01001111 %
b01110111 &
b11000110 '

#296
b11001111 %
b00101111 &
b11111110 '

#297
b11010111 %
b11001111 &
b10100110 '

#298
b01000111 %
b10110111 &
b11111110 '

#299
b11100000 %
b10001010 &
b01101010 '

#300
b00101101 %
b00100001 &
b01001110 '

#301
b00011111 %
b11000111 &
b11100110 '

#302
b01000001 %
b10111110 &
b11111111 '

#303
b01110110 %
b10011001 &
b00001111 '

#304
b00110110 %
b10010110 &
b11001100 '

#305
b11111111 %
b01100111 &
b01100110 '

#306
b10101010 %
b11001101 &
b01110111 '

#307
b01010100 %
b10111000 &
b00001100 '

#308
b10011001 %
b00010001 &
b10101010 '

#309
b10001000 %
b01010001 &
b11011001 '

#310
b00110000 %
b00111011 &
b01101011 '

#311
b01011110 %
b10100101 &
b00000011 '

#312
b11111001 %
b01110111 &
b01110000 '

#313
b10010101 %
b10110100 &
b01001001 '

#314
b10100111 %
b10011110 &
b01000101 '

#315
b10001101 %
b01100000 &
b11101101 '

#316
b11011111 %
b10001101 &
b01101100 '

#317
b10101010 %
b11000010 &
b01101100 '

#318
b10101010 %
b01011100 &
b00000110 '

#319
b10011001 %
b00111110 &
b11010111 '

#320
b01000100 %
b01101001 &
b10101101 '

#321
b11000000 %
b11100111 &
b10100111 '

#322
b01010110 %
b00000000 &
b01010110 '

#323
b10011010 %
b00111010 &
b11010100 '

#324
b10011001 %
b10100000 &
b00111001 '

#325
b11101011 %
b01001101 &
b00111000 '

#326
b11110100 %
b11011111 &
b11010011 '

#327
b11011111 %
b01010110 &
b00110101 '

#328
b00001001 %
b00000110 &
b00001111 '

#329
b00110111 %
b10100100 &
b11011011 '

#330
b11011110 %
b00011100 &
b11111010 '

#331
b01101001 %
b10010000 &
b11111001 '

#332
b11111011 %
b00001000 &
b00000011 '

#333
b00111111 %
b00010000 &
b01001111 '

#334
b01100100 %
b10001110 &
b11110010 '

#335
b01001100 %
b10101111 &
b11111011 '

#336
b00000000 %
b00011000 &
b00011000 '

#337
b01001101 %
b00101001 &
b01110110 '

#338
b10001100 %
b10101101 &
b00111001 '

#339
b00000001 %
b10001011 &
b10001100 '

#340
b01111011 %
b01011000 &
b11010011 '

#341
b10100010 %
b01101100 &
b00001110 '

#342
b11010100 %
b01110111 &
b01001011 '

#343
b10110100 %
b10011111 &
b01010011 '

#344
b01101101 %
b01011100 &
b11001001 '

#345
b11011010 %
b00011000 &
b11110010 '

#346
b00110001 %
b11001000 &
b11111001 '

#347
b01101110 %
b01001110 &
b10111100 '

#348
b10111100 %
b00011110 &
b11011010 '

#349
b11001111 %
b01000100 &
b00010011 '

#350
b10111011 %
b01101000 &
b00100011 '

#351
b10011111 %
b10011111 &
b00111110 '

#352
b10011010 %
b01011101 &
b11110111 '

#353
b00111100 %
b01010101 &
b10010001 '

#354
b00111001 %
b01111100 &
b10110101 '

#355
b00111110 %
b10011010 &
b11011000 '

#356
b11101011 %
b01100000 &
b01001011 '

#357
b01011001 %
b11000011 &
b00011100 '

#358
b01010010 %
b00101010 &
b01111100 '

#359
b00110001 %
b10000000 &
b10110001 '

#360
b10111100 %
b10111000 &
b01110100 '

#361
b01101111 %
b01001011 &
b10111010 '

#362
b00111010 %
b01100110 &
b10100000 '

#363
b01000001 %
b00100101 &
b01100110 '

#364
b00001101 %
b11101101 &
b11111010 '

#365
b00111110 %
b00001010 &
b01001000 '

#366
b01111111 %
b10000001 &
b00000000 '

#367
b00001100 %
b11100110 &
b11110010 '

#368
b10001000 %
b10100100 &
b00101100 '

#369
b00100000 %
b00101101 &
b01001101 '

#370
b00111111 %
b00111111 &
b01111110 '

#371
b00001000 %
b01010000 &
b01011000 '

#372
b00001011 %
b00100000 &
b00101011 '

#373
b10010001 %
b00111101 &
b11001110 '

#374
b01011111 %
b10101101 &
b00001100 '

#375
b10000100 %
b00110110 &
b10111010 '

#376
b11000010 %
b00011111 &
b11100001 '

#377
b00110111 %
b00011100 &
b01010011 '

#378
b01000001 %
b11111001 &
b00111010 '

#379
b10100000 %
b10110011 &
b01010011 '

#380
b11110010 %
b10000010 &
b01110100 '

#381
b00111011 %
b11111011 &
b00110110 '

#382
b00001111 %
b10011011 &
b10101010 '

#383
b10100100 %
b10000100 &
b00101000 '

#384
b01010100 %
b01010101 &
b10101001 '

#385
b01001101 %
b11011110 &
b00101011 '

#386
b00111000 %
b11001101 &
b00000101 '

#387
b01001111 %
b10010111 &
b11100110 '

#388
b10001010 %
b10100111 &
b00110001 '

#389
b11000011 %
b00011101 &
b11100000 '

#390
b10110110 %
b10100100 &
b01011010 '

#391
b11010100 %
b10100010 &
b01110110 '

#392
b11111010 %
b10100101 &
b10011111 '

#393
b11001100 %
b11001001 &
b10010101 '

#394
b10010001 %
b10101011 &
b00111100 '

#395
b01111000 %
b00000100 &
b01111100 '

#396
b11100000 %
b00101011 &
b00001011 '

#397
b00111010 %
b01011110 &
b10011000 '

#398
b10010111 %
b11111000 &
b10001111 '

#399
b10110100 %
b00010100 &
b11001000 '

#400
b10111111 %
b00110010 &
b11110001 '

#401
b00000001 %
b10111010 &
b10111011 '

#402
b11100100 %
b11110000 &
b11010100 '

#403
b11010000 %
b01111011 &
b01001011 '

#404
b01110011 %
b11001011 &
b00111110 '

#405
b00001111 %
b01011011 &
b01101010 '

#406
b10111011 %
b10101001 &
b01100100 '

#407
b01001101 %
b10010111 &
b11100100 '

#408
b10010010 %
b11000010 &
b01010100 '

#409
b11001011 %
b01010101 &
b00100000 '

#410
b11011111 %
b10100101 &
b10000100 '

#411
b10111011 %
b01001111 &
b00001010 '

#412
b10110000 %
b10010111 &
b01000111 '

#413
b01000100 %
b01000111 &
b10001011 '

#414
b01110100 %
b11010110 &
b01001010 '

#415
b10110000 %
b10011101 &
b01001101 '

#416
b01100010 %
b00010010 &
b01110100 '

#417
b01001001 %
b01000100 &
b10001101 '

#418
b10000101 %
b00101100 &
b10110001 '

#419
b11100100 %
b11100100 &
b11001000 '

#420
b10001101 %
b11010100 &
b01100001 '

#421
b10000111 %
b10010111 &
b00011110 '

#422
b00110101 %
b01000011 &
b01111000 '

#423
b01010110 %
b10110111 &
b00001101 '

#424
b00011110 %
b10111100 &
b11011010 '

#425
b00010000 %
b11110000 &
b00000000 '

#426
b10001110 %
b10000000 &
b00001110 '

#427
b00011010 %
b00001101 &
b00100111 '

#428
b01011101 %
b10010001 &
b11101110 '

#429
b00011111 %
b01011101 &
b01111100 '

#430
b10001001 %
b01001011 &
b11010100 '

#431
b01000111 %
b11000011 &
b00001010 '

#432
b01101000 %
b11101011 &
b01010011 '

#433
b10010001 %
b11000111 &
b01011000 '

#434
b01110100 %
b00011000 &
b10001100 '

#435
b00001001 %
b11001000 &
b11010001 '

#436
b10110111 %
b01101001 &
b00100000 '

#437
b10011100 %
b11100100 &
b10000000 '

#438
b01011110 %
b10100001 &
b11111111 '

#439
b01100110 %
b10011001 &
b11111111 '

#440
b10111010 %
b11100001 &
b10011011 '

#441
b11000110 %
b01010111 &
b00011101 '

#442
b00010001 %
b11001100 &
b11011101 '

#443
b10001111 %
b00110001 &
b11000000 '

#444
b00100111 %
b10010001 &
b10111000 '

#445
b10011100 %
b00010001 &
b10101101 '

#446
b01111001 %
b00100011 &
b10011100 '

#447
b00010111 %
b00100000 &
b00110111 '

#448
b01100101 %
b01111100 &
b11100001 '

#449
b10111101 %
b11010000 &
b10001101 '

#450
b11100101 %
b01001100 &
b00110001 '

#451
b00110001 %
b01111010 &
b10101011 '

#452
b11010001 %
b00111110 &
b00001111 '

#453
b10010111 %
b10111000 &
b01001111 '

#454
b00100010 %
b11001110 &
b11110000 '

#455
b00000011 %
b01100110 &
b01101001 '

#456
b00100111 %
b10011100 &
b11000011 '

#457
b00000000 %
b01011111 &
b01011111 '

#458
b10000001 %
b11100101 &
b01100110 '

#459
b11101000 %
b01010111 &
b00111111 '

#460
b00111111 %
b00001001 &
b01001000 '

#461
b01000010 %
b01101000 &
b10101010 '

#462
b00010010 %
b10110100 &
b11000110 '

#463
b01101000 %
b10001010 &
b11110010 '

#464
b01011101 %
b10100011 &
b00000000 '

#465
b01101000 %
b01011010 &
b11000010 '

#466
b00100111 %
b00101100 &
b01010011 '

#467
b01000110 %
b11000011 &
b00001001 '

#468
b10101001 %
b00001011 &
b10110100 '

#469
b01101011 %
b00000111 &
b01110010 '

#470
b00100110 %
b00101100 &
b01010010 '

#471
b11001111 %
b00011010 &
b11101001 '

#472
b01000110 %
b10000000 &
b11000110 '

#473
b01100101 %
b00001001 &
b01101110 '

#474
b10000101 %
b00111111 &
b11000100 '

#475
b00010111 %
b10101001 &
b11000000 '

#476
b10100000 %
b01011010 &
b11111010 '

#477
b01110011 %
b00111011 &
b10101110 '

#478
b11000011 %
b01010000 &
b00010011 '

#479
b00001111 %
b01111100 &
b10001011 '

#480
b00010100 %
b11101111 &
b00000011 '

#481
b11110101 %
b01100000 &
b01010101 '

#482
b00110100 %
b01011110 &
b10010010 '

#483
b01111001 %
b00000100 &
b01111101 '

#484
b10101001 %
b10011111 &
b01001000 '

#485
b01000011 %
b10111101 &
b00000000 '

#486
b01001100 %
b01100010 &
b10101110 '

#487
b10000001 %
b10100110 &
b00100111 '

#488
b11111011 %
b01011001 &
b01010100 '

#489
b00100111 %
b01010011 &
b01111010 '

#490
b00010000 %
b01000101 &
b01010101 '

#491
b01010100 %
b00101001 &
b01111101 '

#492
b00010010 %
b01101011 &
b01111101 '

#493
b01011101 %
b11100000 &
b00111101 '

#494
b11101011 %
b01110010 &
b01011101 '

#495
b01111010 %
b00100000 &
b10011010 '

#496
b10101100 %
b10011111 &
b01001011 '

#497
b11100110 %
b00100011 &
b00001001 '

#498
b01111110 %
b11010110 &
b01010100 '

#499
b00000101 %
b10101000 &
b10101101 '

#500
b10011100 %
b01011001 &
b11110101 '

#501
b11100011 %
b10101011 &
b10001110 '

#502
b10000010 %
b11011100 &
b01011110 '

#503
b11110010 %
b00110000 &
b00100010 '

#504
b00011111 %
b11101101 &
b00001100 '

#505
b10111101 %
b01101010 &
b00100111 '

#506
b11011000 %
b01101011 &
b01000011 '

#507
b01100100 %
b11110101 &
b01011001 '

#508
b00100100 %
b10011111 &
b11000011 '

#509
b11000000 %
b10001101 &
b01001101 '

#510
b01011010 %
b11111000 &
b01010010 '

#511
b11010000 %
b01101000 &
b00111000 '

#512
b11001110 %
b00011010 &
b11101000 '

#513
b01101110 %
b11000101 &
b00110011 '

#514
b00000000 %
b01000001 &
b01000001 '

#515
b00000011 %
b11011110 &
b11100001 '

#516
b11001001 %
b00000000 &
b11001001 '

#517
b00011110 %
b10110011 &
b11010001 '

#518
b01111111 %
b10010111 &
b00010110 '

#519
b01000001 %
b10110101 &
b11110110 '

#520
b00101001 %
b00011111 &
b01001000 '

#521
b10000011 %
b10000111 &
b00001010 '

#522
b11010010 %
b10010011 &
b01100101 '

#523
b10101010 %
b10010011 &
b00111101 '

#524
b11111111 %
b10110000 &
b10101111 '

#525
b01101010 %
b11011101 &
b01000111 '

#526
b01011101 %
b00101110 &
b10001011 '

#527
b01001111 %
b01000001 &
b10010000 '

#528
b10111110 %
b00000100 &
b11000010 '

#529
b11101110 %
b01001011 &
b00111001 '

#530
b01100001 %
b01100101 &
b11000110 '

#531
b01101010 %
b11010001 &
b00111011 '

#532
b01000000 %
b10111100 &
b11111100 '

#533
b11101100 %
b01100111 &
b01010011 '

#534
b00110101 %
b11110100 &
b00101001 '

#535
b11101011 %
b00000110 &
b11110001 '

#536
b10111111 %
b01010011 &
b00010010 '

#537
b11000111 %
b01110110 &
b00111101 '

#538
b10010110 %
b11111101 &
b10010011 '

#539
b10101000 %
b11111111 &
b10100111 '

#540
b11010100 %
b11110000 &
b11000100 '

#541
b10000100 %
b10100010 &
b00100110 '

#542
b10011100 %
b00101111 &
b11001011 '

#543
b01100001 %
b10101001 &
b00001010 '

#544
b00000110 %
b10000001 &
b10000111 '

#545
b11100001 %
b00111011 &
b00011100 '

#546
b00110111 %
b00100111 &
b01011110 '

#547
b01001111 %
b00110000 &
b01111111 '

#548
b10110110 %
b01110111 &
b00101101 '

#549
b11110011 %
b10011011 &
b10001110 '

#550
b01101001 %
b11101101 &
b01010110 '

#551
b11111010 %
b10110110 &
b10110000 '

#552
b11000111 %
b10011000 &
b01011111 '

#553
b00011000 %
b01100101 &
b01111101 '

#554
b00100010 %
b11101011 &
b00001101 '

#555
b01000001 %
b01011111 &
b10100000 '

#556
b00001000 %
b11011101 &
b11100101 '

#557
b00100010 %
b11010000 &
b11110010 '

#558
b00010111 %
b11001101 &
b11100100 '

#559
b10011111 %
b01001001 &
b11101000 '

#560
b11111110 %
b11010110 &
b11010100 '

#561
b00010001 %
b11101111 &
b00000000 '

#562
b01000001 %
b10011010 &
b11011011 '

#563
b00100010 %
b11001011 &
b11101101 '

#564
b00101101 %
b11100110 &
b00010011 '

#565
b01010000 %
b01011011 &
b10101011 '

#566
b10010000 %
b10000011 &
b00010011 '

#567
b10010101 %
b11110011 &
b10001000 '

#568
b10010110 %
b00001101 &
b10100011 '

#569
b00000111 %
b10000110 &
b10001101 '

#570
b00111110 %
b10100011 &
b11100001 '

#571
b00001101 %
b01000101 &
b01010010 '

#572
b01001010 %
b01100100 &
b10101110 '

#573
b10010001 %
b00110110 &
b11000111 '

#574
b01011100 %
b00011010 &
b01110110 '

#575
b00001010 %
b01101010 &
b01110100 '

#576
b10101010 %
b11000010 &
b01101100 '

#577
b10000011 %
b10111001 &
b00111100 '

#578
b11100101 %
b11100000 &
b11000101 '

#579
b11111111 %
b00101100 &
b00101011 '

#580
b11110100 %
b11101101 &
b11100001 '

#581
b10111000 %
b00000000 &
b10111000 '

#582
b11100100 %
b00000101 &
b11101001 '

#583
b10111100 %
b00000011 &
b10111111 '

#584
b00011110 %
b10110100 &
b11010010 '

#585
b11011010 %
b01010111 &
b00110001 '

#586
b00000111 %
b00001110 &
b00010101 '

#587
b01011010 %
b01101000 &
b11000010 '

#588
b01010111 %
b00101110 &
b10000101 '

#589
b11010011 %
b00011001 &
b11101100 '

#590
b01011101 %
b01100101 &
b11000010 '

#591
b11011101 %
b10101100 &
b10001001 '

#592
b10101101 %
b01110110 &
b00100011 '

#593
b01000100 %
b10010000 &
b11010100 '

#594
b00001101 %
b11000100 &
b11010001 '

#595
b00001011 %
b10111011 &
b11000110 '

#596
b01010010 %
b00011101 &
b01101111 '

#597
b10101010 %
b11111010 &
b10100100 '

#598
b00111101 %
b11101011 &
b00101000 '

#599
b11001101 %
b10101100 &
b01111001 '

#600
b00111010 %
b00110011 &
b01101101 '

#601
b11101011 %
b01011000 &
b01000011 '

#602
b10000101 %
b10010001 &
b00010110 '

#603
b00100110 %
b10110101 &
b11011011 '

#604
b11101001 %
b11110110 &
b11011111 '

#605
b00000111 %
b11001010 &
b11010001 '

#606
b01011110 %
b00111110 &
b10011100 '

#607
b01000011 %
b01011011 &
b10011110 '

