src/tests/resources/operation/sv/if/if.sv
// Generated by CIRCT firtool-1.71.0
module Foo(	// sv/if/if.generic.mlir:3:3
  input        clk,	// sv/if/if.generic.mlir:4:8
  input  [7:0] a,	// sv/if/if.generic.mlir:4:19
               b,	// sv/if/if.generic.mlir:4:30
  output [7:0] res	// sv/if/if.mlir:1:54
);

  always @(posedge clk)	// sv/if/if.generic.mlir:6:5
    $info("hitIf");	// sv/if/if.generic.mlir:8:9
  assign res = a + b;	// sv/if/if.generic.mlir:12:10, :13:5
endmodule

src/tests/resources/operation/sv/if/trace_vtor.vcd
$version Generated by VerilatedVcd $end
$timescale 1ps $end
 $scope module Foo $end
  $var wire 1 # clk $end
  $var wire 8 $ a [7:0] $end
  $var wire 8 % b [7:0] $end
  $var wire 8 & res [7:0] $end
  $scope module Foo $end
   $var wire 1 # clk $end
   $var wire 8 $ a [7:0] $end
   $var wire 8 % b [7:0] $end
   $var wire 8 & res [7:0] $end
  $upscope $end
 $upscope $end
$enddefinitions $end


#0
1#
b10010101 $
b11110100 %
b10001001 &
#1
0#
b01111110 $
b00001010 %
b10001000 &
#2
1#
b10100000 $
b10100100 %
b01000100 &
#3
0#
b00111111 $
b00110110 %
b01110101 &
#4
1#
b00000100 $
b01101001 %
b01101101 &
#5
0#
b11000000 $
b10101110 %
b01101110 &
#6
1#
b01010010 $
b01111011 %
b11001101 &
#7
0#
b01111100 $
b11101000 %
b01100100 &
#8
1#
b10111001 $
b01000001 %
b11111010 &
#9
0#
b10001101 $
b10101111 %
b00111100 &
#10
1#
b10100000 $
b10101001 %
b01001001 &
#11
0#
b11100111 $
b11101100 %
b11010011 &
#12
1#
b11111010 $
b01000111 %
b01000001 &
#13
0#
b01100110 $
b11010100 %
b00111010 &
#14
1#
b10000100 $
b01111011 %
b11111111 &
#15
0#
b10001101 $
b00010110 %
b10100011 &
#16
1#
b11110110 $
b10000101 %
b01111011 &
#17
0#
b00101110 $
b10110111 %
b11100101 &
#18
1#
b01010101 $
b10111010 %
b00001111 &
#19
0#
b11100100 $
b10100010 %
b10000110 &
#20
1#
b01010111 $
b11010001 %
b00101000 &
#21
0#
b11000000 $
b01110000 %
b00110000 &
#22
1#
b00001010 $
b11001010 %
b11010100 &
#23
0#
b11100001 $
b00101110 %
b00001111 &
#24
1#
b01011101 $
b11110101 %
b01010010 &
#25
0#
b10101001 $
b11101101 %
b10010110 &
#26
1#
b01111011 $
b10100100 %
b00011111 &
#27
0#
b11001101 $
b10111100 %
b10001001 &
#28
1#
b01111001 $
b10001000 %
b00000001 &
#29
0#
b10000110 $
b10001101 %
b00010011 &
#30
1#
b11001101 $
b11111001 %
b11000110 &
#31
0#
b10100101 $
b00001011 %
b10110000 &
#32
1#
b11011000 $
b11011000 %
#33
0#
b10110000 $
b11100111 %
b10010111 &
#34
1#
b10101001 $
b10101100 %
b01010101 &
#35
0#
b00100011 $
b11010010 %
b11110101 &
#36
1#
b10101101 $
b00110001 %
b11011110 &
#37
0#
b00100001 $
b00001101 %
b00101110 &
#38
1#
b11101011 $
b00111000 %
b00100011 &
#39
0#
b11000011 $
b00010100 %
b11010111 &
#40
1#
b10010111 $
b10101110 %
b01000101 &
#41
0#
b01101111 $
b11011111 %
b01001110 &
#42
1#
b01111101 $
b11101001 %
b01100110 &
#43
0#
b01011000 $
b00000001 %
b01011001 &
#44
1#
b10111111 $
b10110100 %
b01110011 &
#45
0#
b10000000 $
b11011000 %
b01011000 &
#46
1#
b11010011 $
b11110001 %
b11000100 &
#47
0#
b00011100 $
b10010001 %
b10101101 &
#48
1#
b01000100 $
b11111101 %
b01000001 &
#49
0#
b10110000 $
b11111001 %
b10101001 &
#50
1#
b11110000 $
b10101100 %
b10011100 &
#51
0#
b11111010 $
b00011011 %
b00010101 &
#52
1#
b00110010 $
b00000010 %
b00110100 &
#53
0#
b11000000 $
b10100001 %
b01100001 &
#54
1#
b11101110 $
b11011011 %
b11001001 &
#55
0#
b01010011 $
b10101000 %
b11111011 &
#56
1#
b11001011 $
b01110111 %
b01000010 &
#57
0#
b01110000 $
b01010000 %
b11000000 &
#58
1#
b11111100 $
b11010000 %
b11001100 &
#59
0#
b11011000 $
b10110101 %
b10001101 &
#60
1#
b10000011 $
b00101011 %
b10101110 &
#61
0#
b00000100 $
b01010001 %
b01010101 &
#62
1#
b11100000 $
b01000111 %
b00100111 &
#63
0#
b01011100 $
b01100000 %
b10111100 &
#64
1#
b00101101 $
b01101000 %
b10010101 &
#65
0#
b00010001 $
b01010010 %
b01100011 &
#66
1#
b00110110 $
b10101101 %
b11100011 &
#67
0#
b11000100 $
b11111000 %
b10111100 &
#68
1#
b11001110 $
b11001111 %
b10011101 &
#69
0#
b10110010 $
b11111100 %
b10101110 &
#70
1#
b10110110 $
b00001001 %
b10111111 &
#71
0#
b01000001 $
b11111101 %
b00111110 &
#72
1#
b10100110 $
b11100001 %
b10000111 &
#73
0#
b11011000 $
b00111111 %
b00010111 &
#74
1#
b00110101 $
b00110100 %
b01101001 &
#75
0#
b11111111 $
b00100100 %
b00100011 &
#76
1#
b00000011 $
b00010010 %
b00010101 &
#77
0#
b00000100 $
b01110011 %
b01110111 &
#78
1#
b10100111 $
b11010101 %
b01111100 &
#79
0#
b11000111 $
b11001101 %
b10010100 &
#80
1#
b11111001 $
b00110011 %
b00101100 &
#81
0#
b01010111 $
b00100101 %
b01111100 &
#82
1#
b11111011 $
b01001010 %
b01000101 &
#83
0#
b00010100 $
b00100111 %
b00111011 &
#84
1#
b10101010 $
b10000110 %
b00110000 &
#85
0#
b00001011 $
b01011110 %
b01101001 &
#86
1#
b01000101 $
b11001001 %
b00001110 &
#87
0#
b11010011 $
b11110011 %
b11000110 &
#88
1#
b00100011 $
b01000111 %
b01101010 &
#89
0#
b00001100 $
b11000101 %
b11010001 &
#90
1#
b10010000 $
b11100001 %
b01110001 &
#91
0#
b00101010 $
b00001010 %
b00110100 &
#92
1#
b10010110 $
b01001000 %
b11011110 &
#93
0#
b10010001 $
b10011101 %
b00101110 &
#94
1#
b01000010 $
b00010100 %
b01010110 &
#95
0#
b01010000 $
b11111011 %
b01001011 &
#96
1#
b01101001 $
b10011111 %
b00001000 &
#97
0#
b00000101 $
b10110001 %
b10110110 &
#98
1#
b10011010 $
b10101010 %
b01000100 &
#99
0#
b10111111 $
b01100010 %
b00100001 &
#100
1#
b01010001 $
b11010111 %
b00101000 &
#101
0#
b10001110 $
b11110010 %
b10000000 &
#102
1#
b10010101 $
b00011000 %
b10101101 &
#103
0#
b01001101 $
b11000001 %
b00001110 &
#104
1#
b00001010 $
b11111010 %
b00000100 &
#105
0#
b11110010 $
b00101101 %
b00011111 &
#106
1#
b11011110 $
b10000101 %
b01100011 &
#107
0#
b10111111 $
b00110110 %
b11110101 &
#108
1#
b01001100 $
b00100000 %
b01101100 &
#109
0#
b11111111 $
b11000010 %
b11000001 &
#110
1#
b00100110 $
b01010110 %
b01111100 &
#111
0#
b11000001 $
b10000110 %
b01000111 &
#112
1#
b10101100 $
b01110000 %
b00011100 &
#113
0#
b11101011 $
b11001110 %
b10111001 &
#114
1#
b11101100 $
b00001001 %
b11110101 &
#115
0#
b10011101 $
b01101010 %
b00000111 &
#116
1#
b01100001 $
b00010001 %
b01110010 &
#117
0#
b11111010 $
b11110100 %
b11101110 &
#118
1#
b10101011 $
b11100111 %
b10010010 &
#119
0#
b01010000 $
b01101001 %
b10111001 &
#120
1#
b00101110 $
b11101110 %
b00011100 &
#121
0#
b01111111 $
b11111001 %
b01111000 &
#122
1#
b11001011 $
b10001110 %
b01011001 &
#123
0#
b00110000 $
b11101110 %
b00011110 &
#124
1#
b00010000 $
b00000111 %
b00010111 &
#125
0#
b00010111 $
b00001111 %
b00100110 &
#126
1#
b01001001 $
b01110100 %
b10111101 &
#127
0#
b01011100 $
b10101001 %
b00000101 &
#128
1#
b10110000 $
b00111000 %
b11101000 &
#129
0#
b00000001 $
b00000010 %
b00000011 &
#130
1#
b01101010 $
b01111001 %
b11100011 &
#131
0#
b00010101 $
b11111101 %
b00010010 &
#132
1#
b00100100 $
b01000101 %
b01101001 &
#133
0#
b00001001 $
b11001000 %
b11010001 &
#134
1#
b00000000 $
b01111000 %
b01111000 &
#135
0#
b00110010 $
b00011000 %
b01001010 &
#136
1#
b11001000 $
b10011000 %
b01100000 &
#137
0#
b01110011 $
b11010001 %
b01000100 &
#138
1#
b00100000 $
b11001011 %
b11101011 &
#139
0#
b10011100 $
b01000000 %
b11011100 &
#140
1#
b11111001 $
b00110100 %
b00101101 &
#141
0#
b00111011 $
b01000001 %
b01111100 &
#142
1#
b00111110 $
b11001000 %
b00000110 &
#143
0#
b01010100 $
b10111100 %
b00010000 &
#144
1#
b01111100 $
b11100000 %
b01011100 &
#145
0#
b00001001 $
b10000001 %
b10001010 &
#146
1#
b11111111 $
b11110100 %
b11110011 &
#147
0#
b11011110 $
b00010101 %
#148
1#
b01010000 $
b11100110 %
b00110110 &
#149
0#
b10100101 $
b01111011 %
b00100000 &
#150
1#
b00111011 $
b10100010 %
b11011101 &
#151
0#
b01011000 $
b10010111 %
b11101111 &
#152
1#
b10111100 $
b11100111 %
b10100011 &
#153
0#
b10001001 $
b00001100 %
b10010101 &
#154
1#
b00111000 $
b10011111 %
b11010111 &
#155
0#
b01100010 $
b11011100 %
b00111110 &
#156
1#
b11001011 $
b10110111 %
b10000010 &
#157
0#
b00100101 $
b10101011 %
b11010000 &
#158
1#
b10110111 $
b11000110 %
b01111101 &
#159
0#
b10000011 $
b10010001 %
b00010100 &
#160
1#
b11100110 $
b10100100 %
b10001010 &
#161
0#
b00110100 $
b11101000 %
b00011100 &
#162
1#
b10001001 $
b00001001 %
b10010010 &
#163
0#
b00111000 $
b01011111 %
b10010111 &
#164
1#
b00110100 $
b11000001 %
b11110101 &
#165
0#
b00110000 $
b11100110 %
b00010110 &
#166
1#
b00011101 $
b11011000 %
b11110101 &
#167
0#
b10000011 $
b01010010 %
b11010101 &
#168
1#
b00100010 $
b10000101 %
b10100111 &
#169
0#
b10101000 $
b00000110 %
b10101110 &
#170
1#
b01000101 $
b00111110 %
b10000011 &
#171
0#
b10000110 $
b11101101 %
b01110011 &
#172
1#
b01000101 $
b10100001 %
b11100110 &
#173
0#
b01100111 $
b11000111 %
b00101110 &
#174
1#
b11001001 $
b01110010 %
b00111011 &
#175
0#
b10110011 %
b01111100 &
#176
1#
b10110010 $
b00110101 %
b11100111 &
#177
0#
b10110101 $
b00100011 %
b11011000 &
#178
1#
b10011011 $
b01011010 %
b11110101 &
#179
0#
b00100110 $
b00001011 %
b00110001 &
#180
1#
b11101111 $
b10011110 %
b10001101 &
#181
0#
b11100011 $
b01011011 %
b00111110 &
#182
1#
b11111000 $
b10000111 %
b01111111 &
#183
0#
b11110010 $
b01111000 %
b01101010 &
#184
1#
b01101100 $
b01001001 %
b10110101 &
#185
0#
b00110001 $
b10110110 %
b11100111 &
#186
1#
b01111101 $
b00001101 %
b10001010 &
#187
0#
b11111111 $
b11010011 %
b11010010 &
#188
1#
b00111011 $
b00110001 %
b01101100 &
#189
0#
b11101011 $
b11110011 %
b11011110 &
#190
1#
b01101101 $
b10001101 %
b11111010 &
#191
0#
b10101011 $
b00000110 %
b10110001 &
#192
1#
b11110101 $
b11101111 %
b11100100 &
#193
0#
b00000001 $
b11011101 %
b11011110 &
#194
1#
b10100001 $
b11100111 %
b10001000 &
#195
0#
b11011101 $
b11001001 %
b10100110 &
#196
1#
b11111000 $
b10100100 %
b10011100 &
#197
0#
b11101101 $
b00101010 %
b00010111 &
#198
1#
b11100000 $
b11000111 %
b10100111 &
#199
0#
b10100011 $
b01011011 %
b11111110 &
#200
1#
b11011001 $
b11010110 %
b10101111 &
#201
0#
b00011111 $
b11101011 %
b00001010 &
#202
1#
b00011100 $
b11100001 %
b11111101 &
#203
0#
b01001101 $
b01011001 %
b10100110 &
#204
1#
b01111110 $
b00000000 %
b01111110 &
#205
0#
b10101001 $
b00111001 %
b11100010 &
#206
1#
b11000110 $
b11001101 %
b10010011 &
#207
0#
b10010010 $
b01110010 %
b00000100 &
#208
1#
b01111101 $
b11111001 %
b01110110 &
#209
0#
b01101011 $
b11011001 %
b01000100 &
#210
1#
b11110000 $
b10011101 %
b10001101 &
#211
0#
b00111010 $
b10100011 %
b11011101 &
#212
1#
b00010110 $
b10001111 %
b10100101 &
#213
0#
b10110111 $
b11001101 %
b10000100 &
#214
1#
b00001101 $
b01100011 %
b01110000 &
#215
0#
b11110010 $
b10111101 %
b10101111 &
#216
1#
b00010010 $
b01010001 %
b01100011 &
#217
0#
b01001100 $
b11110011 %
b00111111 &
#218
1#
b10000001 $
b01101010 %
b11101011 &
#219
0#
b00111011 $
b10101100 %
b11100111 &
#220
1#
b01110001 $
b11111100 %
b01101101 &
#221
0#
b01110000 $
b00011100 %
b10001100 &
#222
1#
b11110100 $
b00011001 %
b00001101 &
#223
0#
b10110110 $
b00010010 %
b11001000 &
#224
1#
b00111011 $
b10100011 %
b11011110 &
#225
0#
b11111001 $
b11001101 %
b11000110 &
#226
1#
b11101110 $
b01100000 %
b01001110 &
#227
0#
b00001110 $
b11110011 %
b00000001 &
#228
1#
b11000111 $
b10000101 %
b01001100 &
#229
0#
b00010111 $
b11010101 %
b11101100 &
#230
1#
b01000001 %
b01011000 &
#231
0#
b11000110 $
b00111010 %
b00000000 &
#232
1#
b11010001 $
b01001000 %
b00011001 &
#233
0#
b11011100 $
b10011001 %
b01110101 &
#234
1#
b01010111 $
b11100011 %
b00111010 &
#235
0#
b01111001 $
b00011010 %
b10010011 &
#236
1#
b11101111 $
b11101110 %
b11011101 &
#237
0#
b00010100 $
b01010101 %
b01101001 &
#238
1#
b00011000 $
b10110110 %
b11001110 &
#239
0#
b10110000 $
b00011001 %
b11001001 &
#240
1#
b01000110 $
b10001001 %
b11001111 &
#241
0#
b00000100 $
b01101011 %
b01101111 &
#242
1#
b01111101 $
b01100110 %
b11100011 &
#243
0#
b01101100 $
b11000000 %
b00101100 &
#244
1#
b00010000 $
b01011111 %
b01101111 &
#245
0#
b01010000 $
b01110011 %
b11000011 &
#246
1#
b00110011 $
b10000010 %
b10110101 &
#247
0#
b00101001 $
b01001011 %
b01110100 &
#248
1#
b10101101 $
b01101001 %
b00010110 &
#249
0#
b00101011 $
b11000100 %
b11101111 &
#250
1#
b10100001 $
b10100000 %
b01000001 &
#251
0#
b11100101 $
b00001010 %
b11101111 &
#252
1#
b00000000 $
b01110111 %
b01110111 &
#253
0#
b10111010 $
b01111000 %
b00110010 &
#254
1#
b01010000 $
b00101000 %
b01111000 &
#255
0#
b11110101 $
b01001111 %
b01000100 &
#256
1#
b01000001 $
b00010111 %
b01011000 &
#257
0#
b01010111 $
b10110000 %
b00000111 &
#258
1#
b01000000 $
b01101100 %
b10101100 &
#259
0#
b10000011 $
b01011110 %
b11100001 &
#260
1#
b11000111 $
b11110111 %
b10111110 &
#261
0#
b00001111 $
b00100000 %
b00101111 &
#262
1#
b01101011 $
b01001111 %
b10111010 &
#263
0#
b10111010 $
b00110111 %
b11110001 &
#264
1#
b00001000 $
b11111011 %
b00000011 &
#265
0#
b11101000 $
b00100000 %
b00001000 &
#266
1#
b10111101 $
b10110011 %
b01110000 &
#267
0#
b10111111 $
b11101100 %
b10101011 &
#268
1#
b01001011 $
b00111010 %
b10000101 &
#269
0#
b10100101 $
b00110000 %
b11010101 &
#270
1#
b10111001 $
b10110001 %
b01101010 &
#271
0#
b10011111 $
b01000100 %
b11100011 &
#272
1#
b10011110 $
b10010000 %
b00101110 &
#273
0#
b01010111 $
b10101011 %
b00000010 &
#274
1#
b00100001 $
b11101010 %
b00001011 &
#275
0#
b00111011 $
b10111000 %
b11110011 &
#276
1#
b01110111 $
b10111010 %
b00110001 &
#277
0#
b10000000 $
b10000000 %
b00000000 &
#278
1#
b00000010 $
b10000111 %
b10001001 &
#279
0#
b11101010 $
b11010111 %
b11000001 &
#280
1#
b11010010 $
b01101010 %
b00111100 &
#281
0#
b11100001 $
b00111000 %
b00011001 &
#282
1#
b11011010 $
b10001111 %
b01101001 &
#283
0#
b11111011 $
b01111100 %
b01110111 &
#284
1#
b01011000 $
b10101000 %
b00000000 &
#285
0#
b11000001 $
b10001101 %
b01001110 &
#286
1#
b00001000 $
b00111011 %
b01000011 &
#287
0#
b00000100 %
b00001100 &
#288
1#
b01110101 $
b10100001 %
b00010110 &
#289
0#
b01011011 $
b11111100 &
#290
1#
b01010000 $
b10010100 %
b11100100 &
#291
0#
b00111111 $
b10111001 %
b11111000 &
#292
1#
b01111100 $
b10001111 %
b00001011 &
#293
0#
b01000010 $
b00001001 %
b01001011 &
#294
1#
b11101000 $
b11101010 %
b11010010 &
#295
0#
b00100000 $
b10101000 %
b11001000 &
#296
1#
b01101011 $
b00000100 %
b01101111 &
#297
0#
b11111111 $
b00000000 %
b11111111 &
#298
1#
b00000111 $
b10010111 %
b10011110 &
#299
0#
b01001110 $
b11001000 %
b00010110 &
#300
1#
b11001001 $
b00010100 %
b11011101 &
#301
0#
b01001110 $
b10000010 %
b11010000 &
#302
1#
b10110010 $
b11101110 %
b10100000 &
#303
0#
b01010001 $
b00000100 %
b01010101 &
#304
1#
b00000010 $
b11101001 %
b11101011 &
#305
0#
b01100000 $
b10010100 %
b11110100 &
#306
1#
b11011110 $
b00110010 %
b00010000 &
#307
0#
b01101101 $
b00011101 %
b10001010 &
#308
1#
b00101101 $
b00000001 %
b00101110 &
#309
0#
b00100011 $
b01011111 %
b10000010 &
#310
1#
b00111011 $
b01101101 %
b10101000 &
#311
0#
b10010111 $
b10010000 %
b00100111 &
#312
1#
b11100101 $
b00100000 %
b00000101 &
#313
0#
b00010000 $
b01111000 %
b10001000 &
#314
1#
b10011111 $
b10101110 %
b01001101 &
#315
0#
b01001000 $
b01011010 %
b10100010 &
#316
1#
b11100011 $
b01010010 %
b00110101 &
#317
0#
b00110100 $
b10000010 %
b10110110 &
#318
1#
b00111111 $
b00011000 %
b01010111 &
#319
0#
b11111110 $
b01101001 %
b01100111 &
#320
1#
b01111111 $
b10000011 %
b00000010 &
#321
0#
b00011010 $
b01100000 %
b01111010 &
#322
1#
b10100110 $
b00000010 %
b10101000 &
#323
0#
b00010111 $
b11000000 %
b11010111 &
#324
1#
b11011010 $
b00100101 %
b11111111 &
#325
0#
b10100010 $
b00011100 %
b10111110 &
#326
1#
b00100101 $
b11010000 %
b11110101 &
#327
0#
b00000101 $
b01101001 %
b01101110 &
#328
1#
b10110101 $
b01110111 %
b00101100 &
#329
0#
b11111000 $
b11100011 %
b11011011 &
#330
1#
b00011011 $
b11111111 %
b00011010 &
#331
0#
b01100111 $
b01001010 %
b10110001 &
#332
1#
b01011100 $
b11010001 %
b00101101 &
#333
0#
b11111111 $
b11010000 &
#334
1#
b10010010 $
b01100110 %
b11111000 &
#335
0#
b01000011 $
b00100101 %
b01101000 &
#336
1#
b01010011 $
b00000100 %
b01010111 &
#337
0#
b11100011 $
b00110101 %
b00011000 &
#338
1#
b01010110 $
b10011000 %
b11101110 &
#339
0#
b00010000 $
b01111011 %
b10001011 &
#340
1#
b00110111 $
b01010110 %
b10001101 &
#341
0#
b00100011 $
b10110100 %
b11010111 &
#342
1#
b11011010 $
b10100110 %
b10000000 &
#343
0#
b10111110 $
b11010001 %
b10001111 &
#344
1#
b01011110 $
b10000111 %
b11100101 &
#345
0#
b11100101 $
b11010100 %
b10111001 &
#346
1#
b10000110 $
b10000010 %
b00001000 &
#347
0#
b01111111 $
b10110100 %
b00110011 &
#348
1#
b00111000 $
b00110111 %
b01101111 &
#349
0#
b10100000 $
b11011100 %
b01111100 &
#350
1#
b01100110 $
b00100000 %
b10000110 &
#351
0#
b01000100 $
b11101100 %
b00110000 &
#352
1#
b00001000 $
b01110101 %
b01111101 &
#353
0#
b11010001 $
b01010010 %
b00100011 &
#354
1#
b01011110 $
b00001100 %
b01101010 &
#355
0#
b00111111 $
b11001111 %
b00001110 &
#356
1#
b10011110 $
b10000101 %
b00100011 &
#357
0#
b00010011 $
b11010000 %
b11100011 &
#358
1#
b01001110 $
b10100001 %
b11101111 &
#359
0#
b00100000 $
b00100000 %
b01000000 &
#360
1#
b10001110 $
b01101111 %
b11111101 &
#361
0#
b01000010 $
b10100111 %
b11101001 &
#362
1#
b11101101 $
b11000111 %
b10110100 &
#363
0#
b10011000 $
b10101100 %
b01000100 &
#364
1#
b11000000 $
b01100101 %
b00100101 &
#365
0#
b10101111 $
b00000110 %
b10110101 &
#366
1#
b11001010 $
b00001111 %
b11011001 &
#367
0#
b10011100 $
b10100010 %
b00111110 &
#368
1#
b00001011 $
b00100011 %
b00101110 &
#369
0#
b11000111 $
b00100111 %
b11101110 &
#370
1#
b00010111 $
b10100011 %
b10111010 &
#371
0#
b01111011 $
b11000000 %
b00111011 &
#372
1#
b10010010 $
b01110010 %
b00000100 &
#373
0#
b11011010 $
b11100100 %
b10111110 &
#374
1#
b10101111 $
b11101011 %
b10011010 &
#375
0#
b11010000 $
b00111010 %
b00001010 &
#376
1#
b11010011 $
b11000001 %
b10010100 &
#377
0#
b00001110 $
b00110100 %
b01000010 &
#378
1#
b00000101 $
b00011000 %
b00011101 &
#379
0#
b01111011 $
b10100101 %
b00100000 &
#380
1#
b01100010 $
b01111111 %
b11100001 &
#381
0#
b10110010 $
b10100111 %
b01011001 &
#382
1#
b00111001 $
b10100011 %
b11011100 &
#383
0#
b11110010 $
b10101010 %
b10011100 &
#384
1#
b11111011 $
b11000111 %
b11000010 &
#385
0#
b11110111 $
b01001000 %
b00111111 &
#386
1#
b11001010 $
b10001001 %
b01010011 &
#387
0#
b10011000 $
b10011111 %
b00110111 &
#388
1#
b10010101 $
b10111111 %
b01010100 &
#389
0#
b10011001 $
b00010101 %
b10101110 &
#390
1#
b00010000 $
b01011101 %
b01101101 &
#391
0#
b11111100 $
b01001000 %
b01000100 &
#392
1#
b01010001 $
b00010100 %
b01100101 &
#393
0#
b01001101 $
b10001010 %
b11010111 &
#394
1#
b01111110 $
b11101110 %
b01101100 &
#395
0#
b10100000 $
b01010001 %
b11110001 &
#396
1#
b11010101 $
b10111000 %
b10001101 &
#397
0#
b11010100 $
b01011101 %
b00110001 &
#398
1#
b01000110 $
b10011000 %
b11011110 &
#399
0#
b00100010 $
b01010001 %
b01110011 &
#400
1#
b00000001 $
b10000000 %
b10000001 &
#401
0#
b10111011 $
b01100101 %
b00100000 &
#402
1#
b00011111 $
b00101100 %
b01001011 &
#403
0#
b11111100 $
b11010101 %
b11010001 &
#404
1#
b11101000 $
b11100101 %
b11001101 &
#405
0#
b10101000 $
b01101011 %
b00010011 &
#406
1#
b11011010 $
b01111001 %
b01010011 &
#407
0#
b10010010 $
b10111010 %
b01001100 &
#408
1#
b01111110 $
b10010010 %
b00010000 &
#409
0#
b00101000 $
b00001100 %
b00110100 &
#410
1#
b11011011 $
b10100101 %
b10000000 &
#411
0#
b00111001 $
b10010101 %
b11001110 &
#412
1#
b00100011 $
b00011100 %
b00111111 &
#413
0#
b11100011 $
b10101100 %
b10001111 &
#414
1#
b01011010 $
b01010011 %
b10101101 &
#415
0#
b00000001 $
b00111101 %
b00111110 &
#416
1#
b11100011 $
b00001101 %
b11110000 &
#417
0#
b01001001 $
b10000101 %
b11001110 &
#418
1#
b11100110 $
b10110100 %
b10011010 &
#419
0#
b11101010 $
b01100100 %
b01001110 &
#420
1#
b11001111 $
b11101001 %
b10111000 &
#421
0#
b10110101 $
b01011100 %
b00010001 &
#422
1#
b11101011 $
b01010100 %
b00111111 &
#423
0#
b10011010 $
b11001000 %
b01100010 &
#424
1#
b01000111 $
b00100101 %
b01101100 &
#425
0#
b01011110 $
b01101011 %
b11001001 &
#426
1#
b00101111 $
b01111111 %
b10101110 &
#427
0#
b00001010 $
b00111011 %
b01000101 &
#428
1#
b10001111 $
b10011100 %
b00101011 &
#429
0#
b11001111 $
b01000111 %
b00010110 &
#430
1#
b11100010 $
b10111100 %
b10011110 &
#431
0#
b01101000 $
b00111111 %
b10100111 &
#432
1#
b00000111 $
b10111001 %
b11000000 &
#433
0#
b10001001 $
b01000000 %
b11001001 &
#434
1#
b11100111 $
b11100111 %
b11001110 &
#435
0#
b01001001 $
b11100001 %
b00101010 &
#436
1#
b11110000 $
b11110110 %
b11100110 &
#437
0#
b00011000 $
b10010110 %
b10101110 &
#438
1#
b11111101 $
b11101101 %
b11101010 &
#439
0#
b00101001 $
b01111001 %
b10100010 &
#440
1#
b00000011 $
b11110110 %
b11111001 &
#441
0#
b11111110 $
b01011101 %
b01011011 &
#442
1#
b00000110 $
b10010011 %
b10011001 &
#443
0#
b01100111 $
b11010011 %
b00111010 &
#444
1#
b10000111 $
b01101100 %
b11110011 &
#445
0#
b10100011 $
b10000111 %
b00101010 &
#446
1#
b00100100 $
b10101011 %
b11001111 &
#447
0#
b11110111 $
b01101101 %
b01100100 &
#448
1#
b00110011 $
b00001011 %
b00111110 &
#449
0#
b01101110 $
b10111001 %
b00100111 &
#450
1#
b10111111 $
b11101011 %
b10101010 &
#451
0#
b00100110 $
b00101110 %
b01010100 &
#452
1#
b10111111 $
b11101101 %
b10101100 &
#453
0#
b01111000 $
b11010110 %
b01001110 &
#454
1#
b01101101 $
b00011011 %
b10001000 &
#455
0#
b10001111 $
b11110101 %
b10000100 &
#456
1#
b01001110 $
b11101000 %
b00110110 &
#457
0#
b10101011 $
b10000000 %
b00101011 &
#458
1#
b10010010 $
b10010111 %
b00101001 &
#459
0#
b01111011 $
b01110010 %
b11101101 &
#460
1#
b11100000 $
b10111111 %
b10011111 &
#461
0#
b00111110 $
b01110001 %
b10101111 &
#462
1#
b11010111 $
b00011010 %
b11110001 &
#463
0#
b10101110 $
b01111011 %
b00101001 &
#464
1#
b11011001 $
b11100010 %
b10111011 &
#465
0#
b00011110 $
b01011111 %
b01111101 &
#466
1#
b01110001 $
b10101000 %
b00011001 &
#467
0#
b10011111 $
b00100111 %
b11000110 &
#468
1#
b11011110 $
b00100110 %
b00000100 &
#469
0#
b10101100 $
b10000110 %
b00110010 &
#470
1#
b10110010 $
b01010101 %
b00000111 &
#471
0#
b11110001 $
b01000101 %
b00110110 &
#472
1#
b00101110 $
b00010001 %
b00111111 &
#473
0#
b01110001 $
b11110111 %
b01101000 &
#474
1#
b01010101 $
b00011110 %
b01110011 &
#475
0#
b00111010 $
b10101001 %
b11100011 &
#476
1#
b11110110 $
b11001000 %
b10111110 &
#477
0#
b00111011 $
b10011011 %
b11010110 &
#478
1#
b01011100 $
b01001110 %
b10101010 &
#479
0#
b00001010 $
b01011011 %
b01100101 &
#480
1#
b10010111 $
b11110100 %
b10001011 &
#481
0#
b10010011 $
b01001010 %
b11011101 &
#482
1#
b01111011 $
b00101000 %
b10100011 &
#483
0#
b00011110 $
b01000101 %
b01100011 &
#484
1#
b01001111 $
b01110010 %
b11000001 &
#485
0#
b11011011 $
b11101111 %
b11001010 &
#486
1#
b10001111 $
b01110011 %
b00000010 &
#487
0#
b10010101 $
b00010001 %
b10100110 &
#488
1#
b10100100 $
b10000111 %
b00101011 &
#489
0#
b10100101 $
b11000110 %
b01101011 &
#490
1#
b01101001 $
b00000000 %
b01101001 &
#491
0#
b10011110 $
b11001100 %
b01101010 &
#492
1#
b11100110 $
b11010111 %
b10111101 &
#493
0#
b11011111 $
b10111111 %
b10011110 &
#494
1#
b00011010 $
b11110101 %
b00001111 &
#495
0#
b10010001 $
b11000011 %
b01010100 &
#496
1#
b00101001 $
b11111000 %
b00100001 &
#497
0#
b10110000 $
b10110110 %
b01100110 &
#498
1#
b10111100 $
b01000010 %
b11111110 &
#499
0#
b10011010 $
b00000101 %
b10011111 &
#500
1#
b01000100 $
b10111101 %
b00000001 &
#501
0#
b00101110 $
b11101011 &
#502
1#
b10110101 $
b01101101 %
b00100010 &
#503
0#
b00101111 $
b11110001 %
b00100000 &
#504
1#
b01011011 $
b11100010 %
b00111101 &
#505
0#
b00111011 $
b00100010 %
b01011101 &
#506
1#
b01011010 $
b01110100 %
b11001110 &
#507
0#
b10110100 $
b00000110 %
b10111010 &
#508
1#
b01001010 $
b11100000 %
b00101010 &
#509
0#
b00010101 $
b11110111 %
b00001100 &
#510
1#
b01010001 $
b00100110 %
b01110111 &
#511
0#
b00000100 $
b10001100 %
b10010000 &
#512
1#
b01010011 $
b01110011 %
b11000110 &
#513
0#
b10110100 $
b00000001 %
b10110101 &
#514
1#
b01001000 $
b10110011 %
b11111011 &
#515
0#
b00101101 $
b01100000 %
b10001101 &
#516
1#
b11101010 $
b11100001 %
b11001011 &
#517
0#
b01001000 $
b11010001 %
b00011001 &
#518
1#
b11000000 $
b10111111 %
b01111111 &
#519
0#
b01110110 $
b10001001 %
b11111111 &
#520
1#
b10100000 $
b11011000 %
b01111000 &
#521
0#
b10010101 $
b10101110 %
b01000011 &
#522
1#
b11101110 $
b00011000 %
b00000110 &
#523
0#
b00100011 $
b10001010 %
b10101101 &
#524
1#
b01001011 $
b11001100 %
b00010111 &
#525
0#
b11110001 $
b00101101 %
b00011110 &
#526
1#
b01000011 $
b01000100 %
b10000111 &
#527
0#
b10111100 $
b11111100 %
b10111000 &
#528
1#
b11101010 $
b11101110 %
b11011000 &
#529
0#
b10101001 $
b01010011 %
b11111100 &
#530
1#
b01101100 $
b01101100 %
b11011000 &
#531
0#
b00101000 $
b11101101 %
b00010101 &
#532
1#
b01000000 $
b01100100 %
b10100100 &
#533
0#
b00001010 $
b10100011 %
b10101101 &
#534
1#
b01101011 $
b11100001 %
b01001100 &
#535
0#
b01100101 $
b01000100 %
b10101001 &
#536
1#
b10000100 $
b10100010 %
b00100110 &
#537
0#
b10101010 $
b11100011 %
b10001101 &
