src/tests/resources/operation/hw/aggregate_constant3/aggregate_constant3.sv
// Generated by CIRCT firtool-1.71.0
module Foo(	// hw/aggregate_constant3/aggregate_constant3.generic.mlir:3:3
  input  [1:0]  a,	// hw/aggregate_constant3/aggregate_constant3.generic.mlir:4:8
  input  [63:0] b,	// hw/aggregate_constant3/aggregate_constant3.generic.mlir:4:19
  output [63:0] res	// hw/aggregate_constant3/aggregate_constant3.mlir:1:43
);

  assign res = b - 64'h1;	// hw/aggregate_constant3/aggregate_constant3.generic.mlir:8:10, :9:5
endmodule

src/tests/resources/operation/hw/aggregate_constant3/test.vcd
$version Generated by KCIRCT $end
$timescale 1s $end
 $scope module Foo $end
  $var wire 2 % a [1:0] $end
  $var wire 64 & b [63:0] $end
  $var wire 64 ' res [63:0] $end
  $scope module Foo $end
   $var wire 2 % a [1:0] $end
   $var wire 64 & b [63:0] $end
   $var wire 64 ' res [63:0] $end
  $upscope $end
 $upscope $end
$enddefinitions $end

#0
b01 %
b0000011011111110101011001010000010111011100110000011100111000001 &
b0000011011111110101011001010000010111011100110000011100111000000 '

#1
b00 %
b1111010001111111101101011100010001001001111100000000011010011000 &
b1111010001111111101101011100010001001001111100000000011010010111 '

#2
b11 %
b1111101100001101010010101101100000000001100111101101101001011100 &
b1111101100001101010010101101100000000001100111101101101001011011 '

#3
b00 %
b0011111100001001011001011100011111001100101010111010010001101010 &
b0011111100001001011001011100011111001100101010111010010001101001 '

#4
b01 %
b1100001001100011010011100011100101000101000000100111111110100000 &
b1100001001100011010011100011100101000101000000100111111110011111 '

#5
b10 %
b0001110110011111101100100101101100001100000000001011101111001110 &
b0001110110011111101100100101101100001100000000001011101111001101 '

#6
b01 %
b1111110101110111111101001100001110011001100001101010010000010100 &
b1111110101110111111101001100001110011001100001101010010000010011 '

#7
b00 %
b1100111111011100101100011010011011010111000010110100000100100110 &
b1100111111011100101100011010011011010111000010110100000100100101 '

#8
b00 %
b1111101011100100111101110001111111000111010101111111001011100001 &
b1111101011100100111101110001111111000111010101111111001011100000 '

#9
b10 %
b1000110010110011111110001001101000001110010110101101100001001111 &
b1000110010110011111110001001101000001110010110101101100001001110 '

#10
b00 %
b1111010101100011010010111001010000010001111100010000100010111101 &
b1111010101100011010010111001010000010001111100010000100010111100 '

#11
b01 %
b1111001111111010101011110010010011011001000111011000011111001010 &
b1111001111111010101011110010010011011001000111011000011111001001 '

#12
b10 %
b1111011111001010000100110000100010110011101001000011110000011101 &
b1111011111001010000100110000100010110011101001000011110000011100 '

#13
b00 %
b0100100010011001000010111000111101101010101101100101011010111000 &
b0100100010011001000010111000111101101010101101100101011010110111 '

#14
b00 %
b1111010111111111001101101110111000111001010011010110010011111001 &
b1111010111111111001101101110111000111001010011010110010011111000 '

#15
b00 %
b1100011000011110111101001101001010010101000111110111001110110001 &
b1100011000011110111101001101001010010101000111110111001110110000 '

#16
b11 %
b1111101001000001111110011100100000100101000011111110010110111000 &
b1111101001000001111110011100100000100101000011111110010110110111 '

#17
b11 %
b0010011110000000111101110111101110001100101010110001110110110110 &
b0010011110000000111101110111101110001100101010110001110110110101 '

#18
b01 %
b1110100010011101110011011100010001101100100010000110100000000111 &
b1110100010011101110011011100010001101100100010000110100000000110 '

#19
b10 %
b1001100010011011001101010100111100001010010000111111111000110110 &
b1001100010011011001101010100111100001010010000111111111000110101 '

#20
b01 %
b1000100000011101111001000000110101001100000101000101010110101100 &
b1000100000011101111001000000110101001100000101000101010110101011 '

#21
b01 %
b1110001001010000011011010011100111110111101100110011110110001110 &
b1110001001010000011011010011100111110111101100110011110110001101 '

#22
b10 %
b1010110110110001011001011101011110100000001100001011001111000000 &
b1010110110110001011001011101011110100000001100001011001110111111 '

#23
b00 %
b1110001001111101001101100100100000000010001001000111000001001111 &
b1110001001111101001101100100100000000010001001000111000001001110 '

#24
b00 %
b0000101101000100001001011101010111100001100011010100000010100011 &
b0000101101000100001001011101010111100001100011010100000010100010 '

#25
b00 %
b0010101100101001110000100000011010011011000000100110011111111110 &
b0010101100101001110000100000011010011011000000100110011111111101 '

#26
b00 %
b0100011110100101001010100001000111000000001000010010110000011000 &
b0100011110100101001010100001000111000000001000010010110000010111 '

#27
b11 %
b0110011110101010010110111010011001000100010111000010110010010001 &
b0110011110101010010110111010011001000100010111000010110010010000 '

#28
b11 %
b0000000010101001111100001111111010101011010010110000001010000100 &
b0000000010101001111100001111111010101011010010110000001010000011 '

#29
b10 %
b1110010011101111111111110101011001111011010001101010101011010010 &
b1110010011101111111111110101011001111011010001101010101011010001 '

#30
b10 %
b0011110110100011110010010111111110110000000110000000000011110100 &
b0011110110100011110010010111111110110000000110000000000011110011 '

#31
b01 %
b0100000011100101110011010100011000000110011100110111110011001000 &
b0100000011100101110011010100011000000110011100110111110011000111 '

#32
b10 %
b0100001111111100010101001010000110001001110111010111001101001100 &
b0100001111111100010101001010000110001001110111010111001101001011 '

#33
b01 %
b0100100011010100101101101001100001011111101000001110110111100111 &
b0100100011010100101101101001100001011111101000001110110111100110 '

#34
b00 %
b0001110010001111010010010010010110100101100110110110000010000010 &
b0001110010001111010010010010010110100101100110110110000010000001 '

#35
b10 %
b0100110010010111111110000011101110111000111010001111001000100000 &
b0100110010010111111110000011101110111000111010001111001000011111 '

#36
b01 %
b1000110010011111010111100110101011110011100001111000111000111011 &
b1000110010011111010111100110101011110011100001111000111000111010 '

#37
b01 %
b1010101011011011000110011010100001111011100101001011110110101010 &
b1010101011011011000110011010100001111011100101001011110110101001 '

#38
b10 %
b0100011010110100100101110110011111010111110001110100011000011101 &
b0100011010110100100101110110011111010111110001110100011000011100 '

#39
b00 %
b0110100000110110101010001111111000101011110011110110011101111001 &
b0110100000110110101010001111111000101011110011110110011101111000 '

#40
b11 %
b1111101110000111100110001001000100111001011110010001001010000110 &
b1111101110000111100110001001000100111001011110010001001010000101 '

#41
b00 %
b1000010101111111010101010101011001101001001011000001100100001011 &
b1000010101111111010101010101011001101001001011000001100100001010 '

#42
b10 %
b1110100110001110101010010011111000010100011001010010001111010001 &
b1110100110001110101010010011111000010100011001010010001111010000 '

#43
b01 %
b0101010100011001110111011101110101011100101001000111111111010110 &
b0101010100011001110111011101110101011100101001000111111111010101 '

#44
b11 %
b0110000000101010111011110110000010010101001101111111100101110001 &
b0110000000101010111011110110000010010101001101111111100101110000 '

#45
b00 %
b0101000001101101110101000111010011001010100111000100101101101101 &
b0101000001101101110101000111010011001010100111000100101101101100 '

#46
b10 %
b0000111110010010001110101100001101011100010100010001101001100010 &
b0000111110010010001110101100001101011100010100010001101001100001 '

#47
b01 %
b0110011010100000001010010000111111001110100100001010100111000111 &
b0110011010100000001010010000111111001110100100001010100111000110 '

#48
b11 %
b0110010110100000001100010110011100100101011010101010101010000011 &
b0110010110100000001100010110011100100101011010101010101010000010 '

#49
b01 %
b1110111110000001101000011110011111010101101101110110110101111000 &
b1110111110000001101000011110011111010101101101110110110101110111 '

#50
b11 %
b0101000011001100011010010011101011110010100010111000101100010001 &
b0101000011001100011010010011101011110010100010111000101100010000 '

#51
b01 %
b0010000000010000101011110001010110111101101000010001000011010100 &
b0010000000010000101011110001010110111101101000010001000011010011 '

#52
b00 %
b0000101100011010110011111010001100101001100000010000010101010001 &
b0000101100011010110011111010001100101001100000010000010101010000 '

#53
b01 %
b0011111001100111100000111101000110110111010010010111010001001010 &
b0011111001100111100000111101000110110111010010010111010001001001 '

#54
b10 %
b1111010110100111111010010010010100101100010111101001101001000111 &
b1111010110100111111010010010010100101100010111101001101001000110 '

#55
b01 %
b1101110111100001110010101110011011101110000011110111100000100000 &
b1101110111100001110010101110011011101110000011110111100000011111 '

#56
b01 %
b1111000010111001011101111011000101011111001101100110100100001110 &
b1111000010111001011101111011000101011111001101100110100100001101 '

#57
b11 %
b1101001001000001110101001110101100001010000111111100010100010100 &
b1101001001000001110101001110101100001010000111111100010100010011 '

#58
b10 %
b0010000011001011001010100000100011000000110010111001010010000110 &
b0010000011001011001010100000100011000000110010111001010010000101 '

#59
b11 %
b1010101001100000001100111001010010101110011101010000100101011100 &
b1010101001100000001100111001010010101110011101010000100101011011 '

#60
b11 %
b0011000110010000010100001100101100010000100100110101001010001001 &
b0011000110010000010100001100101100010000100100110101001010001000 '

#61
b00 %
b1100011110111010100100100101110111100110101010111111001000011011 &
b1100011110111010100100100101110111100110101010111111001000011010 '

#62
b10 %
b1010010001001101100101010100110111110000000100101011001011000101 &
b1010010001001101100101010100110111110000000100101011001011000100 '

#63
b00 %
b1101011001010101011001100010100110111100011100001011100110010111 &
b1101011001010101011001100010100110111100011100001011100110010110 '

#64
b11 %
b0111111000101010010000101111110011000010000111001101100001101001 &
b0111111000101010010000101111110011000010000111001101100001101000 '

#65
b10 %
b0011101111111111001111000100001011110010111110000100011110000000 &
b0011101111111111001111000100001011110010111110000100011101111111 '

#66
b10 %
b0100010110010101110001110110001000111010001010111101101101000010 &
b0100010110010101110001110110001000111010001010111101101101000001 '

#67
b01 %
b1011001010111011100011110110000110011001110011000010010011000111 &
b1011001010111011100011110110000110011001110011000010010011000110 '

#68
b10 %
b1011011010000000111101001010110011101110011010110110101001101000 &
b1011011010000000111101001010110011101110011010110110101001100111 '

#69
b11 %
b1011001101000010110000111110110101100000110111001010010011001110 &
b1011001101000010110000111110110101100000110111001010010011001101 '

#70
b10 %
b1101011110101011001010010111100010010111101010100110000001100111 &
b1101011110101011001010010111100010010111101010100110000001100110 '

#71
b10 %
b0011100101000101100000010011110010010010110011111111001011010010 &
b0011100101000101100000010011110010010010110011111111001011010001 '

#72
b00 %
b1101100110000000000001001000001101001011010010111100000011110011 &
b1101100110000000000001001000001101001011010010111100000011110010 '

#73
b10 %
b0011100010000111000001101110100101111101001101110000101000110000 &
b0011100010000111000001101110100101111101001101110000101000101111 '

#74
b11 %
b1001000110100111101110110111100010100001000001100101101111100111 &
b1001000110100111101110110111100010100001000001100101101111100110 '

#75
b10 %
b0010001001011101111000100000110100110101110100011010110101001110 &
b0010001001011101111000100000110100110101110100011010110101001101 '

#76
b11 %
b1101100001011100011001100011010000011101110000001010101101110110 &
b1101100001011100011001100011010000011101110000001010101101110101 '

#77
b10 %
b0111001110110000101011110110111100100011001110001001111001111101 &
b0111001110110000101011110110111100100011001110001001111001111100 '

#78
b00 %
b1111100010111000000001000110111001010101110100000011110000000111 &
b1111100010111000000001000110111001010101110100000011110000000110 '

#79
b10 %
b0001100010011100110010101001101001000111010001111111011100000101 &
b0001100010011100110010101001101001000111010001111111011100000100 '

#80
b11 %
b1111101011111101100101110111100100110010000110111000110011000101 &
b1111101011111101100101110111100100110010000110111000110011000100 '

#81
b00 %
b1011110001000010101011110110100011111101110111010010001001101101 &
b1011110001000010101011110110100011111101110111010010001001101100 '

#82
b01 %
b1111011011101101110001110111111111100110000000101001010011100011 &
b1111011011101101110001110111111111100110000000101001010011100010 '

#83
b00 %
b1011100110001100010000011100010010110010111010000101001010111100 &
b1011100110001100010000011100010010110010111010000101001010111011 '

#84
b00 %
b0011000110000100011011101000001100101111000100011000011101011001 &
b0011000110000100011011101000001100101111000100011000011101011000 '

#85
b11 %
b0010101000010000001001111011011110000010110011100101000001100010 &
b0010101000010000001001111011011110000010110011100101000001100001 '

#86
b01 %
b1010011111101010100001101111011110111000101100001011110101110110 &
b1010011111101010100001101111011110111000101100001011110101110101 '

#87
b10 %
b1011010001110100001111010101100000010101100100001110101010001100 &
b1011010001110100001111010101100000010101100100001110101010001011 '

#88
b00 %
b1110111011101000110001100111101000010001010010001001101011100101 &
b1110111011101000110001100111101000010001010010001001101011100100 '

#89
b01 %
b0000001010110000101011001101000000010101001111000100011110001001 &
b0000001010110000101011001101000000010101001111000100011110001000 '

#90
b11 %
b1100000011010110110110101010110000000110000010000101010000111001 &
b1100000011010110110110101010110000000110000010000101010000111000 '

#91
b01 %
b0110101011101001001001110100111000100000011100110111010000110010 &
b0110101011101001001001110100111000100000011100110111010000110001 '

#92
b01 %
b1001101100110101000110111101011100110000010111010010011101110010 &
b1001101100110101000110111101011100110000010111010010011101110001 '

#93
b11 %
b0100111110011010011001110101100011101001000111001100011000110110 &
b0100111110011010011001110101100011101001000111001100011000110101 '

#94
b10 %
b0011110001010001101001110001011100100111010100111010100110000111 &
b0011110001010001101001110001011100100111010100111010100110000110 '

#95
b10 %
b0011111011110000010111000000100110111111111010001111001110001011 &
b0011111011110000010111000000100110111111111010001111001110001010 '

#96
b01 %
b0010011011010001100110101101100110011100111110000001000101101111 &
b0010011011010001100110101101100110011100111110000001000101101110 '

#97
b01 %
b1111000100111011000111011101001111100111110101001010011111001100 &
b1111000100111011000111011101001111100111110101001010011111001011 '

#98
b10 %
b0100100011100010111010000100001101001101111000101110000100010110 &
b0100100011100010111010000100001101001101111000101110000100010101 '

#99
b10 %
b1101110111011111000001100011000011110001011100110010111010110011 &
b1101110111011111000001100011000011110001011100110010111010110010 '

#100
b10 %
b0010001011001001101111011011001110100100010101011111111001111110 &
b0010001011001001101111011011001110100100010101011111111001111101 '

#101
b00 %
b0011110001011110011011110001011001000001110100000101011110010010 &
b0011110001011110011011110001011001000001110100000101011110010001 '

#102
b01 %
b1010000010110110001011111000110111111111110001000110000010000010 &
b1010000010110110001011111000110111111111110001000110000010000001 '

#103
b00 %
b1000001001111000101111110011111111110110001001110011011010011010 &
b1000001001111000101111110011111111110110001001110011011010011001 '

#104
b11 %
b0011100000000101111010001110110110000110001111001110111001010001 &
b0011100000000101111010001110110110000110001111001110111001010000 '

#105
b01 %
b1110011010111010110000000000101101101100010110010101101111010001 &
b1110011010111010110000000000101101101100010110010101101111010000 '

#106
b00 %
b1111110011110111001000101010100001110110110010101001101011001011 &
b1111110011110111001000101010100001110110110010101001101011001010 '

#107
b10 %
b0001010011001000111001100000011001011111100111111101110111010000 &
b0001010011001000111001100000011001011111100111111101110111001111 '

#108
b11 %
b0011101010011111001001101100101001001010101111110010000001100001 &
b0011101010011111001001101100101001001010101111110010000001100000 '

#109
b01 %
b0010010000011111000100000001001010100100001010110111010110100000 &
b0010010000011111000100000001001010100100001010110111010110011111 '

#110
b01 %
b1100100101110101011010000100100111110001010011110010110010010100 &
b1100100101110101011010000100100111110001010011110010110010010011 '

#111
b10 %
b0011100110011111110111100101101001000100110000111111011010011100 &
b0011100110011111110111100101101001000100110000111111011010011011 '

#112
b10 %
b1111100100000100110100101101110011000001111111111111001011010110 &
b1111100100000100110100101101110011000001111111111111001011010101 '

#113
b00 %
b1010110101011001100100010000100011111001011100001100000100100001 &
b1010110101011001100100010000100011111001011100001100000100100000 '

#114
b11 %
b0100001001101010111100000011101100110111001001000011100100001011 &
b0100001001101010111100000011101100110111001001000011100100001010 '

#115
b00 %
b1001111000010000001111011001000001001100101010111100010100100000 &
b1001111000010000001111011001000001001100101010111100010100011111 '

#116
b01 %
b1010001101101001100111010011011000101110011111100111000101010111 &
b1010001101101001100111010011011000101110011111100111000101010110 '

#117
b11 %
b1100000010011000000100100101111110010000010011100111111000111000 &
b1100000010011000000100100101111110010000010011100111111000110111 '

#118
b00 %
b0011000100000011000100100101110011110110000100110100000011110011 &
b0011000100000011000100100101110011110110000100110100000011110010 '

#119
b11 %
b0000000010000010110111101001001101101000110011000010000100100011 &
b0000000010000010110111101001001101101000110011000010000100100010 '

#120
b00 %
b1110010011101011000110110111101010010000010011001100110110000110 &
b1110010011101011000110110111101010010000010011001100110110000101 '

#121
b00 %
b0101101010110110011000100001000011100000010001110110110101000001 &
b0101101010110110011000100001000011100000010001110110110101000000 '

#122
b10 %
b0111000011011101010011100111011010101100100010110001000000100010 &
b0111000011011101010011100111011010101100100010110001000000100001 '

#123
b10 %
b1011000111110000100011100111000100001000000000111001010100110110 &
b1011000111110000100011100111000100001000000000111001010100110101 '

#124
b11 %
b1011000101100100110100110000000110100000000001110111110011010111 &
b1011000101100100110100110000000110100000000001110111110011010110 '

#125
b10 %
b0010001110000101000000111001000111110101011010111101001010011000 &
b0010001110000101000000111001000111110101011010111101001010010111 '

#126
b00 %
b1111001011010011111100010010010101101001001000100100010101010001 &
b1111001011010011111100010010010101101001001000100100010101010000 '

#127
b11 %
b1111011001110010111100110111001101010110000000111011101001110001 &
b1111011001110010111100110111001101010110000000111011101001110000 '

#128
b11 %
b1100100011101000101001111101101101010111000011010000001100000100 &
b1100100011101000101001111101101101010111000011010000001100000011 '

#129
b00 %
b1000011010010111001010000111101111011000010100101001000010111110 &
b1000011010010111001010000111101111011000010100101001000010111101 '

#130
b10 %
b0110100100001001100110011011011010101010111010110101101111100011 &
b0110100100001001100110011011011010101010111010110101101111100010 '

#131
b00 %
b0101000001000000100101010101011100110100001100000011101110110001 &
b0101000001000000100101010101011100110100001100000011101110110000 '

#132
b10 %
b1111111101111001111111101101010110000000000000010011110101010100 &
b1111111101111001111111101101010110000000000000010011110101010011 '

#133
b10 %
b1100100101001111010010110000011010001000001110100001001110100101 &
b1100100101001111010010110000011010001000001110100001001110100100 '

#134
b11 %
b0100101100000001011111101001011101110000010110000011000110101011 &
b0100101100000001011111101001011101110000010110000011000110101010 '

#135
b00 %
b1101111001101110110110011001110010011100001110110111011110010001 &
b1101111001101110110110011001110010011100001110110111011110010000 '

#136
b11 %
b0010010000111101011001110110011100010100011011010111001101111000 &
b0010010000111101011001110110011100010100011011010111001101110111 '

#137
b00 %
b1011100011000010001101111100000000101110001101000000001000010100 &
b1011100011000010001101111100000000101110001101000000001000010011 '

#138
b01 %
b0000101000110111110110111101111000001011000101010100001001000000 &
b0000101000110111110110111101111000001011000101010100001000111111 '

#139
b00 %
b0101101000101101000011011100010110110001000010100010000000101000 &
b0101101000101101000011011100010110110001000010100010000000100111 '

#140
b00 %
b0001001101100011111001101100000110100001111111100001010010000100 &
b0001001101100011111001101100000110100001111111100001010010000011 '

#141
b00 %
b1111101011101011001100111010101111100000010001110100110011001101 &
b1111101011101011001100111010101111100000010001110100110011001100 '

#142
b10 %
b0011111001110111001001111011001110011101110101111000001010111110 &
b0011111001110111001001111011001110011101110101111000001010111101 '

#143
b11 %
b0011001100111111111100111100011011010011110111100101000101100111 &
b0011001100111111111100111100011011010011110111100101000101100110 '

#144
b11 %
b1010111011011000001000111011001101001110101110110100001000000110 &
b1010111011011000001000111011001101001110101110110100001000000101 '

#145
b01 %
b0010001101101110100111111000011000001110110100011010111011001001 &
b0010001101101110100111111000011000001110110100011010111011001000 '

#146
b01 %
b1010100101111101101110100111101100010111001011110111001101000100 &
b1010100101111101101110100111101100010111001011110111001101000011 '

#147
b11 %
b1101000101010010110100110110110001011111011110010100111000110001 &
b1101000101010010110100110110110001011111011110010100111000110000 '

#148
b10 %
b1111100101011111110110110101101110011100111100100010101011111010 &
b1111100101011111110110110101101110011100111100100010101011111001 '

#149
b00 %
b0101101100001011101000111000101111111111111100111011000100110100 &
b0101101100001011101000111000101111111111111100111011000100110011 '

#150
b01 %
b0100110010111111110010101111110000100110100100100011110110001010 &
b0100110010111111110010101111110000100110100100100011110110001001 '

#151
b01 %
b1001011110010101100011110100000011010111011100010010111110001100 &
b1001011110010101100011110100000011010111011100010010111110001011 '

#152
b00 %
b1100110100001100001001001010110100010100010100001111000011010111 &
b1100110100001100001001001010110100010100010100001111000011010110 '

#153
b11 %
b1110100001001100001000000001001011111101010100010100010101101111 &
b1110100001001100001000000001001011111101010100010100010101101110 '

#154
b11 %
b0000111010000001011101001100110100100011001001011010010111001101 &
b0000111010000001011101001100110100100011001001011010010111001100 '

#155
b00 %
b0110011010010100100000101001101111001111111001111000011000111100 &
b0110011010010100100000101001101111001111111001111000011000111011 '

#156
b10 %
b1101010010101001000000100010000001100001110010010011011011110101 &
b1101010010101001000000100010000001100001110010010011011011110100 '

#157
b10 %
b1101110001001000001110001111110110000101100011010101000011101011 &
b1101110001001000001110001111110110000101100011010101000011101010 '

#158
b00 %
b0111000111111111100001110110001101101101100010001011001000010001 &
b0111000111111111100001110110001101101101100010001011001000010000 '

#159
b11 %
b0011000010110111111010110111000111111000001110100001010000010000 &
b0011000010110111111010110111000111111000001110100001010000001111 '

#160
b01 %
b0111010110100011000010001000000011011000110000000110011000010101 &
b0111010110100011000010001000000011011000110000000110011000010100 '

#161
b11 %
b0111010101101111010000000011000101001111101100000100011111100110 &
b0111010101101111010000000011000101001111101100000100011111100101 '

#162
b01 %
b1001101011010000000001010111100101001011011010011001100111110111 &
b1001101011010000000001010111100101001011011010011001100111110110 '

#163
b00 %
b0000010001011111001001011000011001001100111000110011010101111011 &
b0000010001011111001001011000011001001100111000110011010101111010 '

#164
b10 %
b0010001011011010011010010111101011011001100110001011001010010111 &
b0010001011011010011010010111101011011001100110001011001010010110 '

#165
b11 %
b0010100011110101000011101100110011000101000011010000101110100010 &
b0010100011110101000011101100110011000101000011010000101110100001 '

#166
b00 %
b0011111010010001111110011110000001010101100101100010010111001000 &
b0011111010010001111110011110000001010101100101100010010111000111 '

#167
b10 %
b0100001111110101100010000000001111010101110110000011010111000111 &
b0100001111110101100010000000001111010101110110000011010111000110 '

#168
b11 %
b0110001000011110111011101111110000100101010011000101001101101110 &
b0110001000011110111011101111110000100101010011000101001101101101 '

#169
b01 %
b0101011010100001100001101001001110101011111011110111001000111001 &
b0101011010100001100001101001001110101011111011110111001000111000 '

#170
b11 %
b0100010010101111001001011010100101100010010001100110100110010000 &
b0100010010101111001001011010100101100010010001100110100110001111 '

#171
b00 %
b0101101101111000100000111000101111010011000001010010111000011111 &
b0101101101111000100000111000101111010011000001010010111000011110 '

#172
b01 %
b0100110110011101001100001011001100001001001100111001000000100101 &
b0100110110011101001100001011001100001001001100111001000000100100 '

#173
b01 %
b0000100111110111101110111111110001011110010001110110111101001110 &
b0000100111110111101110111111110001011110010001110110111101001101 '

#174
b01 %
b0100000110111100110001110110001101000110000101111010011000000100 &
b0100000110111100110001110110001101000110000101111010011000000011 '

#175
b01 %
b1010000010001111011100011011010101100000000100010011110101001000 &
b1010000010001111011100011011010101100000000100010011110101000111 '

#176
b11 %
b0111111000111001110000011010101111101110100010011010010100111101 &
b0111111000111001110000011010101111101110100010011010010100111100 '

#177
b00 %
b0110110111111100100001100101001111101011110110011010001011111111 &
b0110110111111100100001100101001111101011110110011010001011111110 '

#178
b11 %
b0000111100011100010010000011000100110111010001010011110110100010 &
b0000111100011100010010000011000100110111010001010011110110100001 '

#179
b11 %
b0000111111001000000101000011101111000000001100011011011110011110 &
b0000111111001000000101000011101111000000001100011011011110011101 '

#180
b11 %
b1001000011001111100010101000111011101001001111100011001001000011 &
b1001000011001111100010101000111011101001001111100011001001000010 '

#181
b00 %
b1011101101100011010111010010101100110011101010100000111100110000 &
b1011101101100011010111010010101100110011101010100000111100101111 '

#182
b10 %
b1000001111000011111001110001100101101011010110000000000110110100 &
b1000001111000011111001110001100101101011010110000000000110110011 '

#183
b11 %
b0101011001011111100001010100011000001110101110110010110011000111 &
b0101011001011111100001010100011000001110101110110010110011000110 '

#184
b11 %
b1100000110000011100011011110101010010111100010001000111011100000 &
b1100000110000011100011011110101010010111100010001000111011011111 '

#185
b00 %
b1110001101001001100001101110110010010110010010111000101111010010 &
b1110001101001001100001101110110010010110010010111000101111010001 '

#186
b11 %
b0101110100000000000101011111110011110000111100000010100000000111 &
b0101110100000000000101011111110011110000111100000010100000000110 '

#187
b01 %
b0111111101101001011100001100110000010111101100110001001111011111 &
b0111111101101001011100001100110000010111101100110001001111011110 '

#188
b01 %
b1101001010001001001001010101100100011000010101111011111111101111 &
b1101001010001001001001010101100100011000010101111011111111101110 '

#189
b00 %
b1001010111101111001000010111110111000111100000100011000010000010 &
b1001010111101111001000010111110111000111100000100011000010000001 '

#190
b10 %
b0101111111111100001001111010010110101110111111011100001010001111 &
b0101111111111100001001111010010110101110111111011100001010001110 '

#191
b01 %
b0110000101110011100011101001001000001111000000010110100011100101 &
b0110000101110011100011101001001000001111000000010110100011100100 '

#192
b10 %
b0110000001110010101110001010010011001111001110110111111110110010 &
b0110000001110010101110001010010011001111001110110111111110110001 '

#193
b01 %
b0101100101000100000000010001000111001010010000001010001100000100 &
b0101100101000100000000010001000111001010010000001010001100000011 '

#194
b11 %
b1101111001011000100100001001000101111001000001111111110010001101 &
b1101111001011000100100001001000101111001000001111111110010001100 '

#195
b01 %
b0001011011110100111000100111100100001010101001000010010110111010 &
b0001011011110100111000100111100100001010101001000010010110111001 '

#196
b11 %
b0100101101010011001000111010111101100001011011001101111111100010 &
b0100101101010011001000111010111101100001011011001101111111100001 '

#197
b00 %
b0101000011010110001101111001111000111010010000000001011000011110 &
b0101000011010110001101111001111000111010010000000001011000011101 '

#198
b11 %
b0111100011110011101000011011001110000001101010101101100011110010 &
b0111100011110011101000011011001110000001101010101101100011110001 '

#199
b00 %
b0110111110111101011110100111101100000101010000000010011111000100 &
b0110111110111101011110100111101100000101010000000010011111000011 '

#200
b11 %
b0001111000101000100110100001011010110110111001101100100110011000 &
b0001111000101000100110100001011010110110111001101100100110010111 '

#201
b00 %
b1111110000011011101001100010111010000101100010000111010101111000 &
b1111110000011011101001100010111010000101100010000111010101110111 '

#202
b11 %
b0001011100000101011011000001000100100000011110111101000011001010 &
b0001011100000101011011000001000100100000011110111101000011001001 '

#203
b00 %
b0000011010110100010000010010010111101101011011010110010000000000 &
b0000011010110100010000010010010111101101011011010110001111111111 '

#204
b11 %
b0111000010100101100011001111010110001010100110001001010101000111 &
b0111000010100101100011001111010110001010100110001001010101000110 '

#205
b11 %
b0110100110111010011111111111000101100010111100011000011110011101 &
b0110100110111010011111111111000101100010111100011000011110011100 '

#206
b10 %
b0111110010000110100001000001000011011011110010011111000000110100 &
b0111110010000110100001000001000011011011110010011111000000110011 '

#207
b10 %
b1000001011000111010001110000101110001000000111000000100010101110 &
b1000001011000111010001110000101110001000000111000000100010101101 '

#208
b10 %
b1010111000001110010110111001111010001111100110000011110110111100 &
b1010111000001110010110111001111010001111100110000011110110111011 '

#209
b11 %
b1011111101011111010011111110110110110001000101001010001000100010 &
b1011111101011111010011111110110110110001000101001010001000100001 '

#210
b01 %
b0100001011111111001001001111001101111111001010101111000010011110 &
b0100001011111111001001001111001101111111001010101111000010011101 '

#211
b01 %
b0100010110001100100101001000010100001001101010101010001000011010 &
b0100010110001100100101001000010100001001101010101010001000011001 '

#212
b01 %
b0110110110010100111010101110110100101100101100100110011001110000 &
b0110110110010100111010101110110100101100101100100110011001101111 '

#213
b11 %
b0011100111011110011001111000010001100100111111011010100100001110 &
b0011100111011110011001111000010001100100111111011010100100001101 '

#214
b10 %
b1110101011100111010101111001101011110100111000001101011101100011 &
b1110101011100111010101111001101011110100111000001101011101100010 '

#215
b11 %
b1100110101010101000010100010001100011101010011000110011010101100 &
b1100110101010101000010100010001100011101010011000110011010101011 '

#216
b11 %
b0100111101111110100001000110111000001000100100010100010111011111 &
b0100111101111110100001000110111000001000100100010100010111011110 '

#217
b10 %
b1000001001001001010100001011000010001011100011001101100011110000 &
b1000001001001001010100001011000010001011100011001101100011101111 '

#218
b01 %
b0111101011101011111101111001001101000000111000110000011100101100 &
b0111101011101011111101111001001101000000111000110000011100101011 '

#219
b01 %
b0101111001101111100101000010011100100100101111000101111000000010 &
b0101111001101111100101000010011100100100101111000101111000000001 '

#220
b11 %
b1011100011101010111101000010111110110111110010110001101110100111 &
b1011100011101010111101000010111110110111110010110001101110100110 '

#221
b11 %
b0100001010000110101010001111101110101111100111110000000011111111 &
b0100001010000110101010001111101110101111100111110000000011111110 '

#222
b01 %
b0001000000111100010110001100100001000000111011001001010000010000 &
b0001000000111100010110001100100001000000111011001001010000001111 '

#223
b00 %
b0000111010001101100010111000001110011001010100011010011110010000 &
b0000111010001101100010111000001110011001010100011010011110001111 '

#224
b11 %
b1101011000010110100101101101011111001111011001111100001001110100 &
b1101011000010110100101101101011111001111011001111100001001110011 '

#225
b01 %
b1001111110001101111111011101000101010010000110010101110000011100 &
b1001111110001101111111011101000101010010000110010101110000011011 '

#226
b01 %
b0111011110011010101111001001101101011100011011100000000100101010 &
b0111011110011010101111001001101101011100011011100000000100101001 '

#227
b00 %
b1010001111011000001100011000001001110111111010100100010011000011 &
b1010001111011000001100011000001001110111111010100100010011000010 '

#228
b11 %
b1110001101011110111011000111101100110101001110110101101111100100 &
b1110001101011110111011000111101100110101001110110101101111100011 '

#229
b11 %
b1111101010101011101101011011100101000010111111100000011000101111 &
b1111101010101011101101011011100101000010111111100000011000101110 '

#230
b10 %
b0001001111111110001110010111111100000010000111011101010011000000 &
b0001001111111110001110010111111100000010000111011101010010111111 '

#231
b01 %
b1000110010000100101110111010101111001010000110110110000100011111 &
b1000110010000100101110111010101111001010000110110110000100011110 '

#232
b10 %
b0001100000000011011010011001111100110100100101111101010100001111 &
b0001100000000011011010011001111100110100100101111101010100001110 '

#233
b11 %
b1111011000111010001101100000100010101000111000110001101101111111 &
b1111011000111010001101100000100010101000111000110001101101111110 '

#234
b10 %
b0001001000001101001000011111010101110110101010011111111100011010 &
b0001001000001101001000011111010101110110101010011111111100011001 '

#235
b11 %
b1010100110011110101000010101100011101001000010111111101110010001 &
b1010100110011110101000010101100011101001000010111111101110010000 '

#236
b01 %
b1001110010110011011000110100101101100100101011100101111001010100 &
b1001110010110011011000110100101101100100101011100101111001010011 '

#237
b10 %
b0000110111110100100100011001111001011001001011111010111010001101 &
b0000110111110100100100011001111001011001001011111010111010001100 '

#238
b11 %
b0100110110111001010001001100000100101100010011111000001000010010 &
b0100110110111001010001001100000100101100010011111000001000010001 '

#239
b11 %
b0100010000010100001000000100101111100111001011111110000001011000 &
b0100010000010100001000000100101111100111001011111110000001010111 '

#240
b00 %
b1100011000001000111001001110010010011011100111000001111101110011 &
b1100011000001000111001001110010010011011100111000001111101110010 '

