src/tests/resources/operation/hw/output/output.sv
// Generated by CIRCT firtool-1.71.0
module Foo(	// hw/output/output.generic.mlir:3:3
  input  [7:0] a,	// hw/output/output.generic.mlir:4:8
               b,	// hw/output/output.generic.mlir:4:19
  output [7:0] res	// hw/output/output.mlir:1:42
);

  assign res = a + b;	// hw/output/output.generic.mlir:5:10, :6:5
endmodule

src/tests/resources/operation/hw/output/trace_vtor.vcd
$version Generated by VerilatedVcd $end
$date Tue Nov 12 18:08:39 2024
 $end
$timescale   1ps $end

 $scope module Foo $end
  $var wire  8 # a [7:0] $end
  $var wire  8 $ b [7:0] $end
  $var wire  8 % res [7:0] $end
  $scope module Foo $end
   $var wire  8 # a [7:0] $end
   $var wire  8 $ b [7:0] $end
   $var wire  8 % res [7:0] $end
  $upscope $end
 $upscope $end
$enddefinitions $end


#0
b10111101 #
b01010011 $
b00010000 %
#1
b10111111 #
b11101000 $
b10100111 %
#2
b00010100 #
b10011010 $
b10101110 %
#3
b11101100 #
b10111110 $
b10101010 %
#4
b11101001 #
b11000000 $
b10101001 %
#5
b00100010 #
b00010001 $
b00110011 %
#6
b10110000 #
b00011010 $
b11001010 %
#7
b10110101 #
b00000101 $
b10111010 %
#8
b01001100 #
b00100011 $
b01101111 %
#9
b10010110 #
b01011100 $
b11110010 %
#10
b11101011 #
b01001101 $
b00111000 %
#11
b10010000 #
b11101000 $
b01111000 %
#12
b11111110 #
b00100110 $
b00100100 %
#13
b01111101 #
b11010100 $
b01010001 %
#14
b10001010 #
b01111011 $
b00000101 %
#15
b11011101 #
b00010001 $
b11101110 %
#16
b10110001 #
b01111101 $
b00101110 %
#17
b10000111 #
b10110100 $
b00111011 %
#18
b10111110 #
b10100100 $
b01100010 %
#19
b11011110 #
b10000111 $
b01100101 %
#20
b11001100 #
b10010101 $
b01100001 %
#21
b01011110 #
b00110010 $
b10010000 %
#22
b10100111 #
b01110101 $
b00011100 %
#23
b10000010 #
b00100010 $
b10100100 %
#24
b10111110 #
b00100000 $
b11011110 %
#25
b11101110 #
b00000101 $
b11110011 %
#26
b01001101 #
b01111110 $
b11001011 %
#27
b01010111 #
b00000010 $
b01011001 %
#28
b10010010 #
b00110110 $
b11001000 %
#29
b10001001 #
b01000010 $
b11001011 %
#30
b11010101 #
b00100010 $
b11110111 %
#31
b01000101 #
b00111010 $
b01111111 %
#32
b11101100 #
b00000100 $
b11110000 %
#33
b10100101 #
b11000000 $
b01100101 %
#34
b11001011 #
b00000110 $
b11010001 %
#35
b00111100 #
b01001010 $
b10000110 %
#36
b10100010 #
b11011110 $
b10000000 %
#37
b01000011 #
b10101110 $
b11110001 %
#38
b01000010 #
b11101000 $
b00101010 %
#39
b01111100 #
b11010101 $
b01010001 %
#40
b00001100 #
b01011111 $
b01101011 %
#41
b11100011 #
b01000010 $
b00100101 %
#42
b01110100 #
b01001101 $
b11000001 %
#43
b11000000 #
b00111001 $
b11111001 %
#44
b11101001 #
b00101001 $
b00010010 %
#45
b10110011 #
b01010101 $
b00001000 %
#46
b00111011 #
b01111010 $
b10110101 %
#47
b11010101 #
b11101000 $
b10111101 %
#48
b10001000 #
b01100011 $
b11101011 %
#49
b01011101 #
b01010100 $
b10110001 %
#50
b00110110 #
b11000111 $
b11111101 %
#51
b01110110 #
b11110000 $
b01100110 %
#52
b00101111 #
b01010011 $
b10000010 %
#53
b01001000 #
b11001010 $
b00010010 %
#54
b01011010 #
b00111000 $
b10010010 %
#55
b00101010 #
b00000101 $
b00101111 %
#56
b00000001 #
b10011100 $
b10011101 %
#57
b11111110 #
b01001101 $
b01001011 %
#58
b01010100 #
b00100111 $
b01111011 %
#59
b01011010 #
b11101101 $
b01000111 %
#60
b11011000 #
b11010101 $
b10101101 %
#61
b01000000 #
b00010000 $
b01010000 %
#62
b10001011 #
b01001000 $
b11010011 %
#63
b00010001 #
b11101011 $
b11111100 %
#64
b10110011 #
b11101100 $
b10011111 %
#65
b01100110 #
b11100110 $
b01001100 %
#66
b11001101 #
b01000101 $
b00010010 %
#67
b10010100 #
b10101010 $
b00111110 %
#68
b11011101 #
b00101111 $
b00001100 %
#69
b01100011 #
b00011000 $
b01111011 %
#70
b10010001 #
b11001110 $
b01011111 %
#71
b00010011 #
b01100010 $
b01110101 %
#72
b00100001 #
b01100001 $
b10000010 %
#73
b01111010 #
b01110110 $
b11110000 %
#74
b01111111 #
b00111000 $
b10110111 %
#75
b10011111 #
b00010110 $
b10110101 %
#76
b00101010 #
b00111001 $
b01100011 %
#77
b01101001 #
b11001100 $
b00110101 %
#78
b01011101 #
b00100111 $
b10000100 %
#79
b10101101 #
b01011110 $
b00001011 %
#80
b00100101 #
b01100001 $
b10000110 %
#81
b10010000 #
b11000010 $
b01010010 %
#82
b01001010 #
b01011111 $
b10101001 %
#83
b01110010 #
b00010011 $
b10000101 %
#84
b00110111 #
b01111001 $
b10110000 %
#85
b01000101 #
b01001101 $
b10010010 %
#86
b00000011 #
b01011111 $
b01100010 %
#87
b00011000 #
b00100100 $
b00111100 %
#88
b01000010 #
b10000010 $
b11000100 %
#89
b00100010 #
b11110011 $
b00010101 %
#90
b01011010 #
b01000111 $
b10100001 %
#91
b01100000 #
b11100111 $
b01000111 %
#92
b00011000 #
b11000011 $
b11011011 %
#93
b00001011 #
b11111000 $
b00000011 %
#94
b00100111 #
b10100110 $
b11001101 %
#95
b00011010 #
b01010000 $
b01101010 %
#96
b00010000 #
b01110111 $
b10000111 %
#97
b01010111 #
b00000010 $
b01011001 %
#98
b10100010 #
b11011100 $
b01111110 %
#99
b10101100 #
b10100111 $
b01010011 %
#100
b10110100 #
b11000001 $
b01110101 %
#101
b00111100 #
b00001101 $
b01001001 %
#102
b11001001 #
b11010110 $
b10011111 %
#103
b00010100 #
b00101010 $
b00111110 %
#104
b01101111 #
b00000001 $
b01110000 %
#105
b01010011 #
b01100001 $
b10110100 %
#106
b11011111 #
b01011101 $
b00111100 %
#107
b11101000 #
b10001010 $
b01110010 %
#108
b10010100 #
b10101001 $
b00111101 %
#109
b11110001 #
b00011101 $
b00001110 %
#110
b11110100 #
b01010011 $
b01000111 %
#111
b01010100 #
b01100100 $
b10111000 %
#112
b01001001 #
b00001100 $
b01010101 %
#113
b10010111 #
b00011001 $
b10110000 %
#114
b10101001 #
b00100101 $
b11001110 %
#115
b00011100 #
b00100110 $
b01000010 %
#116
b10111001 #
b01010110 $
b00001111 %
#117
b11101111 #
b11110001 $
b11100000 %
#118
b01010000 #
b11110000 $
b01000000 %
#119
b01000101 #
b10011101 $
b11100010 %
#120
b00011110 #
b00110010 $
b01010000 %
#121
b00011011 #
b11101010 $
b00000101 %
#122
b11101100 #
b00100111 $
b00010011 %
#123
b01000010 #
b10101100 $
b11101110 %
#124
b00010110 #
b01101110 $
b10000100 %
#125
b11111100 #
b11000001 $
b10111101 %
#126
b00000111 #
b00000111 $
b00001110 %
#127
b11110010 #
b01001111 $
b01000001 %
#128
b01000100 #
b00001011 $
b01001111 %
#129
b11011110 #
b11000011 $
b10100001 %
#130
b10010011 #
b11000100 $
b01010111 %
#131
b10000110 #
b01100101 $
b11101011 %
#132
b11101000 #
b01011100 $
b01000100 %
#133
b10011101 #
b11100010 $
b01111111 %
#134
b10010010 #
b10010010 $
b00100100 %
#135
b01011001 #
b00100100 $
b01111101 %
#136
b11101101 #
b10111000 $
b10100101 %
#137
b01010010 #
b01100100 $
b10110110 %
#138
b01110101 #
b10100001 $
b00010110 %
#139
b11010001 #
b10101010 $
b01111011 %
#140
b01000101 #
b10110010 $
b11110111 %
#141
b00011101 #
b10011001 $
b10110110 %
#142
b10000100 #
b00010100 $
b10011000 %
#143
b11110010 #
b00110001 $
b00100011 %
#144
b10011101 #
b00010001 $
b10101110 %
#145
b11111101 #
b11100111 $
b11100100 %
#146
b11001101 #
b00011011 $
b11101000 %
#147
b10100100 #
b11100010 $
b10000110 %
#148
b11000000 #
b01110010 $
b00110010 %
#149
b00110101 #
b01101001 $
b10011110 %
#150
b11110000 #
b00001001 $
b11111001 %
#151
b00001000 #
b10010000 $
b10011000 %
#152
b10110010 #
b00111001 $
b11101011 %
#153
b01111010 #
b10000011 $
b11111101 %
#154
b10110010 #
b10010010 $
b01000100 %
#155
b11100110 #
b00100010 $
b00001000 %
#156
b10101001 #
b01110111 $
b00100000 %
#157
b00000100 #
b11100111 $
b11101011 %
#158
b11001111 #
b00010000 $
b11011111 %
#159
b00111100 #
b11110111 $
b00110011 %
#160
b01110110 #
b01101110 $
b11100100 %
#161
b01100110 #
b10000110 $
b11101100 %
#162
b00111101 #
b10010001 $
b11001110 %
#163
b00100001 #
b11111110 $
b00011111 %
#164
b00010000 #
b11001110 $
b11011110 %
#165
b00000110 #
b01101000 $
b01101110 %
#166
b00010000 #
b11011011 $
b11101011 %
#167
b11111010 #
b11010111 $
b11010001 %
#168
b00111111 #
b10000111 $
b11000110 %
#169
b01000010 #
b11011000 $
b00011010 %
#170
b10100001 #
b01001000 $
b11101001 %
#171
b10101101 #
b11001010 $
b01110111 %
#172
b11111001 #
b01000111 $
b01000000 %
#173
b01010011 #
b10100111 $
b11111010 %
#174
b01001001 #
b10000010 $
b11001011 %
#175
b10010000 #
b00011111 $
b10101111 %
#176
b00100000 #
b01100010 $
b10000010 %
#177
b00110000 #
b00101100 $
b01011100 %
#178
b00110011 #
b01100100 $
b10010111 %
#179
b00111000 #
b01000100 $
b01111100 %
#180
b01010000 #
b11000011 $
b00010011 %
#181
b11000111 #
b11100101 $
b10101100 %
#182
b01111111 #
b11101101 $
b01101100 %
#183
b10001110 #
b10001111 $
b00011101 %
#184
b10110111 #
b11101011 $
b10100010 %
#185
b01111011 #
b10100001 $
b00011100 %
#186
b10010111 #
b11110011 $
b10001010 %
#187
b00111011 #
b00100001 $
b01011100 %
#188
b10110110 #
b00101001 $
b11011111 %
#189
b00011010 #
b10100010 $
b10111100 %
#190
b11111100 #
b10000011 $
b01111111 %
#191
b01101101 #
b01000101 $
b10110010 %
#192
b01100011 #
b01111110 $
b11100001 %
#193
b01101111 #
b11000101 $
b00110100 %
#194
b01110100 #
b10010010 $
b00000110 %
#195
b11011000 #
b01010100 $
b00101100 %
#196
b01000111 #
b11111001 $
b01000000 %
#197
b10001010 #
b01101001 $
b11110011 %
#198
b00110101 #
b10010110 $
b11001011 %
#199
b01100100 #
b00010100 $
b01111000 %
#200
b00011101 #
b11100000 $
b11111101 %
#201
b10101110 #
b11101100 $
b10011010 %
#202
b00001011 #
b00110111 $
b01000010 %
#203
b01001001 #
b00101100 $
b01110101 %
#204
b11110101 #
b01101001 $
b01011110 %
#205
b10111100 #
b10001110 $
b01001010 %
#206
b01011100 #
b11001101 $
b00101001 %
#207
b11111000 #
b01001101 $
b01000101 %
#208
b11000001 #
b01000101 $
b00000110 %
#209
b00110000 #
b01000010 $
b01110010 %
#210
b10111101 #
b00001101 $
b11001010 %
#211
b01111001 #
b11111110 $
b01110111 %
#212
b11101111 #
b00111111 $
b00101110 %
#213
b01101110 #
b00110011 $
b10100001 %
#214
b00011101 #
b01010011 $
b01110000 %
#215
b11001000 #
b11100101 $
b10101101 %
#216
b11101010 #
b01001001 $
b00110011 %
#217
b01101101 #
b00011011 $
b10001000 %
#218
b10111000 #
b10110001 $
b01101001 %
#219
b10010001 #
b11010000 $
b01100001 %
#220
b10010011 #
b00111000 $
b11001011 %
#221
b11110110 #
b00010000 $
b00000110 %
#222
b10001110 #
b10100000 $
b00101110 %
#223
b10110110 #
b01001100 $
b00000010 %
#224
b10001000 #
b01010011 $
b11011011 %
#225
b01011111 #
b11010001 $
b00110000 %
#226
b11100000 #
b11100000 $
b11000000 %
#227
b11010010 #
b10101101 $
b01111111 %
#228
b10001111 #
b01101011 $
b11111010 %
#229
b01000111 #
b10010000 $
b11010111 %
#230
b11111101 #
b11011011 $
b11011000 %
#231
b01000000 #
b10100101 $
b11100101 %
#232
b10100101 #
b11100100 $
b10001001 %
#233
b00011001 #
b10010011 $
b10101100 %
#234
b00111111 #
b10100000 $
b11011111 %
#235
b11010111 #
b10111011 $
b10010010 %
#236
b01111101 #
b01010000 $
b11001101 %
#237
b01101010 #
b11101010 $
b01010100 %
#238
b01000100 #
b00100110 $
b01101010 %
#239
b11101011 #
b00110100 $
b00011111 %
#240
b10110100 #
b01111010 $
b00101110 %
#241
b10110001 #
b01110011 $
b00100100 %
#242
b10111110 #
b10011110 $
b01011100 %
#243
b10011011 #
b00100111 $
b11000010 %
#244
b10111011 #
b10011111 $
b01011010 %
#245
b11101111 #
b10010111 $
b10000110 %
#246
b01100100 #
b00111101 $
b10100001 %
#247
b01000000 #
b00100001 $
b01100001 %
#248
b01101110 #
b00001000 $
b01110110 %
#249
b01110000 $
b11011110 %
#250
b11000000 #
b00100001 $
b11100001 %
#251
b11111101 #
b01111100 $
b01111001 %
#252
b10001011 #
b10101010 $
b00110101 %
#253
b01000001 #
b01101000 $
b10101001 %
#254
b00000000 #
b11001011 $
b11001011 %
#255
b00101100 #
b11001010 $
b11110110 %
#256
b01010100 #
b00100101 $
b01111001 %
#257
b00110111 #
b00101111 $
b01100110 %
#258
b10001100 #
b10000110 $
b00010010 %
#259
b11011011 #
b11001111 $
b10101010 %
#260
b00010010 #
b01100100 $
b01110110 %
#261
b10101100 #
b10101101 $
b01011001 %
#262
b00001000 #
b10011010 $
b10100010 %
#263
b11010100 #
b11100111 $
b10111011 %
#264
b10111110 #
b01001100 $
b00001010 %
#265
b00110000 #
b10000000 $
b10110000 %
#266
b10001101 #
b10001000 $
b00010101 %
#267
b00111010 #
b11010010 $
b00001100 %
#268
b10111111 #
b01111110 $
b00111101 %
#269
b00100000 #
b00001000 $
b00101000 %
#270
b01001110 #
b01010000 $
b10011110 %
#271
b11001000 #
b11111011 $
b11000011 %
#272
b10001000 #
b10011001 $
b00100001 %
#273
b11000100 #
b11100001 $
b10100101 %
#274
b11100111 #
b11111010 $
b11100001 %
#275
b10101111 #
b10001011 $
b00111010 %
#276
b01110011 #
b11111101 $
b01110000 %
#277
b11101110 #
b10001001 $
b01110111 %
#278
b00000100 #
b11000110 $
b11001010 %
#279
b00100100 #
b01000110 $
b01101010 %
#280
b00000000 #
b10011100 $
b10011100 %
#281
b10010001 #
b11100010 $
b01110011 %
#282
b00111001 #
b11010111 $
b00010000 %
#283
b01100110 #
b00011110 $
b10000100 %
#284
b11110000 #
b11001101 $
b10111101 %
#285
b00111110 #
b00000010 $
b01000000 %
#286
b00101010 #
b01011011 $
b10000101 %
#287
b11001000 #
b00101111 $
b11110111 %
#288
b00111101 #
b01000000 $
b01111101 %
#289
b01010000 #
b01100111 $
b10110111 %
#290
b10101111 #
b00010110 %
#291
b10011000 #
b01111111 $
b00010111 %
#292
b01101100 #
b10011010 $
b00000110 %
#293
b01110010 #
b10100111 $
b00011001 %
#294
b10111101 #
b00111111 $
b11111100 %
#295
b10101010 #
b10101101 $
b01010111 %
#296
b11010111 #
b10011101 $
b01110100 %
#297
b10110011 #
b11110101 $
b10101000 %
#298
b11100010 #
b11000111 $
b10101001 %
#299
b00011010 #
b01100111 $
b10000001 %
#300
b00110111 #
b01010011 $
b10001010 %
#301
b00001001 #
b11111101 $
b00000110 %
#302
b01000110 #
b00000110 $
b01001100 %
#303
b01010110 #
b01010000 $
b10100110 %
#304
b10000111 #
b01100001 $
b11101000 %
#305
b10001010 #
b01001001 $
b11010011 %
#306
b11101111 #
b10010011 $
b10000010 %
#307
b00010001 #
b01111111 $
b10010000 %
#308
b10001001 #
b10101100 $
b00110101 %
#309
b11110010 #
b10101000 $
b10011010 %
#310
b00100100 #
b10101100 $
b11010000 %
#311
b01010100 #
b10001100 $
b11100000 %
#312
b11000100 #
b00000100 $
b11001000 %
#313
b00011111 #
b10010100 $
b10110011 %
#314
b11110010 #
b10001111 $
b10000001 %
#315
b01011100 #
b01100111 $
b11000011 %
#316
b01110001 #
b10101111 $
b00100000 %
#317
b00100001 #
b11001011 $
b11101100 %
#318
b10101100 #
b00100110 $
b11010010 %
#319
b10001111 #
b11110011 $
b10000010 %
#320
b10001010 #
b01110010 $
b11111100 %
#321
b10000110 #
b00110001 $
b10110111 %
#322
b01010011 #
b00100001 $
b01110100 %
#323
b00011101 #
b00110110 $
b01010011 %
#324
b11110011 #
b10111001 $
b10101100 %
#325
b01000110 #
b10001110 $
b11010100 %
#326
b11111101 #
b01010100 $
b01010001 %
#327
b01010001 #
b11001111 $
b00100000 %
#328
b01000111 #
b00111000 $
b01111111 %
#329
b10111000 #
b01110111 $
b00101111 %
#330
b11101011 #
b10011101 $
b10001000 %
#331
b10000111 #
b10100011 $
b00101010 %
#332
b11000110 #
b11010011 $
b10011001 %
#333
b10101001 #
b00110000 $
b11011001 %
#334
b10110010 #
b00011001 $
b11001011 %
#335
b00101110 #
b00101100 $
b01011010 %
#336
b01101101 #
b01001100 $
b10111001 %
#337
b11101011 #
b00010000 $
b11111011 %
#338
b10001101 #
b10111010 $
b01000111 %
#339
b10101001 #
b01001010 $
b11110011 %
#340
b11011010 #
b01111100 $
b01010110 %
#341
b00011100 #
b10111101 $
b11011001 %
#342
b00111100 #
b00111011 $
b01110111 %
#343
b00001001 #
b00011001 $
b00100010 %
#344
b00100011 #
b10110101 $
b11011000 %
#345
b01000000 #
b10011010 $
b11011010 %
#346
b11000001 #
b10100101 $
b01100110 %
#347
b01110110 #
b01010010 $
b11001000 %
#348
b11011100 #
b00110000 $
b00001100 %
#349
b01111111 #
b00101101 $
b10101100 %
#350
b00110011 #
b11001011 $
b11111110 %
#351
b00100110 #
b00111101 $
b01100011 %
#352
b00010010 #
b10110001 $
b11000011 %
#353
b10110010 #
b10000001 $
b00110011 %
#354
b01011000 #
b00110001 $
b10001001 %
#355
b01000010 #
b10001011 $
b11001101 %
#356
b10100001 #
b10101100 $
b01001101 %
#357
b10000010 #
b00110000 $
b10110010 %
#358
b00101111 #
b10111101 $
b11101100 %
#359
b10101110 #
b10110010 $
b01100000 %
#360
b10111111 #
b11101111 $
b10101110 %
#361
b01001011 #
b11111001 $
b01000100 %
#362
b10101010 #
b01000011 $
b11101101 %
#363
b11011101 #
b01001111 $
b00101100 %
#364
b01100110 #
b01001010 $
b10110000 %
#365
b01011110 #
b10111011 $
b00011001 %
#366
b11011100 #
b10000100 $
b01100000 %
#367
b00111101 #
b00000101 $
b01000010 %
#368
b00010001 #
b10001100 $
b10011101 %
#369
b00101111 #
b01010101 $
b10000100 %
#370
b10000100 #
b10011101 $
b00100001 %
#371
b10110011 #
b01100101 $
b00011000 %
#372
b00101011 #
b11011011 $
b00000110 %
#373
b01001011 #
b01001001 $
b10010100 %
#374
b10110010 #
b10100010 $
b01010100 %
#375
b00011100 #
b11001110 $
b11101010 %
#376
b00101111 #
b11100110 $
b00010101 %
#377
b11000011 #
b01100011 $
b00100110 %
#378
b00000110 #
b00000001 $
b00000111 %
#379
b10111011 #
b01000000 $
b11111011 %
#380
b10010010 #
b11001110 $
b01100000 %
#381
b00001101 #
b00101110 $
b00111011 %
#382
b00010010 #
b00010100 $
b00100110 %
#383
b00111010 #
b01100001 $
b10011011 %
#384
b00110111 #
b11000110 $
b11111101 %
#385
b01000001 #
b10101000 $
b11101001 %
#386
b11111001 #
b11101010 $
b11100011 %
#387
b01010100 #
b00111010 $
b10001110 %
#388
b10101110 #
b10001110 $
b00111100 %
#389
b11010001 #
b00010010 $
b11100011 %
#390
b11100111 #
b00001011 $
b11110010 %
#391
b00100100 #
b01001000 $
b01101100 %
#392
b01000110 #
b00110100 $
b01111010 %
#393
b10001101 #
b10111101 $
b01001010 %
#394
b01000010 #
b01010011 $
b10010101 %
#395
b00000101 #
b11101100 $
b11110001 %
#396
b10100000 #
b01000000 $
b11100000 %
#397
b11010011 #
b11101011 $
b10111110 %
#398
b00100111 #
b10110110 $
b11011101 %
#399
b10111010 #
b00110010 $
b11101100 %
#400
b00111100 #
b00011011 $
b01010111 %
#401
b11001111 #
b11100110 $
b10110101 %
#402
b10111000 #
b00110000 $
b11101000 %
#403
b11111001 #
b01110010 $
b01101011 %
#404
b01011010 #
b01000001 $
b10011011 %
#405
b00111111 #
b10110101 $
b11110100 %
#406
b11100100 #
b01011111 $
b01000011 %
#407
b11010111 #
b00010110 $
b11101101 %
#408
b11000110 #
b00001110 $
b11010100 %
#409
b10100110 #
b01011111 $
b00000101 %
#410
b00111111 #
b11100000 $
b00011111 %
#411
b11101010 #
b11001111 $
b10111001 %
#412
b10000111 #
b10101110 $
b00110101 %
#413
b10001100 #
b01111000 $
b00000100 %
#414
b10111110 #
b10101110 $
b01101100 %
#415
b11010100 #
b11011111 $
b10110011 %
#416
b00000100 #
b10011101 $
b10100001 %
#417
b00110000 #
b01101011 $
b10011011 %
#418
b11110000 #
b00010110 $
b00000110 %
#419
b10010000 #
b01011110 $
b11101110 %
#420
b10010010 #
b01101100 $
b11111110 %
#421
b10111001 #
b11000101 $
b01111110 %
#422
b10000111 #
b10110001 $
b00111000 %
#423
b10011110 #
b11100100 $
b10000010 %
#424
b01001010 #
b11110011 $
b00111101 %
#425
b11001101 #
b10010101 $
b01100010 %
#426
b00010011 #
b01000001 $
b01010100 %
#427
b11111101 #
b10100110 $
b10100011 %
#428
b10000010 #
b11010010 $
b01010100 %
#429
b10101000 #
b11000000 $
b01101000 %
#430
b10010111 #
b10100110 $
b00111101 %
#431
b00001010 #
b00000111 $
b00010001 %
#432
b10010010 #
b11001001 $
b01011011 %
#433
b00011001 #
b10000001 $
b10011010 %
#434
b11101011 #
b10101100 $
b10010111 %
#435
b00001111 #
b11100001 $
b11110000 %
#436
b01100011 #
b11011101 $
b01000000 %
#437
b10110100 #
b00011011 $
b11001111 %
#438
b01101000 #
b01111010 $
b11100010 %
#439
b00011001 #
b11110011 $
b00001100 %
#440
b00110011 #
b11001100 $
b11111111 %
#441
b11111101 #
b01110101 $
b01110010 %
#442
b01110110 #
b01000010 $
b10111000 %
#443
b01111000 #
b01011110 $
b11010110 %
#444
b00110011 #
b11111100 $
b00101111 %
#445
b00101010 #
b00101110 $
b01011000 %
#446
b00111111 #
b10010011 $
b11010010 %
#447
b00001101 #
b00000111 $
b00010100 %
#448
b11011110 #
b10011100 $
b01111010 %
#449
b01111000 #
b01100001 $
b11011001 %
#450
b00000100 #
b10100100 $
b10101000 %
#451
b00101000 #
b11000100 $
b11101100 %
#452
b01100101 $
b10001101 %
#453
b11110111 #
b11111001 $
b11110000 %
#454
b00011100 #
b01100010 $
b01111110 %
#455
b01010010 #
b00100101 $
b01110111 %
#456
b10101110 #
b00100110 $
b11010100 %
#457
b11010001 #
b10010110 $
b01100111 %
#458
b01011111 #
b00010100 $
b01110011 %
#459
b01010110 #
b10101111 $
b00000101 %
#460
b11110101 #
b10110100 $
b10101001 %
#461
b00010110 #
b00000000 $
b00010110 %
#462
b00010001 #
b01000010 $
b01010011 %
#463
b11011001 #
b10100010 $
b01111011 %
#464
b00101011 #
b10001111 $
b10111010 %
#465
b10100011 #
b00011110 $
b11000001 %
#466
b01101011 #
b01110010 $
b11011101 %
#467
b10011111 #
b10100001 $
b01000000 %
#468
b10000100 #
b11011011 $
b01011111 %
#469
b11001010 #
b01001011 $
b00010101 %
#470
b11010011 #
b10100000 $
b01110011 %
#471
b01010110 #
b10001111 $
b11100101 %
#472
b01100000 #
b01100110 $
b11000110 %
#473
b01100011 #
b10100001 $
b00000100 %
#474
b10110011 #
b00101001 $
b11011100 %
#475
b10000010 #
b10100100 $
b00100110 %
#476
b11101001 #
b10100010 $
b10001011 %
#477
b10000000 #
b01110110 $
b11110110 %
#478
b00101010 #
b01010001 $
b01111011 %
#479
b00110111 #
b10101011 $
b11100010 %
#480
b01101110 #
b01100010 $
b11010000 %
#481
b01001001 #
b11110110 $
b00111111 %
#482
b11100110 #
b10010101 $
b01111011 %
#483
b01110001 #
b01001010 $
b10111011 %
#484
b11011101 #
b00111110 $
b00011011 %
#485
b00011110 #
b10111101 $
b11011011 %
#486
b10100100 #
b00010010 $
b10110110 %
#487
b01001100 #
b00100100 $
b01110000 %
#488
b10101101 #
b00100001 $
b11001110 %
#489
b01001110 #
b10100000 $
b11101110 %
#490
b10010100 #
b10101100 $
b01000000 %
#491
b10011101 #
b00100000 $
b10111101 %
#492
b11100110 #
b00110010 $
b00011000 %
#493
b11101010 #
b10011000 $
b10000010 %
#494
b11100001 #
b01001111 $
b00110000 %
#495
b00110010 #
b00010010 $
b01000100 %
#496
b11010110 #
b01110101 $
b01001011 %
#497
b10001011 #
b00101000 $
b10110011 %
#498
b01100011 #
b01010101 $
b10111000 %
#499
b10110101 #
b00111111 $
b11110100 %
#500
b00011011 #
b10110100 $
b11001111 %
#501
b01110101 #
b11010000 $
b01000101 %
#502
b10110011 #
b01000110 $
b11111001 %
#503
b01101011 #
b00110011 $
b10011110 %
#504
b01011110 #
b10010000 $
b11101110 %
#505
b00111011 #
b11000110 $
b00000001 %
#506
b10101001 #
b01011100 $
b00000101 %
#507
b01011001 #
b00011100 $
b01110101 %
#508
b01010100 #
b01001100 $
b10100000 %
#509
b11000100 #
b11101101 $
b10110001 %
#510
b11001000 #
b11101110 $
b10110110 %
#511
b00001010 #
b10001010 $
b10010100 %
#512
b10000100 #
b01100011 $
b11100111 %
#513
b11000011 #
b01110100 $
b00110111 %
#514
b01010011 #
b00100010 $
b01110101 %
#515
b10111110 #
b10110011 $
b01110001 %
#516
b01100010 #
b10111001 $
b00011011 %
#517
b11001010 #
b10100001 $
b01101011 %
#518
b00011111 #
b01101101 $
b10001100 %
#519
b01100101 #
b10001100 $
b11110001 %
#520
b10000000 #
b00100111 $
b10100111 %
#521
b10000011 #
b10001000 $
b00001011 %
#522
b00011110 #
b11011101 $
b11111011 %
#523
b01101001 #
b10111101 $
b00100110 %
#524
b00000010 #
b10010100 $
b10010110 %
#525
b11110101 #
b01001100 $
b01000001 %
#526
b10101111 #
b01001010 $
b11111001 %
#527
b11111011 #
b11111000 $
b11110011 %
#528
b00101111 #
b00100110 $
b01010101 %
#529
b11000011 #
b01101010 $
b00101101 %
#530
b00100010 #
b01011011 $
b01111101 %
#531
b11001101 #
b11111100 $
b11001001 %
#532
b11111110 #
b11110011 $
b11110001 %
#533
b10100111 #
b00010011 $
b10111010 %
#534
b00100001 #
b00110111 $
b01011000 %
#535
b01001001 #
b01100110 $
b10101111 %
#536
b10011001 #
b00100110 $
b10111111 %
#537
b10111100 #
b11001100 $
b10001000 %
#538
b01001101 #
b00000101 $
b01010010 %
#539
b01100110 #
b00101000 $
b10001110 %
#540
b00000000 #
b10101101 $
b10101101 %
#541
b10001100 #
b11111110 $
b10001010 %
#542
b10100010 #
b10111100 $
b01011110 %
#543
b00111011 #
b01100100 $
b10011111 %
#544
b01001110 #
b11011111 $
b00101101 %
#545
b11110110 #
b00101101 $
b00100011 %
#546
b00010011 #
b10100010 $
b10110101 %
#547
b00100010 #
b10111101 $
b11011111 %
#548
b00010111 #
b01100111 $
b01111110 %
#549
b10110101 #
b01011101 $
b00010010 %
#550
b10001110 #
b10100111 $
b00110101 %
#551
b10100011 #
b00100101 $
b11001000 %
#552
b10100101 #
b00010010 $
b10110111 %
#553
b11100101 #
b10111001 $
b10011110 %
#554
b00110001 #
b00100011 $
b01010100 %
#555
b00000001 #
b10011011 $
b10011100 %
#556
b00010100 #
b01000001 $
b01010101 %
#557
b10110001 #
b10101001 $
b01011010 %
#558
b00001001 #
b01110001 $
b01111010 %
#559
b10101100 #
b10101000 $
b01010100 %
#560
b00000000 #
b01110100 $
b01110100 %
#561
b10101110 #
b10001001 $
b00110111 %
#562
b00111010 #
b10100011 $
b11011101 %
#563
b11100110 #
b11000001 $
b10100111 %
#564
b01000001 #
b00010001 $
b01010010 %
#565
b00011110 #
b11010100 $
b11110010 %
#566
b00010001 #
b01011011 $
b01101100 %
#567
b00000001 #
b01010101 $
b01010110 %
#568
b00010000 #
b00110111 $
b01000111 %
#569
b11000111 #
b00011010 $
b11100001 %
#570
b10111101 #
b01010111 $
b00010100 %
#571
b01100100 #
b10001011 $
b11101111 %
#572
b01001111 #
b00110101 $
b10000100 %
#573
b10111010 #
b11110111 $
b10110001 %
#574
b10110110 #
b00001110 $
b11000100 %
#575
b00000000 #
b10111100 $
b10111100 %
#576
b00101011 #
b00111100 $
b01100111 %
#577
b11110100 #
b10010110 $
b10001010 %
#578
b10100010 #
b00100010 $
b11000100 %
#579
b01010110 #
b11110000 $
b01000110 %
#580
b01011000 #
b10111011 $
b00010011 %
#581
b00101111 #
b00011011 $
b01001010 %
#582
b00110010 #
b01000100 $
b01110110 %
#583
b01101011 #
b01000110 $
b10110001 %
#584
b10000111 #
b10111101 $
b01000100 %
#585
b00001111 #
b11011000 $
b11100111 %
#586
b01010010 #
b11001100 $
b00011110 %
#587
b01010001 #
b10110101 $
b00000110 %
#588
b01000000 #
b11001110 $
b00001110 %
#589
b10100011 #
b10001100 $
b00101111 %
#590
b11010111 #
b00111101 $
b00010100 %
#591
b11001011 #
b11111101 $
b11001000 %
#592
b00111011 #
b10011010 $
b11010101 %
#593
b01001110 #
b00001110 $
b01011100 %
#594
b11110000 #
b11110100 $
b11100100 %
#595
b11100101 #
b11000101 $
b10101010 %
#596
b01100111 #
b11010101 $
b00111100 %
#597
b01010001 #
b01000001 $
b10010010 %
#598
b00100010 $
b01110011 %
#599
b10000000 #
b00100111 $
b10100111 %
#600
b00000100 #
b00000100 $
b00001000 %
#601
b00100111 #
b01011101 $
b10000100 %
#602
b00111111 #
b11100111 $
b00100110 %
#603
b01000101 #
b10001110 $
b11010011 %
#604
b10010111 #
b10010100 $
b00101011 %
#605
b01111001 #
b11000110 $
b00111111 %
#606
b11111111 #
b01010010 $
b01010001 %
#607
b10100011 #
b01111000 $
b00011011 %
