src/tests/resources/operation/comb/sub/sub.sv
// Generated by CIRCT firtool-1.71.0
module Foo(	// comb/sub/sub.generic.mlir:3:3
  input  [7:0] a,	// comb/sub/sub.generic.mlir:4:8
               b,	// comb/sub/sub.generic.mlir:4:19
  output [7:0] res	// comb/sub/sub.mlir:1:42
);

  assign res = a - b;	// comb/sub/sub.generic.mlir:5:10, :6:5
endmodule

src/tests/resources/operation/comb/sub/test.vcd
$version Generated by KCIRCT $end
$timescale 1s $end
 $scope module Foo $end
  $var wire 8 } a [7:0] $end
  $var wire 8 ~ b [7:0] $end
  $var wire 8 !" res [7:0] $end
  $scope module Foo $end
   $var wire 8 } a [7:0] $end
   $var wire 8 ~ b [7:0] $end
   $var wire 8 !" res [7:0] $end
  $upscope $end
 $upscope $end
$enddefinitions $end

#0
b11101111 }
b11100100 ~
b00001011 !"

#1
b00011010 }
b01011100 ~
b10111110 !"

#2
b00101100 }
b10010010 ~
b10011010 !"

#3
b11011111 }
b00000011 ~
b11011100 !"

#4
b00101100 }
b10100000 ~
b10001100 !"

#5
b11111111 }
b11010000 ~
b00101111 !"

#6
b10011101 }
b11100101 ~
b10111000 !"

#7
b00000000 }
b01100100 ~
b10011100 !"

#8
b10100100 }
b01010110 ~
b01001110 !"

#9
b11110111 }
b00010100 ~
b11100011 !"

#10
b00000010 }
b00000000 ~
b00000010 !"

#11
b01011011 }
b10111001 ~
b10100010 !"

#12
b01110111 }
b01100001 ~
b00010110 !"

#13
b10011111 }
b00100011 ~
b01111100 !"

#14
b11100101 }
b11111001 ~
b11101100 !"

#15
b00001111 }
b01100010 ~
b10101101 !"

#16
b10000101 }
b11010110 ~
b10101111 !"

#17
b10001100 }
b11000011 ~
b11001001 !"

#18
b00000011 }
b00100110 ~
b11011101 !"

#19
b01101110 }
b00101110 ~
b01000000 !"

#20
b11110000 }
b00000001 ~
b11101111 !"

#21
b00100000 }
b01001010 ~
b11010110 !"

#22
b01001100 }
b11101011 ~
b01100001 !"

#23
b01101100 }
b11110001 ~
b01111011 !"

#24
b10101010 }
b10010011 ~
b00010111 !"

#25
b01010110 }
b00110001 ~
b00100101 !"

#26
b00011111 }
b10111000 ~
b01100111 !"

#27
b11110111 }
b10010001 ~
b01100110 !"

#28
b11000101 }
b01011110 ~
b01100111 !"

#29
b01000010 }
b11011111 ~
b01100011 !"

#30
b10000100 }
b11001000 ~
b10111100 !"

#31
b10000011 }
b01010011 ~
b00110000 !"

#32
b11111010 }
b10010010 ~
b01101000 !"

#33
b00101110 }
b10010110 ~
b10011000 !"

#34
b01001101 }
b01001001 ~
b00000100 !"

#35
b01101101 }
b01001000 ~
b00100101 !"

#36
b00101101 }
b00000110 ~
b00100111 !"

#37
b11001101 }
b11101111 ~
b11011110 !"

#38
b00000110 }
b00111101 ~
b11001001 !"

#39
b10011001 }
b01110110 ~
b00100011 !"

#40
b10100111 }
b00101101 ~
b01111010 !"

#41
b01101010 }
b01100010 ~
b00001000 !"

#42
b00011010 }
b01101011 ~
b10101111 !"

#43
b01001011 }
b00001010 ~
b01000001 !"

#44
b01100001 }
b10011110 ~
b11000011 !"

#45
b11011011 }
b01111011 ~
b01100000 !"

#46
b10010110 }
b00101001 ~
b01101101 !"

#47
b11010111 }
b11110010 ~
b11100101 !"

#48
b01101000 }
b00001001 ~
b01011111 !"

#49
b01101011 }
b11001001 ~
b10100010 !"

#50
b01011011 }
b11111110 ~
b01011101 !"

#51
b11001001 }
b00011000 ~
b10110001 !"

#52
b01000100 }
b11100001 ~
b01100011 !"

#53
b11100100 }
b01001111 ~
b10010101 !"

#54
b11010111 }
b10111101 ~
b00011010 !"

#55
b00111101 }
b11010010 ~
b01101011 !"

#56
b00111100 }
b10101011 ~
b10010001 !"

#57
b01001011 }
b10010001 ~
b10111010 !"

#58
b01011111 }
b10110101 ~
b10101010 !"

#59
b10010001 }
b00000101 ~
b10001100 !"

#60
b10111110 }
b10000010 ~
b00111100 !"

#61
b00111110 }
b00111110 ~
b00000000 !"

#62
b01100101 }
b10011000 ~
b11001101 !"

#63
b11110110 }
b00000011 ~
b11110011 !"

#64
b11010111 }
b01010010 ~
b10000101 !"

#65
b00100101 }
b00101011 ~
b11111010 !"

#66
b01101111 }
b01000010 ~
b00101101 !"

#67
b00110010 }
b00111011 ~
b11110111 !"

#68
b11101100 }
b10011000 ~
b01010100 !"

#69
b00101000 }
b00100101 ~
b00000011 !"

#70
b00010011 }
b01100101 ~
b10101110 !"

#71
b00010000 }
b00010000 ~
b00000000 !"

#72
b01011001 }
b01010010 ~
b00000111 !"

#73
b10001000 }
b00001100 ~
b01111100 !"

#74
b11000010 }
b01011101 ~
b01100101 !"

#75
b11011110 }
b11001011 ~
b00010011 !"

#76
b10011101 }
b10011000 ~
b00000101 !"

#77
b11010100 }
b00001010 ~
b11001010 !"

#78
b00011110 }
b10010111 ~
b10000111 !"

#79
b10001001 }
b01110011 ~
b00010110 !"

#80
b10011000 }
b00101101 ~
b01101011 !"

#81
b01011000 }
b00000101 ~
b01010011 !"

#82
b01111010 }
b11010011 ~
b10100111 !"

#83
b11101110 }
b10000010 ~
b01101100 !"

#84
b11001000 }
b10101011 ~
b00011101 !"

#85
b01100110 }
b00101011 ~
b00111011 !"

#86
b01110101 }
b11110010 ~
b10000011 !"

#87
b11111111 }
b10000010 ~
b01111101 !"

#88
b01111001 }
b01111000 ~
b00000001 !"

#89
b00000000 }
b11111111 ~
b00000001 !"

#90
b11110011 }
b10001101 ~
b01100110 !"

#91
b10111100 }
b00001110 ~
b10101110 !"

#92
b10111010 }
b01001100 ~
b01101110 !"

#93
b00001111 }
b11001000 ~
b01000111 !"

#94
b00101100 }
b01111011 ~
b10110001 !"

#95
b10010010 }
b11100000 ~
b10110010 !"

#96
b11101111 }
b00101011 ~
b11000100 !"

#97
b10111001 }
b10010010 ~
b00100111 !"

#98
b01001010 }
b01100011 ~
b11100111 !"

#99
b01010100 }
b01001000 ~
b00001100 !"

#100
b11010000 }
b10111011 ~
b00010101 !"

#101
b01100001 }
b01000111 ~
b00011010 !"

#102
b01000010 }
b01110011 ~
b11001111 !"

#103
b11111000 }
b10001111 ~
b01101001 !"

#104
b10101001 }
b00011010 ~
b10001111 !"

#105
b00110111 }
b10101111 ~
b10001000 !"

#106
b01111101 }
b00110110 ~
b01000111 !"

#107
b11110101 }
b11111010 ~
b11111011 !"

#108
b11000011 }
b10011001 ~
b00101010 !"

#109
b01110110 }
b00101101 ~
b01001001 !"

#110
b01010010 }
b01011101 ~
b11110101 !"

#111
b01011101 }
b10101011 ~
b10110010 !"

#112
b00011011 }
b10101010 ~
b01110001 !"

#113
b11000110 }
b10010011 ~
b00110011 !"

#114
b11101000 }
b10010000 ~
b01011000 !"

#115
b01011011 }
b00011111 ~
b00111100 !"

#116
b11010110 }
b10111000 ~
b00011110 !"

#117
b10100111 }
b00001010 ~
b10011101 !"

#118
b10010000 }
b01101001 ~
b00100111 !"

#119
b01001000 }
b10100000 ~
b10101000 !"

#120
b01110100 }
b00011000 ~
b01011100 !"

#121
b00001001 }
b00000011 ~
b00000110 !"

#122
b00111110 }
b10110011 ~
b10001011 !"

#123
b01001100 }
b11100001 ~
b01101011 !"

#124
b11001000 }
b11001110 ~
b11111010 !"

#125
b11001010 }
b10001010 ~
b01000000 !"

#126
b10001110 }
b11000010 ~
b11001100 !"

#127
b11101101 }
b10001000 ~
b01100101 !"

#128
b11100011 }
b10101000 ~
b00111011 !"

#129
b00110010 }
b11001010 ~
b01101000 !"

#130
b10011000 }
b11101000 ~
b10110000 !"

#131
b10001010 }
b11000101 ~
b11000101 !"

#132
b01100111 }
b10011010 ~
b11001101 !"

#133
b11100101 }
b11110100 ~
b11110001 !"

#134
b01000001 }
b11001100 ~
b01110101 !"

#135
b10011111 }
b01000010 ~
b01011101 !"

#136
b00100101 }
b10000100 ~
b10100001 !"

#137
b10110111 }
b01010011 ~
b01100100 !"

#138
b11100101 }
b00101011 ~
b10111010 !"

#139
b01001111 }
b10011001 ~
b10110110 !"

#140
b01110000 }
b01001000 ~
b00101000 !"

#141
b01110000 }
b10101011 ~
b11000101 !"

#142
b00111100 }
b10011001 ~
b10100011 !"

#143
b01111111 }
b00010111 ~
b01101000 !"

#144
b10100100 }
b11111110 ~
b10100110 !"

#145
b00000001 }
b11010100 ~
b00101101 !"

#146
b00100011 }
b00011000 ~
b00001011 !"

#147
b11111001 }
b10010111 ~
b01100010 !"

#148
b01111000 }
b01011110 ~
b00011010 !"

#149
b10101010 }
b10011001 ~
b00010001 !"

#150
b10101110 }
b10100001 ~
b00001101 !"

#151
b11110110 }
b10001100 ~
b01101010 !"

#152
b00110110 }
b01001000 ~
b11101110 !"

#153
b11101001 }
b00000010 ~
b11100111 !"

#154
b11001011 }
b10011110 ~
b00101101 !"

#155
b00110111 }
b10001001 ~
b10101110 !"

#156
b10100111 }
b00101010 ~
b01111101 !"

#157
b01101011 }
b11001010 ~
b10100001 !"

#158
b11101001 }
b11100110 ~
b00000011 !"

#159
b01010000 }
b01010001 ~
b11111111 !"

#160
b00101010 }
b01000001 ~
b11101001 !"

#161
b10000101 }
b01000110 ~
b00111111 !"

#162
b10111011 }
b00010000 ~
b10101011 !"

#163
b01100110 }
b11101101 ~
b01111001 !"

#164
b10001100 }
b01011101 ~
b00101111 !"

#165
b10001110 }
b00101101 ~
b01100001 !"

#166
b01011101 }
b00101010 ~
b00110011 !"

#167
b01101011 }
b11010101 ~
b10010110 !"

#168
b11111111 }
b10011111 ~
b01100000 !"

#169
b01011011 }
b00001110 ~
b01001101 !"

#170
b01110010 }
b11011110 ~
b10010100 !"

#171
b10100001 }
b10011111 ~
b00000010 !"

#172
b11100111 }
b01000011 ~
b10100100 !"

#173
b10101011 }
b01100011 ~
b01001000 !"

#174
b01010011 }
b01110010 ~
b11100001 !"

#175
b11100100 }
b10111001 ~
b00101011 !"

#176
b11101101 }
b00100100 ~
b11001001 !"

#177
b00000011 }
b10110110 ~
b01001101 !"

#178
b00101110 }
b00001110 ~
b00100000 !"

#179
b01110010 }
b00011110 ~
b01010100 !"

#180
b10010100 }
b00100000 ~
b01110100 !"

#181
b10100101 }
b11111010 ~
b10101011 !"

#182
b01000000 }
b01100011 ~
b11011101 !"

#183
b11101000 }
b01101001 ~
b01111111 !"

#184
b00100001 }
b11011011 ~
b01000110 !"

#185
b01111011 }
b11110110 ~
b10000101 !"

#186
b10110100 }
b11010100 ~
b11100000 !"

#187
b00011000 }
b01111000 ~
b10100000 !"

#188
b01010100 }
b11100011 ~
b01110001 !"

#189
b11000111 }
b10011100 ~
b00101011 !"

#190
b01110001 }
b11111011 ~
b01110110 !"

#191
b10011000 }
b11011110 ~
b10111010 !"

#192
b01101101 }
b01110000 ~
b11111101 !"

#193
b11010101 }
b11001010 ~
b00001011 !"

#194
b10010011 }
b11110100 ~
b10011111 !"

#195
b11001110 }
b11011111 ~
b11101111 !"

#196
b01000111 }
b00000001 ~
b01000110 !"

#197
b11001001 }
b10111000 ~
b00010001 !"

#198
b01101111 }
b11011111 ~
b10010000 !"

#199
b10101101 }
b00001100 ~
b10100001 !"

#200
b11111011 }
b11010101 ~
b00100110 !"

#201
b00011000 }
b01110001 ~
b10100111 !"

#202
b11111011 }
b00001100 ~
b11101111 !"

#203
b00011101 }
b10010010 ~
b10001011 !"

#204
b00101101 }
b01010101 ~
b11011000 !"

#205
b01010000 }
b11011011 ~
b01110101 !"

#206
b11001100 }
b10110100 ~
b00011000 !"

#207
b11101101 }
b00000100 ~
b11101001 !"

#208
b11111100 }
b10010100 ~
b01101000 !"

#209
b10011001 }
b11010100 ~
b11000101 !"

#210
b00101100 }
b00000001 ~
b00101011 !"

#211
b11111011 }
b00110000 ~
b11001011 !"

#212
b01010010 }
b01100010 ~
b11110000 !"

#213
b01111110 }
b10000101 ~
b11111001 !"

#214
b10101011 }
b10111101 ~
b11101110 !"

#215
b11100101 }
b00000111 ~
b11011110 !"

#216
b00110000 }
b10100011 ~
b10001101 !"

#217
b01010011 }
b11111111 ~
b01010100 !"

#218
b10110101 }
b11100010 ~
b11010011 !"

#219
b00110100 }
b11010101 ~
b01011111 !"

#220
b01010000 }
b01100011 ~
b11101101 !"

#221
b01101101 }
b11001110 ~
b10011111 !"

#222
b10111000 }
b00110101 ~
b10000011 !"

#223
b00111111 }
b01100110 ~
b11011001 !"

#224
b11101101 }
b01101100 ~
b10000001 !"

#225
b10110111 }
b01111010 ~
b00111101 !"

#226
b11101101 }
b00001001 ~
b11100100 !"

#227
b01101100 }
b00010011 ~
b01011001 !"

#228
b00101110 }
b10101000 ~
b10000110 !"

#229
b11010101 }
b01110011 ~
b01100010 !"

#230
b11010100 }
b11110101 ~
b11011111 !"

#231
b10100101 }
b10100110 ~
b11111111 !"

#232
b01111110 }
b11000000 ~
b10111110 !"

#233
b01000111 }
b11101111 ~
b01011000 !"

#234
b10111101 }
b00001110 ~
b10101111 !"

#235
b00100110 }
b10000100 ~
b10100010 !"

#236
b10111111 }
b11110101 ~
b11001010 !"

#237
b11000111 }
b01011010 ~
b01101101 !"

#238
b10010100 }
b01110000 ~
b00100100 !"

#239
b01011001 }
b00001010 ~
b01001111 !"

#240
b00100011 }
b01110001 ~
b10110010 !"

#241
b11100000 }
b10000001 ~
b01011111 !"

#242
b10010001 }
b00110011 ~
b01011110 !"

#243
b00001100 }
b11011001 ~
b00110011 !"

#244
b01100111 }
b10110111 ~
b10110000 !"

#245
b01000100 }
b10110011 ~
b10010001 !"

#246
b10011011 }
b00110100 ~
b01100111 !"

#247
b10100101 }
b10111111 ~
b11100110 !"

#248
b00001000 }
b00111100 ~
b11001100 !"

#249
b01100101 }
b00000110 ~
b01011111 !"

#250
b00101000 }
b01010101 ~
b11010011 !"

#251
b01111000 }
b11111101 ~
b01111011 !"

#252
b10111000 }
b11110110 ~
b11000010 !"

#253
b00011010 }
b11101010 ~
b00110000 !"

#254
b10011010 }
b01100000 ~
b00111010 !"

#255
b00010011 }
b01001010 ~
b11001001 !"

#256
b00011111 }
b01011010 ~
b11000101 !"

#257
b00001001 }
b01011110 ~
b10101011 !"

#258
b11111010 }
b01101101 ~
b10001101 !"

#259
b00000001 }
b11011001 ~
b00101000 !"

#260
b01001110 }
b10100101 ~
b10101001 !"

#261
b10100001 }
b10001100 ~
b00010101 !"

#262
b00101111 }
b11110111 ~
b00111000 !"

#263
b01011011 }
b10110001 ~
b10101010 !"

#264
b10011101 }
b11001000 ~
b11010101 !"

#265
b00100011 }
b00110001 ~
b11110010 !"

#266
b10100111 }
b01110001 ~
b00110110 !"

#267
b11001000 }
b00100010 ~
b10100110 !"

#268
b01000011 }
b11111000 ~
b01001011 !"

#269
b10010100 }
b00000100 ~
b10010000 !"

#270
b01001111 }
b11000000 ~
b10001111 !"

#271
b00011010 }
b11101010 ~
b00110000 !"

#272
b00100100 }
b01100000 ~
b11000100 !"

#273
b00010001 }
b10100110 ~
b01101011 !"

#274
b10110011 }
b00011001 ~
b10011010 !"

#275
b01101011 }
b00001011 ~
b01100000 !"

#276
b01000100 }
b10100011 ~
b10100001 !"

#277
b00110110 }
b01001000 ~
b11101110 !"

#278
b01110000 }
b10001000 ~
b11101000 !"

#279
b01000101 }
b01100101 ~
b11100000 !"

#280
b11101010 }
b00110101 ~
b10110101 !"

#281
b01001011 }
b00000110 ~
b01000101 !"

#282
b00111110 }
b10010100 ~
b10101010 !"

#283
b01110110 }
b01111000 ~
b11111110 !"

#284
b00010111 }
b10010011 ~
b10000100 !"

#285
b11001110 }
b01111001 ~
b01010101 !"

#286
b00011001 }
b00001011 ~
b00001110 !"

#287
b01100100 }
b11110011 ~
b01110001 !"

#288
b01010011 }
b10000001 ~
b11010010 !"

#289
b10100011 }
b10010010 ~
b00010001 !"

#290
b10010100 }
b00110011 ~
b01100001 !"

#291
b01100110 }
b01100100 ~
b00000010 !"

#292
b00011000 }
b00101001 ~
b11101111 !"

#293
b01011111 }
b10100011 ~
b10111100 !"

#294
b10000110 }
b00101100 ~
b01011010 !"

#295
b10101000 }
b01111010 ~
b00101110 !"

#296
b01011001 }
b11001100 ~
b10001101 !"

#297
b10110000 }
b10101110 ~
b00000010 !"

#298
b10110110 }
b11000101 ~
b11110001 !"

#299
b00000010 }
b10011110 ~
b01100100 !"

#300
b11111000 }
b00010011 ~
b11100101 !"

#301
b00111111 }
b10110101 ~
b10001010 !"

#302
b00000110 }
b11101100 ~
b00011010 !"

#303
b01010110 }
b10011110 ~
b10111000 !"

#304
b01101001 }
b11100111 ~
b10000010 !"

#305
b10101001 }
b10001000 ~
b00100001 !"

#306
b01000100 }
b00000100 ~
b01000000 !"

#307
b00010001 }
b00011101 ~
b11110100 !"

#308
b10100101 }
b00111101 ~
b01101000 !"

#309
b10010001 }
b10000111 ~
b00001010 !"

#310
b10010001 }
b10000100 ~
b00001101 !"

#311
b10010010 }
b01001001 ~
b01001001 !"

#312
b01010100 }
b10001100 ~
b11001000 !"

#313
b11000101 }
b00001011 ~
b10111010 !"

#314
b10010000 }
b01111100 ~
b00010100 !"

#315
b11101100 }
b01000100 ~
b10101000 !"

#316
b01000101 }
b00000011 ~
b01000010 !"

#317
b01101111 }
b11010111 ~
b10011000 !"

#318
b11110010 }
b00011000 ~
b11011010 !"

#319
b11100111 }
b00101101 ~
b10111010 !"

#320
b10110110 }
b01010001 ~
b01100101 !"

#321
b10000010 }
b01111111 ~
b00000011 !"

#322
b00011111 }
b00001101 ~
b00010010 !"

#323
b11101000 }
b00000100 ~
b11100100 !"

#324
b01001010 }
b11101110 ~
b01011100 !"

#325
b01110100 }
b11111110 ~
b01110110 !"

#326
b01010000 }
b10001110 ~
b11000010 !"

#327
b11001000 }
b01011110 ~
b01101010 !"

#328
b10101001 }
b00000110 ~
b10100011 !"

#329
b11000011 }
b11010010 ~
b11110001 !"

#330
b00101000 }
b11001101 ~
b01011011 !"

#331
b11110100 }
b10101011 ~
b01001001 !"

#332
b11110111 }
b10110111 ~
b01000000 !"

#333
b10101000 }
b01110011 ~
b00110101 !"

#334
b00101101 }
b00111000 ~
b11110101 !"

#335
b01000000 }
b11111101 ~
b01000011 !"

#336
b10000010 }
b00000100 ~
b01111110 !"

#337
b00011011 }
b11001110 ~
b01001101 !"

#338
b01000000 }
b00001000 ~
b00111000 !"

#339
b11110111 }
b11001000 ~
b00101111 !"

#340
b00111000 }
b11000001 ~
b01110111 !"

#341
b10001101 }
b01010011 ~
b00111010 !"

#342
b11010001 }
b01000110 ~
b10001011 !"

#343
b01111010 }
b11111111 ~
b01111011 !"

#344
b01000111 }
b01010110 ~
b11110001 !"

#345
b01110101 }
b01011001 ~
b00011100 !"

#346
b10010100 }
b00100010 ~
b01110010 !"

#347
b11000110 }
b01000110 ~
b10000000 !"

#348
b11101001 }
b11010111 ~
b00010010 !"

#349
b01010110 }
b01101101 ~
b11101001 !"

#350
b10111011 }
b11101100 ~
b11001111 !"

#351
b11111110 }
b01101010 ~
b10010100 !"

#352
b11100101 }
b00110110 ~
b10101111 !"

#353
b11000101 }
b01000111 ~
b01111110 !"

#354
b00000111 }
b00100010 ~
b11100101 !"

#355
b10000011 }
b11100000 ~
b10100011 !"

#356
b10110000 }
b11111101 ~
b10110011 !"

#357
b11101101 }
b10101110 ~
b00111111 !"

#358
b00101110 }
b10011010 ~
b10010100 !"

#359
b01010011 }
b11110011 ~
b01100000 !"

#360
b00010001 }
b00111100 ~
b11010101 !"

#361
b10001111 }
b11111110 ~
b10010001 !"

#362
b01011101 }
b00000111 ~
b01010110 !"

#363
b11011000 }
b11111101 ~
b11011011 !"

#364
b01001001 }
b01000001 ~
b00001000 !"

#365
b00001100 }
b11001110 ~
b00111110 !"

#366
b01000110 }
b01010011 ~
b11110011 !"

#367
b01110111 }
b01010010 ~
b00100101 !"

#368
b01110110 }
b11001101 ~
b10101001 !"

#369
b00011110 }
b01001010 ~
b11010100 !"

#370
b00111110 }
b11000111 ~
b01110111 !"

#371
b00110010 }
b11110000 ~
b01000010 !"

#372
b11010010 }
b00011010 ~
b10111000 !"

#373
b11101001 }
b11110001 ~
b11111000 !"

#374
b00101000 }
b00000100 ~
b00100100 !"

#375
b10110000 }
b10001010 ~
b00100110 !"

#376
b01010000 }
b01000111 ~
b00001001 !"

#377
b11000101 }
b11011100 ~
b11101001 !"

#378
b00010011 }
b10110110 ~
b01011101 !"

#379
b11110010 }
b10110001 ~
b01000001 !"

#380
b00110000 }
b11000111 ~
b01101001 !"

#381
b11001101 }
b11000011 ~
b00001010 !"

#382
b11000000 }
b00000010 ~
b10111110 !"

#383
b10110100 }
b10101110 ~
b00000110 !"

#384
b01101011 }
b10000111 ~
b11100100 !"

#385
b11000010 }
b01111111 ~
b01000011 !"

#386
b00101101 }
b10010111 ~
b10010110 !"

#387
b01110011 }
b00111100 ~
b00110111 !"

#388
b01010001 }
b10111001 ~
b10011000 !"

#389
b10001110 }
b10101101 ~
b11100001 !"

#390
b01110101 }
b00101111 ~
b01000110 !"

#391
b11011001 }
b01110000 ~
b01101001 !"

#392
b00001011 }
b11100101 ~
b00100110 !"

#393
b01110110 }
b11110101 ~
b10000001 !"

#394
b10011010 }
b01101000 ~
b00110010 !"

#395
b01110000 }
b00000001 ~
b01101111 !"

#396
b01110011 }
b10110100 ~
b10111111 !"

#397
b11010111 }
b10011010 ~
b00111101 !"

#398
b10101111 }
b11111100 ~
b10110011 !"

#399
b10111101 }
b01010101 ~
b01101000 !"

#400
b01011000 }
b00100001 ~
b00110111 !"

#401
b10001111 }
b01001011 ~
b01000100 !"

#402
b11000110 }
b00110001 ~
b10010101 !"

#403
b11001000 }
b00110011 ~
b10010101 !"

#404
b10011001 }
b11001001 ~
b11010000 !"

#405
b10011001 }
b01000100 ~
b01010101 !"

#406
b00111100 }
b00001111 ~
b00101101 !"

#407
b01010111 }
b00101000 ~
b00101111 !"

#408
b00000100 }
b01100110 ~
b10011110 !"

#409
b11101011 }
b00000000 ~
b11101011 !"

#410
b10011011 }
b01110001 ~
b00101010 !"

#411
b11111001 }
b01010011 ~
b10100110 !"

#412
b11000100 }
b00011010 ~
b10101010 !"

#413
b11101011 }
b01100111 ~
b10000100 !"

#414
b01100001 }
b10000000 ~
b11100001 !"

#415
b10011100 }
b01101011 ~
b00110001 !"

#416
b01010101 }
b01011010 ~
b11111011 !"

#417
b01101000 }
b01111111 ~
b11101001 !"

#418
b10001001 }
b11111011 ~
b10001110 !"

#419
b11011100 }
b00110110 ~
b10100110 !"

#420
b10010011 }
b01011100 ~
b00110111 !"

#421
b01011111 }
b10000010 ~
b11011101 !"

#422
b01110111 }
b10101011 ~
b11001100 !"

#423
b00011000 }
b01101111 ~
b10101001 !"

#424
b01110010 }
b00011000 ~
b01011010 !"

#425
b00000100 }
b00110011 ~
b11010001 !"

#426
b11000000 }
b11111011 ~
b11000101 !"

#427
b00111100 }
b11001111 ~
b01101101 !"

#428
b01010011 }
b00010010 ~
b01000001 !"

#429
b10101100 }
b00100000 ~
b10001100 !"

#430
b11010111 }
b01001010 ~
b10001101 !"

#431
b01101101 }
b10000001 ~
b11101100 !"

#432
b11011000 }
b10000000 ~
b01011000 !"

#433
b01001100 }
b10000111 ~
b11000101 !"

#434
b01011010 }
b01100110 ~
b11110100 !"

#435
b10111000 }
b01101110 ~
b01001010 !"

#436
b10101010 }
b00001000 ~
b10100010 !"

#437
b01110100 }
b01000001 ~
b00110011 !"

#438
b00111001 }
b11110010 ~
b01000111 !"

#439
b00001000 }
b01001000 ~
b11000000 !"

#440
b00001111 }
b00011111 ~
b11110000 !"

#441
b10100101 }
b00111100 ~
b01101001 !"

#442
b01110101 }
b01011000 ~
b00011101 !"

#443
b10011101 }
b01111110 ~
b00011111 !"

#444
b01010000 }
b01000101 ~
b00001011 !"

#445
b00101000 }
b00001100 ~
b00011100 !"

#446
b01010111 }
b01010010 ~
b00000101 !"

#447
b00010110 }
b11101100 ~
b00101010 !"

#448
b00101101 }
b00111101 ~
b11110000 !"

#449
b00011001 }
b10110100 ~
b01100101 !"

#450
b01110100 }
b10101100 ~
b11001000 !"

#451
b00011001 }
b10001110 ~
b10001011 !"

#452
b10001101 }
b11110001 ~
b10011100 !"

#453
b01101111 }
b01000010 ~
b00101101 !"

#454
b01101001 }
b00111010 ~
b00101111 !"

#455
b10001011 }
b11010111 ~
b10110100 !"

#456
b00000101 }
b10000111 ~
b01111110 !"

#457
b01100111 }
b10111000 ~
b10101111 !"

#458
b10111000 }
b11000111 ~
b11110001 !"

#459
b00011100 }
b01101001 ~
b10110011 !"

#460
b01000001 }
b00011001 ~
b00101000 !"

#461
b00101110 }
b11001100 ~
b01100010 !"

#462
b11010001 }
b10001000 ~
b01001001 !"

#463
b01100111 }
b01000011 ~
b00100100 !"

#464
b11101001 }
b01101101 ~
b01111100 !"

#465
b11000100 }
b00000101 ~
b10111111 !"

#466
b01011001 }
b11010010 ~
b10000111 !"

#467
b00010101 }
b01110111 ~
b10011110 !"

#468
b11100111 }
b11101110 ~
b11111001 !"

#469
b11011100 }
b00010000 ~
b11001100 !"

#470
b11000011 }
b10110001 ~
b00010010 !"

#471
b01011011 }
b01011000 ~
b00000011 !"

#472
b00011110 }
b01110000 ~
b10101110 !"

#473
b01011101 }
b00110110 ~
b00100111 !"

#474
b11111011 }
b10111101 ~
b00111110 !"

#475
b11111111 }
b01001010 ~
b10110101 !"

#476
b01110000 }
b00011111 ~
b01010001 !"

#477
b10000101 }
b11000101 ~
b11000000 !"

#478
b00010100 }
b11010111 ~
b00111101 !"

#479
b01101101 }
b01111111 ~
b11101110 !"

#480
b11010011 }
b00101000 ~
b10101011 !"

#481
b10001111 }
b00011100 ~
b01110011 !"

#482
b10101110 }
b01110110 ~
b00111000 !"

#483
b10111110 }
b11111100 ~
b11000010 !"

#484
b00001101 }
b11011011 ~
b00110010 !"

#485
b01001010 }
b01000110 ~
b00000100 !"

#486
b00110010 }
b10000111 ~
b10101011 !"

#487
b01101001 }
b11010110 ~
b10010011 !"

#488
b10100111 }
b00111000 ~
b01101111 !"

#489
b01010000 }
b11100001 ~
b01101111 !"

#490
b11111001 }
b01001101 ~
b10101100 !"

#491
b11111010 }
b00101010 ~
b11010000 !"

#492
b10110101 }
b10111100 ~
b11111001 !"

#493
b00011011 }
b11111001 ~
b00100010 !"

#494
b10111011 }
b10010101 ~
b00100110 !"

#495
b00001010 }
b01101000 ~
b10100010 !"

#496
b01111010 }
b11001100 ~
b10101110 !"

#497
b11100110 }
b01110101 ~
b01110001 !"

#498
b01100111 }
b10010011 ~
b11010100 !"

#499
b11101100 }
b00110110 ~
b10110110 !"

#500
b01010010 }
b00010100 ~
b00111110 !"

#501
b11101101 }
b10110000 ~
b00111101 !"

#502
b10000100 }
b10001010 ~
b11111010 !"

#503
b10001000 }
b10100010 ~
b11100110 !"

#504
b11111011 }
b01001101 ~
b10101110 !"

#505
b11001011 }
b10100111 ~
b00100100 !"

#506
b11111011 }
b11111101 ~
b11111110 !"

#507
b11001110 }
b00110010 ~
b10011100 !"

#508
b00000011 }
b11101110 ~
b00010101 !"

#509
b00011110 }
b10000111 ~
b10010111 !"

#510
b11011101 }
b00110110 ~
b10100111 !"

#511
b00100100 }
b10000011 ~
b10100001 !"

#512
b10010111 }
b11001000 ~
b11001111 !"

#513
b00010111 }
b00000010 ~
b00010101 !"

#514
b00000000 }
b10111001 ~
b01000111 !"

#515
b10101001 }
b10100110 ~
b00000011 !"

#516
b00100110 }
b00101100 ~
b11111010 !"

#517
b11000111 }
b00101110 ~
b10011001 !"

#518
b01011111 }
b10010011 ~
b11001100 !"

#519
b10110111 }
b10000101 ~
b00110010 !"

#520
b01010010 }
b00100010 ~
b00110000 !"

#521
b11011101 }
b01010011 ~
b10001010 !"

#522
b00000010 }
b00100000 ~
b11100010 !"

#523
b01000111 }
b10111001 ~
b10001110 !"

#524
b11100011 }
b01011011 ~
b10001000 !"

#525
b10111101 }
b11011110 ~
b11011111 !"

#526
b10111101 }
b11100110 ~
b11010111 !"

#527
b10110011 }
b11101110 ~
b11000101 !"

#528
b10011001 }
b01000110 ~
b01010011 !"

#529
b00001001 }
b10101110 ~
b01011011 !"

#530
b11011010 }
b11111110 ~
b11011100 !"

#531
b11000110 }
b11001000 ~
b11111110 !"

#532
b10100001 }
b01001100 ~
b01010101 !"

#533
b10110010 }
b10111101 ~
b11110101 !"

#534
b10110001 }
b11010101 ~
b11011100 !"

#535
b10011101 }
b11101010 ~
b10110011 !"

#536
b10100010 }
b00100010 ~
b10000000 !"

#537
b10111000 }
b01011101 ~
b01011011 !"

#538
b00010111 }
b01110000 ~
b10100111 !"

#539
b11010001 }
b00101000 ~
b10101001 !"

#540
b11010110 }
b00010110 ~
b11000000 !"

#541
b00010010 }
b11101110 ~
b00100100 !"

#542
b10011010 }
b00111010 ~
b01100000 !"

#543
b01110011 }
b01100101 ~
b00001110 !"

#544
b01101000 }
b00101110 ~
b00111010 !"

#545
b01111001 }
b00100010 ~
b01010111 !"

#546
b11000010 }
b11001000 ~
b11111010 !"

#547
b11001100 }
b11110100 ~
b11011000 !"

#548
b00000000 }
b00110100 ~
b11001100 !"

#549
b10011001 }
b11100110 ~
b10110011 !"

#550
b00101111 }
b00111011 ~
b11110100 !"

#551
b11011111 }
b10001011 ~
b01010100 !"

#552
b11100100 }
b01111111 ~
b01100101 !"

#553
b01100100 }
b10101100 ~
b10111000 !"

#554
b10100111 }
b10000000 ~
b00100111 !"

#555
b00101000 }
b01100101 ~
b11000011 !"

#556
b11111110 }
b01101010 ~
b10010100 !"

#557
b01110010 }
b00101100 ~
b01000110 !"

#558
b00111001 }
b10010111 ~
b10100010 !"

#559
b00110001 }
b11011010 ~
b01010111 !"

#560
b11010001 }
b01111010 ~
b01010111 !"

