src/tests/resources/operation/comb/divu/divu.sv
// Generated by CIRCT firtool-1.71.0
module Foo(	// comb/divu/divu.generic.mlir:3:3
  input  [7:0] a,	// comb/divu/divu.generic.mlir:4:8
               b,	// comb/divu/divu.generic.mlir:4:19
  output [7:0] res	// comb/divu/divu.mlir:1:42
);

  assign res = a / b;	// comb/divu/divu.generic.mlir:5:10, :6:5
endmodule

src/tests/resources/operation/comb/divu/trace_vtor.vcd
$version Generated by VerilatedVcd $end
$timescale 1ps $end
 $scope module Foo $end
  $var wire 8 # a [7:0] $end
  $var wire 8 $ b [7:0] $end
  $var wire 8 % res [7:0] $end
  $scope module Foo $end
   $var wire 8 # a [7:0] $end
   $var wire 8 $ b [7:0] $end
   $var wire 8 % res [7:0] $end
  $upscope $end
 $upscope $end
$enddefinitions $end


#0
b10110100 #
b00001010 $
b00010010 %
#1
b10010101 #
b01001011 $
b00000001 %
#2
b11010111 #
b11111001 $
b00000000 %
#3
b00001100 #
b10001111 $
#4
b10100011 #
b00000011 $
b00110110 %
#5
b10100111 #
b01111011 $
b00000001 %
#6
b11000111 #
b11011100 $
b00000000 %
#7
b01011011 #
b10000110 $
#8
b01011000 #
b01100001 $
#9
b00001010 #
b11101101 $
#10
b00011100 #
b10010011 $
#11
b01011110 #
b01011111 $
#12
b11000111 #
b01011100 $
b00000010 %
#13
b01100000 #
b10101011 $
b00000000 %
#14
b10011001 #
b11111000 $
#15
b10010010 #
b11010001 $
#16
b11000101 #
b11010011 $
#17
b01111011 #
b11101101 $
#18
b01000110 #
b10111101 $
#19
b10111000 #
b11010010 $
#20
b01111101 #
b00111001 $
b00000010 %
#21
b01101110 #
b10001100 $
b00000000 %
#22
b01111011 #
b11111011 $
#23
b10100100 #
b11001010 $
#24
b01110000 #
b00100011 $
b00000011 %
#25
b01000110 #
b11111011 $
b00000000 %
#26
b00000100 #
b01111111 $
#27
b01110001 #
b00000011 $
b00100101 %
#28
b10000110 #
b11110001 $
b00000000 %
#29
b10001010 #
b01001101 $
b00000001 %
#30
b01011001 #
b01000011 $
#31
b10000100 #
b00100001 $
b00000100 %
#32
b11101001 #
b10111110 $
b00000001 %
#33
b10101001 #
b10110100 $
b00000000 %
#34
b00010100 #
b10011100 $
#35
b11111001 #
b10001001 $
b00000001 %
#36
b01011010 #
b01110011 $
b00000000 %
#37
b10101100 #
b11001000 $
#38
b11110001 #
b10000100 $
b00000001 %
#39
b01001011 #
b10010100 $
b00000000 %
#40
b01010010 #
b10000010 $
#41
b11010110 #
b01001011 $
b00000010 %
#42
b11110111 #
b00000111 $
b00100011 %
#43
b10001000 #
b01010111 $
b00000001 %
#44
b10101000 #
b01010110 $
#45
b11001001 #
b11010011 $
b00000000 %
#46
b01000101 #
b00000110 $
b00001011 %
#47
b01101010 #
b01001100 $
b00000001 %
#48
b11000000 #
b11101010 $
b00000000 %
#49
b00001101 #
b10000101 $
#50
b01000111 #
b01011101 $
#51
b10100011 #
b10101101 $
#52
b01011100 #
b11110011 $
#53
b01010110 #
b00010111 $
b00000011 %
#54
b01110001 #
b00001000 $
b00001110 %
#55
b11000111 #
b00111111 $
b00000011 %
#56
b01110100 #
b10100111 $
b00000000 %
#57
b10100111 #
b01110011 $
b00000001 %
#58
b11000010 #
b00010001 $
b00001011 %
#59
b11100011 #
b00110011 $
b00000100 %
#60
b01011001 #
b00100011 $
b00000010 %
#61
b11110011 #
b00001111 $
b00010000 %
#62
b11000000 #
b11100101 $
b00000000 %
#63
b01111011 #
b10110010 $
#64
b01000010 #
b00110001 $
b00000001 %
#65
b01100001 #
b10101000 $
b00000000 %
#66
b11000100 #
b00110110 $
b00000011 %
#67
b10101110 #
b01101101 $
b00000001 %
#68
b11110010 #
b01001101 $
b00000011 %
#69
b10011010 #
b01110111 $
b00000001 %
#70
b11001010 #
b01011001 $
b00000010 %
#71
b00011111 #
b11101010 $
b00000000 %
#72
b11101101 #
b11010111 $
b00000001 %
#73
b00110110 #
b10101001 $
b00000000 %
#74
b01101001 #
b00111101 $
b00000001 %
#75
b01100110 #
b10110000 $
b00000000 %
#76
b11110001 #
b10101010 $
b00000001 %
#77
b01001100 #
b00000010 $
b00100110 %
#78
b10110100 #
b00001000 $
b00010110 %
#79
b01010001 #
b10011001 $
b00000000 %
#80
b11011010 #
b00000001 $
b11011010 %
#81
b11100011 #
b01101011 $
b00000010 %
#82
b00010000 #
b11011001 $
b00000000 %
#83
b00011110 #
b10111100 $
#84
b00000101 #
b00110111 $
#85
b10011111 #
b01100101 $
b00000001 %
#86
b01101001 #
b01111010 $
b00000000 %
#87
b10111111 #
b10100100 $
b00000001 %
#88
b11010110 #
b01111100 $
#89
b00100000 #
b11100000 $
b00000000 %
#90
b00111101 #
b10100010 $
#91
b00010100 #
b10100001 $
#92
b01001101 #
b10101000 $
#93
b10011001 #
b01001101 $
b00000001 %
#94
b01011011 #
b00001011 $
b00001000 %
#95
b01100100 #
b01001111 $
b00000001 %
#96
b01010101 #
b10101000 $
b00000000 %
#97
b00110001 #
b01110001 $
#98
b10010001 #
b10101101 $
#99
b01111111 #
b11011000 $
#100
b00110101 #
b11011111 $
#101
b00000110 #
b00011101 $
#102
b10001100 #
b10100100 $
#103
b00010000 #
b11001011 $
#104
b11111010 #
b00110111 $
b00000100 %
#105
b00000111 #
b01111000 $
b00000000 %
#106
b11011100 #
b00111010 $
b00000011 %
#107
b00110100 #
b00000110 $
b00001000 %
#108
b01001000 #
b10000100 $
b00000000 %
#109
b01001100 #
b10101111 $
#110
b11001010 #
b00010101 $
b00001001 %
#111
b00111110 #
b00011111 $
b00000010 %
#112
b10110110 #
b11101101 $
b00000000 %
#113
b10001000 #
b11101111 $
#114
b10101111 #
b10001110 $
b00000001 %
#115
b10000100 #
b00100101 $
b00000011 %
#116
b11111111 #
b00100100 $
b00000111 %
#117
b10011111 #
b00100011 $
b00000100 %
#118
b01100101 #
b11001110 $
b00000000 %
#119
b01110101 #
b00000100 $
b00011101 %
#120
b00100011 #
b01111011 $
b00000000 %
#121
b11001100 #
b01110000 $
b00000001 %
#122
b10000010 #
b01111011 $
#123
b10011101 #
b10000010 $
#124
b00100100 #
b00001010 $
b00000011 %
#125
b11010111 #
b10010101 $
b00000001 %
#126
b11000100 #
b00010001 $
b00001011 %
#127
b10110101 #
b01010100 $
b00000010 %
#128
b00000100 #
b00011000 $
b00000000 %
#129
b01110000 #
b11111111 $
#130
b10000011 #
b00110111 $
b00000010 %
#131
b10110001 #
b11110000 $
b00000000 %
#132
b10111101 #
b00110001 $
b00000011 %
#133
b10111011 #
b01011001 $
b00000010 %
#134
b10000111 #
b10100001 $
b00000000 %
#135
b11000110 #
b11110000 $
#136
b11110111 #
b11101101 $
b00000001 %
#137
b01101101 #
b01101100 $
#138
b11100000 #
b10000010 $
#139
b00001011 #
b11001000 $
b00000000 %
#140
b01001100 #
b10011110 $
#141
b11000110 #
b10000000 $
b00000001 %
#142
b10011010 #
b00100111 $
b00000011 %
#143
b00011011 #
b11100001 $
b00000000 %
#144
b11110000 #
b01001110 $
b00000011 %
#145
b10111111 #
b01001000 $
b00000010 %
#146
b00101101 #
b11011111 $
b00000000 %
#147
b00100111 #
b01010001 $
#148
b11100101 #
b01001000 $
b00000011 %
#149
b01000000 #
b10001011 $
b00000000 %
#150
b00001001 #
b00100110 $
#151
b10111110 #
b10000000 $
b00000001 %
#152
b11100001 #
b11100001 $
#153
b01100001 #
b00111011 $
#154
b11110100 #
b10001100 $
#155
b11101011 #
b11010010 $
#156
b01100000 #
b01001100 $
#157
b10100100 #
b10100001 $
#158
b01110101 #
b11010001 $
b00000000 %
#159
b01001010 #
b10111011 $
#160
b10101010 #
b00011001 $
b00000110 %
#161
b11111001 #
b00111101 $
b00000100 %
#162
b11011010 #
b11111110 $
b00000000 %
#163
b01101010 #
b11010011 $
#164
b11001011 #
b01101111 $
b00000001 %
#165
b11100010 #
b00100001 $
b00000110 %
#166
b10001000 #
b01010011 $
b00000001 %
#167
b11001001 #
b11001011 $
b00000000 %
#168
b11100000 #
b01001000 $
b00000011 %
#169
b01101001 #
b11111000 $
b00000000 %
#170
b00001001 #
b01011111 $
#171
b11000011 #
b10011001 $
b00000001 %
#172
b10001101 #
b10001010 $
#173
b00111110 #
b10111000 $
b00000000 %
#174
b10111000 #
b11010001 $
#175
b11101100 #
b00101010 $
b00000101 %
#176
b01011001 #
b00000010 %
#177
b11001110 #
b00111111 $
b00000011 %
#178
b01111000 #
b11010001 $
b00000000 %
#179
b11100100 #
b00011011 $
b00001000 %
#180
b10001101 #
b10110101 $
b00000000 %
#181
b10101011 #
b01001000 $
b00000010 %
#182
b10010011 #
b11110111 $
b00000000 %
#183
b00000010 #
b11100110 $
#184
b10010100 #
b11000111 $
#185
b00111111 #
b00110001 $
b00000001 %
#186
b01100110 #
b01000001 $
#187
b10001111 #
b00101110 $
b00000011 %
#188
b00111110 #
b11101011 $
b00000000 %
#189
b01111001 #
b10001101 $
#190
b10000101 #
b11100100 $
#191
b01100011 #
b10010010 $
#192
b00110110 #
b11000101 $
#193
b10011100 #
b10101011 $
#194
b11001101 #
b01000011 $
b00000011 %
#195
b10101000 #
b10010010 $
b00000001 %
#196
b10001100 #
b00100010 $
b00000100 %
#197
b01011001 #
b01101100 $
b00000000 %
#198
b00010100 #
b10010010 $
#199
b01100000 #
b01011101 $
b00000001 %
#200
b01101110 #
b01100011 $
#201
b01111010 #
b11100001 $
b00000000 %
#202
b01010010 #
b11111110 $
#203
b00011001 #
b01111100 $
#204
b01110011 #
b00101001 $
b00000010 %
#205
b10000000 #
b00011000 $
b00000101 %
#206
b00011011 #
b00000010 $
b00001101 %
#207
b10001100 #
b10011011 $
b00000000 %
#208
b01011001 #
b00001000 $
b00001011 %
#209
b01000100 #
b11010101 $
b00000000 %
#210
b00110001 #
b00011110 $
b00000001 %
#211
b01000000 #
b11111011 $
b00000000 %
#212
b00110011 #
b01101100 $
#213
b10010000 #
b00011111 $
b00000100 %
#214
b01100111 #
b01100001 $
b00000001 %
#215
b10111011 #
b10011111 $
#216
b01000011 #
b01011111 $
b00000000 %
#217
b00110100 #
b10010011 $
#218
b10100110 #
b11011100 $
#219
b10110101 #
b00110110 $
b00000011 %
#220
b01000000 #
b10100100 $
b00000000 %
#221
b00110110 #
b01001101 $
#222
b11111010 #
b11011101 $
b00000001 %
#223
b11111000 #
b00111010 $
b00000100 %
#224
b01010010 #
b01001101 $
b00000001 %
#225
b00001100 #
b11101101 $
b00000000 %
#226
b00100100 #
b00000011 $
b00001100 %
#227
b00111100 #
b00111110 $
b00000000 %
#228
b00011000 #
b01000101 $
#229
b00100010 #
#230
b00000100 #
b11111001 $
#231
b01001010 #
b10010001 $
#232
b00000101 #
b00111100 $
#233
b11101111 #
b00111001 $
b00000100 %
#234
b11011011 #
b10110110 $
b00000001 %
#235
b10111100 #
b01100100 $
#236
b01101001 #
b11010010 $
b00000000 %
#237
b00010101 #
b00011000 $
#238
b11101100 #
b10010011 $
b00000001 %
#239
b11001011 #
b00011001 $
b00001000 %
#240
b10100100 #
b01101011 $
b00000001 %
#241
b11001100 #
b00110110 $
b00000011 %
#242
b11000010 #
b10000011 $
b00000001 %
#243
b11011101 #
b11000000 $
#244
b11101110 #
b10100100 $
#245
b01100000 #
b00010001 $
b00000101 %
#246
b11011100 #
b00101101 $
b00000100 %
#247
b00111101 #
b01001110 $
b00000000 %
#248
b11110010 #
b00111010 $
b00000100 %
#249
b01101110 #
b00101000 $
b00000010 %
#250
b01010110 #
b11001100 $
b00000000 %
#251
b10001011 #
b01001101 $
b00000001 %
#252
b11111110 #
b10000010 $
#253
b11100001 #
b01011000 $
b00000010 %
#254
b01000100 #
b01110011 $
b00000000 %
#255
b11101111 #
b10001101 $
b00000001 %
#256
b11100011 #
b00111101 $
b00000011 %
#257
b11100110 #
b11100111 $
b00000000 %
#258
b10010111 #
b11101000 $
#259
b10010001 #
b10101101 $
#260
b10110101 #
b10111010 $
#261
b00101101 #
b00011000 $
b00000001 %
#262
b10010111 #
b01111100 $
#263
b10000010 #
b11001000 $
b00000000 %
#264
b11001100 #
b10010111 $
b00000001 %
#265
b01000001 #
b11110001 $
b00000000 %
#266
b00110101 #
b01011011 $
#267
b00011111 #
b01111101 $
#268
b10000111 #
b11100111 $
#269
b10100001 #
b00000101 $
b00100000 %
#270
b11000000 #
b11101110 $
b00000000 %
#271
b11110101 #
b11011101 $
b00000001 %
#272
b10001000 #
b11001000 $
b00000000 %
#273
b01111100 #
b11100100 $
#274
b00101011 #
b01000110 $
#275
b00110000 #
b01010100 $
#276
b11111111 #
b10010110 $
b00000001 %
#277
b11000101 #
b10111001 $
#278
b11000000 #
b00010110 $
b00001000 %
#279
b10110000 #
b01010010 $
b00000010 %
#280
b01101000 #
b10101100 $
b00000000 %
#281
b00111100 #
b11001100 $
#282
b01011100 #
b01100111 $
#283
b01011110 #
b01011101 $
b00000001 %
#284
b10011011 #
b10111000 $
b00000000 %
#285
b10001011 #
b00011010 $
b00000101 %
#286
b00101000 #
b00110101 $
b00000000 %
#287
b10101111 #
b00000100 $
b00101011 %
#288
b11110111 #
b11100011 $
b00000001 %
#289
b01101110 #
b11110001 $
b00000000 %
#290
b10111111 #
b11001100 $
#291
b11110000 #
b00100100 $
b00000110 %
#292
b11001101 #
b01011011 $
b00000010 %
#293
b00010110 #
b11001011 $
b00000000 %
#294
b10100111 #
b10101010 $
#295
b10100011 #
b00001000 $
b00010100 %
#296
b11000000 #
b00100100 $
b00000101 %
#297
b01110011 #
b00011100 $
b00000100 %
#298
b10111000 #
b00100101 $
#299
b01110010 #
b11000101 $
b00000000 %
#300
b01010010 #
b10000111 $
#301
b11100010 #
b01010010 $
b00000010 %
#302
b01111110 #
b00110111 $
#303
b00011111 #
b11100110 $
b00000000 %
#304
b01100101 #
b01000110 $
b00000001 %
#305
b00001011 #
b11101011 $
b00000000 %
#306
b00010100 #
b00010000 $
b00000001 %
#307
b10011110 #
b10101100 $
b00000000 %
#308
b11010110 #
b00010000 $
b00001101 %
#309
b10000000 #
b11011010 $
b00000000 %
#310
b01000100 #
b00011010 $
b00000010 %
#311
b11001111 #
b00101011 $
b00000100 %
#312
b00110001 #
b01011111 $
b00000000 %
#313
b11101001 #
b00111010 $
b00000100 %
#314
b01100100 #
b10010101 $
b00000000 %
#315
b01001010 #
b01110001 $
#316
b01101110 #
b10111011 $
#317
b00001110 #
b00011001 $
#318
b11010101 #
b10010101 $
b00000001 %
#319
b11111111 #
b11001101 $
#320
b11100101 #
b01111110 $
#321
b11001011 #
b01110001 $
#322
b01001110 #
b10100110 $
b00000000 %
#323
b11011110 #
b10111111 $
b00000001 %
#324
b01111101 #
b10100011 $
b00000000 %
#325
b10011001 #
b01000101 $
b00000010 %
#326
b01000100 #
b11100110 $
b00000000 %
#327
b01110101 #
b00110010 $
b00000010 %
#328
b11110111 #
b01111000 $
#329
b01101001 #
b00010110 $
b00000100 %
#330
b11101110 #
b10000111 $
b00000001 %
#331
b11100110 #
b10111111 $
#332
b00010101 #
b11111100 $
b00000000 %
#333
b10010001 #
b00011011 $
b00000101 %
#334
b10111011 #
b00100010 $
#335
b10010111 #
b10000001 $
b00000001 %
#336
b01011011 #
b10110110 $
b00000000 %
#337
b11011101 #
b00010011 $
b00001011 %
#338
b11110011 #
b00111011 $
b00000100 %
#339
b11011101 #
b11001011 $
b00000001 %
#340
b10110001 #
b10110000 $
#341
b00111011 #
b01011000 $
b00000000 %
#342
b11110111 #
b10000100 $
b00000001 %
#343
b11011100 #
b11000010 $
#344
b00000001 #
b11000111 $
b00000000 %
#345
b10111011 #
b00011011 $
b00000110 %
#346
b00010111 #
b10011011 $
b00000000 %
#347
b10110000 #
b11100010 $
#348
b01000001 #
b11110010 $
#349
b00000100 #
b11111110 $
#350
b00100111 #
b11010000 $
#351
b11100000 #
b00111101 $
b00000011 %
#352
b11000111 #
b11101110 $
b00000000 %
#353
b10000011 #
b01001001 $
b00000001 %
#354
b01111001 #
b10111101 $
b00000000 %
#355
b00010010 #
b01010100 $
#356
b11000001 #
b01111011 $
b00000001 %
#357
b10111111 #
b10000100 $
#358
b10100000 #
b01010110 $
#359
b11100100 #
b01111110 $
#360
b00101100 #
b00110001 $
b00000000 %
#361
b11100101 #
b01001110 $
b00000010 %
#362
b10110011 #
b11000001 $
b00000000 %
#363
b01011011 #
b01100110 $
#364
b10100111 #
b01000100 $
b00000010 %
#365
b00111010 #
b01110010 $
b00000000 %
#366
b00001100 #
b11010101 $
#367
b01111111 #
b10111010 $
#368
b01110011 #
b11001010 $
#369
b11111101 #
b00011011 $
b00001001 %
#370
b10110101 #
b10101100 $
b00000001 %
#371
b10011110 #
b11011111 $
b00000000 %
#372
b10101100 #
#373
b11011000 #
b00001101 $
b00010000 %
#374
b01010100 #
b01111110 $
b00000000 %
#375
b11001001 #
b10010110 $
b00000001 %
#376
b10111111 #
b11010010 $
b00000000 %
#377
b00001011 #
b01010001 $
#378
b01100101 #
b00000010 $
b00110010 %
#379
b00100101 #
b00100110 $
b00000000 %
#380
b11001101 #
b00111000 $
b00000011 %
#381
b01111111 #
b10010101 $
b00000000 %
#382
b11011011 #
b01010101 $
b00000010 %
#383
b01101001 #
b00001101 $
b00001000 %
#384
b00101011 #
b10001110 $
b00000000 %
#385
b10110101 #
b10010001 $
b00000001 %
#386
b11111011 #
b10111001 $
#387
b11001111 #
b11000101 $
#388
b10000010 #
b01000001 $
b00000010 %
#389
b10010110 #
b00101000 $
b00000011 %
#390
b11000001 #
b00001110 $
b00001101 %
#391
b10111111 #
#392
b10100011 #
b10110010 $
b00000000 %
#393
b10010111 #
b10111101 $
#394
b01100011 #
b00101101 $
b00000010 %
#395
b01011101 #
b11111111 $
b00000000 %
#396
b10100000 #
b01011011 $
b00000001 %
#397
b00100011 #
b10100101 $
b00000000 %
#398
b01011100 #
b01000011 $
b00000001 %
#399
b00101111 #
b00011110 $
#400
b10001101 #
b00101110 $
b00000011 %
#401
b00100001 #
b01011101 $
b00000000 %
#402
b00001101 #
b01101110 $
#403
b01000001 #
b11011010 $
#404
b01101010 #
b01001010 $
b00000001 %
#405
b01110111 #
b01100101 $
#406
b01001100 #
b00100010 $
b00000010 %
#407
b10010110 #
b10110100 $
b00000000 %
#408
b01011001 #
b01000010 $
b00000001 %
#409
b10110111 #
b00000111 $
b00011010 %
#410
b10010001 #
b01110001 $
b00000001 %
#411
b10010000 #
b00101000 $
b00000011 %
#412
b10010111 #
b10000101 $
b00000001 %
#413
b10010101 #
b10001110 $
#414
b01001100 #
b10011101 $
b00000000 %
#415
b10011101 #
b10101100 $
#416
b11110000 #
b10100111 $
b00000001 %
#417
b10101100 #
b01010011 $
b00000010 %
#418
b00111011 #
b00001101 $
b00000100 %
#419
b10110001 #
b10110100 $
b00000000 %
#420
b11110011 #
b00101100 $
b00000101 %
#421
b11100011 #
b01011001 $
b00000010 %
#422
b01001000 #
b10001000 $
b00000000 %
#423
b00110110 #
b11000100 $
#424
b10101010 #
b10001011 $
b00000001 %
#425
b01000010 #
b11110001 $
b00000000 %
#426
b11111101 #
b11101011 $
b00000001 %
#427
b00001110 #
b10111111 $
b00000000 %
#428
b11000001 #
b01101001 $
b00000001 %
#429
b10110000 #
b01100001 $
#430
b00101001 #
b01100110 $
b00000000 %
#431
b01111000 #
b01101011 $
b00000001 %
#432
b00111000 #
b10101101 $
b00000000 %
#433
b00101100 #
b00101000 $
b00000001 %
#434
b01100110 #
b00110010 $
b00000010 %
#435
b10000001 #
b10000111 $
b00000000 %
#436
b00101101 #
b11001010 $
#437
b00110001 #
b01010001 $
#438
b11101100 #
b10110110 $
b00000001 %
#439
b11000010 #
b11110010 $
b00000000 %
#440
b11011010 #
b11101011 $
#441
b01000100 #
b01111001 $
#442
b00011000 #
b01011100 $
#443
b10000011 #
b11101010 $
#444
b00001001 #
b00110100 $
#445
b11111001 #
b00000101 $
b00110001 %
#446
b01000111 #
b10110000 $
b00000000 %
#447
b01111101 #
b00010011 $
b00000110 %
#448
b10011011 #
b11111011 $
b00000000 %
#449
b10111000 #
b01110010 $
b00000001 %
#450
b01011011 #
b01011111 $
b00000000 %
#451
b11010011 #
b10001011 $
b00000001 %
#452
b10001110 #
b10100101 $
b00000000 %
#453
b01101001 #
b11101011 $
#454
b10001011 #
b11110010 $
#455
b11100010 #
b11001000 $
b00000001 %
#456
b00001011 #
b10011000 $
b00000000 %
#457
b11001011 #
b11111010 $
#458
b01011110 #
b11101001 $
#459
b01001101 #
b11101101 $
#460
b01111111 #
b11110100 $
#461
b11110001 #
b00011100 $
b00001000 %
#462
b01011010 #
b01101010 $
b00000000 %
#463
b01111100 #
b00001101 $
b00001001 %
#464
b01011101 #
b10100010 $
b00000000 %
#465
b00000111 #
b00100101 $
#466
b11010100 #
b00111010 $
b00000011 %
#467
b10111001 #
b01011110 $
b00000001 %
#468
b10101110 #
b01101100 $
#469
b00000110 #
b10110010 $
b00000000 %
#470
b00011111 #
b00100010 $
#471
b11110001 #
b11101101 $
b00000001 %
#472
b11010001 #
b00101110 $
b00000100 %
#473
b01010110 #
b11010110 $
b00000000 %
#474
b10100100 #
b01110001 $
b00000001 %
#475
b01011001 #
b00001100 $
b00000111 %
#476
b10000001 #
b00111110 $
b00000010 %
#477
b01010001 #
b01110011 $
b00000000 %
#478
b11110010 #
b00001101 $
b00010010 %
#479
b00101110 #
b10100110 $
b00000000 %
#480
b00010000 #
b10000000 $
#481
b11010000 #
b01011001 $
b00000010 %
#482
b11001110 #
b10101001 $
b00000001 %
#483
b10000011 #
b11010010 $
b00000000 %
#484
b11111101 #
b01000000 $
b00000011 %
#485
b11011010 #
b10010001 $
b00000001 %
#486
b11000010 #
b01010001 $
b00000010 %
#487
b01001000 #
b10100000 $
b00000000 %
#488
b10101101 #
b11000110 $
#489
b10111110 #
b00011100 $
b00000110 %
#490
b00111101 #
b01111011 $
b00000000 %
#491
b10110011 #
b10000001 $
b00000001 %
#492
b01010011 #
b10011110 $
b00000000 %
#493
b10010001 #
b11100100 $
#494
b11100111 #
b11101100 $
#495
b10101101 #
b01011011 $
b00000001 %
#496
b10000011 #
b11100101 $
b00000000 %
#497
b01011101 #
b01011000 $
b00000001 %
#498
b00100011 #
b00000110 $
b00000101 %
#499
b01000001 #
b11000101 $
b00000000 %
#500
b10111101 #
b11111011 $
#501
b00001010 #
b01101010 $
#502
b01010111 #
b01000111 $
b00000001 %
#503
b10101000 #
b01011001 $
#504
b01001001 #
b10000100 $
b00000000 %
#505
b01010111 #
b00111010 $
b00000001 %
#506
b11011101 #
b10011101 $
#507
b01101101 #
b00100111 $
b00000010 %
#508
b10110101 #
b11001001 $
b00000000 %
#509
b00100111 #
b10101110 $
#510
b01111011 #
b01101111 $
b00000001 %
#511
b10010111 #
b10011011 $
b00000000 %
#512
b11001100 #
b11111010 $
#513
b10001110 #
b00111000 $
b00000010 %
#514
b00101100 #
b10010111 $
b00000000 %
#515
b10111001 #
b10001011 $
b00000001 %
#516
b00100101 #
b01010110 $
b00000000 %
#517
b00111001 #
b01001111 $
#518
b00110100 #
b00101000 $
b00000001 %
#519
b00001001 #
b11001110 $
b00000000 %
#520
b11110001 #
b10011000 $
b00000001 %
#521
b11101110 #
b10111001 $
#522
b11110110 #
b11011100 $
#523
b01000011 #
b00101001 $
#524
b11011110 #
b10011111 $
#525
b10010111 #
b10000000 $
#526
b00011001 #
b00001011 $
b00000010 %
#527
b10110111 #
b11001000 $
b00000000 %
#528
b10101101 #
b11111100 $
#529
b01000001 #
b00100000 $
b00000010 %
#530
b00110011 #
b10001010 $
b00000000 %
#531
b10011110 #
b01100100 $
b00000001 %
#532
b00011111 #
b11110001 $
b00000000 %
#533
b00010100 #
b10100010 $
#534
b11010111 #
b01010111 $
b00000010 %
#535
b01110111 #
b11001101 $
b00000000 %
#536
b00001010 #
b01000011 $
#537
b00011111 #
b11110111 $
#538
b00011010 #
b11011000 $
#539
b11100111 #
b10000001 $
b00000001 %
#540
b11001100 #
b00001000 $
b00011001 %
#541
b11100000 #
b11000110 $
b00000001 %
#542
b10101101 #
b00101010 $
b00000100 %
#543
b01011011 #
b10111111 $
b00000000 %
#544
b00101101 #
b11110111 $
#545
b00110111 #
b11101000 $
#546
b01000111 #
b10100000 $
#547
b00011101 #
b10010010 $
#548
b00111000 #
b00011010 $
b00000010 %
#549
b11010001 #
b00011101 $
b00000111 %
#550
b10111001 #
b11010100 $
b00000000 %
#551
b01001110 #
b01010111 $
#552
b10000110 #
b11100100 $
#553
b01011101 #
b10101111 $
#554
b00100100 #
b00100100 $
b00000001 %
#555
b00110101 #
b11101010 $
b00000000 %
#556
b10010011 #
b10111011 $
#557
b01001101 #
b10111010 $
#558
b11001001 #
b00001000 $
b00011001 %
#559
b10110101 #
b00101011 $
b00000100 %
#560
b11101000 #
b00110010 $
#561
b01111000 #
b01101101 $
b00000001 %
#562
b10000101 #
b10010110 $
b00000000 %
#563
b01100101 #
b10100101 $
#564
b01011001 #
b11101000 $
#565
b01101001 #
b01111000 $
#566
b00010100 #
b00111010 $
#567
b01100000 #
b01000001 $
b00000001 %
#568
b11000001 #
b11000011 $
b00000000 %
#569
b01111011 #
b11101001 $
#570
b01010010 #
b10111101 $
#571
b11000010 #
b11100101 $
#572
b10111010 #
b10111000 $
b00000001 %
#573
b00010000 #
b10011000 $
b00000000 %
#574
b10101100 $
#575
b00011101 #
b10001110 $
#576
b01001000 #
b10010010 $
#577
b11100010 #
b11001010 $
b00000001 %
#578
b10010110 #
b00011011 $
b00000101 %
#579
b10001110 #
b01010011 $
b00000001 %
#580
b10000000 #
b11000000 $
b00000000 %
#581
b11101011 #
b11010101 $
b00000001 %
#582
b11011111 #
b11111000 $
b00000000 %
#583
b00100001 #
b01001110 $
#584
b00111010 #
b00111010 $
b00000001 %
#585
b11001101 #
b11110110 $
b00000000 %
#586
b10111110 #
b10110100 $
b00000001 %
#587
b11101010 #
b01010001 $
b00000010 %
#588
b00100101 #
b00111111 $
b00000000 %
#589
b00001100 #
b01001010 $
#590
b01000100 #
b01110111 $
#591
b11110111 #
b10001001 $
b00000001 %
#592
b00111101 #
b01111110 $
b00000000 %
#593
b11000101 #
b10110001 $
b00000001 %
#594
b01010111 #
b00000111 $
b00001100 %
#595
b00111011 #
b10001101 $
b00000000 %
#596
b11100101 #
b01101100 $
b00000010 %
#597
b00010011 #
b10011101 $
b00000000 %
#598
b11011001 #
b00001010 $
b00010101 %
#599
b00111111 #
b01010101 $
b00000000 %
#600
b00111001 #
b11101011 $
#601
b10111100 #
b00011001 $
b00000111 %
#602
b00000100 #
b11001110 $
b00000000 %
#603
b11000110 #
b00011101 $
b00000110 %
#604
b11001100 #
b11010110 $
b00000000 %
#605
b10011010 #
b11110101 $
#606
b01110010 #
b00110101 $
b00000010 %
#607
b11001100 #
b01110101 $
b00000001 %
#608
b10001000 #
b10010101 $
b00000000 %
#609
b10100100 #
b10001001 $
b00000001 %
#610
b00111101 #
b00001000 $
b00000111 %
#611
b10100111 #
b00110000 $
b00000011 %
#612
b11110000 #
b01001110 $
#613
b11100100 #
b11001001 $
b00000001 %
#614
b10000010 #
b10100001 $
b00000000 %
#615
b01100101 #
b11000110 $
#616
b00110100 #
b11110000 $
#617
b00101101 #
b00010100 $
b00000010 %
#618
b00100111 #
b00001000 $
b00000100 %
#619
b01011001 #
b00110001 $
b00000001 %
#620
b11101110 #
b00111110 $
b00000011 %
#621
b00111000 #
b10100101 $
b00000000 %
#622
b00100010 #
b11010000 $
#623
b11101001 #
b01010101 $
b00000010 %
#624
b11010011 #
b00111100 $
b00000011 %
#625
b10101000 #
b10001101 $
b00000001 %
#626
b11110011 #
b10011010 $
#627
b00000001 #
b10000001 $
b00000000 %
#628
b00011001 #
b11000001 $
#629
b00101100 #
b11100100 $
#630
b00100100 #
b01000110 $
#631
b00001101 #
b10000101 $
#632
b10111101 $
#633
b00110110 #
b10011000 $
#634
b11111000 #
b11111110 $
#635
b10010101 #
b00001000 $
b00010010 %
#636
b01010000 #
b10000101 $
b00000000 %
#637
b10001010 #
b10001110 $
#638
b11001100 #
b11111101 $
#639
b11010000 #
b00110110 $
b00000011 %
#640
b00111110 #
b01111001 $
b00000000 %
#641
b11010100 #
b00110111 $
b00000011 %
#642
b11100000 #
b01011010 $
b00000010 %
#643
b11100011 #
b01111100 $
b00000001 %
#644
b01110111 #
b00100101 $
b00000011 %
#645
b11011000 #
b00111111 $
#646
b11001010 #
b11100101 $
b00000000 %
#647
b10010111 #
b01110110 $
b00000001 %
#648
b10101110 #
b01001011 $
b00000010 %
#649
b00011000 #
b01010010 $
b00000000 %
#650
b01000110 #
b00001011 $
b00000110 %
#651
b11111010 #
b00100111 $
#652
b11101011 #
b01011000 $
b00000010 %
#653
b11111001 #
b01010101 $
#654
b00111101 #
b00101010 $
b00000001 %
#655
b01100001 #
b11100101 $
b00000000 %
#656
b10010001 #
b10001010 $
b00000001 %
#657
b11101101 #
b11000011 $
#658
b11000010 #
b10110010 $
#659
b10011101 #
b00001000 $
b00010011 %
#660
b00110010 #
b01111101 $
b00000000 %
#661
b00110011 #
#662
b10010000 #
b11101101 $
#663
b11011001 #
b00111000 $
b00000011 %
#664
b10000010 #
b01100111 $
b00000001 %
#665
b10011111 #
b11111001 $
b00000000 %
#666
b01011010 #
b01111001 $
#667
b10111101 #
b10110010 $
b00000001 %
#668
b10111100 #
b10000110 $
#669
b01101001 #
b10100110 $
b00000000 %
#670
b11000010 #
b11111110 $
#671
b11100100 #
b00100010 $
b00000110 %
#672
b11000110 #
b10111100 $
b00000001 %
#673
b11110001 #
b00001001 $
b00011010 %
#674
b10010100 #
b00111001 $
b00000010 %
#675
b10100101 #
b01001000 $
