src/tests/resources/operation/seq/from_clock/from_clock.sv
// Generated by CIRCT firtool-1.71.0
module Foo(	// seq/from_clock/from_clock.generic.mlir:2:3
  input  clk,	// seq/from_clock/from_clock.generic.mlir:3:8
  output res
);

  assign res = clk;	// seq/from_clock/from_clock.generic.mlir:5:5
endmodule

src/tests/resources/operation/seq/from_clock/trace_vtor.vcd
$version Generated by VerilatedVcd $end
$timescale 1ps $end
 $scope module Foo $end
  $var wire 1 # clk $end
  $var wire 1 $ res $end
  $scope module Foo $end
   $var wire 1 # clk $end
   $var wire 1 $ res $end
  $upscope $end
 $upscope $end
$enddefinitions $end


#0
0#
0$
#1
1#
1$
#2
0#
0$
#3
1#
1$
#6
0#
0$
#7
1#
1$
#10
0#
0$
#11
1#
1$
#12
0#
0$
#13
1#
1$
#14
0#
0$
#15
1#
1$
#17
0#
0$
#19
1#
1$
#22
0#
0$
#23
1#
1$
#26
0#
0$
#27
1#
1$
#29
0#
0$
#30
1#
1$
#37
0#
0$
#39
1#
1$
#40
0#
0$
#41
1#
1$
#42
0#
0$
#43
1#
1$
#46
0#
0$
#47
1#
1$
#48
0#
0$
#52
1#
1$
#54
0#
0$
#56
1#
1$
#57
0#
0$
#58
1#
1$
#59
0#
0$
#60
1#
1$
#61
0#
0$
#63
1#
1$
#64
0#
0$
#65
1#
1$
#67
0#
0$
#72
1#
1$
#73
0#
0$
#74
1#
1$
#75
0#
0$
#78
1#
1$
#82
0#
0$
#87
1#
1$
#89
0#
0$
#90
1#
1$
#91
0#
0$
#93
1#
1$
#95
0#
0$
#96
1#
1$
#97
0#
0$
#101
1#
1$
#102
0#
0$
#103
1#
1$
#107
0#
0$
#109
1#
1$
#110
0#
0$
#112
1#
1$
#113
0#
0$
#114
1#
1$
#116
0#
0$
#119
1#
1$
#120
0#
0$
#121
1#
1$
#126
0#
0$
#127
1#
1$
#128
0#
0$
#130
1#
1$
#132
0#
0$
#135
1#
1$
#136
0#
0$
#138
1#
1$
#144
0#
0$
#145
1#
1$
#146
0#
0$
#149
1#
1$
#150
0#
0$
#152
1#
1$
#155
0#
0$
#157
1#
1$
#158
0#
0$
#159
1#
1$
#161
0#
0$
#163
1#
1$
#165
0#
0$
#166
1#
1$
#170
0#
0$
#171
1#
1$
#173
0#
0$
#177
1#
1$
#180
0#
0$
#181
1#
1$
#182
0#
0$
#184
1#
1$
#185
0#
0$
#186
1#
1$
#187
0#
0$
#194
1#
1$
#197
0#
0$
#203
1#
1$
#204
0#
0$
#208
1#
1$
#209
0#
0$
#212
1#
1$
#215
0#
0$
#216
1#
1$
#217
0#
0$
#218
1#
1$
#219
0#
0$
#221
1#
1$
#222
0#
0$
#224
1#
1$
#227
0#
0$
#231
1#
1$
#232
0#
0$
#235
1#
1$
#236
0#
0$
#240
1#
1$
#243
0#
0$
#250
1#
1$
#253
0#
0$
#254
1#
1$
#255
0#
0$
#256
1#
1$
#259
0#
0$
#262
1#
1$
#263
0#
0$
#264
1#
1$
#266
0#
0$
#267
1#
1$
#268
0#
0$
#272
1#
1$
#273
0#
0$
#275
1#
1$
#276
0#
0$
#279
1#
1$
#280
0#
0$
#281
1#
1$
#282
0#
0$
#283
1#
1$
#288
0#
0$
#291
1#
1$
#292
0#
0$
#296
1#
1$
#297
0#
0$
#300
1#
1$
#302
0#
0$
#304
1#
1$
#305
0#
0$
#308
1#
1$
#309
0#
0$
#310
1#
1$
#312
0#
0$
#317
1#
1$
#321
0#
0$
#322
1#
1$
#326
0#
0$
#327
1#
1$
#328
0#
0$
#330
1#
1$
#335
0#
0$
#339
1#
1$
#340
0#
0$
#342
1#
1$
#344
0#
0$
#345
1#
1$
#346
0#
0$
#348
1#
1$
#349
0#
0$
#351
1#
1$
#353
0#
0$
#355
1#
1$
#356
0#
0$
#357
1#
1$
#364
0#
0$
#366
1#
1$
#367
0#
0$
#368
1#
1$
#369
0#
0$
#371
1#
1$
#373
0#
0$
#376
1#
1$
#377
0#
0$
#378
1#
1$
#379
0#
0$
#381
1#
1$
#382
0#
0$
#385
1#
1$
#386
0#
0$
#387
1#
1$
#392
0#
0$
#393
1#
1$
#395
0#
0$
#399
1#
1$
#400
0#
0$
#403
1#
1$
#404
0#
0$
#407
1#
1$
#410
0#
0$
#412
1#
1$
#414
0#
0$
#415
1#
1$
#417
0#
0$
#419
1#
1$
#420
0#
0$
#421
1#
1$
#422
0#
0$
#423
1#
1$
#424
0#
0$
#425
1#
1$
#427
0#
0$
#428
1#
1$
#430
0#
0$
#431
1#
1$
#435
0#
0$
#436
1#
1$
#438
0#
0$
#440
1#
1$
#442
0#
0$
#443
1#
1$
#444
0#
0$
#445
1#
1$
#446
0#
0$
#447
1#
1$
#450
0#
0$
#454
1#
1$
#455
0#
0$
#456
1#
1$
#457
0#
0$
#458
1#
1$
#460
0#
0$
#462
1#
1$
#463
0#
0$
#465
1#
1$
#472
0#
0$
#478
1#
1$
#479
0#
0$
#481
1#
1$
#482
0#
0$
#483
1#
1$
#484
0#
0$
#486
1#
1$
#487
0#
0$
#490
1#
1$
#491
0#
0$
#495
1#
1$
#498
0#
0$
#500
1#
1$
#502
0#
0$
#503
1#
1$
#505
0#
0$
#506
1#
1$
#508
0#
0$
#509
1#
1$
#510
0#
0$
#513
1#
1$
#514
0#
0$
#518
1#
1$
#519
0#
0$
#521
1#
1$
#525
0#
0$
#527
1#
1$
#528
0#
0$
#534
1#
1$
#538
0#
0$
#543
1#
1$
#544
0#
0$
#545
1#
1$
#546
0#
0$
#548
1#
1$
#549
0#
0$
#550
1#
1$
#551
0#
0$
#552
1#
1$
#553
0#
0$
#555
1#
1$
#559
0#
0$
#560
1#
1$
#563
0#
0$
#568
1#
1$
#569
0#
0$
#571
1#
1$
#572
0#
0$
#574
1#
1$
#575
0#
0$
#576
1#
1$
#577
0#
0$
#578
1#
1$
#579
0#
0$
#583
1#
1$
#584
0#
0$
#590
1#
1$
#593
0#
0$
#595
1#
1$
#596
0#
0$
#600
1#
1$
#601
0#
0$
#603
1#
1$
#605
0#
0$
#606
1#
1$
#607
0#
0$
#609
1#
1$
#612
0#
0$
#613
1#
1$
#614
0#
0$
#616
1#
1$
#617
0#
0$
#620
1#
1$
#621
0#
0$
#626
1#
1$
#628
0#
0$
#629
1#
1$
#631
0#
0$
#632
1#
1$
#633
0#
0$
#634
1#
1$
#635
0#
0$
#637
1#
1$
#640
0#
0$
#644
1#
1$
#645
0#
0$
#647
1#
1$
#652
0#
0$
#653
1#
1$
#654
0#
0$
#655
1#
1$
#657
0#
0$
#658
1#
1$
#662
0#
0$
#663
1#
1$
#664
0#
0$
#665
1#
1$
#666
0#
0$
#668
1#
1$
#673
0#
0$
#675
1#
1$
#676
0#
0$
#677
1#
1$
#678
0#
0$
#680
1#
1$
#685
0#
0$
#686
1#
1$
#688
0#
0$
#690
1#
1$
#694
0#
0$
#695
1#
1$
#697
0#
0$
#699
1#
1$
#701
0#
0$
#702
1#
1$
#707
0#
0$
#713
1#
1$
#714
0#
0$
#715
1#
1$
#716
0#
0$
#717
1#
1$
#718
0#
0$
#719
1#
1$
#722
0#
0$
#724
1#
1$
#725
0#
0$
#726
1#
1$
#727
0#
0$
#730
1#
1$
#734
0#
0$
#737
1#
1$
#738
0#
0$
#739
1#
1$
#745
0#
0$
#746
1#
1$
#748
0#
0$
#750
1#
1$
#751
0#
0$
#752
1#
1$
#753
0#
0$
#757
1#
1$
#758
0#
0$
#759
1#
1$
#765
0#
0$
#766
1#
1$
#771
0#
0$
#772
1#
1$
#773
0#
0$
#777
1#
1$
#778
0#
0$
#779
1#
1$
#783
0#
0$
#787
1#
1$
#789
0#
0$
#790
1#
1$
#792
0#
0$
#794
1#
1$
#795
0#
0$
#796
1#
1$
#797
0#
0$
#799
1#
1$
#800
0#
0$
#801
1#
1$
#802
0#
0$
#803
1#
1$
#807
0#
0$
#808
1#
1$
#810
0#
0$
#811
1#
1$
#816
0#
0$
#818
1#
1$
#819
0#
0$
#820
1#
1$
#822
0#
0$
#823
1#
1$
#826
0#
0$
#831
1#
1$
#834
0#
0$
#835
1#
1$
#836
0#
0$
#837
1#
1$
#840
0#
0$
#841
1#
1$
#842
0#
0$
#844
1#
1$
#845
0#
0$
#846
1#
1$
#847
0#
0$
#848
1#
1$
#850
0#
0$
#852
1#
1$
#853
0#
0$
#856
1#
1$
#857
0#
0$
#858
1#
1$
#859
0#
0$
#862
1#
1$
#863
0#
0$
#864
1#
1$
#866
0#
0$
#868
1#
1$
#872
0#
0$
#873
1#
1$
#874
0#
0$
#877
1#
1$
#880
0#
0$
#881
1#
1$
#882
0#
0$
#884
1#
1$
#887
0#
0$
#892
1#
1$
#893
0#
0$
#894
1#
1$
#896
0#
0$
#898
1#
1$
#899
0#
0$
#900
1#
1$
#901
0#
0$
#902
1#
1$
#906
0#
0$
#910
1#
1$
#912
0#
0$
#914
1#
1$
#916
0#
0$
#917
1#
1$
#918
0#
0$
#919
1#
1$
#920
0#
0$
#922
1#
1$
#923
0#
0$
#924
1#
1$
#925
0#
0$
#926
1#
1$
#930
0#
0$
#933
1#
1$
#936
0#
0$
#937
1#
1$
#939
0#
0$
#940
1#
1$
#941
0#
0$
#944
1#
1$
#945
0#
0$
#948
1#
1$
#949
0#
0$
#951
1#
1$
#952
0#
0$
#954
1#
1$
#955
0#
0$
#957
1#
1$
#960
0#
0$
#961
1#
1$
#964
0#
0$
#966
1#
1$
#967
0#
0$
#972
1#
1$
#976
0#
0$
#977
1#
1$
#979
0#
0$
#982
1#
1$
#983
0#
0$
#986
1#
1$
#991
0#
0$
#993
1#
1$
#995
0#
0$
#996
1#
1$
#997
0#
0$
#999
1#
1$
