src/tests/resources/operation/seq/firreg/firreg.sv
// Generated by CIRCT firtool-1.71.0
// Standard header to adapt well known macros for register randomization.

// RANDOM may be set to an expression that produces a 32-bit random unsigned value.
`ifndef RANDOM
  `define RANDOM $random
`endif // not def RANDOM

// Users can define INIT_RANDOM as general code that gets injected into the
// initializer block for modules with registers.
`ifndef INIT_RANDOM
  `define INIT_RANDOM
`endif // not def INIT_RANDOM

// If using random initialization, you can also define RANDOMIZE_DELAY to
// customize the delay used, otherwise 0.002 is used.
`ifndef RANDOMIZE_DELAY
  `define RANDOMIZE_DELAY 0.002
`endif // not def RANDOMIZE_DELAY

// Define INIT_RANDOM_PROLOG_ for use in our modules below.
`ifndef INIT_RANDOM_PROLOG_
  `ifdef RANDOMIZE
    `ifdef VERILATOR
      `define INIT_RANDOM_PROLOG_ `INIT_RANDOM
    `else  // VERILATOR
      `define INIT_RANDOM_PROLOG_ `INIT_RANDOM #`RANDOMIZE_DELAY begin end
    `endif // VERILATOR
  `else  // RANDOMIZE
    `define INIT_RANDOM_PROLOG_
  `endif // RANDOMIZE
`endif // not def INIT_RANDOM_PROLOG_

// Include register initializers in init blocks unless synthesis is set
`ifndef RANDOMIZE
  `ifdef RANDOMIZE_REG_INIT
    `define RANDOMIZE
  `endif // RANDOMIZE_REG_INIT
`endif // not def RANDOMIZE
`ifndef SYNTHESIS
  `ifndef ENABLE_INITIAL_REG_
    `define ENABLE_INITIAL_REG_
  `endif // not def ENABLE_INITIAL_REG_
`endif // not def SYNTHESIS

module Foo(	// seq/firreg/firreg.generic.mlir:3:3
  input        clk,	// seq/firreg/firreg.generic.mlir:4:8
               reset,	// seq/firreg/firreg.generic.mlir:4:27
  output [7:0] res	// seq/firreg/firreg.mlir:1:55
);

  reg [7:0] reg_port;	// seq/firreg/firreg.generic.mlir:5:10
  always @(posedge clk) begin	// seq/firreg/firreg.generic.mlir:4:8
    if (reset)	// seq/firreg/firreg.generic.mlir:4:8
      reg_port <= 8'h0;	// seq/firreg/firreg.generic.mlir:5:10
    else	// seq/firreg/firreg.generic.mlir:4:8
      reg_port <= reg_port + 8'h1;	// seq/firreg/firreg.generic.mlir:5:10, :8:10
  end // always @(posedge)
  `ifdef ENABLE_INITIAL_REG_	// seq/firreg/firreg.generic.mlir:3:3
    `ifdef FIRRTL_BEFORE_INITIAL	// seq/firreg/firreg.generic.mlir:3:3
      `FIRRTL_BEFORE_INITIAL	// seq/firreg/firreg.generic.mlir:3:3
    `endif // FIRRTL_BEFORE_INITIAL
    logic [31:0] _RANDOM[0:0];	// seq/firreg/firreg.generic.mlir:3:3
    initial begin	// seq/firreg/firreg.generic.mlir:3:3
      `ifdef INIT_RANDOM_PROLOG_	// seq/firreg/firreg.generic.mlir:3:3
        `INIT_RANDOM_PROLOG_	// seq/firreg/firreg.generic.mlir:3:3
      `endif // INIT_RANDOM_PROLOG_
      `ifdef RANDOMIZE_REG_INIT	// seq/firreg/firreg.generic.mlir:3:3
        _RANDOM[/*Zero width*/ 1'b0] = `RANDOM;	// seq/firreg/firreg.generic.mlir:3:3
        reg_port = _RANDOM[/*Zero width*/ 1'b0][7:0];	// seq/firreg/firreg.generic.mlir:3:3, :5:10
      `endif // RANDOMIZE_REG_INIT
    end // initial
    `ifdef FIRRTL_AFTER_INITIAL	// seq/firreg/firreg.generic.mlir:3:3
      `FIRRTL_AFTER_INITIAL	// seq/firreg/firreg.generic.mlir:3:3
    `endif // FIRRTL_AFTER_INITIAL
  `endif // ENABLE_INITIAL_REG_
  assign res = reg_port;	// seq/firreg/firreg.generic.mlir:5:10, :9:5
endmodule

src/tests/resources/operation/seq/firreg/trace_vtor.vcd
$version Generated by VerilatedVcd $end
$timescale 1ps $end
 $scope module Foo $end
  $var wire 1 # clk $end
  $var wire 1 $ reset $end
  $var wire 8 % res [7:0] $end
  $scope module Foo $end
   $var wire 1 # clk $end
   $var wire 1 $ reset $end
   $var wire 8 % res [7:0] $end
   $var wire 8 & reg_port [7:0] $end
  $upscope $end
 $upscope $end
$enddefinitions $end


#0
1#
0$
b00000001 %
b00000001 &

#1
0#
1$

#2
1#
b00000000 %
b00000000 &
#3
0#
#4
1#
#5
0#
0$
#6
1#
1$
#7
0#
0$
#8
1#
1$
#9
0#

#10
1#
0$
b00000001 %
b00000001 &

#11
0#


#12
1#
b00000010 %
b00000010 &

#13
0#
1$

#14
1#
0$
b00000011 %
b00000011 &

#15
0#
#16
1#
1$
b00000000 %
b00000000 &
#17
0#
0$
#18
1#
1$
#19
0#
#20
1#
0$
b00000001 %
b00000001 &
#21
0#
1$
#22
1#
0$
b00000010 %
b00000010 &
#23
0#
1$
#24
1#
b00000000 %
b00000000 &
#25
0#
0$
#26
1#
b00000001 %
b00000001 &
#27
0#
#28
1#
b00000010 %
b00000010 &
#29
0#
1$
#30
1#
b00000000 %
b00000000 &
#31
0#
#32
1#
#33
0#
0$
#34
1#
1$
#35
0#
0$
#36
1#
b00000001 %
b00000001 &
#37
0#
#38
1#
b00000010 %
b00000010 &
#39
0#
#40
1#
1$
b00000000 %
b00000000 &
#41
0#
0$
#42
1#
1$
#43
0#
0$
#44
1#
b00000001 %
b00000001 &
#45
0#
1$
#46
1#
0$
b00000010 %
b00000010 &
#47
0#
1$
#48
1#
b00000000 %
b00000000 &
#49
0#
0$
#50
1#
1$
#51
0#
#52
1#
#53
0#
0$
#54
1#
1$
#55
0#
0$
#56
1#
1$
#57
0#
0$
#58
1#
1$
#59
0#
0$
#60
1#
1$
#61
0#
#62
1#
0$
b00000001 %
b00000001 &
#63
0#
#64
1#
b00000010 %
b00000010 &
#65
0#
#66
1#
1$
b00000000 %
b00000000 &
#67
0#
#68
1#
#69
0#
#70
1#
0$
b00000001 %
b00000001 &
#71
0#
1$
#72
1#
0$
b00000010 %
b00000010 &
#73
0#
#74
1#
b00000011 %
b00000011 &
#75
0#
1$
#76
1#
b00000000 %
b00000000 &
#77
0#
#78
1#
#79
0#
#80
1#
0$
b00000001 %
b00000001 &
#81
0#
#82
1#
1$
b00000000 %
b00000000 &
#83
0#
0$
#84
1#
b00000001 %
b00000001 &
#85
0#
#86
1#
b00000010 %
b00000010 &
#87
0#
1$
#88
1#
b00000000 %
b00000000 &
#89
0#
0$
#90
1#
b00000001 %
b00000001 &
#91
0#
1$
#92
1#
b00000000 %
b00000000 &
#93
0#
#94
1#
#95
0#
#96
1#
0$
b00000001 %
b00000001 &
#97
0#
1$
#98
1#
0$
b00000010 %
b00000010 &
#99
0#
#100
1#
b00000011 %
b00000011 &
#101
0#
1$
#102
1#
0$
b00000100 %
b00000100 &
#103
0#
#104
1#
1$
b00000000 %
b00000000 &
#105
0#
#106
1#
#107
0#
#108
1#
0$
b00000001 %
b00000001 &
#109
0#
#110
1#
1$
b00000000 %
b00000000 &
#111
0#
0$
#112
1#
1$
#113
0#
#114
1#
0$
b00000001 %
b00000001 &
#115
0#
1$
#116
1#
b00000000 %
b00000000 &
#117
0#
0$
#118
1#
b00000001 %
b00000001 &
#119
0#
#120
1#
b00000010 %
b00000010 &
#121
0#
#122
1#
b00000011 %
b00000011 &
#123
0#
1$
#124
1#
b00000000 %
b00000000 &
#125
0#
0$
#126
1#
1$
#127
0#
0$
#128
1#
b00000001 %
b00000001 &
#129
0#
1$
#130
1#
b00000000 %
b00000000 &
#131
0#
#132
1#
0$
b00000001 %
b00000001 &
#133
0#
1$
#134
1#
0$
b00000010 %
b00000010 &
#135
0#
#136
1#
b00000011 %
b00000011 &
#137
0#
1$
#138
1#
b00000000 %
b00000000 &
#139
0#
0$
#140
1#
b00000001 %
b00000001 &
#141
0#
1$
#142
1#
b00000000 %
b00000000 &
#143
0#
0$
#144
1#
1$
#145
0#
#146
1#
#147
0#
#148
1#
#149
0#
#150
1#
#151
0#
#152
1#
#153
0#
0$
#154
1#
1$
#155
0#
#156
1#
0$
b00000001 %
b00000001 &
#157
0#
1$
#158
1#
b00000000 %
b00000000 &
#159
0#
0$
#160
1#
b00000001 %
b00000001 &
#161
0#
1$
#162
1#
0$
b00000010 %
b00000010 &
#163
0#
#164
1#
1$
b00000000 %
b00000000 &
#165
0#
0$
#166
1#
1$
#167
0#
0$
#168
1#
1$
#169
0#
0$
#170
1#
1$
#171
0#
#172
1#
#173
0#
#174
1#
#175
0#
0$
#176
1#
b00000001 %
b00000001 &
#177
0#
#178
1#
b00000010 %
b00000010 &
#179
0#
#180
1#
1$
b00000000 %
b00000000 &
#181
0#
#182
1#
#183
0#
0$
#184
1#
b00000001 %
b00000001 &
#185
0#
1$
#186
1#
b00000000 %
b00000000 &
#187
0#
0$
#188
1#
1$
#189
0#
0$
#190
1#
1$
#191
0#
#192
1#
0$
b00000001 %
b00000001 &
#193
0#
#194
1#
b00000010 %
b00000010 &
#195
0#
1$
#196
1#
0$
b00000011 %
b00000011 &
#197
0#
#198
1#
b00000100 %
b00000100 &
#199
0#
#200
1#
b00000101 %
b00000101 &
#201
0#
1$
#202
1#
0$
b00000110 %
b00000110 &
#203
0#
1$
#204
1#
b00000000 %
b00000000 &
#205
0#
#206
1#
#207
0#
#208
1#
#209
0#
0$
#210
1#
b00000001 %
b00000001 &
#211
0#
#212
1#
1$
b00000000 %
b00000000 &
#213
0#
0$
#214
1#
b00000001 %
b00000001 &
#215
0#
#216
1#
1$
b00000000 %
b00000000 &
#217
0#
0$
#218
1#
1$
#219
0#
#220
1#
0$
b00000001 %
b00000001 &
#221
0#
1$
#222
1#
0$
b00000010 %
b00000010 &
#223
0#
1$
#224
1#
b00000000 %
b00000000 &
#225
0#
0$
#226
1#
1$
#227
0#
#228
1#
#229
0#
0$
#230
1#
1$
#231
0#
#232
1#
#233
0#
0$
#234
1#
b00000001 %
b00000001 &
#235
0#
#236
1#
b00000010 %
b00000010 &
#237
0#
1$
#238
1#
0$
b00000011 %
b00000011 &
#239
0#
1$
#240
1#
0$
b00000100 %
b00000100 &
#241
0#
1$
#242
1#
0$
b00000101 %
b00000101 &
#243
0#
#244
1#
b00000110 %
b00000110 &
#245
0#
#246
1#
b00000111 %
b00000111 &
#247
0#
1$
#248
1#
b00000000 %
b00000000 &
#249
0#
#250
1#
#251
0#
0$
#252
1#
b00000001 %
b00000001 &
#253
0#
1$
#254
1#
0$
b00000010 %
b00000010 &
#255
0#
1$
#256
1#
0$
b00000011 %
b00000011 &
#257
0#
1$
#258
1#
b00000000 %
b00000000 &
#259
0#
#260
1#
0$
b00000001 %
b00000001 &
#261
0#
#262
1#
b00000010 %
b00000010 &
#263
0#
1$
#264
1#
b00000000 %
b00000000 &
#265
0#
0$
#266
1#
b00000001 %
b00000001 &
#267
0#
1$
#268
1#
b00000000 %
b00000000 &
#269
0#
#270
1#
0$
b00000001 %
b00000001 &
#271
0#
#272
1#
1$
b00000000 %
b00000000 &
#273
0#
#274
1#
0$
b00000001 %
b00000001 &
#275
0#
1$
#276
1#
0$
b00000010 %
b00000010 &
#277
0#
1$
#278
1#
b00000000 %
b00000000 &
#279
0#
#280
1#
#281
0#
#282
1#
0$
b00000001 %
b00000001 &
#283
0#
#284
1#
1$
b00000000 %
b00000000 &
#285
0#
#286
1#
0$
b00000001 %
b00000001 &
#287
0#
#288
1#
1$
b00000000 %
b00000000 &
#289
0#
#290
1#
0$
b00000001 %
b00000001 &
#291
0#
#292
1#
1$
b00000000 %
b00000000 &
#293
0#
0$
#294
1#
1$
#295
0#
#296
1#
#297
0#
0$
#298
1#
1$
#299
0#
#300
1#
#301
0#
#302
1#
#303
0#
0$
#304
1#
b00000001 %
b00000001 &
#305
0#
#306
1#
1$
b00000000 %
b00000000 &
#307
0#
#308
1#
0$
b00000001 %
b00000001 &
#309
0#
1$
#310
1#
b00000000 %
b00000000 &
#311
0#
0$
#312
1#
b00000001 %
b00000001 &
#313
0#
1$
#314
1#
b00000000 %
b00000000 &
#315
0#
#316
1#
#317
0#
0$
#318
1#
b00000001 %
b00000001 &
#319
0#
#320
1#
1$
b00000000 %
b00000000 &
#321
0#
0$
#322
1#
b00000001 %
b00000001 &
#323
0#
#324
1#
1$
b00000000 %
b00000000 &
#325
0#
0$
#326
1#
1$
#327
0#
#328
1#
0$
b00000001 %
b00000001 &
#329
0#
1$
#330
1#
b00000000 %
b00000000 &
#331
0#
#332
1#
0$
b00000001 %
b00000001 &
#333
0#
#334
1#
1$
b00000000 %
b00000000 &
#335
0#
0$
#336
1#
b00000001 %
b00000001 &
#337
0#
#338
1#
1$
b00000000 %
b00000000 &
#339
0#
0$
#340
1#
b00000001 %
b00000001 &
#341
0#
1$
#342
1#
b00000000 %
b00000000 &
#343
0#
#344
1#
#345
0#
0$
#346
1#
b00000001 %
b00000001 &
#347
0#
#348
1#
b00000010 %
b00000010 &
#349
0#
#350
1#
b00000011 %
b00000011 &
#351
0#
#352
1#
1$
b00000000 %
b00000000 &
#353
0#
0$
#354
1#
b00000001 %
b00000001 &
#355
0#
#356
1#
1$
b00000000 %
b00000000 &
#357
0#
0$
#358
1#
b00000001 %
b00000001 &
#359
0#
#360
1#
1$
b00000000 %
b00000000 &
#361
0#
0$
#362
1#
1$
#363
0#
#364
1#
0$
b00000001 %
b00000001 &
#365
0#
1$
#366
1#
b00000000 %
b00000000 &
#367
0#
0$
#368
1#
b00000001 %
b00000001 &
#369
0#
#370
1#
1$
b00000000 %
b00000000 &
#371
0#
#372
1#
#373
0#
#374
1#
#375
0#
0$
#376
1#
1$
#377
0#
0$
#378
1#
1$
#379
0#
0$
#380
1#
b00000001 %
b00000001 &
#381
0#
1$
#382
1#
0$
b00000010 %
b00000010 &
#383
0#
#384
1#
b00000011 %
b00000011 &
#385
0#
1$
#386
1#
b00000000 %
b00000000 &
#387
0#
#388
1#
#389
0#
#390
1#
0$
b00000001 %
b00000001 &
#391
0#
#392
1#
b00000010 %
b00000010 &
#393
0#
#394
1#
b00000011 %
b00000011 &
#395
0#
1$
#396
1#
0$
b00000100 %
b00000100 &
#397
0#
#398
1#
b00000101 %
b00000101 &
#399
0#
1$
#400
1#
0$
b00000110 %
b00000110 &
#401
0#
#402
1#
1$
b00000000 %
b00000000 &
#403
0#
0$
#404
1#
1$
#405
0#
#406
1#
#407
0#
#408
1#
#409
0#
0$
#410
1#
b00000001 %
b00000001 &
#411
0#
1$
#412
1#
b00000000 %
b00000000 &
#413
0#
#414
1#
0$
b00000001 %
b00000001 &
#415
0#
1$
#416
1#
0$
b00000010 %
b00000010 &
#417
0#
#418
1#
1$
b00000000 %
b00000000 &
#419
0#
0$
#420
1#
b00000001 %
b00000001 &
#421
0#
#422
1#
1$
b00000000 %
b00000000 &
#423
0#
#424
1#
#425
0#
0$
#426
1#
1$
#427
0#
#428
1#
0$
b00000001 %
b00000001 &
#429
0#
1$
#430
1#
0$
b00000010 %
b00000010 &
#431
0#
1$
#432
1#
0$
b00000011 %
b00000011 &
#433
0#
1$
#434
1#
b00000000 %
b00000000 &
#435
0#
#436
1#
0$
b00000001 %
b00000001 &
#437
0#
#438
1#
b00000010 %
b00000010 &
#439
0#
#440
1#
b00000011 %
b00000011 &
#441
0#
1$
#442
1#
b00000000 %
b00000000 &
#443
0#
#444
1#
#445
0#
0$
#446
1#
1$
#447
0#
0$
#448
1#
1$
#449
0#
#450
1#
0$
b00000001 %
b00000001 &
#451
0#
1$
#452
1#
0$
b00000010 %
b00000010 &
#453
0#
1$
#454
1#
b00000000 %
b00000000 &
#455
0#
#456
1#
#457
0#
#458
1#
#459
0#
#460
1#
0$
b00000001 %
b00000001 &
#461
0#
#462
1#
b00000010 %
b00000010 &
#463
0#
1$
#464
1#
b00000000 %
b00000000 &
#465
0#
#466
1#
#467
0#
0$
#468
1#
b00000001 %
b00000001 &
#469
0#
#470
1#
b00000010 %
b00000010 &
#471
0#
1$
#472
1#
0$
b00000011 %
b00000011 &
#473
0#
1$
#474
1#
b00000000 %
b00000000 &
#475
0#
0$
#476
1#
b00000001 %
b00000001 &
#477
0#
#478
1#
b00000010 %
b00000010 &
#479
0#
1$
#480
1#
0$
b00000011 %
b00000011 &
#481
0#
1$
#482
1#
b00000000 %
b00000000 &
#483
0#
#484
1#
0$
b00000001 %
b00000001 &
#485
0#
1$
#486
1#
0$
b00000010 %
b00000010 &
#487
0#
1$
#488
1#
0$
b00000011 %
b00000011 &
#489
0#
#490
1#
1$
b00000000 %
b00000000 &
#491
0#
#492
1#
#493
0#
#494
1#
0$
b00000001 %
b00000001 &
#495
0#
1$
#496
1#
b00000000 %
b00000000 &
#497
0#
#498
1#
#499
0#
0$
#500
1#
1$
#501
0#
#502
1#
0$
b00000001 %
b00000001 &
#503
0#
1$
#504
1#
0$
b00000010 %
b00000010 &
#505
0#
#506
1#
1$
b00000000 %
b00000000 &
#507
0#
#508
1#
#509
0#
0$
#510
1#
b00000001 %
b00000001 &
#511
0#
#512
1#
b00000010 %
b00000010 &
#513
0#
1$
#514
1#
0$
b00000011 %
b00000011 &
#515
0#
1$
#516
1#
b00000000 %
b00000000 &
#517
0#
0$
#518
1#
1$
#519
0#
0$
#520
1#
1$
#521
0#
#522
1#
#523
0#
#524
1#
#525
0#
0$
#526
1#
b00000001 %
b00000001 &
#527
0#
#528
1#
1$
b00000000 %
b00000000 &
#529
0#
#530
1#
#531
0#
#532
1#
0$
b00000001 %
b00000001 &
#533
0#
#534
1#
b00000010 %
b00000010 &
#535
0#
1$
#536
1#
b00000000 %
b00000000 &
#537
0#
0$
#538
1#
1$
#539
0#
#540
1#
0$
b00000001 %
b00000001 &
#541
0#
1$
#542
1#
0$
b00000010 %
b00000010 &
#543
0#
#544
1#
1$
b00000000 %
b00000000 &
#545
0#
0$
#546
1#
b00000001 %
b00000001 &
#547
0#
#548
1#
b00000010 %
b00000010 &
#549
0#
#550
1#
1$
b00000000 %
b00000000 &
#551
0#
#552
1#
0$
b00000001 %
b00000001 &
#553
0#
1$
#554
1#
0$
b00000010 %
b00000010 &
#555
0#
#556
1#
b00000011 %
b00000011 &
#557
0#
1$
#558
1#
0$
b00000100 %
b00000100 &
#559
0#
1$
#560
1#
0$
b00000101 %
b00000101 &
#561
0#
#562
1#
b00000110 %
b00000110 &
#563
0#
1$
#564
1#
0$
b00000111 %
b00000111 &
#565
0#
1$
#566
1#
b00000000 %
b00000000 &
#567
0#
#568
1#
#569
0#
#570
1#
#571
0#
0$
#572
1#
1$
#573
0#
0$
#574
1#
1$
#575
0#
0$
#576
1#
b00000001 %
b00000001 &
#577
0#
#578
1#
b00000010 %
b00000010 &
#579
0#
1$
#580
1#
0$
b00000011 %
b00000011 &
#581
0#
#582
1#
1$
b00000000 %
b00000000 &
#583
0#
0$
#584
1#
b00000001 %
b00000001 &
#585
0#
1$
#586
1#
0$
b00000010 %
b00000010 &
#587
0#
#588
1#
1$
b00000000 %
b00000000 &
#589
0#
#590
1#
#591
0#
#592
1#
0$
b00000001 %
b00000001 &
#593
0#
1$
#594
1#
b00000000 %
b00000000 &
#595
0#
0$
#596
1#
b00000001 %
b00000001 &
#597
0#
#598
1#
b00000010 %
b00000010 &
#599
0#
1$
#600
1#
0$
b00000011 %
b00000011 &
#601
0#
#602
1#
b00000100 %
b00000100 &
#603
0#
#604
1#
b00000101 %
b00000101 &
#605
0#
1$
#606
1#
0$
b00000110 %
b00000110 &
#607
0#
#608
1#
b00000111 %
b00000111 &
#609
0#
#610
1#
b00001000 %
b00001000 &
#611
0#
#612
1#
1$
b00000000 %
b00000000 &
#613
0#
#614
1#
0$
b00000001 %
b00000001 &
#615
0#
1$
#616
1#
b00000000 %
b00000000 &
#617
0#
0$
#618
1#
b00000001 %
b00000001 &
#619
0#
1$
#620
1#
0$
b00000010 %
b00000010 &
#621
0#
1$
#622
1#
0$
b00000011 %
b00000011 &
#623
0#
#624
1#
1$
b00000000 %
b00000000 &
#625
0#
0$
#626
1#
1$
#627
0#
#628
1#
0$
b00000001 %
b00000001 &
#629
0#
#630
1#
1$
b00000000 %
b00000000 &
#631
0#
#632
1#
#633
0#
0$
#634
1#
b00000001 %
b00000001 &
#635
0#
#636
1#
b00000010 %
b00000010 &
#637
0#
1$
#638
1#
0$
b00000011 %
b00000011 &
#639
0#
1$
#640
1#
0$
b00000100 %
b00000100 &
#641
0#
#642
1#
1$
b00000000 %
b00000000 &
#643
0#
#644
1#
0$
b00000001 %
b00000001 &
#645
0#
1$
#646
1#
0$
b00000010 %
b00000010 &
#647
0#
#648
1#
b00000011 %
b00000011 &
#649
0#
#650
1#
1$
b00000000 %
b00000000 &
#651
0#
#652
1#
#653
0#
#654
1#
#655
0#
0$
#656
1#
1$
#657
0#
0$
#658
1#
b00000001 %
b00000001 &
#659
0#
#660
1#
1$
b00000000 %
b00000000 &
#661
0#
0$
#662
1#
b00000001 %
b00000001 &
#663
0#
#664
1#
1$
b00000000 %
b00000000 &
#665
0#
0$
#666
1#
1$
#667
0#
0$
#668
1#
b00000001 %
b00000001 &
#669
0#
#670
1#
1$
b00000000 %
b00000000 &
#671
0#
0$
#672
1#
b00000001 %
b00000001 &
#673
0#
1$
#674
1#
0$
b00000010 %
b00000010 &
#675
0#
#676
1#
1$
b00000000 %
b00000000 &
#677
0#
#678
1#
0$
b00000001 %
b00000001 &
#679
0#
1$
#680
1#
b00000000 %
b00000000 &
#681
0#
0$
#682
1#
1$
#683
0#
0$
#684
1#
1$
#685
0#
0$
#686
1#
b00000001 %
b00000001 &
#687
0#
#688
1#
1$
b00000000 %
b00000000 &
#689
0#
0$
#690
1#
b00000001 %
b00000001 &
#691
0#
#692
1#
b00000010 %
b00000010 &
#693
0#
1$
#694
1#
b00000000 %
b00000000 &
#695
0#
#696
1#
#697
0#
0$
#698
1#
1$
#699
0#
0$
#700
1#
1$
#701
0#
0$
#702
1#
1$
#703
0#
#704
1#
0$
b00000001 %
b00000001 &
#705
0#
#706
1#
1$
b00000000 %
b00000000 &
#707
0#
#708
1#
#709
0#
#710
1#
#711
0#
#712
1#
#713
0#
0$
#714
1#
1$
#715
0#
0$
#716
1#
b00000001 %
b00000001 &
#717
0#
#718
1#
1$
b00000000 %
b00000000 &
#719
0#
0$
#720
1#
b00000001 %
b00000001 &
#721
0#
#722
1#
1$
b00000000 %
b00000000 &
#723
0#
#724
1#
#725
0#
0$
#726
1#
b00000001 %
b00000001 &
#727
0#
#728
1#
b00000010 %
b00000010 &
#729
0#
#730
1#
b00000011 %
b00000011 &
#731
0#
1$
#732
1#
0$
b00000100 %
b00000100 &
#733
0#
1$
#734
1#
b00000000 %
b00000000 &
#735
0#
0$
#736
1#
b00000001 %
b00000001 &
#737
0#
#738
1#
b00000010 %
b00000010 &
#739
0#
1$
#740
1#
b00000000 %
b00000000 &
#741
0#
#742
1#
0$
b00000001 %
b00000001 &
#743
0#
1$
#744
1#
0$
b00000010 %
b00000010 &
#745
0#
#746
1#
b00000011 %
b00000011 &
#747
0#
1$
#748
1#
b00000000 %
b00000000 &
#749
0#
0$
#750
1#
b00000001 %
b00000001 &
#751
0#
#752
1#
1$
b00000000 %
b00000000 &
#753
0#
#754
1#
0$
b00000001 %
b00000001 &
#755
0#
1$
#756
1#
b00000000 %
b00000000 &
#757
0#
#758
1#
0$
b00000001 %
b00000001 &
#759
0#
1$
#760
1#
b00000000 %
b00000000 &
#761
0#
#762
1#
#763
0#
0$
#764
1#
b00000001 %
b00000001 &
#765
0#
#766
1#
1$
b00000000 %
b00000000 &
#767
0#
0$
#768
1#
b00000001 %
b00000001 &
#769
0#
#770
1#
1$
b00000000 %
b00000000 &
#771
0#
0$
#772
1#
b00000001 %
b00000001 &
#773
0#
#774
1#
b00000010 %
b00000010 &
#775
0#
1$
#776
1#
0$
b00000011 %
b00000011 &
#777
0#
#778
1#
1$
b00000000 %
b00000000 &
#779
0#
#780
1#
#781
0#
0$
#782
1#
b00000001 %
b00000001 &
#783
0#
1$
#784
1#
0$
b00000010 %
b00000010 &
#785
0#
1$
#786
1#
0$
b00000011 %
b00000011 &
#787
0#
1$
#788
1#
0$
b00000100 %
b00000100 &
#789
0#
1$
#790
1#
b00000000 %
b00000000 &
#791
0#
0$
#792
1#
b00000001 %
b00000001 &
#793
0#
#794
1#
1$
b00000000 %
b00000000 &
#795
0#
0$
#796
1#
b00000001 %
b00000001 &
#797
0#
1$
#798
1#
0$
b00000010 %
b00000010 &
#799
0#
#800
1#
1$
b00000000 %
b00000000 &
#801
0#
0$
#802
1#
1$
#803
0#
#804
1#
0$
b00000001 %
b00000001 &
#805
0#
#806
1#
1$
b00000000 %
b00000000 &
#807
0#
#808
1#
#809
0#
#810
1#
#811
0#
#812
1#
#813
0#
0$
#814
1#
b00000001 %
b00000001 &
#815
0#
#816
1#
1$
b00000000 %
b00000000 &
#817
0#
#818
1#
#819
0#
0$
#820
1#
1$
#821
0#
#822
1#
#823
0#
0$
#824
1#
b00000001 %
b00000001 &
#825
0#
#826
1#
b00000010 %
b00000010 &
#827
0#
#828
1#
1$
b00000000 %
b00000000 &
#829
0#
#830
1#
#831
0#
#832
1#
0$
b00000001 %
b00000001 &
#833
0#
#834
1#
b00000010 %
b00000010 &
#835
0#
#836
1#
b00000011 %
b00000011 &
#837
0#
#838
1#
1$
b00000000 %
b00000000 &
#839
0#
0$
#840
1#
1$
#841
0#
0$
#842
1#
b00000001 %
b00000001 &
#843
0#
#844
1#
1$
b00000000 %
b00000000 &
#845
0#
0$
#846
1#
b00000001 %
b00000001 &
#847
0#
1$
#848
1#
b00000000 %
b00000000 &
#849
0#
#850
1#
0$
b00000001 %
b00000001 &
#851
0#
1$
#852
1#
b00000000 %
b00000000 &
#853
0#
0$
#854
1#
1$
#855
0#
#856
1#
#857
0#
#858
1#
#859
0#
#860
1#
0$
b00000001 %
b00000001 &
#861
0#
#862
1#
b00000010 %
b00000010 &
#863
0#
1$
#864
1#
b00000000 %
b00000000 &
#865
0#
0$
#866
1#
1$
#867
0#
#868
1#
#869
0#
#870
1#
#871
0#
#872
1#
0$
b00000001 %
b00000001 &
#873
0#
#874
1#
b00000010 %
b00000010 &
#875
0#
1$
#876
1#
b00000000 %
b00000000 &
#877
0#
#878
1#
0$
b00000001 %
b00000001 &
#879
0#
1$
#880
1#
0$
b00000010 %
b00000010 &
#881
0#
1$
#882
1#
b00000000 %
b00000000 &
#883
0#
0$
#884
1#
b00000001 %
b00000001 &
#885
0#
#886
1#
b00000010 %
b00000010 &
#887
0#
1$
#888
1#
b00000000 %
b00000000 &
#889
0#
#890
1#
#891
0#
0$
#892
1#
1$
#893
0#
#894
1#
#895
0#
#896
1#
#897
0#
#898
1#
0$
b00000001 %
b00000001 &
#899
0#
1$
#900
1#
0$
b00000010 %
b00000010 &
#901
0#
1$
#902
1#
b00000000 %
b00000000 &
#903
0#
0$
#904
1#
b00000001 %
b00000001 &
#905
0#
1$
#906
1#
b00000000 %
b00000000 &
#907
0#
#908
1#
0$
b00000001 %
b00000001 &
#909
0#
1$
#910
1#
0$
b00000010 %
b00000010 &
#911
0#
#912
1#
b00000011 %
b00000011 &
#913
0#
1$
#914
1#
0$
b00000100 %
b00000100 &
#915
0#
#916
1#
1$
b00000000 %
b00000000 &
#917
0#
0$
#918
1#
b00000001 %
b00000001 &
#919
0#
1$
#920
1#
0$
b00000010 %
b00000010 &
#921
0#
#922
1#
1$
b00000000 %
b00000000 &
#923
0#
#924
1#
#925
0#
0$
#926
1#
1$
#927
0#
#928
1#
#929
0#
#930
1#
#931
0#
0$
#932
1#
1$
#933
0#
0$
#934
1#
1$
#935
0#
0$
#936
1#
b00000001 %
b00000001 &
#937
0#
#938
1#
1$
b00000000 %
b00000000 &
#939
0#
#940
1#
0$
b00000001 %
b00000001 &
#941
0#
#942
1#
1$
b00000000 %
b00000000 &
#943
0#
#944
1#
0$
b00000001 %
b00000001 &
#945
0#
#946
1#
b00000010 %
b00000010 &
#947
0#
#948
1#
1$
b00000000 %
b00000000 &
#949
0#
0$
#950
1#
1$
#951
0#
0$
#952
1#
b00000001 %
b00000001 &
#953
0#
#954
1#
1$
b00000000 %
b00000000 &
#955
0#
0$
#956
1#
b00000001 %
b00000001 &
#957
0#
#958
1#
1$
b00000000 %
b00000000 &
#959
0#
0$
#960
1#
1$
#961
0#
#962
1#
#963
0#
#964
1#
0$
b00000001 %
b00000001 &
#965
0#
1$
#966
1#
0$
b00000010 %
b00000010 &
#967
0#
1$
#968
1#
b00000000 %
b00000000 &
#969
0#
#970
1#
0$
b00000001 %
b00000001 &
#971
0#
#972
1#
1$
b00000000 %
b00000000 &
#973
0#
0$
#974
1#
b00000001 %
b00000001 &
#975
0#
#976
1#
b00000010 %
b00000010 &
#977
0#
#978
1#
b00000011 %
b00000011 &
#979
0#
#980
1#
1$
b00000000 %
b00000000 &
#981
0#
0$
#982
1#
b00000001 %
b00000001 &
#983
0#
#984
1#
1$
b00000000 %
b00000000 &
#985
0#
#986
1#
0$
b00000001 %
b00000001 &
#987
0#
1$
#988
1#
0$
b00000010 %
b00000010 &
#989
0#
1$
#990
1#
b00000000 %
b00000000 &
#991
0#
0$
#992
1#
1$
#993
0#
0$
#994
1#
1$
#995
0#
#996
1#
#997
0#
#998
1#
0$
b00000001 %
b00000001 &
