src/tests/resources/operation/comb/or/or.sv
// Generated by CIRCT firtool-1.71.0
module Foo(	// comb/or/or.generic.mlir:3:3
  input  [7:0] a,	// comb/or/or.generic.mlir:4:8
               b,	// comb/or/or.generic.mlir:4:19
  output [7:0] res	// comb/or/or.mlir:1:42
);

  assign res = a | b;	// comb/or/or.generic.mlir:5:10, :6:5
endmodule

src/tests/resources/operation/comb/or/test.vcd
$version Generated by KCIRCT $end
$timescale 1s $end
 $scope module Foo $end
  $var wire 8 K a [7:0] $end
  $var wire 8 L b [7:0] $end
  $var wire 8 M res [7:0] $end
  $scope module Foo $end
   $var wire 8 K a [7:0] $end
   $var wire 8 L b [7:0] $end
   $var wire 8 M res [7:0] $end
  $upscope $end
 $upscope $end
$enddefinitions $end

#0
b00100010 K
b11101000 L
b11101010 M

#1
b01011101 K
b10001000 L
b11011101 M

#2
b00101110 K
b11100100 L
b11101110 M

#3
b01011100 K
b00000000 L
b01011100 M

#4
b10100011 K
b10010001 L
b10110011 M

#5
b11101101 K
b10100011 L
b11101111 M

#6
b00101101 K
b01000111 L
b01101111 M

#7
b00000100 K
b11110011 L
b11110111 M

#8
b10011111 K
b11001101 L
b11011111 M

#9
b01011011 K
b10110010 L
b11111011 M

#10
b10101010 K
b11011011 L
b11111011 M

#11
b00010001 K
b01001011 L
b01011011 M

#12
b01011101 K
b01001011 L
b01011111 M

#13
b11111010 K
b10100001 L
b11111011 M

#14
b01011101 K
b11000100 L
b11011101 M

#15
b01010011 K
b01111110 L
b01111111 M

#16
b00111111 K
b10111101 L
b10111111 M

#17
b01010100 K
b00110010 L
b01110110 M

#18
b01111101 K
b11111001 L
b11111101 M

#19
b01101101 K
b00010001 L
b01111101 M

#20
b10001011 K
b01101111 L
b11101111 M

#21
b00001000 K
b11101110 L
b11101110 M

#22
b10001101 K
b00100010 L
b10101111 M

#23
b10110110 K
b11000101 L
b11110111 M

#24
b00110100 K
b11110100 L
b11110100 M

#25
b10000001 K
b10011010 L
b10011011 M

#26
b01111000 K
b11000011 L
b11111011 M

#27
b11001011 K
b10001000 L
b11001011 M

#28
b11010110 K
b11010111 L
b11010111 M

#29
b00001101 K
b01111100 L
b01111101 M

#30
b10110110 K
b00011111 L
b10111111 M

#31
b00100000 K
b10110111 L
b10110111 M

#32
b01011101 K
b10110011 L
b11111111 M

#33
b11011101 K
b10011111 L
b11011111 M

#34
b11010000 K
b11101100 L
b11111100 M

#35
b11100011 K
b10011011 L
b11111011 M

#36
b11110110 K
b01111110 L
b11111110 M

#37
b11010011 K
b00111110 L
b11111111 M

#38
b11000000 K
b00111001 L
b11111001 M

#39
b10101111 K
b11000011 L
b11101111 M

#40
b10110010 K
b01111000 L
b11111010 M

#41
b00110100 K
b10001011 L
b10111111 M

#42
b00011110 K
b11111111 L
b11111111 M

#43
b01110001 K
b01110101 L
b01110101 M

#44
b11101100 K
b11010010 L
b11111110 M

#45
b00100110 K
b11011001 L
b11111111 M

#46
b11000101 K
b01010011 L
b11010111 M

#47
b00000111 K
b11011101 L
b11011111 M

#48
b01001100 K
b00100000 L
b01101100 M

#49
b01000001 K
b00011110 L
b01011111 M

#50
b00011010 K
b10101011 L
b10111011 M

#51
b00110101 K
b11001110 L
b11111111 M

#52
b01000000 K
b10001010 L
b11001010 M

#53
b01001100 K
b01111000 L
b01111100 M

#54
b00111100 K
b01011110 L
b01111110 M

#55
b10010000 K
b00001010 L
b10011010 M

#56
b10110111 K
b01111110 L
b11111111 M

#57
b10010010 K
b11111000 L
b11111010 M

#58
b00110110 K
b10001100 L
b10111110 M

#59
b01010010 K
b00110000 L
b01110010 M

#60
b11100101 K
b11010100 L
b11110101 M

#61
b00101011 K
b10011110 L
b10111111 M

#62
b00010000 K
b01011101 L
b01011101 M

#63
b01011010 K
b11001000 L
b11011010 M

#64
b11110110 K
b01110000 L
b11110110 M

#65
b11101100 K
b11100101 L
b11101101 M

#66
b10010111 K
b00101010 L
b10111111 M

#67
b00100101 K
b11011100 L
b11111101 M

#68
b00100100 K
b10111101 L
b10111101 M

#69
b00110010 K
b10110101 L
b10110111 M

#70
b10011100 K
b11100001 L
b11111101 M

#71
b10111001 K
b10111110 L
b10111111 M

#72
b00010011 K
b10101011 L
b10111011 M

#73
b01000101 K
b01011010 L
b01011111 M

#74
b11001101 K
b11101100 L
b11101101 M

#75
b01001000 K
b11110000 L
b11111000 M

#76
b01010001 K
b10011110 L
b11011111 M

#77
b00111111 K
b10101000 L
b10111111 M

#78
b10100111 K
b10011001 L
b10111111 M

#79
b00111110 K
b00100011 L
b00111111 M

#80
b10010101 K
b11001100 L
b11011101 M

#81
b11111100 K
b11001001 L
b11111101 M

#82
b00101010 K
b00011100 L
b00111110 M

#83
b11011100 K
b11000111 L
b11011111 M

#84
b11110001 K
b10101001 L
b11111001 M

#85
b11110001 K
b00111110 L
b11111111 M

#86
b00111010 K
b11111000 L
b11111010 M

#87
b11101010 K
b01011100 L
b11111110 M

#88
b11000110 K
b10011110 L
b11011110 M

#89
b11001011 K
b11011010 L
b11011011 M

#90
b00000001 K
b11110111 L
b11110111 M

#91
b10111110 K
b00010010 L
b10111110 M

#92
b01010100 K
b11111111 L
b11111111 M

#93
b00011111 K
b01100011 L
b01111111 M

#94
b10011010 K
b00110100 L
b10111110 M

#95
b01111001 K
b00111100 L
b01111101 M

#96
b10100011 K
b00001100 L
b10101111 M

#97
b10110001 K
b01010000 L
b11110001 M

#98
b01110010 K
b11101001 L
b11111011 M

#99
b01000010 K
b01110010 L
b01110010 M

#100
b10011001 K
b11111111 L
b11111111 M

#101
b11001100 K
b00100000 L
b11101100 M

#102
b11010010 K
b00011000 L
b11011010 M

#103
b01101101 K
b11110010 L
b11111111 M

#104
b10100010 K
b01000100 L
b11100110 M

#105
b01010001 K
b01110001 L
b01110001 M

#106
b10101011 K
b10000010 L
b10101011 M

#107
b00110111 K
b11000100 L
b11110111 M

#108
b01100111 K
b00111001 L
b01111111 M

#109
b01010111 K
b01110000 L
b01110111 M

#110
b00101110 K
b01100111 L
b01101111 M

#111
b10101101 K
b00001010 L
b10101111 M

#112
b00010011 K
b10101011 L
b10111011 M

#113
b01000101 K
b01011010 L
b01011111 M

#114
b11001101 K
b11101100 L
b11101101 M

#115
b01001000 K
b11110000 L
b11111000 M

#116
b01010001 K
b10011110 L
b11011111 M

#117
b00111111 K
b10101000 L
b10111111 M

#118
b11011100 K
b01010101 L
b11011101 M

#119
b11100001 K
b10110101 L
b11110101 M

#120
b00010001 K
b01110011 L
b01110011 M

#121
b10100000 K
b00100101 L
b10100101 M

#122
b01111000 K
b10101000 L
b11111000 M

#123
b01110000 K
b01100110 L
b01110110 M

#124
b01010111 K
b01000010 L
b01010111 M

#125
b10101110 K
b01110010 L
b11111110 M

#126
b11110010 K
b01101010 L
b11111010 M

#127
b10011000 K
b01110111 L
b11111111 M

#128
b11000110 K
b11111100 L
b11111110 M

#129
b00100011 K
b11011110 L
b11111111 M

#130
b11110111 K
b10000110 L
b11110111 M

#131
b00111001 K
b00111100 L
b00111101 M

#132
b10001100 K
b11001010 L
b11001110 M

#133
b01000010 K
b00110101 L
b01110111 M

#134
b01001101 K
b01111010 L
b01111111 M

#135
b10101111 K
b11001001 L
b11101111 M

#136
b00110011 K
b00110110 L
b00110111 M

#137
b11001011 K
b01110000 L
b11111011 M

#138
b00100100 K
b10011000 L
b10111100 M

#139
b01001001 K
b11011000 L
b11011001 M

#140
b00100010 K
b00101000 L
b00101010 M

#141
b10111011 K
b10110011 L
b10111011 M

#142
b01011101 K
b00011000 L
b01011101 M

#143
b01100001 K
b01100011 L
b01100011 M

#144
b00000100 K
b10111010 L
b10111110 M

#145
b01000001 K
b00000000 L
b01000001 M

#146
b00101101 K
b00111010 L
b00111111 M

#147
b00110110 K
b10010101 L
b10110111 M

#148
b10001111 K
b00011111 L
b10011111 M

#149
b00001001 K
b01111010 L
b01111011 M

#150
b00100011 K
b11001110 L
b11101111 M

#151
b10111101 K
b10000101 L
b10111101 M

#152
b11010010 K
b11011110 L
b11011110 M

#153
b01101001 K
b00101010 L
b01101011 M

#154
b11001010 K
b11001100 L
b11001110 M

#155
b10000010 K
b11001011 L
b11001011 M

#156
b11010111 K
b10000010 L
b11010111 M

#157
b10100101 K
b11010011 L
b11110111 M

#158
b11010011 K
b10000111 L
b11010111 M

#159
b10100100 K
b10111100 L
b10111100 M

#160
b10001110 K
b01000000 L
b11001110 M

#161
b11010101 K
b11100000 L
b11110101 M

#162
b01011000 K
b01011101 L
b01011101 M

#163
b01111110 K
b11101110 L
b11111110 M

#164
b10111000 K
b11110000 L
b11111000 M

#165
b01000110 K
b11111011 L
b11111111 M

#166
b10011101 K
b00111000 L
b10111101 M

#167
b10000011 K
b10110001 L
b10110011 M

#168
b10000000 K
b01110010 L
b11110010 M

#169
b11100111 K
b00000011 L
b11100111 M

#170
b10111101 K
b00000010 L
b10111111 M

#171
b11110011 K
b00011011 L
b11111011 M

#172
b01101101 K
b01111100 L
b01111101 M

#173
b00000011 K
b10100010 L
b10100011 M

#174
b00001010 K
b11000010 L
b11001010 M

#175
b10000110 K
b01100011 L
b11100111 M

#176
b10011010 K
b11110001 L
b11111011 M

#177
b01000101 K
b01101111 L
b01101111 M

#178
b10011110 K
b00101010 L
b10111110 M

#179
b00110001 K
b00110011 L
b00110011 M

#180
b01111011 K
b01010001 L
b01111011 M

#181
b10011011 K
b11101100 L
b11111111 M

#182
b11101101 K
b00001000 L
b11101101 M

#183
b11011010 K
b01001011 L
b11011011 M

#184
b11100110 K
b10100011 L
b11100111 M

#185
b11100000 K
b10001100 L
b11101100 M

#186
b00101100 K
b00110011 L
b00111111 M

#187
b00100010 K
b10011000 L
b10111010 M

#188
b01100010 K
b01101100 L
b01101110 M

#189
b01001111 K
b01101011 L
b01101111 M

#190
b00111100 K
b11110001 L
b11111101 M

#191
b10000000 K
b01101100 L
b11101100 M

#192
b01101001 K
b11101011 L
b11101011 M

#193
b11000101 K
b11010100 L
b11010101 M

#194
b01110001 K
b10001101 L
b11111101 M

#195
b01110111 K
b10101100 L
b11111111 M

#196
b01101000 K
b11010110 L
b11111110 M

#197
b10010101 K
b11101000 L
b11111101 M

#198
b11100011 K
b01110110 L
b11110111 M

#199
b00110000 K
b01110001 L
b01110001 M

#200
b00011000 K
b10101000 L
b10111000 M

#201
b00100110 K
b01000100 L
b01100110 M

#202
b01011110 K
b00101111 L
b01111111 M

#203
b10010110 K
b00011000 L
b10011110 M

#204
b01000101 K
b10111110 L
b11111111 M

#205
b00001110 K
b11101110 L
b11101110 M

#206
b01001100 K
b10110001 L
b11111101 M

#207
b01000100 K
b11000101 L
b11000101 M

#208
b00001100 K
b00001001 L
b00001101 M

#209
b00011001 K
b00110000 L
b00111001 M

#210
b11011101 K
b10000100 L
b11011101 M

#211
b10101000 K
b11101010 L
b11101010 M

#212
b00111110 K
b00110110 L
b00111110 M

#213
b00010100 K
b01010100 L
b01010100 M

#214
b00011100 K
b10001101 L
b10011101 M

#215
b01110001 K
b00001111 L
b01111111 M

#216
b00011011 K
b00011101 L
b00011111 M

#217
b11010111 K
b01001110 L
b11011111 M

#218
b11111110 K
b01001010 L
b11111110 M

#219
b01000011 K
b01010111 L
b01010111 M

#220
b00100110 K
b00001110 L
b00101110 M

#221
b00101111 K
b10010011 L
b10111111 M

#222
b10011010 K
b01111110 L
b11111110 M

#223
b01010001 K
b11100111 L
b11110111 M

#224
b00010110 K
b01101011 L
b01111111 M

#225
b10101110 K
b11101011 L
b11101111 M

#226
b00101101 K
b01100001 L
b01101101 M

#227
b01110111 K
b11111111 L
b11111111 M

#228
b11110010 K
b01011010 L
b11111010 M

#229
b10011101 K
b01001011 L
b11011111 M

#230
b01011011 K
b00011110 L
b01011111 M

#231
b01111100 K
b11110001 L
b11111101 M

#232
b11000110 K
b11111110 L
b11111110 M

#233
b01010100 K
b10010100 L
b11010100 M

#234
b00110000 K
b00001100 L
b00111100 M

#235
b10101000 K
b00010000 L
b10111000 M

#236
b00001110 K
b00001110 L
b00001110 M

#237
b10010001 K
b10101100 L
b10111101 M

#238
b11001000 K
b01010111 L
b11011111 M

#239
b11111001 K
b11101011 L
b11111011 M

#240
b01011011 K
b00000111 L
b01011111 M

#241
b01001101 K
b11110100 L
b11111101 M

#242
b10011010 K
b00001000 L
b10011010 M

#243
b10111110 K
b01101001 L
b11111111 M

#244
b10011000 K
b00011110 L
b10011110 M

#245
b11100000 K
b00101100 L
b11101100 M

#246
b00100010 K
b10110111 L
b10110111 M

#247
b01110110 K
b00100100 L
b01110110 M

#248
b10100101 K
b00110111 L
b10110111 M

#249
b00011010 K
b01110111 L
b01111111 M

#250
b01111101 K
b11011011 L
b11111111 M

#251
b00010110 K
b10000011 L
b10010111 M

#252
b00000101 K
b00011100 L
b00011101 M

#253
b10100010 K
b11100111 L
b11100111 M

#254
b11010111 K
b00000110 L
b11010111 M

#255
b11000101 K
b00100011 L
b11100111 M

#256
b01011110 K
b10000100 L
b11011110 M

#257
b00001100 K
b00011111 L
b00011111 M

#258
b11100001 K
b10110000 L
b11110001 M

#259
b10000110 K
b00010111 L
b10010111 M

#260
b01011110 K
b11011011 L
b11011111 M

#261
b11000011 K
b00011100 L
b11011111 M

#262
b10001011 K
b10101011 L
b10101011 M

#263
b01110110 K
b10111111 L
b11111111 M

#264
b10101101 K
b10011000 L
b10111101 M

#265
b10001100 K
b11010110 L
b11011110 M

#266
b11001011 K
b01100111 L
b11101111 M

#267
b00011000 K
b00101010 L
b00111010 M

#268
b01010000 K
b01000001 L
b01010001 M

#269
b00000000 K
b01011000 L
b01011000 M

#270
b01110111 K
b00110110 L
b01110111 M

#271
b10001000 K
b10001010 L
b10001010 M

#272
b10101010 K
b10111111 L
b10111111 M

#273
b11010110 K
b00111101 L
b11111111 M

#274
b00111101 K
b11111010 L
b11111111 M

#275
b11000000 K
b10010000 L
b11010000 M

#276
b11001011 K
b00011100 L
b11011111 M

#277
b11001001 K
b11111100 L
b11111101 M

#278
b11110110 K
b01110011 L
b11110111 M

#279
b11110000 K
b00110101 L
b11110101 M

#280
b00101011 K
b00110011 L
b00111011 M

#281
b01011100 K
b00011011 L
b01011111 M

#282
b00010101 K
b11000100 L
b11010101 M

#283
b01011101 K
b00111100 L
b01111101 M

#284
b10111111 K
b01010000 L
b11111111 M

#285
b10010101 K
b00000101 L
b10010101 M

#286
b10110010 K
b11111100 L
b11111110 M

#287
b11000001 K
b11111000 L
b11111001 M

#288
b11010101 K
b10100011 L
b11110111 M

#289
b01010110 K
b00101011 L
b01111111 M

#290
b11111000 K
b01101101 L
b11111101 M

#291
b01011010 K
b11000011 L
b11011011 M

#292
b00001010 K
b01111000 L
b01111010 M

#293
b01100011 K
b11110001 L
b11110011 M

#294
b01000011 K
b11010001 L
b11010011 M

#295
b01010111 K
b10110101 L
b11110111 M

#296
b11000100 K
b00011111 L
b11011111 M

#297
b00101001 K
b01101111 L
b01101111 M

#298
b01110011 K
b10111111 L
b11111111 M

#299
b11001110 K
b01011010 L
b11011110 M

#300
b01101001 K
b10001000 L
b11101001 M

#301
b00011110 K
b10001010 L
b10011110 M

#302
b11001000 K
b00110100 L
b11111100 M

#303
b00011110 K
b11110101 L
b11111111 M

#304
b01010100 K
b00100110 L
b01110110 M

#305
b10111010 K
b00001110 L
b10111110 M

#306
b01000010 K
b10011110 L
b11011110 M

#307
b11101100 K
b01001101 L
b11101101 M

#308
b10000000 K
b10101000 L
b10101000 M

#309
b00101001 K
b01101101 L
b01101101 M

#310
b00100111 K
b00000010 L
b00100111 M

#311
b00111111 K
b01100100 L
b01111111 M

#312
b10001001 K
b10001110 L
b10001111 M

#313
b10001110 K
b00010001 L
b10011111 M

#314
b01011110 K
b11001110 L
b11011110 M

#315
b00010000 K
b11000100 L
b11010100 M

#316
b11111101 K
b01000001 L
b11111101 M

#317
b00010001 K
b11100100 L
b11110101 M

#318
b11010110 K
b00001010 L
b11011110 M

#319
b10111000 K
b10111110 L
b10111110 M

#320
b11011001 K
b01001111 L
b11011111 M

#321
b11000111 K
b01101110 L
b11101111 M

#322
b00011101 K
b10011101 L
b10011101 M

#323
b10110001 K
b11100111 L
b11110111 M

#324
b00111101 K
b11101111 L
b11111111 M

#325
b01010011 K
b11000011 L
b11010011 M

#326
b10110100 K
b00011011 L
b10111111 M

#327
b00101110 K
b10101001 L
b10101111 M

#328
b01010011 K
b11100100 L
b11110111 M

#329
b11111100 K
b10011111 L
b11111111 M

#330
b10110000 K
b10111111 L
b10111111 M

#331
b01000100 K
b11101011 L
b11101111 M

#332
b01000100 K
b10011001 L
b11011101 M

#333
b11000111 K
b11000101 L
b11000111 M

#334
b10000111 K
b00101000 L
b10101111 M

#335
b00111001 K
b11111010 L
b11111011 M

#336
b00111110 K
b10110000 L
b10111110 M

#337
b00001001 K
b10011101 L
b10011101 M

#338
b10101110 K
b01101100 L
b11101110 M

#339
b00011010 K
b00110110 L
b00111110 M

#340
b00010010 K
b11010001 L
b11010011 M

#341
b01101010 K
b11111001 L
b11111011 M

#342
b00110110 K
b00100101 L
b00110111 M

#343
b10011100 K
b01111010 L
b11111110 M

#344
b00001011 K
b10110000 L
b10111011 M

#345
b11011011 K
b01110000 L
b11111011 M

#346
b10011000 K
b00011000 L
b10011000 M

#347
b01001111 K
b01000000 L
b01001111 M

#348
b01000000 K
b01010111 L
b01010111 M

#349
b01101000 K
b11111110 L
b11111110 M

#350
b10011110 K
b00000101 L
b10011111 M

#351
b00001010 K
b01010100 L
b01011110 M

#352
b00110010 K
b01001001 L
b01111011 M

#353
b10101011 K
b00001100 L
b10101111 M

#354
b01001111 K
b01101100 L
b01101111 M

#355
b11111101 K
b10011100 L
b11111101 M

#356
b00011100 K
b01100011 L
b01111111 M

#357
b11101111 K
b10011110 L
b11111111 M

#358
b10010111 K
b01001001 L
b11011111 M

#359
b10101001 K
b01111000 L
b11111001 M

#360
b11101100 K
b00101111 L
b11101111 M

#361
b10010001 K
b00101011 L
b10111011 M

#362
b10000100 K
b00010011 L
b10010111 M

#363
b10010001 K
b10101100 L
b10111101 M

#364
b01111111 K
b00101111 L
b01111111 M

#365
b00001000 K
b01000100 L
b01001100 M

#366
b11001000 K
b01101100 L
b11101100 M

#367
b01000101 K
b10110101 L
b11110101 M

#368
b10001110 K
b11010001 L
b11011111 M

#369
b00100111 K
b11110001 L
b11110111 M

#370
b01100101 K
b01101110 L
b01101111 M

#371
b11110100 K
b00110111 L
b11110111 M

#372
b10111111 K
b10011011 L
b10111111 M

#373
b01011101 K
b11110010 L
b11111111 M

#374
b11011000 K
b11010010 L
b11011010 M

#375
b10000010 K
b00110101 L
b10110111 M

#376
b11110101 K
b11110000 L
b11110101 M

#377
b11001010 K
b10111111 L
b11111111 M

#378
b00010111 K
b00010010 L
b00010111 M

#379
b11111000 K
b00000010 L
b11111010 M

#380
b01011101 K
b01011101 L
b01011101 M

#381
b10011101 K
b01100011 L
b11111111 M

#382
b00111000 K
b01000001 L
b01111001 M

#383
b11110000 K
b11110111 L
b11110111 M

#384
b11001001 K
b10111110 L
b11111111 M

#385
b00011000 K
b10010111 L
b10011111 M

#386
b00010100 K
b11010110 L
b11010110 M

#387
b11111111 K
b11011101 L
b11111111 M

#388
b00100010 K
b10100110 L
b10100110 M

#389
b11010001 K
b01100010 L
b11110011 M

#390
b00000000 K
b00101101 L
b00101101 M

#391
b10000011 K
b10011110 L
b10011111 M

#392
b10000011 K
b10001011 L
b10001011 M

#393
b11110000 K
b00100000 L
b11110000 M

#394
b10001101 K
b10110100 L
b10111101 M

#395
b10011010 K
b10101101 L
b10111111 M

#396
b11010101 K
b00100100 L
b11110101 M

#397
b01100100 K
b01101000 L
b01101100 M

#398
b01100011 K
b11111111 L
b11111111 M

#399
b11110100 K
b00111100 L
b11111100 M

#400
b11110110 K
b00011111 L
b11111111 M

#401
b11110000 K
b10010010 L
b11110010 M

#402
b11011110 K
b10110111 L
b11111111 M

#403
b00100100 K
b01001111 L
b01101111 M

#404
b10111011 K
b10110100 L
b10111111 M

#405
b01111000 K
b00001001 L
b01111001 M

#406
b01010110 K
b11011111 L
b11011111 M

#407
b10111101 K
b11001101 L
b11111101 M

#408
b01100001 K
b01100110 L
b01100111 M

#409
b11010110 K
b11010111 L
b11010111 M

#410
b00011001 K
b10010001 L
b10011001 M

#411
b10001000 K
b00100111 L
b10101111 M

#412
b01001100 K
b01010101 L
b01011101 M

#413
b10111000 K
b11110000 L
b11111000 M

#414
b00010011 K
b10110101 L
b10110111 M

#415
b01011101 K
b10101111 L
b11111111 M

#416
b11001011 K
b00111110 L
b11111111 M

#417
b01100011 K
b11001101 L
b11101111 M

#418
b11000011 K
b00101000 L
b11101011 M

#419
b11011010 K
b11010011 L
b11011011 M

#420
b01011100 K
b11111101 L
b11111101 M

#421
b11011011 K
b11110100 L
b11111111 M

#422
b11011101 K
b01000011 L
b11011111 M

#423
b11100000 K
b01110000 L
b11110000 M

#424
b00110101 K
b10010000 L
b10110101 M

#425
b01010011 K
b01000111 L
b01010111 M

#426
b11101000 K
b00001100 L
b11101100 M

#427
b01111000 K
b00000011 L
b01111011 M

#428
b11111110 K
b11011000 L
b11111110 M

#429
b10111111 K
b00101101 L
b10111111 M

#430
b11000011 K
b11110011 L
b11110011 M

#431
b10011110 K
b10000000 L
b10011110 M

#432
b00011010 K
b01101001 L
b01111011 M

#433
b10000110 K
b00000110 L
b10000110 M

#434
b11011001 K
b10000011 L
b11011011 M

#435
b11101110 K
b10001100 L
b11101110 M

#436
b01001101 K
b10011000 L
b11011101 M

#437
b01010001 K
b00001000 L
b01011001 M

#438
b10000010 K
b11101100 L
b11101110 M

#439
b01111111 K
b01001000 L
b01111111 M

#440
b10100110 K
b11100101 L
b11100111 M

#441
b10111001 K
b11100011 L
b11111011 M

#442
b11111111 K
b10111101 L
b11111111 M

#443
b00000110 K
b10010010 L
b10010110 M

#444
b11010001 K
b11111100 L
b11111101 M

#445
b00001101 K
b00010001 L
b00011101 M

#446
b01011100 K
b11100000 L
b11111100 M

#447
b01110111 K
b00011010 L
b01111111 M

#448
b10100110 K
b10010011 L
b10110111 M

#449
b00000000 K
b01101010 L
b01101010 M

#450
b10000010 K
b00000000 L
b10000010 M

#451
b11111001 K
b11111001 L
b11111001 M

#452
b00000110 K
b10011011 L
b10011111 M

#453
b01001011 K
b00101101 L
b01101111 M

#454
b10011101 K
b00011101 L
b10011101 M

#455
b11110110 K
b00100111 L
b11110111 M

#456
b00100111 K
b11000101 L
b11100111 M

#457
b11001011 K
b11111010 L
b11111011 M

#458
b00000000 K
b11100000 L
b11100000 M

#459
b00010101 K
b11010001 L
b11010101 M

#460
b11100010 K
b01000101 L
b11100111 M

#461
b00101110 K
b10000000 L
b10101110 M

#462
b10110100 K
b11011001 L
b11111101 M

#463
b01111011 K
b00011100 L
b01111111 M

#464
b00000101 K
b01011100 L
b01011101 M

#465
b11101011 K
b10110000 L
b11111011 M

#466
b11011111 K
b01100111 L
b11111111 M

#467
b00100000 K
b01100010 L
b01100010 M

#468
b01001001 K
b01010111 L
b01011111 M

#469
b10010010 K
b10001011 L
b10011011 M

#470
b11101010 K
b01011010 L
b11111010 M

#471
b01101010 K
b00000111 L
b01101111 M

#472
b00110010 K
b10100001 L
b10110011 M

#473
b01011000 K
b00010001 L
b01011001 M

#474
b10110100 K
b11010100 L
b11110100 M

#475
b10101000 K
b00101100 L
b10101100 M

#476
b10101101 K
b00001100 L
b10101101 M

#477
b10110010 K
b00000000 L
b10110010 M

#478
b11100001 K
b10111010 L
b11111011 M

#479
b01011000 K
b00111010 L
b01111010 M

#480
b00110101 K
b00111001 L
b00111101 M

#481
b01001011 K
b10111100 L
b11111111 M

#482
b10100010 K
b01010011 L
b11110011 M

#483
b01100010 K
b01110001 L
b01110011 M

#484
b00010101 K
b00101101 L
b00111101 M

#485
b11010110 K
b10000110 L
b11010110 M

#486
b00001100 K
b11111011 L
b11111111 M

#487
b00110000 K
b01100001 L
b01110001 M

#488
b10100000 K
b00001010 L
b10101010 M

#489
b00101011 K
b01010111 L
b01111111 M

#490
b11011001 K
b10000001 L
b11011001 M

#491
b00100010 K
b01011000 L
b01111010 M

#492
b10001001 K
b10010010 L
b10011011 M

#493
b11011101 K
b01111000 L
b11111101 M

#494
b10011111 K
b01101011 L
b11111111 M

#495
b01100111 K
b01001011 L
b01101111 M

#496
b10001001 K
b01111000 L
b11111001 M

#497
b00101001 K
b11100100 L
b11101101 M

#498
b10011111 K
b01110011 L
b11111111 M

#499
b11100111 K
b10010000 L
b11110111 M

#500
b01100101 K
b11101110 L
b11101111 M

#501
b01101011 K
b00110100 L
b01111111 M

#502
b01101011 K
b00011100 L
b01111111 M

#503
b01100110 K
b00010000 L
b01110110 M

#504
b11110100 K
b01010010 L
b11110110 M

#505
b00011010 K
b01000110 L
b01011110 M

#506
b10000101 K
b01100011 L
b11100111 M

#507
b00000011 K
b01000101 L
b01000111 M

#508
b00010101 K
b01101111 L
b01111111 M

#509
b01100010 K
b01110001 L
b01110011 M

#510
b00110110 K
b10001110 L
b10111110 M

#511
b00110110 K
b10100011 L
b10110111 M

#512
b01110100 K
b00110000 L
b01110100 M

#513
b11111001 K
b01000100 L
b11111101 M

#514
b11110011 K
b00101001 L
b11111011 M

#515
b11010100 K
b10010001 L
b11010101 M

#516
b00110110 K
b11111000 L
b11111110 M

#517
b11100011 K
b00100101 L
b11100111 M

#518
b11110101 K
b11110111 L
b11110111 M

#519
b01011000 K
b00110010 L
b01111010 M

#520
b11000001 K
b11100101 L
b11100101 M

#521
b10100100 K
b11010110 L
b11110110 M

#522
b01010001 K
b11100101 L
b11110101 M

#523
b00110001 K
b01111001 L
b01111001 M

#524
b00111100 K
b00001001 L
b00111101 M

#525
b11011111 K
b00011100 L
b11011111 M

#526
b00111010 K
b01110101 L
b01111111 M

#527
b10000100 K
b00111101 L
b10111101 M

#528
b01011001 K
b01011110 L
b01011111 M

#529
b01010100 K
b10101101 L
b11111101 M

#530
b11100101 K
b01101110 L
b11101111 M

#531
b10000110 K
b10110111 L
b10110111 M

#532
b11000101 K
b10111101 L
b11111101 M

#533
b11100110 K
b11110101 L
b11110111 M

#534
b11000011 K
b10011100 L
b11011111 M

#535
b11001001 K
b00100110 L
b11101111 M

#536
b01101111 K
b10011001 L
b11111111 M

#537
b10000110 K
b10000110 L
b10000110 M

#538
b10011000 K
b01000111 L
b11011111 M

#539
b10000111 K
b01011001 L
b11011111 M

#540
b01010110 K
b00001000 L
b01011110 M

#541
b01000100 K
b11110111 L
b11110111 M

#542
b11011110 K
b10111001 L
b11111111 M

#543
b11000011 K
b10001100 L
b11001111 M

#544
b01001011 K
b00100101 L
b01101111 M

#545
b10110001 K
b00000010 L
b10110011 M

#546
b10000101 K
b10010110 L
b10010111 M

#547
b10100000 K
b00111001 L
b10111001 M

#548
b01101100 K
b10011111 L
b11111111 M

#549
b11000111 K
b00000110 L
b11000111 M

#550
b11110100 K
b01100010 L
b11110110 M

#551
b00100110 K
b00001010 L
b00101110 M

#552
b11111110 K
b00000000 L
b11111110 M

#553
b10101001 K
b01111110 L
b11111111 M

#554
b01010000 K
b01011011 L
b01011011 M

#555
b11010110 K
b00011100 L
b11011110 M

#556
b00110011 K
b10001100 L
b10111111 M

#557
b01010001 K
b10000000 L
b11010001 M

#558
b00110011 K
b00110010 L
b00110011 M

#559
b11111001 K
b01101111 L
b11111111 M

#560
b00001010 K
b11110110 L
b11111110 M

#561
b11111010 K
b01101000 L
b11111010 M

#562
b10001101 K
b01000011 L
b11001111 M

#563
b11001010 K
b10000111 L
b11001111 M

#564
b01000101 K
b11111110 L
b11111111 M

#565
b11101011 K
b11101110 L
b11101111 M

#566
b00101011 K
b00100100 L
b00101111 M

#567
b10010110 K
b11011011 L
b11011111 M

#568
b11100110 K
b01101010 L
b11101110 M

#569
b01001111 K
b01111001 L
b01111111 M

#570
b11101011 K
b11011010 L
b11111011 M

#571
b10000101 K
b01000111 L
b11000111 M

#572
b00110000 K
b01001111 L
b01111111 M

#573
b00011110 K
b01010000 L
b01011110 M

#574
b11110110 K
b01110110 L
b11110110 M

#575
b01011011 K
b11110010 L
b11111011 M

#576
b10011010 K
b11001010 L
b11011010 M

#577
b10101101 K
b11011000 L
b11111101 M

#578
b11000000 K
b10010000 L
b11010000 M

#579
b00001101 K
b00111100 L
b00111101 M

#580
b10101000 K
b10001100 L
b10101100 M

#581
b01011010 K
b11101011 L
b11111011 M

#582
b00011010 K
b00111110 L
b00111110 M

#583
b10100011 K
b10110111 L
b10110111 M

#584
b01110111 K
b11111101 L
b11111111 M

#585
b11011010 K
b11011110 L
b11011110 M

#586
b11110001 K
b00100100 L
b11110101 M

#587
b00100111 K
b00011110 L
b00111111 M

#588
b10101001 K
b01101111 L
b11101111 M

#589
b10010111 K
b10000010 L
b10010111 M

#590
b00001011 K
b11000110 L
b11001111 M

#591
b10010001 K
b11101110 L
b11111111 M

#592
b00010010 K
b10001000 L
b10011010 M

#593
b11100110 K
b10001101 L
b11101111 M

#594
b01001010 K
b01101111 L
b01101111 M

#595
b01010101 K
b00111001 L
b01111101 M

#596
b00110011 K
b11101001 L
b11111011 M

#597
b01110000 K
b00110100 L
b01110100 M

#598
b01000000 K
b10110000 L
b11110000 M

#599
b01010100 K
b00110010 L
b01110110 M

#600
b11111111 K
b01101101 L
b11111111 M

#601
b00100010 K
b00010101 L
b00110111 M

#602
b11000100 K
b11000101 L
b11000101 M

#603
b10001111 K
b00101101 L
b10101111 M

#604
b11000000 K
b00000001 L
b11000001 M

#605
b11100000 K
b11001101 L
b11101101 M

#606
b01101100 K
b10101001 L
b11101101 M

#607
b01110010 K
b01100010 L
b01110010 M

