src/tests/resources/operation/hw/constant/constant.sv
// Generated by CIRCT firtool-1.71.0
module Foo(	// hw/constant/constant.generic.mlir:3:3
  input  [7:0] a,	// hw/constant/constant.generic.mlir:4:8
  output [7:0] res	// hw/constant/constant.mlir:1:31
);

  assign res = a + 8'h2A;	// hw/constant/constant.generic.mlir:5:10, :6:10, :7:5
endmodule

src/tests/resources/operation/hw/constant/trace_vtor.vcd
$version Generated by VerilatedVcd $end
$timescale 1ps $end
 $scope module Foo $end
  $var wire 8 # a [7:0] $end
  $var wire 8 $ res [7:0] $end
  $scope module Foo $end
   $var wire 8 # a [7:0] $end
   $var wire 8 $ res [7:0] $end
  $upscope $end
 $upscope $end
$enddefinitions $end


#0
b00000100 #
b00101101 $
#1
b11101100 #
b00010101 $
#2
b01010010 #
b01111011 $
#3
b01110010 #
b10011011 $
#4
b01111001 #
b10100010 $
#5
b01111101 #
b10100110 $
#6
b01100101 #
b10001110 $
#7
b01011001 #
b10000010 $
#8
b11100011 #
b00001100 $
#9
b11001001 #
b11110010 $
#10
b01000001 #
b01101010 $
#11
b00010011 #
b00111100 $
#12
b10000100 #
b10101101 $
#13
b01100000 #
b10001001 $
#14
b00101001 #
b01010010 $
#15
b00110000 #
b01011001 $
#16
b11100111 #
b00010000 $
#17
b01101001 #
b10010010 $
#18
b11111011 #
b00100100 $
#19
b01100111 #
b10010000 $
#20
b11010011 #
b11111100 $
#21
b01111100 #
b10100101 $
#22
b10100101 #
b11001110 $
#23
b01010001 #
b01111010 $
#24
b10010001 #
b10111010 $
#25
b00000110 #
b00101111 $
#26
b10110110 #
b11011111 $
#27
b10001101 #
b10110110 $
#28
b10011011 #
b11000100 $
#29
b11001001 #
b11110010 $
#30
b11000101 #
b11101110 $
#31
b01110000 #
b10011001 $
#32
b10100001 #
b11001010 $
#33
b00101101 #
b01010110 $
#34
b10001010 #
b10110011 $
#35
b11010111 #
b00000000 $
#36
b01001100 #
b01110101 $
#37
b11111001 #
b00100010 $
#38
b11101010 #
b00010011 $
#39
b01001110 #
b01110111 $
#40
b10101111 #
b11011000 $
#41
b00011111 #
b01001000 $
#42
b10000010 #
b10101011 $
#43
b11011110 #
b00000111 $
#44
b00001101 #
b00110110 $
#45
b11001111 #
b11111000 $
#46
b11110110 #
b00011111 $
#47
b10110010 #
b11011011 $
#48
b00101010 #
b01010011 $
#49
b11101000 #
b00010001 $
#50
b11000100 #
b11101101 $
#51
b00100001 #
b01001010 $
#52
b01000011 #
b01101100 $
#53
b11000010 #
b11101011 $
#54
b10011010 #
b11000011 $
#55
b10011110 #
b11000111 $
#56
b00010111 #
b01000000 $
#57
b00111100 #
b01100101 $
#58
b10100010 #
b11001011 $
#59
b00000010 #
b00101011 $
#60
b00110101 #
b01011110 $
#61
b10101111 #
b11011000 $
#62
b10101010 #
b11010011 $
#63
b11000010 #
b11101011 $
#64
b11001010 #
b11110011 $
#65
b11111101 #
b00100110 $
#66
b00100011 #
b01001100 $
#67
b11101101 #
b00010110 $
#68
b01000100 #
b01101101 $
#69
b11100100 #
b00001101 $
#70
b00101111 #
b01011000 $
#71
b00001100 #
b00110101 $
#72
b01011010 #
b10000011 $
#73
b00100011 #
b01001100 $
#74
b10100111 #
b11010000 $
#75
b11101010 #
b00010011 $
#76
b11010100 #
b11111101 $
#77
b11010010 #
b11111011 $
#78
b00001010 #
b00110011 $
#79
b01011000 #
b10000001 $
#80
b01111010 #
b10100011 $
#81
b11101001 #
b00010010 $
#82
b00000110 #
b00101111 $
#83
b01101011 #
b10010100 $
#84
b01100110 #
b10001111 $
#85
b00100000 #
b01001001 $
#86
b00100001 #
b01001010 $
#87
b11000110 #
b11101111 $
#88
b00110010 #
b01011011 $
#89
b11110111 #
b00100000 $
#90
b01101101 #
b10010110 $
#91
b00011110 #
b01000111 $
#92
b10001101 #
b10110110 $
#93
b11000111 #
b11110000 $
#94
b11011000 #
b00000001 $
#95
b00101110 #
b01010111 $
#96
b01001101 #
b01110110 $
#97
b10011101 #
b11000110 $
#98
b10101101 #
b11010110 $
#99
b00100101 #
b01001110 $
