src/tests/resources/operation/seq/firmem_mask/firmem_mask.sv
// Generated by CIRCT firtool-1.71.0
// VCS coverage exclude_file
module memory_4x8(	// seq/firmem_mask/firmem_mask.generic.mlir:4:14
  input  [1:0] RW0_addr,
  input        RW0_en,
               RW0_clk,
               RW0_wmode,
  input  [7:0] RW0_wdata,
  output [7:0] RW0_rdata,
  input  [1:0] RW0_wmask
);

  reg [7:0] Memory[0:3];	// seq/firmem_mask/firmem_mask.generic.mlir:4:14
  reg [1:0] _RW0_raddr_d0;	// seq/firmem_mask/firmem_mask.generic.mlir:4:14
  reg       _RW0_ren_d0;	// seq/firmem_mask/firmem_mask.generic.mlir:4:14
  reg       _RW0_rmode_d0;	// seq/firmem_mask/firmem_mask.generic.mlir:4:14
  always @(posedge RW0_clk) begin	// seq/firmem_mask/firmem_mask.generic.mlir:4:14
    _RW0_raddr_d0 <= RW0_addr;	// seq/firmem_mask/firmem_mask.generic.mlir:4:14
    _RW0_ren_d0 <= RW0_en;	// seq/firmem_mask/firmem_mask.generic.mlir:4:14
    _RW0_rmode_d0 <= RW0_wmode;	// seq/firmem_mask/firmem_mask.generic.mlir:4:14
    if (RW0_en & RW0_wmask[0] & RW0_wmode)	// seq/firmem_mask/firmem_mask.generic.mlir:4:14
      Memory[RW0_addr][32'h0 +: 4] <= RW0_wdata[3:0];	// seq/firmem_mask/firmem_mask.generic.mlir:4:14
    if (RW0_en & RW0_wmask[1] & RW0_wmode)	// seq/firmem_mask/firmem_mask.generic.mlir:4:14
      Memory[RW0_addr][32'h4 +: 4] <= RW0_wdata[7:4];	// seq/firmem_mask/firmem_mask.generic.mlir:4:14
  end // always @(posedge)
  `ifdef ENABLE_INITIAL_MEM_	// seq/firmem_mask/firmem_mask.generic.mlir:4:14
    `ifdef RANDOMIZE_REG_INIT	// seq/firmem_mask/firmem_mask.generic.mlir:4:14
      reg [31:0] _RANDOM;	// seq/firmem_mask/firmem_mask.generic.mlir:4:14
    `endif // RANDOMIZE_REG_INIT
    reg [31:0] _RANDOM_MEM;	// seq/firmem_mask/firmem_mask.generic.mlir:4:14
    initial begin	// seq/firmem_mask/firmem_mask.generic.mlir:4:14
      `INIT_RANDOM_PROLOG_	// seq/firmem_mask/firmem_mask.generic.mlir:4:14
      `ifdef RANDOMIZE_MEM_INIT	// seq/firmem_mask/firmem_mask.generic.mlir:4:14
        for (logic [2:0] i = 3'h0; i < 3'h4; i += 3'h1) begin
          _RANDOM_MEM = `RANDOM;	// seq/firmem_mask/firmem_mask.generic.mlir:4:14
          Memory[i[1:0]] = _RANDOM_MEM[7:0];	// seq/firmem_mask/firmem_mask.generic.mlir:4:14
        end
      `endif // RANDOMIZE_MEM_INIT
      `ifdef RANDOMIZE_REG_INIT	// seq/firmem_mask/firmem_mask.generic.mlir:4:14
        _RANDOM = {`RANDOM};	// seq/firmem_mask/firmem_mask.generic.mlir:4:14
        _RW0_raddr_d0 = _RANDOM[1:0];	// seq/firmem_mask/firmem_mask.generic.mlir:4:14
        _RW0_ren_d0 = _RANDOM[2];	// seq/firmem_mask/firmem_mask.generic.mlir:4:14
        _RW0_rmode_d0 = _RANDOM[3];	// seq/firmem_mask/firmem_mask.generic.mlir:4:14
      `endif // RANDOMIZE_REG_INIT
    end // initial
  `endif // ENABLE_INITIAL_MEM_
  assign RW0_rdata = _RW0_ren_d0 & ~_RW0_rmode_d0 ? Memory[_RW0_raddr_d0] : 8'bx;	// seq/firmem_mask/firmem_mask.generic.mlir:4:14
endmodule

// Standard header to adapt well known macros for register randomization.

// RANDOM may be set to an expression that produces a 32-bit random unsigned value.
`ifndef RANDOM
  `define RANDOM $random
`endif // not def RANDOM

// Users can define INIT_RANDOM as general code that gets injected into the
// initializer block for modules with registers.
`ifndef INIT_RANDOM
  `define INIT_RANDOM
`endif // not def INIT_RANDOM

// If using random initialization, you can also define RANDOMIZE_DELAY to
// customize the delay used, otherwise 0.002 is used.
`ifndef RANDOMIZE_DELAY
  `define RANDOMIZE_DELAY 0.002
`endif // not def RANDOMIZE_DELAY

// Define INIT_RANDOM_PROLOG_ for use in our modules below.
`ifndef INIT_RANDOM_PROLOG_
  `ifdef RANDOMIZE
    `ifdef VERILATOR
      `define INIT_RANDOM_PROLOG_ `INIT_RANDOM
    `else  // VERILATOR
      `define INIT_RANDOM_PROLOG_ `INIT_RANDOM #`RANDOMIZE_DELAY begin end
    `endif // VERILATOR
  `else  // RANDOMIZE
    `define INIT_RANDOM_PROLOG_
  `endif // RANDOMIZE
`endif // not def INIT_RANDOM_PROLOG_

// Include rmemory initializers in init blocks unless synthesis is set
`ifndef RANDOMIZE
  `ifdef RANDOMIZE_MEM_INIT
    `define RANDOMIZE
  `endif // RANDOMIZE_MEM_INIT
`endif // not def RANDOMIZE
`ifndef SYNTHESIS
  `ifndef ENABLE_INITIAL_MEM_
    `define ENABLE_INITIAL_MEM_
  `endif // not def ENABLE_INITIAL_MEM_
`endif // not def SYNTHESIS

module Foo(	// seq/firmem_mask/firmem_mask.generic.mlir:2:3
  input        clk,	// seq/firmem_mask/firmem_mask.generic.mlir:3:10
  input  [7:0] data_in_w,	// seq/firmem_mask/firmem_mask.generic.mlir:3:28
               data_in_rw,	// seq/firmem_mask/firmem_mask.generic.mlir:3:44
  input  [1:0] addr_r,	// seq/firmem_mask/firmem_mask.generic.mlir:3:62
               addr_w,	// seq/firmem_mask/firmem_mask.generic.mlir:3:76
               addr_rw,	// seq/firmem_mask/firmem_mask.generic.mlir:3:90
  input        mode,	// seq/firmem_mask/firmem_mask.generic.mlir:3:105
               enable_r,	// seq/firmem_mask/firmem_mask.generic.mlir:3:117
               enable_w,	// seq/firmem_mask/firmem_mask.generic.mlir:3:132
               enable_rw,	// seq/firmem_mask/firmem_mask.generic.mlir:3:148
  input  [1:0] mask_in,	// seq/firmem_mask/firmem_mask.generic.mlir:3:165
  output [7:0] rw_out
);

  memory_4x8 memory_ext (	// seq/firmem_mask/firmem_mask.generic.mlir:4:14
    .RW0_addr  (addr_rw),
    .RW0_en    (enable_rw),
    .RW0_clk   (clk),
    .RW0_wmode (mode),
    .RW0_wdata (data_in_rw),
    .RW0_rdata (rw_out),
    .RW0_wmask (mask_in)
  );	// seq/firmem_mask/firmem_mask.generic.mlir:4:14
endmodule

src/tests/resources/operation/seq/firmem_mask/test.vcd
$version Generated by KCIRCT $end
$timescale 1s $end
 $scope module Foo $end
  $var wire 1 . clk $end
  $var wire 8 / data_in_w [7:0] $end
  $var wire 8 : data_in_rw [7:0] $end
  $var wire 2 ; addr_r [1:0] $end
  $var wire 2 < addr_w [1:0] $end
  $var wire 2 = addr_rw [1:0] $end
  $var wire 1 > mode $end
  $var wire 1 ? enable_r $end
  $var wire 1 @ enable_w $end
  $var wire 1 A enable_rw $end
  $var wire 2 B mask_in [1:0] $end
  $var wire 8 I rw_out [7:0] $end
  $scope module Foo $end
   $var wire 1 . clk $end
   $var wire 8 / data_in_w [7:0] $end
   $var wire 8 : data_in_rw [7:0] $end
   $var wire 2 ; addr_r [1:0] $end
   $var wire 2 < addr_w [1:0] $end
   $var wire 2 = addr_rw [1:0] $end
   $var wire 1 > mode $end
   $var wire 1 ? enable_r $end
   $var wire 1 @ enable_w $end
   $var wire 1 A enable_rw $end
   $var wire 2 B mask_in [1:0] $end
   $var wire 8 I rw_out [7:0] $end
   $scope module memory_ext $end
    $var wire 2 C RW0_addr [1:0] $end
    $var wire 1 D RW0_en $end
    $var wire 1 E RW0_wmode $end
    $var wire 8 F RW0_wdata [7:0] $end
    $var wire 2 G RW0_wmask [1:0] $end
    $var wire 8 H RW0_rdata [7:0] $end
    $var wire 8 J Memory[0] [7:0] $end
    $var wire 8 K Memory[1] [7:0] $end
    $var wire 8 L Memory[2] [7:0] $end
    $var wire 8 M Memory[3] [7:0] $end
   $upscope $end
  $upscope $end
 $upscope $end
$enddefinitions $end

#0
1.
b01010110 /
b01000000 :
b00 ;
b01 <
b10 =
1>
0?
1@
1A
b10 B
b00000000 I
b01000000 L

#1
0.
b10101011 /
b10111000 :
b00 ;
b00 <
b11 =
1>
0?
1@
0A
b01 B
b00000000 I
b01000000 L

#2
1.
b00000000 /
b00000000 :
b01 ;
b00 <
b10 =
0>
1?
0@
1A
b11 B
b01000000 I
b01000000 L

#3
0.
b01000110 /
b01010010 :
b11 ;
b01 <
b00 =
0>
0?
0@
1A
b01 B
b01000000 I
b01000000 L

#4
1.
b01111010 /
b00010111 :
b00 ;
b10 <
b11 =
1>
0?
1@
1A
b01 B
b00000000 I
b01000000 L
b00000111 M

#5
0.
b00001111 /
b00100011 :
b10 ;
b10 <
b11 =
1>
0?
0@
1A
b00 B
b00000000 I
b01000000 L
b00000111 M

#6
1.
b00000000 /
b00000000 :
b01 ;
b00 <
b10 =
0>
1?
0@
1A
b11 B
b01000000 I
b01000000 L
b00000111 M

#7
0.
b11101100 /
b10000101 :
b01 ;
b01 <
b11 =
0>
0?
1@
0A
b00 B
b01000000 I
b01000000 L
b00000111 M

#8
1.
b11110001 /
b10111111 :
b00 ;
b01 <
b10 =
1>
0?
1@
1A
b11 B
b00000000 I
b10111111 L
b00000111 M

#9
0.
b00011000 /
b01000101 :
b01 ;
b01 <
b11 =
1>
1?
1@
0A
b10 B
b00000000 I
b10111111 L
b00000111 M

#10
1.
b00000000 /
b00000000 :
b01 ;
b00 <
b10 =
0>
1?
0@
1A
b11 B
b10111111 I
b10111111 L
b00000111 M

#11
0.
b01000101 /
b00011000 :
b00 ;
b00 <
b00 =
1>
1?
1@
1A
b10 B
b10111111 I
b10111111 L
b00000111 M

#12
1.
b00000101 /
b11001000 :
b00 ;
b01 <
b10 =
1>
0?
1@
1A
b10 B
b00000000 I
b11001111 L
b00000111 M

#13
0.
b11001110 /
b01011000 :
b00 ;
b10 <
b11 =
0>
0?
0@
0A
b00 B
b00000000 I
b11001111 L
b00000111 M

#14
1.
b00000000 /
b00000000 :
b10 ;
b00 <
b11 =
0>
1?
0@
1A
b10 B
b00000111 I
b11001111 L
b00000111 M

#15
0.
b11010000 /
b10001011 :
b01 ;
b00 <
b11 =
1>
1?
0@
0A
b10 B
b00000111 I
b11001111 L
b00000111 M

#16
1.
b01000111 /
b01010101 :
b00 ;
b10 <
b11 =
1>
0?
1@
1A
b00 B
b00000000 I
b11001111 L
b00000111 M

#17
0.
b00110010 /
b11001111 :
b11 ;
b01 <
b10 =
0>
0?
0@
1A
b00 B
b00000000 I
b11001111 L
b00000111 M

#18
1.
b00000000 /
b00000000 :
b00 ;
b00 <
b01 =
0>
1?
0@
1A
b10 B
b00000000 I
b11001111 L
b00000111 M

#19
0.
b00100110 /
b10100011 :
b11 ;
b10 <
b10 =
1>
1?
1@
0A
b10 B
b00000000 I
b11001111 L
b00000111 M

#20
1.
b01011010 /
b00110001 :
b00 ;
b11 <
b00 =
1>
0?
1@
1A
b11 B
b00000000 I
b00110001 J
b11001111 L
b00000111 M

#21
0.
b00011001 /
b01000100 :
b00 ;
b01 <
b10 =
0>
1?
1@
1A
b00 B
b00000000 I
b00110001 J
b11001111 L
b00000111 M

#22
1.
b00000000 /
b00000000 :
b10 ;
b00 <
b11 =
0>
1?
0@
1A
b11 B
b00000111 I
b00110001 J
b11001111 L
b00000111 M

#23
0.
b01111100 /
b01100111 :
b11 ;
b10 <
b01 =
1>
1?
1@
1A
b10 B
b00000111 I
b00110001 J
b11001111 L
b00000111 M

#24
1.
b10001100 /
b00011111 :
b00 ;
b00 <
b01 =
1>
0?
1@
1A
b01 B
b00000000 I
b00110001 J
b00001111 K
b11001111 L
b00000111 M

#25
0.
b10001100 /
b11100000 :
b11 ;
b01 <
b10 =
0>
1?
0@
0A
b10 B
b00000000 I
b00110001 J
b00001111 K
b11001111 L
b00000111 M

#26
1.
b00000000 /
b00000000 :
b01 ;
b00 <
b10 =
0>
1?
0@
1A
b10 B
b11001111 I
b00110001 J
b00001111 K
b11001111 L
b00000111 M

#27
0.
b10110000 /
b10010011 :
b00 ;
b10 <
b11 =
0>
1?
0@
0A
b11 B
b11001111 I
b00110001 J
b00001111 K
b11001111 L
b00000111 M

#28
1.
b01001100 /
b00110100 :
b00 ;
b11 <
b00 =
1>
0?
1@
1A
b00 B
b00000000 I
b00110001 J
b00001111 K
b11001111 L
b00000111 M

#29
0.
b11010100 /
b10001010 :
b11 ;
b10 <
b01 =
1>
1?
1@
1A
b10 B
b00000000 I
b00110001 J
b00001111 K
b11001111 L
b00000111 M

#30
1.
b00000000 /
b00000000 :
b11 ;
b00 <
b00 =
0>
1?
0@
1A
b00 B
b00110001 I
b00110001 J
b00001111 K
b11001111 L
b00000111 M

#31
0.
b10000011 /
b00100110 :
b01 ;
b00 <
b11 =
0>
0?
0@
1A
b10 B
b00110001 I
b00110001 J
b00001111 K
b11001111 L
b00000111 M

#32
1.
b00000001 /
b10000111 :
b00 ;
b10 <
b11 =
1>
0?
1@
1A
b10 B
b00000000 I
b00110001 J
b00001111 K
b11001111 L
b10000111 M

#33
0.
b10101100 /
b00101000 :
b00 ;
b01 <
b10 =
1>
0?
1@
1A
b01 B
b00000000 I
b00110001 J
b00001111 K
b11001111 L
b10000111 M

#34
1.
b00000000 /
b00000000 :
b11 ;
b00 <
b00 =
0>
1?
0@
1A
b11 B
b00110001 I
b00110001 J
b00001111 K
b11001111 L
b10000111 M

#35
0.
b11100100 /
b10001011 :
b00 ;
b01 <
b00 =
0>
1?
0@
1A
b10 B
b00110001 I
b00110001 J
b00001111 K
b11001111 L
b10000111 M

#36
1.
b10000110 /
b10010100 :
b00 ;
b01 <
b10 =
1>
0?
1@
1A
b00 B
b00000000 I
b00110001 J
b00001111 K
b11001111 L
b10000111 M

#37
0.
b01010100 /
b00001101 :
b01 ;
b11 <
b11 =
1>
0?
1@
1A
b00 B
b00000000 I
b00110001 J
b00001111 K
b11001111 L
b10000111 M

#38
1.
b00000000 /
b00000000 :
b01 ;
b00 <
b10 =
0>
1?
0@
1A
b01 B
b11001111 I
b00110001 J
b00001111 K
b11001111 L
b10000111 M

#39
0.
b00010001 /
b11001001 :
b00 ;
b10 <
b01 =
1>
0?
1@
0A
b00 B
b11001111 I
b00110001 J
b00001111 K
b11001111 L
b10000111 M

#40
1.
b11101000 /
b00110011 :
b00 ;
b00 <
b01 =
1>
0?
1@
1A
b00 B
b00000000 I
b00110001 J
b00001111 K
b11001111 L
b10000111 M

#41
0.
b00100101 /
b01110110 :
b01 ;
b11 <
b00 =
0>
0?
1@
1A
b01 B
b00000000 I
b00110001 J
b00001111 K
b11001111 L
b10000111 M

#42
1.
b00000000 /
b00000000 :
b01 ;
b00 <
b10 =
0>
1?
0@
1A
b00 B
b11001111 I
b00110001 J
b00001111 K
b11001111 L
b10000111 M

#43
0.
b10110000 /
b11111101 :
b00 ;
b01 <
b11 =
0>
1?
0@
1A
b00 B
b11001111 I
b00110001 J
b00001111 K
b11001111 L
b10000111 M

#44
1.
b01101100 /
b00101110 :
b00 ;
b11 <
b00 =
1>
0?
1@
1A
b01 B
b00000000 I
b00111110 J
b00001111 K
b11001111 L
b10000111 M

#45
0.
b01001100 /
b00101010 :
b11 ;
b01 <
b10 =
0>
1?
1@
1A
b11 B
b00000000 I
b00111110 J
b00001111 K
b11001111 L
b10000111 M

#46
1.
b00000000 /
b00000000 :
b11 ;
b00 <
b00 =
0>
1?
0@
1A
b10 B
b00111110 I
b00111110 J
b00001111 K
b11001111 L
b10000111 M

#47
0.
b10010000 /
b01011000 :
b11 ;
b10 <
b00 =
1>
0?
1@
0A
b10 B
b00111110 I
b00111110 J
b00001111 K
b11001111 L
b10000111 M

#48
1.
b00101111 /
b10011001 :
b00 ;
b11 <
b00 =
1>
0?
1@
1A
b11 B
b00000000 I
b10011001 J
b00001111 K
b11001111 L
b10000111 M

#49
0.
b11000001 /
b01001101 :
b00 ;
b11 <
b01 =
1>
1?
1@
1A
b01 B
b00000000 I
b10011001 J
b00001111 K
b11001111 L
b10000111 M

#50
1.
b00000000 /
b00000000 :
b01 ;
b00 <
b10 =
0>
1?
0@
1A
b11 B
b11001111 I
b10011001 J
b00001111 K
b11001111 L
b10000111 M

#51
0.
b00101000 /
b10110100 :
b11 ;
b00 <
b00 =
0>
1?
0@
0A
b01 B
b11001111 I
b10011001 J
b00001111 K
b11001111 L
b10000111 M

#52
1.
b11010111 /
b11001111 :
b00 ;
b10 <
b11 =
1>
0?
1@
1A
b00 B
b00000000 I
b10011001 J
b00001111 K
b11001111 L
b10000111 M

#53
0.
b01100110 /
b10111000 :
b00 ;
b10 <
b11 =
1>
0?
1@
1A
b00 B
b00000000 I
b10011001 J
b00001111 K
b11001111 L
b10000111 M

#54
1.
b00000000 /
b00000000 :
b10 ;
b00 <
b11 =
0>
1?
0@
1A
b10 B
b10000111 I
b10011001 J
b00001111 K
b11001111 L
b10000111 M

#55
0.
b11011011 /
b00100100 :
b11 ;
b00 <
b00 =
0>
0?
0@
0A
b01 B
b10000111 I
b10011001 J
b00001111 K
b11001111 L
b10000111 M

#56
1.
b10101001 /
b11110101 :
b00 ;
b00 <
b01 =
1>
0?
1@
1A
b00 B
b00000000 I
b10011001 J
b00001111 K
b11001111 L
b10000111 M

#57
0.
b10000010 /
b11111111 :
b11 ;
b10 <
b10 =
0>
1?
1@
1A
b10 B
b00000000 I
b10011001 J
b00001111 K
b11001111 L
b10000111 M

#58
1.
b00000000 /
b00000000 :
b01 ;
b00 <
b10 =
0>
1?
0@
1A
b01 B
b11001111 I
b10011001 J
b00001111 K
b11001111 L
b10000111 M

#59
0.
b11111001 /
b00110011 :
b11 ;
b10 <
b01 =
0>
1?
0@
0A
b10 B
b11001111 I
b10011001 J
b00001111 K
b11001111 L
b10000111 M

#60
1.
b11001110 /
b00001111 :
b00 ;
b11 <
b00 =
1>
0?
1@
1A
b00 B
b00000000 I
b10011001 J
b00001111 K
b11001111 L
b10000111 M

#61
0.
b11100011 /
b01000111 :
b10 ;
b01 <
b11 =
1>
0?
0@
0A
b10 B
b00000000 I
b10011001 J
b00001111 K
b11001111 L
b10000111 M

#62
1.
b00000000 /
b00000000 :
b00 ;
b00 <
b01 =
0>
1?
0@
1A
b11 B
b00001111 I
b10011001 J
b00001111 K
b11001111 L
b10000111 M

#63
0.
b00100100 /
b11110101 :
b11 ;
b00 <
b10 =
0>
1?
1@
1A
b11 B
b00001111 I
b10011001 J
b00001111 K
b11001111 L
b10000111 M

#64
1.
b10011110 /
b01110011 :
b00 ;
b10 <
b11 =
1>
0?
1@
1A
b00 B
b00000000 I
b10011001 J
b00001111 K
b11001111 L
b10000111 M

#65
0.
b00000001 /
b10010000 :
b01 ;
b11 <
b10 =
1>
0?
1@
1A
b11 B
b00000000 I
b10011001 J
b00001111 K
b11001111 L
b10000111 M

#66
1.
b00000000 /
b00000000 :
b10 ;
b00 <
b11 =
0>
1?
0@
1A
b00 B
b10000111 I
b10011001 J
b00001111 K
b11001111 L
b10000111 M

#67
0.
b10110011 /
b10000110 :
b10 ;
b00 <
b10 =
0>
0?
0@
1A
b00 B
b10000111 I
b10011001 J
b00001111 K
b11001111 L
b10000111 M

#68
1.
b00011010 /
b00000011 :
b00 ;
b01 <
b10 =
1>
0?
1@
1A
b11 B
b00000000 I
b10011001 J
b00001111 K
b00000011 L
b10000111 M

#69
0.
b11011111 /
b10100110 :
b10 ;
b11 <
b01 =
0>
1?
1@
0A
b01 B
b00000000 I
b10011001 J
b00001111 K
b00000011 L
b10000111 M

#70
1.
b00000000 /
b00000000 :
b00 ;
b00 <
b01 =
0>
1?
0@
1A
b01 B
b00001111 I
b10011001 J
b00001111 K
b00000011 L
b10000111 M

#71
0.
b00001101 /
b01101110 :
b00 ;
b11 <
b00 =
1>
0?
0@
1A
b11 B
b00001111 I
b10011001 J
b00001111 K
b00000011 L
b10000111 M

#72
1.
b11111111 /
b11100101 :
b00 ;
b01 <
b10 =
1>
0?
1@
1A
b11 B
b00000000 I
b10011001 J
b00001111 K
b11100101 L
b10000111 M

#73
0.
b10010111 /
b11110010 :
b10 ;
b10 <
b10 =
0>
1?
1@
1A
b10 B
b00000000 I
b10011001 J
b00001111 K
b11100101 L
b10000111 M

#74
1.
b00000000 /
b00000000 :
b00 ;
b00 <
b01 =
0>
1?
0@
1A
b11 B
b00001111 I
b10011001 J
b00001111 K
b11100101 L
b10000111 M

#75
0.
b01000001 /
b01101101 :
b10 ;
b00 <
b00 =
1>
0?
0@
0A
b00 B
b00001111 I
b10011001 J
b00001111 K
b11100101 L
b10000111 M

#76
1.
b10101001 /
b01101111 :
b00 ;
b10 <
b11 =
1>
0?
1@
1A
b11 B
b00000000 I
b10011001 J
b00001111 K
b11100101 L
b01101111 M

#77
0.
b01100101 /
b01110000 :
b01 ;
b10 <
b01 =
1>
1?
0@
1A
b11 B
b00000000 I
b10011001 J
b00001111 K
b11100101 L
b01101111 M

#78
1.
b00000000 /
b00000000 :
b01 ;
b00 <
b10 =
0>
1?
0@
1A
b10 B
b11100101 I
b10011001 J
b00001111 K
b11100101 L
b01101111 M

#79
0.
b00101100 /
b11000011 :
b00 ;
b10 <
b10 =
1>
1?
1@
0A
b11 B
b11100101 I
b10011001 J
b00001111 K
b11100101 L
b01101111 M

#80
1.
b10001001 /
b10011011 :
b00 ;
b10 <
b11 =
1>
0?
1@
1A
b11 B
b00000000 I
b10011001 J
b00001111 K
b11100101 L
b10011011 M

#81
0.
b10110110 /
b10011101 :
b11 ;
b10 <
b01 =
1>
1?
1@
0A
b10 B
b00000000 I
b10011001 J
b00001111 K
b11100101 L
b10011011 M

#82
1.
b00000000 /
b00000000 :
b01 ;
b00 <
b10 =
0>
1?
0@
1A
b11 B
b11100101 I
b10011001 J
b00001111 K
b11100101 L
b10011011 M

#83
0.
b10001110 /
b10000101 :
b00 ;
b10 <
b11 =
1>
0?
1@
0A
b10 B
b11100101 I
b10011001 J
b00001111 K
b11100101 L
b10011011 M

#84
1.
b01110100 /
b11001011 :
b00 ;
b00 <
b01 =
1>
0?
1@
1A
b11 B
b00000000 I
b10011001 J
b11001011 K
b11100101 L
b10011011 M

#85
0.
b10100011 /
b11001110 :
b01 ;
b01 <
b00 =
1>
0?
1@
0A
b00 B
b00000000 I
b10011001 J
b11001011 K
b11100101 L
b10011011 M

#86
1.
b00000000 /
b00000000 :
b00 ;
b00 <
b01 =
0>
1?
0@
1A
b00 B
b11001011 I
b10011001 J
b11001011 K
b11100101 L
b10011011 M

#87
0.
b00100001 /
b00011110 :
b10 ;
b00 <
b11 =
0>
0?
1@
1A
b10 B
b11001011 I
b10011001 J
b11001011 K
b11100101 L
b10011011 M

#88
1.
b00001101 /
b00110101 :
b00 ;
b11 <
b00 =
1>
0?
1@
1A
b11 B
b00000000 I
b00110101 J
b11001011 K
b11100101 L
b10011011 M

#89
0.
b10001011 /
b00010111 :
b11 ;
b01 <
b01 =
1>
1?
1@
0A
b11 B
b00000000 I
b00110101 J
b11001011 K
b11100101 L
b10011011 M

#90
1.
b00000000 /
b00000000 :
b00 ;
b00 <
b01 =
0>
1?
0@
1A
b11 B
b11001011 I
b00110101 J
b11001011 K
b11100101 L
b10011011 M

#91
0.
b00011101 /
b10111010 :
b01 ;
b10 <
b01 =
1>
1?
0@
0A
b10 B
b11001011 I
b00110101 J
b11001011 K
b11100101 L
b10011011 M

#92
1.
b01100101 /
b10001011 :
b00 ;
b00 <
b01 =
1>
0?
1@
1A
b01 B
b00000000 I
b00110101 J
b11001011 K
b11100101 L
b10011011 M

#93
0.
b11100011 /
b00010000 :
b11 ;
b11 <
b01 =
0>
1?
0@
0A
b00 B
b00000000 I
b00110101 J
b11001011 K
b11100101 L
b10011011 M

#94
1.
b00000000 /
b00000000 :
b10 ;
b00 <
b11 =
0>
1?
0@
1A
b00 B
b10011011 I
b00110101 J
b11001011 K
b11100101 L
b10011011 M

#95
0.
b11101111 /
b10111000 :
b01 ;
b01 <
b01 =
1>
1?
0@
0A
b10 B
b10011011 I
b00110101 J
b11001011 K
b11100101 L
b10011011 M

#96
1.
b01110100 /
b00001010 :
b00 ;
b10 <
b11 =
1>
0?
1@
1A
b01 B
b00000000 I
b00110101 J
b11001011 K
b11100101 L
b10011010 M

#97
0.
b10010011 /
b00111011 :
b11 ;
b11 <
b10 =
1>
0?
1@
1A
b10 B
b00000000 I
b00110101 J
b11001011 K
b11100101 L
b10011010 M

#98
1.
b00000000 /
b00000000 :
b11 ;
b00 <
b00 =
0>
1?
0@
1A
b01 B
b00110101 I
b00110101 J
b11001011 K
b11100101 L
b10011010 M

#99
0.
b00111010 /
b11001111 :
b10 ;
b01 <
b00 =
1>
0?
1@
0A
b01 B
b00110101 I
b00110101 J
b11001011 K
b11100101 L
b10011010 M

#100
1.
b00001101 /
b01000100 :
b00 ;
b10 <
b11 =
1>
0?
1@
1A
b00 B
b00000000 I
b00110101 J
b11001011 K
b11100101 L
b10011010 M

#101
0.
b00010101 /
b00100010 :
b10 ;
b11 <
b10 =
0>
1?
0@
1A
b01 B
b00000000 I
b00110101 J
b11001011 K
b11100101 L
b10011010 M

#102
1.
b00000000 /
b00000000 :
b00 ;
b00 <
b01 =
0>
1?
0@
1A
b01 B
b11001011 I
b00110101 J
b11001011 K
b11100101 L
b10011010 M

#103
0.
b00000111 /
b10000001 :
b00 ;
b00 <
b01 =
0>
0?
0@
0A
b01 B
b11001011 I
b00110101 J
b11001011 K
b11100101 L
b10011010 M

#104
1.
b11100001 /
b11011000 :
b00 ;
b11 <
b00 =
1>
0?
1@
1A
b00 B
b00000000 I
b00110101 J
b11001011 K
b11100101 L
b10011010 M

#105
0.
b10111110 /
b11101111 :
b11 ;
b11 <
b11 =
0>
0?
1@
1A
b00 B
b00000000 I
b00110101 J
b11001011 K
b11100101 L
b10011010 M

#106
1.
b00000000 /
b00000000 :
b00 ;
b00 <
b01 =
0>
1?
0@
1A
b00 B
b11001011 I
b00110101 J
b11001011 K
b11100101 L
b10011010 M

#107
0.
b10100000 /
b10000010 :
b01 ;
b00 <
b11 =
0>
1?
1@
1A
b00 B
b11001011 I
b00110101 J
b11001011 K
b11100101 L
b10011010 M

#108
1.
b01111101 /
b00101010 :
b00 ;
b00 <
b01 =
1>
0?
1@
1A
b11 B
b00000000 I
b00110101 J
b00101010 K
b11100101 L
b10011010 M

#109
0.
b11100010 /
b01011000 :
b10 ;
b00 <
b10 =
0>
1?
1@
0A
b10 B
b00000000 I
b00110101 J
b00101010 K
b11100101 L
b10011010 M

#110
1.
b00000000 /
b00000000 :
b11 ;
b00 <
b00 =
0>
1?
0@
1A
b00 B
b00110101 I
b00110101 J
b00101010 K
b11100101 L
b10011010 M

#111
0.
b10111110 /
b11001101 :
b11 ;
b10 <
b11 =
1>
0?
1@
0A
b11 B
b00110101 I
b00110101 J
b00101010 K
b11100101 L
b10011010 M

#112
1.
b00100110 /
b01100110 :
b00 ;
b10 <
b11 =
1>
0?
1@
1A
b01 B
b00000000 I
b00110101 J
b00101010 K
b11100101 L
b10010110 M

#113
0.
b11000010 /
b01010101 :
b01 ;
b00 <
b01 =
1>
0?
1@
0A
b11 B
b00000000 I
b00110101 J
b00101010 K
b11100101 L
b10010110 M

#114
1.
b00000000 /
b00000000 :
b00 ;
b00 <
b01 =
0>
1?
0@
1A
b01 B
b00101010 I
b00110101 J
b00101010 K
b11100101 L
b10010110 M

#115
0.
b01010110 /
b00111000 :
b10 ;
b11 <
b11 =
1>
0?
0@
1A
b00 B
b00101010 I
b00110101 J
b00101010 K
b11100101 L
b10010110 M

#116
1.
b01110100 /
b00111001 :
b00 ;
b10 <
b11 =
1>
0?
1@
1A
b00 B
b00000000 I
b00110101 J
b00101010 K
b11100101 L
b10010110 M

#117
0.
b10010011 /
b11101100 :
b10 ;
b11 <
b10 =
1>
0?
1@
0A
b11 B
b00000000 I
b00110101 J
b00101010 K
b11100101 L
b10010110 M

#118
1.
b00000000 /
b00000000 :
b01 ;
b00 <
b10 =
0>
1?
0@
1A
b00 B
b11100101 I
b00110101 J
b00101010 K
b11100101 L
b10010110 M

#119
0.
b11011100 /
b10101101 :
b00 ;
b11 <
b01 =
1>
1?
0@
1A
b10 B
b11100101 I
b00110101 J
b00101010 K
b11100101 L
b10010110 M

#120
1.
b11110011 /
b01000100 :
b00 ;
b00 <
b01 =
1>
0?
1@
1A
b11 B
b00000000 I
b00110101 J
b01000100 K
b11100101 L
b10010110 M

#121
0.
b00000101 /
b11111100 :
b11 ;
b11 <
b11 =
1>
0?
1@
0A
b11 B
b00000000 I
b00110101 J
b01000100 K
b11100101 L
b10010110 M

#122
1.
b00000000 /
b00000000 :
b01 ;
b00 <
b10 =
0>
1?
0@
1A
b00 B
b11100101 I
b00110101 J
b01000100 K
b11100101 L
b10010110 M

#123
0.
b00100111 /
b01001001 :
b00 ;
b10 <
b00 =
1>
0?
0@
0A
b01 B
b11100101 I
b00110101 J
b01000100 K
b11100101 L
b10010110 M

#124
1.
b01100001 /
b00000010 :
b00 ;
b10 <
b11 =
1>
0?
1@
1A
b00 B
b00000000 I
b00110101 J
b01000100 K
b11100101 L
b10010110 M

#125
0.
b00111111 /
b10001110 :
b11 ;
b11 <
b01 =
1>
1?
0@
0A
b11 B
b00000000 I
b00110101 J
b01000100 K
b11100101 L
b10010110 M

#126
1.
b00000000 /
b00000000 :
b01 ;
b00 <
b10 =
0>
1?
0@
1A
b11 B
b11100101 I
b00110101 J
b01000100 K
b11100101 L
b10010110 M

#127
0.
b11100101 /
b01011100 :
b01 ;
b10 <
b00 =
0>
1?
1@
0A
b00 B
b11100101 I
b00110101 J
b01000100 K
b11100101 L
b10010110 M

#128
1.
b10010011 /
b10111011 :
b00 ;
b01 <
b10 =
1>
0?
1@
1A
b10 B
b00000000 I
b00110101 J
b01000100 K
b10110101 L
b10010110 M

