src/tests/resources/operation/comb/add/add.generic.sv
// Generated by CIRCT firtool-1.71.0
module Foo(	// comb/add/add.generic.generic.mlir:3:3
  input  [7:0] a,	// comb/add/add.generic.generic.mlir:4:8
               b,	// comb/add/add.generic.generic.mlir:4:19
  output [7:0] res	// comb/add/add.mlir:1:42
);

  assign res = a + b;	// comb/add/add.generic.generic.mlir:5:10, :6:5
endmodule

src/tests/resources/operation/comb/add/test.vcd
$version Generated by KCIRCT $end
$timescale 1s $end
 $scope module Foo $end
  $var wire 8 / a [7:0] $end
  $var wire 8 : b [7:0] $end
  $var wire 8 ; res [7:0] $end
  $scope module Foo $end
   $var wire 8 / a [7:0] $end
   $var wire 8 : b [7:0] $end
   $var wire 8 ; res [7:0] $end
  $upscope $end
 $upscope $end
$enddefinitions $end

#0
b11110001 /
b11100001 :
b11010010 ;

#1
b10100110 /
b10010100 :
b00111010 ;

#2
b11111000 /
b00011100 :
b00010100 ;

#3
b10011010 /
b00110000 :
b11001010 ;

#4
b11000110 /
b00010011 :
b11011001 ;

#5
b11101101 /
b01011010 :
b01000111 ;

#6
b00110111 /
b01110111 :
b10101110 ;

#7
b00100011 /
b01101001 :
b10001100 ;

#8
b11110110 /
b11111110 :
b11110100 ;

#9
b11001110 /
b11010011 :
b10100001 ;

#10
b10101111 /
b11100000 :
b10001111 ;

#11
b11111000 /
b11111011 :
b11110011 ;

#12
b10111011 /
b01000110 :
b00000001 ;

#13
b10010010 /
b11010110 :
b01101000 ;

#14
b10100111 /
b01110110 :
b00011101 ;

#15
b10101001 /
b11011111 :
b10001000 ;

#16
b11000110 /
b11101011 :
b10110001 ;

#17
b00011100 /
b11101100 :
b00001000 ;

#18
b11100001 /
b10011010 :
b01111011 ;

#19
b01111011 /
b00110101 :
b10110000 ;

#20
b10010110 /
b11100101 :
b01111011 ;

#21
b10100010 /
b11010001 :
b01110011 ;

#22
b11100100 /
b11001100 :
b10110000 ;

#23
b11000101 /
b10010010 :
b01010111 ;

#24
b01100110 /
b11010111 :
b00111101 ;

#25
b10000110 /
b10001010 :
b00010000 ;

#26
b10001111 /
b10111100 :
b01001011 ;

#27
b00011101 /
b00011111 :
b00111100 ;

#28
b10011001 /
b01101110 :
b00000111 ;

#29
b01110001 /
b10010110 :
b00000111 ;

#30
b10010010 /
b00111000 :
b11001010 ;

#31
b01001001 /
b01000100 :
b10001101 ;

#32
b11110100 /
b11001110 :
b11000010 ;

#33
b11000110 /
b10101010 :
b01110000 ;

#34
b11101101 /
b01100101 :
b01010010 ;

#35
b11100010 /
b01101010 :
b01001100 ;

#36
b01110011 /
b01001011 :
b10111110 ;

#37
b10000011 /
b11111011 :
b01111110 ;

#38
b11110101 /
b00101101 :
b00100010 ;

#39
b10111011 /
b11011100 :
b10010111 ;

#40
b01011011 /
b01001001 :
b10100100 ;

#41
b10111000 /
b11011011 :
b10010011 ;

#42
b10001001 /
b11100001 :
b01101010 ;

#43
b10101010 /
b00111011 :
b11100101 ;

#44
b11001010 /
b10100110 :
b01110000 ;

#45
b00011110 /
b10101010 :
b11001000 ;

#46
b10111100 /
b10110000 :
b01101100 ;

#47
b01101001 /
b11000001 :
b00101010 ;

#48
b10001101 /
b10100100 :
b00110001 ;

#49
b10110011 /
b00111110 :
b11110001 ;

#50
b10100100 /
b10101010 :
b01001110 ;

#51
b00111111 /
b01011111 :
b10011110 ;

#52
b00010001 /
b00001000 :
b00011001 ;

#53
b10101101 /
b10011000 :
b01000101 ;

#54
b10010111 /
b10101101 :
b01000100 ;

#55
b10000000 /
b00100110 :
b10100110 ;

#56
b00111011 /
b11111100 :
b00110111 ;

#57
b11110110 /
b10111100 :
b10110010 ;

#58
b11101100 /
b01100000 :
b01001100 ;

#59
b10010010 /
b00000011 :
b10010101 ;

#60
b10110101 /
b01010110 :
b00001011 ;

#61
b10000010 /
b00001111 :
b10010001 ;

#62
b01101101 /
b11101101 :
b01011010 ;

#63
b01110100 /
b11000100 :
b00111000 ;

#64
b11000110 /
b10000110 :
b01001100 ;

#65
b00000111 /
b10111000 :
b10111111 ;

#66
b11010101 /
b00010110 :
b11101011 ;

#67
b11000101 /
b00011111 :
b11100100 ;

#68
b11101011 /
b01000111 :
b00110010 ;

#69
b10000101 /
b00011100 :
b10100001 ;

#70
b10110101 /
b01100101 :
b00011010 ;

#71
b11110000 /
b10000000 :
b01110000 ;

#72
b11010010 /
b11000010 :
b10010100 ;

#73
b00001101 /
b11100001 :
b11101110 ;

#74
b10110100 /
b10010101 :
b01001001 ;

#75
b11101110 /
b01000001 :
b00101111 ;

#76
b00100101 /
b10011100 :
b11000001 ;

#77
b00011011 /
b11011111 :
b11111010 ;

#78
b11110100 /
b10101000 :
b10011100 ;

#79
b00110101 /
b11101100 :
b00100001 ;

#80
b11111001 /
b11100111 :
b11100000 ;

#81
b01100101 /
b11111010 :
b01011111 ;

#82
b00011101 /
b00110101 :
b01010010 ;

#83
b11101001 /
b00000111 :
b11110000 ;

#84
b10011000 /
b10100000 :
b00111000 ;

#85
b01101011 /
b11000100 :
b00101111 ;

#86
b10110010 /
b10101011 :
b01011101 ;

#87
b11111100 /
b01111110 :
b01111010 ;

#88
b01110001 /
b00011000 :
b10001001 ;

#89
b11111001 /
b01010100 :
b01001101 ;

#90
b10100110 /
b11100010 :
b10001000 ;

#91
b11110100 /
b00010001 :
b00000101 ;

#92
b11011011 /
b11011001 :
b10110100 ;

#93
b11110010 /
b00110001 :
b00100011 ;

#94
b11000101 /
b11111111 :
b11000100 ;

#95
b00100000 /
b10010111 :
b10110111 ;

#96
b10101011 /
b10011001 :
b01000100 ;

#97
b10110010 /
b10100101 :
b01010111 ;

#98
b11010011 /
b00101001 :
b11111100 ;

#99
b10110110 /
b11101100 :
b10100010 ;

#100
b10101101 /
b00010000 :
b10111101 ;

#101
b10001111 /
b11111000 :
b10000111 ;

#102
b00010001 /
b01101101 :
b01111110 ;

#103
b11011010 /
b00101110 :
b00001000 ;

#104
b10000101 /
b10001110 :
b00010011 ;

#105
b10000100 /
b10100110 :
b00101010 ;

#106
b01010111 /
b11000011 :
b00011010 ;

#107
b01100011 /
b01101100 :
b11001111 ;

#108
b10011111 /
b11110100 :
b10010011 ;

#109
b11001011 /
b01000110 :
b00010001 ;

#110
b11111000 /
b10110101 :
b10101101 ;

#111
b10110010 /
b00000000 :
b10110010 ;

#112
b11001110 /
b00000101 :
b11010011 ;

#113
b11101001 /
b11100100 :
b11001101 ;

#114
b10001100 /
b00001111 :
b10011011 ;

#115
b10100001 /
b10101010 :
b01001011 ;

#116
b00000011 /
b01101001 :
b01101100 ;

#117
b10101000 /
b00010010 :
b10111010 ;

#118
b10001010 /
b10011011 :
b00100101 ;

#119
b01000010 /
b10110000 :
b11110010 ;

#120
b10001100 /
b11000000 :
b01001100 ;

#121
b11101000 /
b11101110 :
b11010110 ;

#122
b11011101 /
b10111010 :
b10010111 ;

#123
b01111110 /
b11001100 :
b01001010 ;

#124
b11001110 /
b10111100 :
b10001010 ;

#125
b11010100 /
b11111010 :
b11001110 ;

#126
b00101011 /
b00110010 :
b01011101 ;

#127
b01101111 /
b10100001 :
b00010000 ;

#128
b11010011 /
b11001011 :
b10011110 ;

#129
b10110101 /
b10110001 :
b01100110 ;

#130
b10100001 /
b01010010 :
b11110011 ;

#131
b11100101 /
b10101111 :
b10010100 ;

#132
b00110100 /
b01100100 :
b10011000 ;

#133
b11010111 /
b00101101 :
b00000100 ;

#134
b10111110 /
b11110011 :
b10110001 ;

#135
b10001001 /
b00001010 :
b10010011 ;

#136
b11111011 /
b11010111 :
b11010010 ;

#137
b01001100 /
b11101100 :
b00111000 ;

#138
b01111100 /
b10011010 :
b00010110 ;

#139
b10100110 /
b10011011 :
b01000001 ;

#140
b00111010 /
b01111010 :
b10110100 ;

#141
b00100010 /
b00110000 :
b01010010 ;

#142
b00001101 /
b00011000 :
b00100101 ;

#143
b11001011 /
b10011100 :
b01100111 ;

#144
b11110101 /
b01100010 :
b01010111 ;

#145
b01000111 /
b10100010 :
b11101001 ;

#146
b00000100 /
b10001000 :
b10001100 ;

#147
b00000001 /
b10111111 :
b11000000 ;

#148
b00000011 /
b01111101 :
b10000000 ;

#149
b11100111 /
b11111111 :
b11100110 ;

#150
b00111011 /
b10011111 :
b11011010 ;

#151
b11001100 /
b01000100 :
b00010000 ;

#152
b00110000 /
b10111001 :
b11101001 ;

#153
b10010000 /
b01011110 :
b11101110 ;

#154
b10100000 /
b11101011 :
b10001011 ;

#155
b00100101 /
b00000011 :
b00101000 ;

#156
b01111001 /
b00001110 :
b10000111 ;

#157
b10100110 /
b10100111 :
b01001101 ;

#158
b10000110 /
b11001110 :
b01010100 ;

#159
b00011000 /
b01100001 :
b01111001 ;

#160
b11101001 /
b01011110 :
b01000111 ;

#161
b11000011 /
b00111111 :
b00000010 ;

#162
b11010010 /
b00001100 :
b11011110 ;

#163
b11011111 /
b10101011 :
b10001010 ;

#164
b00111100 /
b00111010 :
b01110110 ;

#165
b10001000 /
b01100110 :
b11101110 ;

#166
b10100110 /
b01101010 :
b00010000 ;

#167
b11010101 /
b10010010 :
b01100111 ;

#168
b10101100 /
b11111000 :
b10100100 ;

#169
b10111001 /
b10000000 :
b00111001 ;

#170
b01101111 /
b10100101 :
b00010100 ;

#171
b01011010 /
b10011011 :
b11110101 ;

#172
b10010000 /
b00001100 :
b10011100 ;

#173
b10011001 /
b01111110 :
b00010111 ;

#174
b11101100 /
b11111110 :
b11101010 ;

#175
b01001110 /
b00101010 :
b01111000 ;

#176
b01100011 /
b11010111 :
b00111010 ;

#177
b01011001 /
b11011110 :
b00110111 ;

#178
b01100111 /
b11010110 :
b00111101 ;

#179
b10101101 /
b11111010 :
b10100111 ;

#180
b01000110 /
b11110101 :
b00111011 ;

#181
b11110010 /
b10000011 :
b01110101 ;

#182
b01000001 /
b11000011 :
b00000100 ;

#183
b01010011 /
b10101100 :
b11111111 ;

#184
b00000011 /
b11000100 :
b11000111 ;

#185
b01010110 /
b00011011 :
b01110001 ;

#186
b11101101 /
b11001011 :
b10111000 ;

#187
b10111001 /
b10111110 :
b01110111 ;

#188
b00010110 /
b10101110 :
b11000100 ;

#189
b00110010 /
b00101111 :
b01100001 ;

#190
b01101000 /
b00110100 :
b10011100 ;

#191
b11111111 /
b11111011 :
b11111010 ;

#192
b10101100 /
b01000001 :
b11101101 ;

#193
b01111000 /
b11001110 :
b01000110 ;

#194
b10100011 /
b11011010 :
b01111101 ;

#195
b10001100 /
b01001010 :
b11010110 ;

#196
b01001101 /
b00001110 :
b01011011 ;

#197
b10000000 /
b11110000 :
b01110000 ;

#198
b11101000 /
b01011101 :
b01000101 ;

#199
b11111100 /
b01100111 :
b01100011 ;

#200
b11100101 /
b10110001 :
b10010110 ;

#201
b11100101 /
b00011101 :
b00000010 ;

#202
b10101001 /
b10100001 :
b01001010 ;

#203
b00010101 /
b11111100 :
b00010001 ;

#204
b01011000 /
b00111100 :
b10010100 ;

#205
b10101111 /
b10111000 :
b01100111 ;

#206
b01100101 /
b10001110 :
b11110011 ;

#207
b11011101 /
b00110100 :
b00010001 ;

#208
b11111010 /
b11011111 :
b11011001 ;

#209
b10010100 /
b01110111 :
b00001011 ;

#210
b01010010 /
b01001001 :
b10011011 ;

#211
b10101000 /
b11010111 :
b01111111 ;

#212
b11000111 /
b10110101 :
b01111100 ;

#213
b00101111 /
b01011100 :
b10001011 ;

#214
b10110111 /
b10000000 :
b00110111 ;

#215
b00000010 /
b10100010 :
b10100100 ;

#216
b11000101 /
b10010001 :
b01010110 ;

#217
b10011010 /
b10100111 :
b01000001 ;

#218
b00010100 /
b10011011 :
b10101111 ;

#219
b10110000 /
b00100000 :
b11010000 ;

#220
b10001100 /
b11010110 :
b01100010 ;

#221
b10110010 /
b00111011 :
b11101101 ;

#222
b11001111 /
b01110011 :
b01000010 ;

#223
b10110001 /
b10001011 :
b00111100 ;

#224
b01011110 /
b10010010 :
b11110000 ;

#225
b01001111 /
b00010011 :
b01100010 ;

#226
b11100000 /
b11110111 :
b11010111 ;

#227
b00110001 /
b00011011 :
b01001100 ;

#228
b11000111 /
b00011011 :
b11100010 ;

#229
b00110110 /
b10111100 :
b11110010 ;

#230
b11001000 /
b11101100 :
b10110100 ;

#231
b00011011 /
b01011101 :
b01111000 ;

#232
b01010011 /
b10011111 :
b11110010 ;

#233
b10110001 /
b01111111 :
b00110000 ;

#234
b10110110 /
b00011001 :
b11001111 ;

#235
b10001001 /
b10100011 :
b00101100 ;

#236
b10011011 /
b11101001 :
b10000100 ;

#237
b10010001 /
b10011110 :
b00101111 ;

#238
b01010001 /
b00101001 :
b01111010 ;

#239
b11010101 /
b10011101 :
b01110010 ;

#240
b11111110 /
b00110101 :
b00110011 ;

#241
b10111000 /
b00110000 :
b11101000 ;

#242
b11011001 /
b10010011 :
b01101100 ;

#243
b11000100 /
b11101000 :
b10101100 ;

#244
b01000101 /
b11111011 :
b01000000 ;

#245
b10111011 /
b01101110 :
b00101001 ;

#246
b11110010 /
b00001100 :
b11111110 ;

#247
b11101100 /
b01011100 :
b01001000 ;

#248
b10100110 /
b10110110 :
b01011100 ;

#249
b11110110 /
b10110101 :
b10101011 ;

#250
b11010100 /
b10010010 :
b01100110 ;

#251
b10100000 /
b00001100 :
b10101100 ;

#252
b10011000 /
b10011100 :
b00110100 ;

#253
b11100001 /
b10000100 :
b01100101 ;

#254
b10110001 /
b10111100 :
b01101101 ;

#255
b00111111 /
b10100001 :
b11100000 ;

#256
b11110011 /
b10100010 :
b10010101 ;

#257
b11111100 /
b00111000 :
b00110100 ;

#258
b01111101 /
b11010100 :
b01010001 ;

#259
b01010011 /
b11011011 :
b00101110 ;

#260
b11001011 /
b00101011 :
b11110110 ;

#261
b10010001 /
b01011011 :
b11101100 ;

#262
b11000011 /
b00110010 :
b11110101 ;

#263
b10011111 /
b10111100 :
b01011011 ;

#264
b00010101 /
b11000110 :
b11011011 ;

#265
b11011100 /
b10011000 :
b01110100 ;

#266
b00100101 /
b10001110 :
b10110011 ;

#267
b00101010 /
b01100110 :
b10010000 ;

#268
b10111011 /
b00011111 :
b11011010 ;

#269
b01100111 /
b11100100 :
b01001011 ;

#270
b00101100 /
b01110010 :
b10011110 ;

#271
b10010101 /
b01000010 :
b11010111 ;

#272
b11010101 /
b10100110 :
b01111011 ;

#273
b11001001 /
b00111101 :
b00000110 ;

#274
b00001000 /
b10000000 :
b10001000 ;

#275
b11100010 /
b11111110 :
b11100000 ;

#276
b11101010 /
b00011100 :
b00000110 ;

#277
b11001000 /
b00110100 :
b11111100 ;

#278
b11110101 /
b11101000 :
b11011101 ;

#279
b11110111 /
b11010011 :
b11001010 ;

#280
b11111101 /
b01111000 :
b01110101 ;

#281
b10000101 /
b10011001 :
b00011110 ;

#282
b11001110 /
b10101011 :
b01111001 ;

#283
b11001101 /
b11100100 :
b10110001 ;

#284
b10010101 /
b01001110 :
b11100011 ;

#285
b11101100 /
b00011111 :
b00001011 ;

#286
b10111011 /
b00100110 :
b11100001 ;

#287
b11111101 /
b10100100 :
b10100001 ;

#288
b10010001 /
b10100010 :
b00110011 ;

#289
b10010111 /
b01001000 :
b11011111 ;

#290
b10010000 /
b01010100 :
b11100100 ;

#291
b01001101 /
b11001100 :
b00011001 ;

#292
b00011111 /
b10100101 :
b11000100 ;

#293
b00010111 /
b10111111 :
b11010110 ;

#294
b10100010 /
b10001010 :
b00101100 ;

#295
b10010111 /
b00011011 :
b10110010 ;

#296
b00110111 /
b00111010 :
b01110001 ;

#297
b00010010 /
b01100011 :
b01110101 ;

#298
b00110111 /
b10111110 :
b11110101 ;

#299
b00110101 /
b10001001 :
b10111110 ;

#300
b01001111 /
b11010001 :
b00100000 ;

#301
b01101101 /
b01011100 :
b11001001 ;

#302
b10000001 /
b00000100 :
b10000101 ;

#303
b11111100 /
b00000001 :
b11111101 ;

#304
b00110111 /
b10101111 :
b11100110 ;

#305
b00110100 /
b10010110 :
b11001010 ;

#306
b11011000 /
b00000110 :
b11011110 ;

#307
b01100010 /
b00010101 :
b01110111 ;

#308
b11110011 /
b00011111 :
b00010010 ;

#309
b11101000 /
b10010100 :
b01111100 ;

#310
b00110101 /
b10111110 :
b11110011 ;

#311
b01101101 /
b11110100 :
b01100001 ;

#312
b11111011 /
b10010101 :
b10010000 ;

#313
b11101101 /
b10110000 :
b10011101 ;

#314
b11110000 /
b10100111 :
b10010111 ;

#315
b11110010 /
b11101010 :
b11011100 ;

#316
b00100011 /
b10101011 :
b11001110 ;

#317
b00110000 /
b01100110 :
b10010110 ;

#318
b11110011 /
b11011001 :
b11001100 ;

#319
b00001001 /
b01110110 :
b01111111 ;

#320
b11111001 /
b10101110 :
b10100111 ;

#321
b10100011 /
b11010011 :
b01110110 ;

#322
b01010110 /
b00101100 :
b10000010 ;

#323
b01001111 /
b00111011 :
b10001010 ;

#324
b11011111 /
b01001110 :
b00101101 ;

#325
b10100011 /
b10001001 :
b00101100 ;

#326
b10000110 /
b00010001 :
b10010111 ;

#327
b00011101 /
b11000110 :
b11100011 ;

#328
b00101010 /
b00011100 :
b01000110 ;

#329
b00011100 /
b00000100 :
b00100000 ;

#330
b01010101 /
b00001011 :
b01100000 ;

#331
b10010000 /
b01100001 :
b11110001 ;

#332
b11100010 /
b11101111 :
b11010001 ;

#333
b10010000 /
b10100010 :
b00110010 ;

#334
b01111110 /
b11000010 :
b01000000 ;

#335
b00001100 /
b10101000 :
b10110100 ;

#336
b10010011 /
b10000000 :
b00010011 ;

#337
b11010001 /
b00110111 :
b00001000 ;

#338
b10111110 /
b01011001 :
b00010111 ;

#339
b10110100 /
b00011011 :
b11001111 ;

#340
b11100001 /
b00110101 :
b00010110 ;

#341
b11110000 /
b10110110 :
b10100110 ;

#342
b01111011 /
b01010001 :
b11001100 ;

#343
b01001011 /
b01110100 :
b10111111 ;

#344
b10001011 /
b10011110 :
b00101001 ;

#345
b00000110 /
b11010011 :
b11011001 ;

#346
b11000111 /
b11101010 :
b10110001 ;

#347
b10010101 /
b10000001 :
b00010110 ;

#348
b10000000 /
b10000001 :
b00000001 ;

#349
b01100100 /
b01101001 :
b11001101 ;

#350
b11011010 /
b11000001 :
b10011011 ;

#351
b11010000 /
b01010010 :
b00100010 ;

#352
b11101001 /
b11010101 :
b10111110 ;

#353
b01010001 /
b11101001 :
b00111010 ;

#354
b10101011 /
b10001100 :
b00110111 ;

#355
b00000010 /
b11100111 :
b11101001 ;

#356
b11000000 /
b01110110 :
b00110110 ;

#357
b01000111 /
b10110001 :
b11111000 ;

#358
b10000100 /
b10000010 :
b00000110 ;

#359
b11101000 /
b01111001 :
b01100001 ;

#360
b01101110 /
b11100101 :
b01010011 ;

#361
b11011111 /
b11011000 :
b10110111 ;

#362
b11010011 /
b11111000 :
b11001011 ;

#363
b00111010 /
b11011111 :
b00011001 ;

#364
b00101110 /
b01110100 :
b10100010 ;

#365
b10011000 /
b00100100 :
b10111100 ;

#366
b01111010 /
b11100101 :
b01011111 ;

#367
b10100110 /
b00001111 :
b10110101 ;

#368
b01110001 /
b00111111 :
b10110000 ;

#369
b00001101 /
b00010011 :
b00100000 ;

#370
b01111011 /
b10111101 :
b00111000 ;

#371
b10011011 /
b10100110 :
b01000001 ;

#372
b11100010 /
b11011110 :
b11000000 ;

#373
b10000101 /
b01010101 :
b11011010 ;

#374
b01100010 /
b10001000 :
b11101010 ;

#375
b11010010 /
b01100001 :
b00110011 ;

#376
b01010100 /
b10000111 :
b11011011 ;

#377
b11110100 /
b00000001 :
b11110101 ;

#378
b10001100 /
b11111101 :
b10001001 ;

#379
b00000011 /
b10111111 :
b11000010 ;

#380
b10101011 /
b10010101 :
b01000000 ;

#381
b11100000 /
b11100111 :
b11000111 ;

#382
b00001011 /
b10001101 :
b10011000 ;

#383
b11001000 /
b01011000 :
b00100000 ;

#384
b01001010 /
b10010010 :
b11011100 ;

#385
b00000011 /
b10111110 :
b11000001 ;

#386
b10010101 /
b11000000 :
b01010101 ;

#387
b11001111 /
b10010111 :
b01100110 ;

#388
b10000001 /
b10100011 :
b00100100 ;

#389
b10011101 /
b11001111 :
b01101100 ;

#390
b10000010 /
b00101010 :
b10101100 ;

#391
b01101111 /
b10010100 :
b00000011 ;

#392
b01000010 /
b11010010 :
b00010100 ;

#393
b01010100 /
b10000000 :
b11010100 ;

#394
b10110011 /
b01000000 :
b11110011 ;

#395
b00000110 /
b10000100 :
b10001010 ;

#396
b00110110 /
b11011001 :
b00001111 ;

#397
b10111011 /
b11000001 :
b01111100 ;

#398
b11001101 /
b10110101 :
b10000010 ;

#399
b11001010 /
b00001101 :
b11010111 ;

#400
b10000011 /
b10111110 :
b01000001 ;

#401
b10101111 /
b00010011 :
b11000010 ;

#402
b01010010 /
b00010101 :
b01100111 ;

#403
b10011010 /
b11101011 :
b10000101 ;

#404
b10100110 /
b00001000 :
b10101110 ;

#405
b00010111 /
b11000000 :
b11010111 ;

#406
b10000010 /
b01001001 :
b11001011 ;

#407
b01110111 /
b00110100 :
b10101011 ;

#408
b01000111 /
b11010010 :
b00011001 ;

#409
b11010000 /
b01000110 :
b00010110 ;

#410
b10011011 /
b11011110 :
b01111001 ;

#411
b11010010 /
b00100000 :
b11110010 ;

#412
b11011011 /
b10111100 :
b10010111 ;

#413
b11010011 /
b10001110 :
b01100001 ;

#414
b00011001 /
b01111011 :
b10010100 ;

#415
b00110110 /
b01111101 :
b10110011 ;

#416
b10011001 /
b00111001 :
b11010010 ;

#417
b10111110 /
b00001011 :
b11001001 ;

#418
b00110010 /
b10101000 :
b11011010 ;

#419
b11101000 /
b01110000 :
b01011000 ;

#420
b10000011 /
b10111101 :
b01000000 ;

#421
b11000100 /
b11110111 :
b10111011 ;

#422
b00000011 /
b11001101 :
b11010000 ;

#423
b11000100 /
b10010011 :
b01010111 ;

#424
b01101001 /
b11110000 :
b01011001 ;

#425
b01111101 /
b00110011 :
b10110000 ;

#426
b10101000 /
b10101010 :
b01010010 ;

#427
b11110011 /
b11100101 :
b11011000 ;

#428
b11101100 /
b11101111 :
b11011011 ;

#429
b10010111 /
b01101001 :
b00000000 ;

#430
b11110101 /
b01110001 :
b01100110 ;

#431
b00011000 /
b11110101 :
b00001101 ;

#432
b11001101 /
b10001101 :
b01011010 ;

#433
b00111011 /
b10111110 :
b11111001 ;

#434
b10011011 /
b11100001 :
b01111100 ;

#435
b00100111 /
b11100110 :
b00001101 ;

#436
b11010001 /
b10110010 :
b10000011 ;

#437
b00101000 /
b11001101 :
b11110101 ;

#438
b10101110 /
b10001001 :
b00110111 ;

#439
b11111000 /
b10000101 :
b01111101 ;

#440
b10101100 /
b11100000 :
b10001100 ;

#441
b01101101 /
b11000100 :
b00110001 ;

#442
b11111101 /
b10101101 :
b10101010 ;

#443
b10011010 /
b00011011 :
b10110101 ;

#444
b00110010 /
b11111111 :
b00110001 ;

#445
b00000001 /
b01111100 :
b01111101 ;

#446
b10011110 /
b11010110 :
b01110100 ;

#447
b10011100 /
b01110011 :
b00001111 ;

#448
b11010100 /
b10000110 :
b01011010 ;

#449
b11000001 /
b10001011 :
b01001100 ;

#450
b01110110 /
b11000000 :
b00110110 ;

#451
b01100111 /
b01001000 :
b10101111 ;

#452
b00100101 /
b11100101 :
b00001010 ;

#453
b01000000 /
b10100011 :
b11100011 ;

#454
b10110101 /
b10110000 :
b01100101 ;

#455
b00100000 /
b11100100 :
b00000100 ;

#456
b11101100 /
b10010011 :
b01111111 ;

#457
b11110001 /
b10010000 :
b10000001 ;

#458
b11000011 /
b11101001 :
b10101100 ;

#459
b11011110 /
b11001000 :
b10100110 ;

#460
b11001111 /
b10111100 :
b10001011 ;

#461
b01000010 /
b10110010 :
b11110100 ;

#462
b01110111 /
b11111010 :
b01110001 ;

#463
b01111110 /
b10000001 :
b11111111 ;

#464
b11000100 /
b10011100 :
b01100000 ;

#465
b01111000 /
b00101001 :
b10100001 ;

#466
b10000010 /
b00010010 :
b10010100 ;

#467
b00001000 /
b10100010 :
b10101010 ;

#468
b00000000 /
b11101110 :
b11101110 ;

#469
b11101110 /
b10111000 :
b10100110 ;

#470
b10101001 /
b11101011 :
b10010100 ;

#471
b11001010 /
b11111111 :
b11001001 ;

#472
b10010111 /
b10111110 :
b01010101 ;

#473
b00111001 /
b11111011 :
b00110100 ;

#474
b11110011 /
b11010100 :
b11000111 ;

#475
b10000111 /
b01010100 :
b11011011 ;

#476
b11101111 /
b10000000 :
b01101111 ;

#477
b10111110 /
b00011000 :
b11010110 ;

#478
b11010010 /
b01100010 :
b00110100 ;

#479
b10010001 /
b00010111 :
b10101000 ;

#480
b11101111 /
b11010110 :
b11000101 ;

#481
b11010010 /
b11111100 :
b11001110 ;

#482
b10100101 /
b11111001 :
b10011110 ;

#483
b10110000 /
b11010100 :
b10000100 ;

#484
b11111011 /
b01000000 :
b00111011 ;

#485
b01001000 /
b00000110 :
b01001110 ;

#486
b01001000 /
b01011000 :
b10100000 ;

#487
b10010110 /
b10101111 :
b01000101 ;

#488
b00111101 /
b10011111 :
b11011100 ;

#489
b10111100 /
b11110111 :
b10110011 ;

#490
b10100010 /
b01000000 :
b11100010 ;

#491
b11100011 /
b11101100 :
b11001111 ;

#492
b10110010 /
b10011011 :
b01001101 ;

#493
b11100110 /
b10100011 :
b10001001 ;

#494
b11000010 /
b11100011 :
b10100101 ;

#495
b11110100 /
b11101101 :
b11100001 ;

#496
b10001010 /
b11000011 :
b01001101 ;

#497
b11010110 /
b10010111 :
b01101101 ;

#498
b00010011 /
b00010110 :
b00101001 ;

#499
b00101111 /
b11101010 :
b00011001 ;

#500
b11010000 /
b11100100 :
b10110100 ;

#501
b10001110 /
b11100000 :
b01101110 ;

#502
b10000101 /
b10111010 :
b00111111 ;

#503
b11001011 /
b01011010 :
b00100101 ;

#504
b10001001 /
b11100011 :
b01101100 ;

#505
b01010110 /
b11011010 :
b00110000 ;

#506
b01011001 /
b01110000 :
b11001001 ;

#507
b11000101 /
b10100010 :
b01100111 ;

#508
b01000000 /
b01010011 :
b10010011 ;

#509
b11100101 /
b00100001 :
b00000110 ;

#510
b10100011 /
b10001000 :
b00101011 ;

#511
b11011010 /
b01100100 :
b00111110 ;

#512
b11011101 /
b10011000 :
b01110101 ;

#513
b11010100 /
b11100011 :
b10110111 ;

#514
b10011011 /
b01001011 :
b11100110 ;

#515
b11111010 /
b10111001 :
b10110011 ;

#516
b10000000 /
b10000011 :
b00000011 ;

#517
b00110010 /
b10111001 :
b11101011 ;

#518
b11011110 /
b10101101 :
b10001011 ;

#519
b00100001 /
b10010000 :
b10110001 ;

#520
b10000010 /
b01111100 :
b11111110 ;

#521
b01011110 /
b10100001 :
b11111111 ;

#522
b01000100 /
b11000110 :
b00001010 ;

#523
b11001111 /
b11100110 :
b10110101 ;

#524
b11101011 /
b10101100 :
b10010111 ;

#525
b01000100 /
b11100010 :
b00100110 ;

#526
b10100011 /
b00110001 :
b11010100 ;

#527
b11101110 /
b11100000 :
b11001110 ;

#528
b11101001 /
b11011000 :
b11000001 ;

#529
b10101001 /
b11011011 :
b10000100 ;

#530
b10111110 /
b10101101 :
b01101011 ;

#531
b10010001 /
b10001010 :
b00011011 ;

#532
b00101101 /
b00101111 :
b01011100 ;

#533
b10100010 /
b10100101 :
b01000111 ;

#534
b10000011 /
b11011101 :
b01100000 ;

#535
b11101111 /
b10100101 :
b10010100 ;

#536
b11111000 /
b00101111 :
b00100111 ;

#537
b11100001 /
b10100001 :
b10000010 ;

#538
b10110001 /
b10100000 :
b01010001 ;

#539
b11101000 /
b11110100 :
b11011100 ;

#540
b11110110 /
b10100000 :
b10010110 ;

#541
b00100101 /
b10011101 :
b11000010 ;

#542
b01010111 /
b11011001 :
b00110000 ;

#543
b01011010 /
b11100010 :
b00111100 ;

#544
b01100101 /
b10011100 :
b00000001 ;

#545
b01111001 /
b00110101 :
b10101110 ;

#546
b00101001 /
b11101011 :
b00010100 ;

#547
b10110111 /
b01010001 :
b00001000 ;

#548
b10110110 /
b10010011 :
b01001001 ;

#549
b11010101 /
b00100101 :
b11111010 ;

#550
b11100110 /
b01010000 :
b00110110 ;

#551
b11001010 /
b10010110 :
b01100000 ;

#552
b10001110 /
b10011010 :
b00101000 ;

#553
b00111011 /
b10100010 :
b11011101 ;

#554
b01111000 /
b11101110 :
b01100110 ;

#555
b11110100 /
b00111110 :
b00110010 ;

#556
b11111101 /
b00011111 :
b00011100 ;

#557
b10011010 /
b10011010 :
b00110100 ;

#558
b01011100 /
b01110110 :
b11010010 ;

#559
b01110000 /
b00010011 :
b10000011 ;

#560
b10011100 /
b11100101 :
b10000001 ;

#561
b10011000 /
b11001001 :
b01100001 ;

#562
b01111100 /
b11110101 :
b01110001 ;

#563
b11111000 /
b00111000 :
b00110000 ;

#564
b01111011 /
b10011111 :
b00011010 ;

#565
b10010001 /
b11100100 :
b01110101 ;

#566
b00100000 /
b10000000 :
b10100000 ;

#567
b10101010 /
b11010000 :
b01111010 ;

#568
b10010000 /
b00101001 :
b10111001 ;

#569
b10111011 /
b00010000 :
b11001011 ;

#570
b11100001 /
b10000111 :
b01101000 ;

#571
b10011111 /
b00010110 :
b10110101 ;

#572
b10100010 /
b10100100 :
b01000110 ;

#573
b10101011 /
b01111000 :
b00100011 ;

#574
b10000111 /
b10111000 :
b00111111 ;

#575
b10001001 /
b11001111 :
b01011000 ;

#576
b10100111 /
b11101001 :
b10010000 ;

#577
b10110001 /
b10101001 :
b01011010 ;

#578
b11000000 /
b00100101 :
b11100101 ;

#579
b00010001 /
b11110001 :
b00000010 ;

#580
b10101111 /
b10101001 :
b01011000 ;

#581
b10010101 /
b00100011 :
b10111000 ;

#582
b11110110 /
b00010111 :
b00001101 ;

