src/tests/resources/operation/comb/add/add.generic.sv
// Generated by CIRCT firtool-1.71.0
module Foo(	// comb/add/add.generic.generic.mlir:3:3
  input  [7:0] a,	// comb/add/add.generic.generic.mlir:4:8
               b,	// comb/add/add.generic.generic.mlir:4:19
  output [7:0] res	// comb/add/add.mlir:1:42
);

  assign res = a + b;	// comb/add/add.generic.generic.mlir:5:10, :6:5
endmodule

src/tests/resources/operation/comb/add/trace_vtor.vcd
$version Generated by VerilatedVcd $end
$timescale 1ps $end
 $scope module Foo $end
  $var wire 8 # a [7:0] $end
  $var wire 8 $ b [7:0] $end
  $var wire 8 % res [7:0] $end
  $scope module Foo $end
   $var wire 8 # a [7:0] $end
   $var wire 8 $ b [7:0] $end
   $var wire 8 % res [7:0] $end
  $upscope $end
 $upscope $end
$enddefinitions $end


#0
b00010111 #
b00011101 $
b00110100 %
#1
b00010001 #
b11001100 $
b11011101 %
#2
b11110000 #
b00011110 $
b00001110 %
#3
b11001001 #
b00110001 $
b11111010 %
#4
b01100111 #
b10100000 $
b00000111 %
#5
b11001010 #
b11111011 $
b11000101 %
#6
b00010011 #
b01000101 $
b01011000 %
#7
b00001010 #
b00000111 $
b00010001 %
#8
b11011100 #
b10100100 $
b10000000 %
#9
b11000000 #
b00101001 $
b11101001 %
#10
b11110001 #
b00101111 $
b00100000 %
#11
b01001001 #
b11000110 $
b00001111 %
#12
b10011011 #
b11011111 $
b01111010 %
#13
b11110101 #
b00000011 $
b11111000 %
#14
b10100011 #
b10001111 $
b00110010 %
#15
b01100101 #
b01100111 $
b11001100 %
#16
b01010011 #
b11000110 $
b00011001 %
#17
b11110010 #
b10000001 $
b01110011 %
#18
b00011011 #
b00011001 $
b00110100 %
#19
b00010110 #
b00001010 $
b00100000 %
#20
b11111110 #
b11110010 $
b11110000 %
#21
b00101010 #
b11101010 $
b00010100 %
#22
b10001000 #
b01011001 $
b11100001 %
#23
b01101101 #
b00010101 $
b10000010 %
#24
b10000110 #
b00000100 $
b10001010 %
#25
b01001000 #
b10000110 $
b11001110 %
#26
b00110100 #
b10000000 $
b10110100 %
#27
b01110010 #
b11110100 $
b01100110 %
#28
b01110001 #
b01011110 $
b11001111 %
#29
b11001000 #
b10001000 $
b01010000 %
#30
b11111100 #
b01111111 $
b01111011 %
#31
b01100001 #
b11000011 $
b00100100 %
#32
b01010000 #
b01101101 $
b10111101 %
#33
b00100011 #
b10101110 $
b11010001 %
#34
b01111100 #
b01000010 $
b10111110 %
#35
b00100100 #
b10100100 $
b11001000 %
#36
b11000101 #
b10011001 $
b01011110 %
#37
b01111110 #
b00111010 $
b10111000 %
#38
b11111000 #
b01011011 $
b01010011 %
#39
b11001000 #
b00000010 $
b11001010 %
#40
b00111001 #
b11100101 $
b00011110 %
#41
b00100111 #
b00001100 $
b00110011 %
#42
b00101010 #
b01010010 $
b01111100 %
#43
b00100110 #
b10011100 $
b11000010 %
#44
b00000100 #
b10111111 $
b11000011 %
#45
b11010110 #
b11100000 $
b10110110 %
#46
b11100000 #
b11000110 $
b10100110 %
#47
b10010011 #
b10011101 $
b00110000 %
#48
b01011101 #
b00111011 $
b10011000 %
#49
b11010101 #
b10101001 $
b01111110 %
#50
b11000001 #
b11010110 $
b10010111 %
#51
b00110110 #
b10001011 $
b11000001 %
#52
b10001110 #
b01110110 $
b00000100 %
#53
b10111111 #
b11000000 $
b01111111 %
#54
b11101000 #
b11011100 $
b11000100 %
#55
b11010000 #
b01011000 $
b00101000 %
#56
b10100011 #
b00100010 $
b11000101 %
#57
b01111101 #
b11011100 $
b01011001 %
#58
b11110111 #
b11110111 $
b11101110 %
#59
b00100101 #
b11001101 $
b11110010 %
#60
b11000101 #
b01010010 $
b00010111 %
#61
b00111110 #
b10101000 $
b11100110 %
#62
b11111001 #
b00110001 $
b00101010 %
#63
b00100011 #
b01110001 $
b10010100 %
#64
b01110001 #
b10000011 $
b11110100 %
#65
b10000001 #
b10010011 $
b00010100 %
#66
b10101110 #
b01110000 $
b00011110 %
#67
b00101001 #
b00110011 $
b01011100 %
#68
b11101101 #
b10001010 $
b01110111 %
#69
b00001101 #
b01100001 $
b01101110 %
#70
b11111101 #
b00011101 $
b00011010 %
#71
b11010101 #
b00010000 $
b11100101 %
#72
b00000101 #
b00101101 $
b00110010 %
#73
b10010011 #
b11110101 $
b10001000 %
#74
b10110001 #
b00001001 $
b10111010 %
#75
b01001111 #
b00010011 $
b01100010 %
#76
b11011111 #
b00000111 $
b11100110 %
#77
b01100010 #
b10000111 $
b11101001 %
#78
b10010010 #
b01111010 $
b00001100 %
#79
b11010011 #
b11010010 $
b10100101 %
#80
b10100001 #
b11011011 $
b01111100 %
#81
b10001110 #
b10110011 $
b01000001 %
#82
b01001001 #
b01010001 $
b10011010 %
#83
b10000010 #
b10100001 $
b00100011 %
#84
b00101000 #
b10001001 $
b10110001 %
#85
b10010101 #
b00101101 $
b11000010 %
#86
b01010000 #
b01011110 $
b10101110 %
#87
b00000101 #
b10010111 $
b10011100 %
#88
b10000001 #
b10000110 $
b00000111 %
#89
b00011100 #
b00111100 $
b01011000 %
#90
b10001100 #
b10111010 $
b01000110 %
#91
b11010111 #
b10001101 $
b01100100 %
#92
b10100011 #
b00001111 $
b10110010 %
#93
b01101100 #
b11000111 $
b00110011 %
#94
b00101010 #
b11001111 $
b11111001 %
#95
b01011100 #
b11100111 $
b01000011 %
#96
b10001100 #
b10001101 $
b00011001 %
#97
b00000111 #
b00100000 $
b00100111 %
#98
b10101011 #
b10000001 $
b00101100 %
#99
b01110111 #
b00010011 $
b10001010 %
#100
b00111110 #
b00100101 $
b01100011 %
#101
b01000100 #
b01000001 $
b10000101 %
#102
b10000111 #
b11111010 $
b10000001 %
#103
b10100000 #
b01010001 $
b11110001 %
#104
b10101110 #
b00000011 $
b10110001 %
#105
b01100010 #
b10101010 $
b00001100 %
#106
b11010010 #
b01111100 %
#107
b10111100 #
b11100000 $
b10011100 %
#108
b10100101 #
b11010010 $
b01110111 %
#109
b10110110 #
b11111100 $
b10110010 %
#110
b01110010 #
b11110111 $
b01101001 %
#111
b00010011 #
b00100110 $
b00111001 %
#112
b01100011 #
b00110000 $
b10010011 %
#113
b00111001 #
b00101101 $
b01100110 %
#114
b00010010 #
b10010111 $
b10101001 %
#115
b01111011 #
b01001111 $
b11001010 %
#116
b00000011 #
b11011110 $
b11100001 %
#117
b00010000 #
b11001111 $
b11011111 %
#118
b10101000 #
b00100011 $
b11001011 %
#119
b11000100 #
b00100111 $
b11101011 %
#120
b10111101 #
b00010111 $
b11010100 %
#121
b01101111 #
b11100011 $
b01010010 %
#122
b11110011 #
b10001000 $
b01111011 %
#123
b10110000 #
b10111100 $
b01101100 %
#124
b11000011 #
b10110001 $
b01110100 %
#125
b00110011 #
b00010100 $
b01000111 %
#126
b11111001 #
b10111001 $
b10110010 %
#127
b01101010 #
b11001010 $
b00110100 %
#128
b11001110 #
b01011100 $
b00101010 %
#129
b11111111 #
b11000111 $
b11000110 %
#130
b11001101 #
b01001010 $
b00010111 %
#131
b01100111 #
b10010111 $
b11111110 %
#132
b10111010 #
b00100001 $
b11011011 %
#133
b01101101 #
b01011000 $
b11000101 %
#134
b11111111 #
b11111010 $
b11111001 %
#135
b11001010 #
b01000111 $
b00010001 %
#136
b01000001 #
b10100111 $
b11101000 %
#137
b11100001 #
b00011011 $
b11111100 %
#138
b11000011 #
b01000001 $
b00000100 %
#139
b10001011 #
b11101011 $
b01110110 %
#140
b10111111 #
b01001001 $
b00001000 %
#141
b00111011 #
b01000010 $
b01111101 %
#142
b01001110 #
b10100010 $
b11110000 %
#143
b10101010 #
b00101111 $
b11011001 %
#144
b11100101 #
b01010101 $
b00111010 %
#145
b00001111 #
b10011000 $
b10100111 %
#146
b01000101 #
b11010010 $
b00010111 %
#147
b10101011 #
b00101100 $
b11010111 %
#148
b11000010 #
b00110101 $
b11110111 %
#149
b11101010 #
b00100111 $
b00010001 %
#150
b01110001 #
b00010111 $
b10001000 %
#151
b10100111 #
b10010000 $
b00110111 %
#152
b10111011 #
b01100101 $
b00100000 %
#153
b10000110 #
b11111010 $
b10000000 %
#154
b10000101 #
b11010000 $
b01010101 %
#155
b10011001 #
b01110101 $
b00001110 %
#156
b01000001 #
b01001010 $
b10001011 %
#157
b11000101 $
b00000110 %
#158
b11001000 #
b01101010 $
b00110010 %
#159
b11011000 #
b11111010 $
b11010010 %
#160
b11001001 #
b00011010 $
b11100011 %
#161
b00111011 #
b11010010 $
b00001101 %
#162
b10100101 #
b11000010 $
b01100111 %
#163
b10101001 #
b11011110 $
b10000111 %
#164
b11010011 #
b01100100 $
b00110111 %
#165
b01001011 #
b01010000 $
b10011011 %
#166
b11100101 #
b01100011 $
b01001000 %
#167
b00000100 #
b01111111 $
b10000011 %
#168
b10011101 #
b00111111 $
b11011100 %
#169
b10111011 #
b11111101 $
b10111000 %
#170
b00011110 #
b11110011 $
b00010001 %
#171
b11000100 #
b10110000 $
b01110100 %
#172
b10110110 #
b00110001 $
b11100111 %
#173
b01011001 #
b01101011 $
b11000100 %
#174
b10101111 #
b00111001 $
b11101000 %
#175
b10000101 #
b11001110 $
b01010011 %
#176
b10010010 #
b11111011 $
b10001101 %
#177
b00011010 #
b01100010 $
b01111100 %
#178
b10100111 #
b11111100 $
b10100011 %
#179
b01110011 #
b11100000 $
b01010011 %
#180
b00010011 #
b10101010 $
b10111101 %
#181
b10111101 #
b11010111 $
b10010100 %
#182
b10100100 #
b11000110 $
b01101010 %
#183
b11100010 #
b00111011 $
b00011101 %
#184
b11101100 #
b10100010 $
b10001110 %
#185
b00101110 #
b01101011 $
b10011001 %
#186
b11101001 #
b10111111 $
b10101000 %
#187
b01101100 #
b00111000 $
b10100100 %
#188
b11010110 #
b10100010 $
b01111000 %
#189
b01001101 #
b10010011 $
b11100000 %
#190
b11001101 #
b01101000 $
b00110101 %
#191
b01000010 #
b11000110 $
b00001000 %
#192
b00101001 #
b00011000 $
b01000001 %
#193
b10000001 #
b01101111 $
b11110000 %
#194
b01111111 #
b01001110 $
b11001101 %
#195
b10100110 #
b11101100 $
b10010010 %
#196
b01111101 #
b01000111 $
b11000100 %
#197
b10101101 #
b01100110 $
b00010011 %
#198
b10001100 #
b11100001 $
b01101101 %
#199
b11011110 #
b10100000 $
b01111110 %
#200
b11111100 #
b11010011 $
b11001111 %
#201
b11011011 #
b01011110 $
b00111001 %
#202
b00101100 #
b00110001 $
b01011101 %
#203
b11000001 #
b10110110 $
b01110111 %
#204
b00010011 #
b11001001 $
b11011100 %
#205
b00101010 #
b10001100 $
b10110110 %
#206
b01111101 #
b00010100 $
b10010001 %
#207
b01000101 #
b00001011 $
b01010000 %
#208
b10010110 #
b11001010 $
b01100000 %
#209
b11000010 #
b10110101 $
b01110111 %
#210
b00101000 #
b01111100 $
b10100100 %
#211
b01101110 #
b11010111 $
b01000101 %
#212
b00100100 #
b11010010 $
b11110110 %
#213
b01110011 #
b00111110 $
b10110001 %
#214
b10111000 #
b00000100 $
b10111100 %
#215
b00001101 #
b00011110 $
b00101011 %
#216
b00001011 #
b00100101 $
b00110000 %
#217
b10100010 #
b00000100 $
b10100110 %
#218
b00101100 #
b11101110 $
b00011010 %
#219
b01101110 #
b10000001 $
b11101111 %
#220
b01000100 #
b01010100 $
b10011000 %
#221
b11111111 #
b10110100 $
b10110011 %
#222
b00101000 #
b00111100 $
b01100100 %
#223
b10111000 #
b01011011 $
b00010011 %
#224
b01011110 #
b11111101 $
b01011011 %
#225
b01000111 #
b11100001 $
b00101000 %
#226
b00011111 #
b10000111 $
b10100110 %
#227
b00111110 #
b10100110 $
b11100100 %
#228
b10001101 #
b00000001 $
b10001110 %
#229
b01100100 #
b11000010 $
b00100110 %
#230
b00011010 #
b00110010 $
b01001100 %
#231
b01010100 #
b01011000 $
b10101100 %
#232
b01011110 #
b01010000 $
b10101110 %
#233
b00001110 #
b11000101 $
b11010011 %
#234
b10101011 #
b10100011 $
b01001110 %
#235
b11011110 #
b00001111 $
b11101101 %
#236
b10010101 #
b00011001 $
b10101110 %
#237
b11000000 #
b01101000 $
b00101000 %
#238
b00101110 #
b00110001 $
b01011111 %
#239
b01111000 #
b00110111 $
b10101111 %
#240
b00101001 #
b01100000 $
b10001001 %
#241
b11111100 #
b01111011 $
b01110111 %
#242
b01010001 #
b01100000 $
b10110001 %
#243
b00100101 #
b01100001 $
b10000110 %
#244
b10010010 #
b11111101 $
b10001111 %
#245
b00010100 #
b11101101 $
b00000001 %
#246
b10000000 #
b11011110 $
b01011110 %
#247
b01111010 #
b10101110 $
b00101000 %
#248
b00111101 #
b00111101 $
b01111010 %
#249
b01110100 #
b00100101 $
b10011001 %
#250
b00010000 #
b01011011 $
b01101011 %
#251
b01110100 #
b00011111 $
b10010011 %
#252
b00110101 #
b10111110 $
b11110011 %
#253
b00001001 #
b01001000 $
b01010001 %
#254
b10001101 #
b00011101 $
b10101010 %
#255
b10110010 #
b00000110 $
b10111000 %
#256
b10110000 #
b01100000 $
b00010000 %
#257
b10000100 #
b11110111 $
b01111011 %
#258
b11111100 #
b00100010 $
b00011110 %
#259
b01100011 #
b10100010 $
b00000101 %
#260
b00101000 #
b10000000 $
b10101000 %
#261
b01100000 #
b00001111 $
b01101111 %
#262
b00000010 #
b01010100 $
b01010110 %
#263
b00001101 #
b01011011 $
b01101000 %
#264
b10110111 #
b11011101 $
b10010100 %
#265
b10000101 #
b00011101 $
b10100010 %
#266
b10010111 #
b00101000 $
b10111111 %
#267
b01110100 #
b11110011 $
b01100111 %
#268
b00011011 #
b10001001 $
b10100100 %
#269
b00000000 #
b00101000 $
b00101000 %
#270
b11111001 #
b00111000 $
b00110001 %
#271
b11010000 #
b11000101 $
b10010101 %
#272
b10100111 #
b10001100 $
b00110011 %
#273
b01110101 #
b00100111 $
b10011100 %
#274
b00100001 #
b11101111 $
b00010000 %
#275
b00001111 #
b10110010 $
b11000001 %
#276
b01000010 #
b00100101 $
b01100111 %
#277
b10111001 #
b01010111 $
b00010000 %
#278
b00110111 #
b01111101 $
b10110100 %
#279
b11001111 #
b00100110 $
b11110101 %
#280
b10100100 #
b00001101 $
b10110001 %
#281
b01110100 #
b11100000 $
b01010100 %
#282
b10110111 #
b11101000 $
b10011111 %
#283
b00010000 #
b10110111 $
b11000111 %
#284
b11100110 #
b11001110 $
b10110100 %
#285
b10001011 #
b11111001 $
b10000100 %
#286
b01110011 #
b01101111 $
b11100010 %
#287
b01101101 #
b01111110 $
b11101011 %
#288
b01001110 #
b00010000 $
b01011110 %
#289
b10010000 #
b10011001 $
b00101001 %
#290
b00001110 #
b00011011 $
#291
b11110001 #
b00111010 $
b00101011 %
#292
b11111100 #
b01111111 $
b01111011 %
#293
b01101001 #
b00110010 $
b10011011 %
#294
b10110110 #
b11010010 $
b10001000 %
#295
b10001100 #
b11011010 $
b01100110 %
#296
b00100100 #
b00111010 $
b01011110 %
#297
b11100000 #
b01000010 $
b00100010 %
#298
b10110111 #
b01111001 $
b00110000 %
#299
b01100011 #
b01111000 $
b11011011 %
#300
b00000000 #
b00000010 $
b00000010 %
#301
b01001110 #
b01101010 $
b10111000 %
#302
b01000001 #
b11110100 $
b00110101 %
#303
b10101100 #
b10101101 $
b01011001 %
#304
b11000101 #
b00110110 $
b11111011 %
#305
b01010000 #
b00001111 $
b01011111 %
#306
b10100101 #
b11000011 $
b01101000 %
#307
b01111100 #
b01000011 $
b10111111 %
#308
b10000000 #
b00001001 $
b10001001 %
#309
b10001011 #
b10101111 $
b00111010 %
#310
b01011101 #
b01001111 $
b10101100 %
#311
b11101001 #
b11101010 $
b11010011 %
#312
b00101111 #
b11010001 $
b00000000 %
#313
b01101100 #
b01011001 $
b11000101 %
#314
b11010011 #
b00100100 $
b11110111 %
#315
b00010010 #
b01010010 $
b01100100 %
#316
b00010111 #
b10000001 $
b10011000 %
#317
b10111111 #
b01011101 $
b00011100 %
#318
b10011101 #
b00001111 $
b10101100 %
#319
b00101000 #
b10001111 $
b10110111 %
#320
b01011111 #
b11100100 $
b01000011 %
#321
b10000111 #
b01000111 $
b11001110 %
#322
b00101001 #
b00000010 $
b00101011 %
#323
b00110110 #
b00101110 $
b01100100 %
#324
b10101111 #
b00110111 $
b11100110 %
#325
b00010110 #
b10111101 $
b11010011 %
#326
b01111100 #
b11011000 $
b01010100 %
#327
b00111110 #
b01101011 $
b10101001 %
#328
b00010101 #
b01101100 $
b10000001 %
#329
b11110001 #
b01100011 $
b01010100 %
#330
b00000001 #
b00001110 $
b00001111 %
#331
b11000000 #
b00111001 $
b11111001 %
#332
b10001001 #
b10110110 $
b00111111 %
#333
b10000011 #
b10001100 $
b00001111 %
#334
b00101010 #
b01011101 $
b10000111 %
#335
b11111100 #
b00011011 $
b00010111 %
#336
b10010000 #
b10101001 $
b00111001 %
#337
b10001101 #
b10010010 $
b00011111 %
#338
b11100000 #
b00000100 $
b11100100 %
#339
b10000011 #
b11011101 $
b01100000 %
#340
b00000000 #
b11010100 $
b11010100 %
#341
b00111011 #
b11000001 $
b11111100 %
#342
b00101101 #
b11001100 $
b11111001 %
#343
b10110110 #
b11100101 $
b10011011 %
#344
b11001011 #
b11000101 $
b10010000 %
#345
b10001110 #
b10011001 $
b00100111 %
#346
b01011111 #
b11101100 $
b01001011 %
#347
b11100010 #
b11110011 $
b11010101 %
#348
b10000110 #
b10001010 $
b00010000 %
#349
b01010001 #
b11000010 $
b00010011 %
#350
b10001111 #
b00110000 $
b10111111 %
#351
b00100110 #
b11011001 $
b11111111 %
#352
b10010011 #
b01000101 $
b11011000 %
#353
b11011111 #
b10011001 $
b01111000 %
#354
b01101000 #
b01111010 $
b11100010 %
#355
b00010110 #
b10111100 $
b11010010 %
#356
b10100110 #
b10010101 $
b00111011 %
#357
b11101111 #
b10010001 $
b10000000 %
#358
b01111010 #
b10101000 $
b00100010 %
#359
b11001011 #
b00100001 $
b11101100 %
#360
b11001111 #
b10010100 $
b01100011 %
#361
b00001011 #
b11111010 $
b00000101 %
#362
b01110000 #
b11111011 $
b01101011 %
#363
b00010111 #
b00001110 $
b00100101 %
#364
b11000010 #
b11011011 $
b10011101 %
#365
b00110100 #
b00111001 $
b01101101 %
#366
b11000001 #
b01110000 $
b00110001 %
#367
b11110111 #
b01111001 $
b01110000 %
#368
b00101001 #
b01001110 $
b01110111 %
#369
b01000010 #
b11101101 $
b00101111 %
#370
b00111011 #
b01101111 $
b10101010 %
#371
b11011101 #
b11011111 $
b10111100 %
#372
b01111011 #
b11011110 $
b01011001 %
#373
b11110011 #
b11101011 $
b11011110 %
#374
b10111101 #
b11111000 $
b10110101 %
#375
b11001000 #
b00000001 $
b11001001 %
#376
b10011010 #
b01011010 $
b11110100 %
#377
b11101010 #
b00001011 $
b11110101 %
#378
b11011110 #
b10111010 $
b10011000 %
#379
b10111011 #
b10011001 $
b01010100 %
#380
b11101010 #
b01001110 $
b00111000 %
#381
b00000001 #
b00000111 $
b00001000 %
#382
b00100000 #
b10110000 $
b11010000 %
#383
b01011001 #
b01110101 $
b11001110 %
#384
b00111010 #
b01100000 $
b10011010 %
#385
b01110110 #
b10110100 $
b00101010 %
#386
b10100010 #
b11111101 $
b10011111 %
#387
b01001101 #
b11100011 $
b00110000 %
#388
b11011100 #
b10110010 $
b10001110 %
#389
b11001010 #
b11110011 $
b10111101 %
#390
b11111001 #
b10100010 $
b10011011 %
#391
b00000100 #
b11010010 $
b11010110 %
#392
b01010111 #
b01101010 $
b11000001 %
#393
b10100010 #
b10010101 $
b00110111 %
#394
b10000010 #
b01011010 $
b11011100 %
#395
b11011111 #
b01010010 $
b00110001 %
#396
b01000010 #
b01100110 $
b10101000 %
#397
b01101011 #
b11110100 $
b01011111 %
#398
b00000011 #
b00010010 $
b00010101 %
#399
b10000111 #
b10000110 $
b00001101 %
#400
b00011110 #
b00101011 $
b01001001 %
#401
b11100111 #
b10001100 $
b01110011 %
#402
b00010001 #
b00101001 $
b00111010 %
#403
b00001001 #
b01111111 $
b10001000 %
#404
b00110000 #
b00011000 $
b01001000 %
#405
b00011000 #
b11001010 $
b11100010 %
#406
b01110001 #
b10001000 $
b11111001 %
#407
b00100000 #
b11111101 $
b00011101 %
#408
b00001110 #
b10010111 $
b10100101 %
#409
b10011111 #
b10000001 $
b00100000 %
#410
b10001111 #
b00111000 $
b11000111 %
#411
b11001000 #
b01110100 $
b00111100 %
#412
b00011111 #
b10100100 $
b11000011 %
#413
b11010001 #
b11010100 $
b10100101 %
#414
b10110111 #
b01010110 $
b00001101 %
#415
b11011100 #
b11010110 $
b10110010 %
#416
b01100010 #
b00110011 $
b10010101 %
#417
b01100000 #
b11011110 $
b00111110 %
#418
b00011101 #
b01011110 $
b01111011 %
#419
b11011110 #
b10001011 $
b01101001 %
#420
b00000001 #
b11110010 $
b11110011 %
#421
b10110001 #
b01010011 $
b00000100 %
#422
b10110110 #
b11110001 $
b10100111 %
#423
b01001111 #
b00110010 $
b10000001 %
#424
b10010101 #
b00100010 $
b10110111 %
#425
b00001011 #
b00101001 $
b00110100 %
#426
b00100101 #
b11011011 $
b00000000 %
#427
b11100010 #
b11000101 $
b10100111 %
#428
b10100000 #
b00101101 $
b11001101 %
#429
b10110100 #
b01001111 $
b00000011 %
#430
b11001111 #
b00111111 $
b00001110 %
#431
b11111111 #
b00001011 $
b00001010 %
#432
b01110100 #
b11111110 $
b01110010 %
#433
b00101100 #
b01100001 $
b10001101 %
#434
b01100010 #
b10100010 $
b00000100 %
#435
b10011011 #
b11100000 $
b01111011 %
#436
b11001110 #
b00011001 $
b11100111 %
#437
b10100001 #
b00000001 $
b10100010 %
#438
b11000100 #
b00110100 $
b11111000 %
#439
b11010010 #
b10001111 $
b01100001 %
#440
b01011000 #
b00101010 $
b10000010 %
#441
b10100111 #
b00100011 $
b11001010 %
#442
b11000101 #
b11101000 $
b10101101 %
#443
b01110101 #
b00101100 $
b10100001 %
#444
b00011100 #
b01101111 $
b10001011 %
#445
b01010100 #
b01111010 $
b11001110 %
#446
b10110110 #
b10011001 $
b01001111 %
#447
b11101111 #
b10001010 $
b01111001 %
#448
b00101000 #
b10000001 $
b10101001 %
#449
b01010000 #
b11101101 $
b00111101 %
#450
b11100111 #
b10000001 $
b01101000 %
#451
b10001000 #
b11101000 $
b01110000 %
#452
b01001101 #
b10010100 $
b11100001 %
#453
b01110110 #
b11011011 $
b01010001 %
#454
b11010100 #
b01011110 $
b00110010 %
#455
b00101001 #
b10111101 $
b11100110 %
#456
b11001110 #
b11101110 $
b10111100 %
#457
b01100010 #
b11101100 $
b01001110 %
#458
b01001111 #
b00010101 $
b01100100 %
#459
b00000010 #
b00000011 $
b00000101 %
#460
b00101101 #
b00101001 $
b01010110 %
#461
b10111100 #
b11100010 $
b10011110 %
#462
b01010001 #
b01000111 $
b10011000 %
#463
b01110100 #
b01000010 $
b10110110 %
#464
b01111001 #
b00010000 $
b10001001 %
#465
b11010010 #
b10101010 $
b01111100 %
#466
b01111010 #
b10111010 $
b00110100 %
#467
b11011010 #
b10010101 $
b01101111 %
#468
b00011011 #
b01010001 $
b01101100 %
#469
b00101011 #
b11001110 $
b11111001 %
#470
b10000100 #
b10010110 $
b00011010 %
#471
b10001111 #
b01011100 $
b11101011 %
#472
b00000100 #
b01111111 $
b10000011 %
#473
b10111111 #
b10111001 $
b01111000 %
#474
b01000110 #
b01000101 $
b10001011 %
#475
b00110000 #
b01111011 $
b10101011 %
#476
b11110100 #
b11110010 $
b11100110 %
#477
b11100000 #
b01011001 $
b00111001 %
#478
b11111000 #
b11110000 $
b11101000 %
#479
b00100111 #
b11100011 $
b00001010 %
#480
b11000011 #
b00110100 $
b11110111 %
#481
b00000011 #
b11100011 $
b11100110 %
#482
b01101100 #
b00111111 $
b10101011 %
#483
b11001100 #
b00101001 $
b11110101 %
#484
b11100111 #
b10111110 $
b10100101 %
#485
b11001000 #
b00001010 $
b11010010 %
#486
b01000011 #
b11110011 $
b00110110 %
#487
b11010100 #
b00100000 $
b11110100 %
#488
b11001111 #
b11010011 $
b10100010 %
#489
b00100001 #
b01100011 $
b10000100 %
#490
b00001010 #
b01001101 $
b01010111 %
#491
b11011001 #
b01100110 $
b00111111 %
#492
b11111000 #
b11011001 $
b11010001 %
#493
b00100111 #
b11101101 $
b00010100 %
#494
b01111100 #
b11101011 $
b01100111 %
#495
b00001101 #
b00010000 $
b00011101 %
#496
b11000010 #
b00100001 $
b11100011 %
#497
b10100011 #
b00100000 $
b11000011 %
#498
b01100010 #
b01000101 $
b10100111 %
#499
b01111100 #
b01111001 $
b11110101 %
#500
b00011000 #
b00010101 $
b00101101 %
#501
b01100111 #
b01011000 $
b10111111 %
#502
b10100011 #
b00011110 $
b11000001 %
#503
b11111001 #
b00001011 $
b00000100 %
#504
b10000011 #
b00111010 $
b10111101 %
#505
b00100111 #
b11000011 $
b11101010 %
#506
b01011110 #
b00111101 $
b10011011 %
#507
b00110001 #
b00100111 $
b01011000 %
#508
b10101010 #
b00111101 $
b11100111 %
#509
b11101101 #
b01011110 $
b01001011 %
#510
b10000010 #
b11000010 $
b01000100 %
#511
b01100111 #
b01100000 $
b11000111 %
#512
b10000001 #
b10010100 $
b00010101 %
#513
b11010000 #
b10010001 $
b01100001 %
#514
b01110000 #
b01011110 $
b11001110 %
#515
b00100110 #
b10001101 $
b10110011 %
#516
b10110100 #
b00010111 $
b11001011 %
#517
b00111111 #
b11000010 $
b00000001 %
#518
b00111010 #
b00011101 $
b01010111 %
#519
b10111011 #
b00001111 $
b11001010 %
#520
b00110011 #
b11101111 $
b00100010 %
#521
b10110101 #
b11111101 $
b10110010 %
#522
b01100111 #
b10000111 $
b11101110 %
#523
b01011101 #
b10100000 $
b11111101 %
#524
b00011001 #
b00001100 $
b00100101 %
#525
b11101100 #
b00110000 $
b00011100 %
#526
b01010011 #
b00111000 $
b10001011 %
#527
b01001101 #
b11100010 $
b00101111 %
#528
b10010101 #
b01111111 $
b00010100 %
#529
b10111100 #
b00010110 $
b11010010 %
#530
b01100100 #
b10010110 $
b11111010 %
#531
b10000011 #
b01101000 $
b11101011 %
#532
b00011001 #
b01110101 $
b10001110 %
#533
b00101111 #
b11011101 $
b00001100 %
#534
b11011010 #
b01001110 $
b00101000 %
#535
b10100111 #
b00000010 $
b10101001 %
#536
b11100010 #
b11110000 $
b11010010 %
#537
b11111010 #
b11010101 $
b11001111 %
#538
b01011100 #
b10101110 $
b00001010 %
#539
b11110110 #
b10111111 $
b10110101 %
#540
b10010011 #
b11111000 $
b10001011 %
#541
b11100000 #
b10011101 $
b01111101 %
#542
b01001100 #
b00100101 $
b01110001 %
#543
b11011101 #
b00101000 $
b00000101 %
#544
b00010101 #
b10111001 $
b11001110 %
#545
b00000000 #
b11000000 $
b11000000 %
#546
b01100100 #
b11100111 $
b01001011 %
#547
b10101111 #
b10001001 $
b00111000 %
#548
b01111101 #
b10011100 $
b00011001 %
#549
b10001001 #
b00111011 $
b11000100 %
#550
b01111111 #
b00100000 $
b10011111 %
#551
b10111000 #
b00101010 $
b11100010 %
#552
b11000110 #
b11111111 $
b11000101 %
#553
b00110111 #
b01100011 $
b10011010 %
#554
b10001100 #
b01000111 $
b11010011 %
#555
b01111001 #
b10100100 $
b00011101 %
#556
b00010100 #
b01001000 $
b01011100 %
#557
b10110101 #
b01000000 $
b11110101 %
#558
b10110000 #
b01100111 $
b00010111 %
#559
b01010011 #
b11011101 $
b00110000 %
#560
b11010110 #
b01101010 $
b01000000 %
#561
b01111110 #
b01110100 $
b11110010 %
#562
b01100101 #
b01100010 $
b11000111 %
#563
b11010001 #
b00000110 $
b11010111 %
#564
b11001100 #
b00001110 $
b11011010 %
#565
b01110100 #
b10001000 $
b11111100 %
#566
b01011110 #
b00111100 $
b10011010 %
#567
b00110111 #
b00100100 $
b01011011 %
#568
b11100101 #
b01001110 $
b00110011 %
#569
b11110000 #
b10010100 $
b10000100 %
#570
b10110001 #
b11100110 $
b10010111 %
#571
b00000010 #
b01110101 $
b01110111 %
#572
b01000010 #
b00100000 $
b01100010 %
#573
b00110011 #
b11100110 $
b00011001 %
#574
b01100010 #
b10111010 $
b00011100 %
#575
b11000000 #
b00000001 $
b11000001 %
#576
b00100011 #
b10100011 $
b11000110 %
#577
b01100011 #
b10110111 $
b00011010 %
#578
b10011110 #
b01000100 $
b11100010 %
#579
b10101110 #
b11010000 $
b01111110 %
#580
b00011110 #
b00000010 $
b00100000 %
#581
b01010101 #
b01001110 $
b10100011 %
#582
b00001100 #
b10001101 $
b10011001 %
#583
b11000001 #
b10111000 $
b01111001 %
#584
b01110010 #
b00011100 $
b10001110 %
#585
b01011011 #
b00110010 $
b10001101 %
#586
b11100000 #
b00111100 $
b00011100 %
#587
b01111011 #
b00100110 $
b10100001 %
#588
b00100001 #
b11000101 $
b11100110 %
#589
b01000110 #
b11111000 $
b00111110 %
#590
b10100101 #
b10011110 $
b01000011 %
#591
b00110110 #
b00011000 $
b01001110 %
#592
b01110000 #
b10011010 $
b00001010 %
#593
b10011010 #
b00000101 $
b10011111 %
#594
b11111100 #
b11011111 $
b11011011 %
#595
b00100100 #
b10100000 $
b11000100 %
#596
b01100001 #
b10111000 $
b00011001 %
#597
b00100101 #
b01010101 $
b01111010 %
#598
b11100110 #
b01110000 $
b01010110 %
#599
b00100010 #
b10111101 $
b11011111 %
#600
b01011011 #
b01011010 $
b10110101 %
#601
b00111010 #
b11001101 $
b00000111 %
#602
b10001110 #
b01001011 $
b11011001 %
#603
b10110011 #
b00011010 $
b11001101 %
#604
b01001111 #
b11000101 $
b00010100 %
#605
b01000110 #
b10000011 $
b11001001 %
#606
b00111010 #
b01100010 $
b10011100 %
#607
b00101011 #
b01001100 $
b01110111 %
