src/tests/resources/operation/comb/shru/shru.sv
// Generated by CIRCT firtool-1.71.0
module Foo(	// comb/shru/shru.generic.mlir:3:3
  input  [7:0] a,	// comb/shru/shru.generic.mlir:4:8
               b,	// comb/shru/shru.generic.mlir:4:19
  output [7:0] res	// comb/shru/shru.mlir:1:42
);

  assign res = a >> b;	// comb/shru/shru.generic.mlir:5:10, :6:5
endmodule

src/tests/resources/operation/comb/shru/trace_vtor.vcd
$version Generated by VerilatedVcd $end
$date Wed Nov 27 20:12:37 2024
 $end
$timescale   1ps $end

 $scope module Foo $end
  $var wire  8 # a [7:0] $end
  $var wire  8 $ b [7:0] $end
  $var wire  8 % res [7:0] $end
  $scope module Foo $end
   $var wire  8 # a [7:0] $end
   $var wire  8 $ b [7:0] $end
   $var wire  8 % res [7:0] $end
  $upscope $end
 $upscope $end
$enddefinitions $end


#0
b01110010 #
b00000101 $
b00000011 %
#1
b00001100 #
b00000011 $
b00000001 %
#2
b11010100 #
b00000101 $
b00000110 %
#3
b00010010 #
b00000000 %
#4
b01010001 #
b00001000 $
#5
b11111110 #
b00000110 $
b00000011 %
#6
b00101010 #
b00001000 $
b00000000 %
#7
b00011110 #
b00000101 $
#8
b00010101 #
b00000111 $
#9
b00000100 #
b00001000 $
#10
b11011001 #
b00000010 $
b00110110 %
#11
b01001010 #
b00000101 $
b00000010 %
#12
b11101000 #
b00000111 %
#13
b00011100 #
b00001000 $
b00000000 %
#14
b01011000 #
b00000010 $
b00010110 %
#15
b01011110 #
b00000101 $
b00000010 %
#16
b10101101 #
b00000010 $
b00101011 %
#17
b00100110 #
b00000001 $
b00010011 %
#18
b10001110 #
b00000101 $
b00000100 %
#19
b10101011 #
b00000110 $
b00000010 %
#20
b10011100 #
b00000010 $
b00100111 %
#21
b01011100 #
b00000100 $
b00000101 %
#22
b00010010 #
b00000010 $
b00000100 %
#23
b10101010 #
b00000100 $
b00001010 %
#24
b00110010 #
b00000011 $
b00000110 %
#25
b10100101 #
b00000010 $
b00101001 %
#26
b01100011 #
b00001000 $
b00000000 %
#27
b00111001 #
b00000110 $
#28
b00001011 #
b00001000 $
#29
b00101001 #
b00000111 $
#30
b10001010 #
b00000001 %
#31
b10011000 #
b00000011 $
b00010011 %
#32
b11111010 #
b00000101 $
b00000111 %
#33
b11001011 #
b00000111 $
b00000001 %
#34
b11101100 #
b00000101 $
b00000111 %
#35
b01011101 #
b00000000 $
b01011101 %
#36
b01010101 #
b00000101 $
b00000010 %
#37
b00010100 #
b00000011 $
#38
b01100100 #
b00000111 $
b00000000 %
#39
b00110110 #
b00000010 $
b00001101 %
#40
b01101011 #
b00001000 $
b00000000 %
#41
b00110100 #
b00000101 $
b00000001 %
#42
b01001010 #
b00001000 $
b00000000 %
#43
b01011111 #
b00000000 $
b01011111 %
#44
b00000101 #
b00000101 $
b00000000 %
#45
b10000010 #
b00000001 $
b01000001 %
#46
b00001011 #
b00001000 $
b00000000 %
#47
b00011110 #
b00000110 $
#48
b01110100 #
b00000010 $
b00011101 %
#49
b11011010 #
b00000111 $
b00000001 %
#50
b01010001 #
b00000001 $
b00101000 %
#51
b01000110 #
b00100011 %
#52
b11110000 #
b00001000 $
b00000000 %
#53
b10111110 #
b00000000 $
b10111110 %
#54
b00010100 #
b00001000 $
b00000000 %
#55
b10110100 #
b00000000 $
b10110100 %
#56
b01010000 #
b00001000 $
b00000000 %
#57
b11110111 #
b00000011 $
b00011110 %
#58
b01000100 #
b00000110 $
b00000001 %
#59
b01100100 #
b00001000 $
b00000000 %
#60
b01100010 #
b00000000 $
b01100010 %
#61
b11111101 #
b00000110 $
b00000011 %
#62
b10001100 #
b00000011 $
b00010001 %
#63
b10101001 #
b00000110 $
b00000010 %
#64
b01111011 #
b00000111 $
b00000000 %
#65
b01100000 #
b00001000 $
#66
b00110011 #
b00000000 $
b00110011 %
#67
b10111110 #
b00000100 $
b00001011 %
#68
b10000000 #
b00000010 $
b00100000 %
#69
b00111010 #
b00000011 $
b00000111 %
#70
b00110110 #
b00000010 $
b00001101 %
#71
b01011101 #
b00000000 $
b01011101 %
#72
b00011100 #
b00000010 $
b00000111 %
#73
b11001110 #
b00000101 $
b00000110 %
#74
b10011001 #
b00000110 $
b00000010 %
#75
b11101101 #
b00000010 $
b00111011 %
#76
b10110011 #
b00000001 $
b01011001 %
#77
b01011010 #
b00000110 $
b00000001 %
#78
b01111101 #
b00001000 $
b00000000 %
#79
b01110000 #
b00000101 $
b00000011 %
#80
b01000101 #
b00000000 $
b01000101 %
#81
b00000000 #
b00000011 $
b00000000 %
#82
b10010110 #
b00010010 %
#83
b01110110 #
b00000010 $
b00011101 %
#84
b01000101 #
b00000011 $
b00001000 %
#85
b11010110 #
b00000000 $
b11010110 %
#86
b10000001 #
b00001000 $
b00000000 %
#87
b01100011 #
b00000110 $
b00000001 %
#88
b10101000 #
b00000101 $
b00000101 %
#89
b00101000 #
b00001000 $
b00000000 %
#90
b11101011 #
b00000000 $
b11101011 %
#91
b01001100 #
b00000001 $
b00100110 %
#92
b01110100 #
b00000101 $
b00000011 %
#93
b11111101 #
b00001000 $
b00000000 %
#94
b01100100 #
b00000111 $
#95
b00001110 #
b00000101 $
#96
b00110011 #
b00000000 $
b00110011 %
#97
b01110001 #
b00000111 $
b00000000 %
#98
b10011000 #
b00001000 $
#99
b00111010 #
b00000111 $
#100
b10100000 #
b00000000 $
b10100000 %
#101
b11011001 #
b00000111 $
b00000001 %
#102
b11000111 #
b00000001 $
b01100011 %
#103
b00010001 #
b00000000 $
b00010001 %
#104
b00011101 #
b00000011 $
b00000011 %
#105
b11111100 #
b00001000 $
b00000000 %
#106
b10000100 #
b00000011 $
b00010000 %
#107
b11100010 #
b00000000 $
b11100010 %
#108
b01001111 #
b00000110 $
b00000001 %
#109
b01001000 #
b00000101 $
b00000010 %
#110
b00110001 #
b00000011 $
b00000110 %
#111
b01000010 #
b00000010 $
b00010000 %
#112
b00011010 #
b00000110 $
b00000000 %
#113
b10110100 #
b00000111 $
b00000001 %
#114
b10101110 #
b00000100 $
b00001010 %
#115
b01011011 #
b00000010 $
b00010110 %
#116
b00001101 #
b00000110 $
b00000000 %
#117
b01011010 #
b00000111 $
#118
b01001010 #
b00000101 $
b00000010 %
#119
b00000010 $
b00010010 %
#120
b01110010 #
b00000001 $
b00111001 %
#121
b01100100 #
b00000110 $
b00000001 %
#122
b11010010 #
b00000100 $
b00001101 %
#123
b10010100 #
b00001000 $
b00000000 %
#124
b01011010 #
b00000000 $
b01011010 %
#125
b00100100 #
b00000111 $
b00000000 %
#126
b00001100 #
b00000011 $
b00000001 %
#127
b01101001 #
b00000100 $
b00000110 %
#128
b00100101 #
b00000010 %
#129
b01101100 #
b00000110 $
b00000001 %
#130
b11000001 #
b00000011 $
b00011000 %
#131
b10111010 #
b00000100 $
b00001011 %
#132
b01111000 #
b00000010 $
b00011110 %
#133
b01101101 #
b00000001 $
b00110110 %
#134
b11000111 #
b00000100 $
b00001100 %
#135
b10111010 #
b00000001 $
b01011101 %
#136
b10011010 #
b00000011 $
b00010011 %
#137
b11101011 #
b00000100 $
b00001110 %
#138
b11101100 #
b00000011 $
b00011101 %
#139
b00101011 #
b00000101 %
#140
b01001000 #
b00000111 $
b00000000 %
#141
b10100001 #
b00000011 $
b00010100 %
#142
b01001000 #
b00000010 $
b00010010 %
#143
b11111010 #
b00000000 $
b11111010 %
#144
b01010001 #
b00000111 $
b00000000 %
#145
b01110010 #
#146
b10011100 #
b00000110 $
b00000010 %
#147
b01111000 #
b00000010 $
b00011110 %
#148
b01011010 #
b00000000 $
b01011010 %
#149
b01101111 #
b00000100 $
b00000110 %
#150
b10111111 #
b00001011 %
#151
b01000100 #
b00000000 $
b01000100 %
#152
b10110001 #
b00000001 $
b01011000 %
#153
b01001100 #
b00000010 $
b00010011 %
#154
b00000100 #
b00000110 $
b00000000 %
#155
b00100010 #
b00000111 $
#156
b10110000 #
b00000001 %
#157
b11001001 #
b00001000 $
b00000000 %
#158
b11011110 #
b00000100 $
b00001101 %
#159
b00010000 #
b00000111 $
b00000000 %
#160
b10001100 #
b00000000 $
b10001100 %
#161
b00011111 #
b00011111 %
#162
b11011000 #
b00000110 $
b00000011 %
#163
b00001001 #
b00000100 $
b00000000 %
#164
b00011100 #
b00001000 $
#165
b10110100 #
#166
b00011001 #
b00000100 $
b00000001 %
#167
b01111111 #
b00000001 $
b00111111 %
#168
b10000011 #
b00000111 $
b00000001 %
#169
b00111011 #
b00000001 $
b00011101 %
#170
b11101000 #
b00000000 $
b11101000 %
#171
b11100000 #
b00000101 $
b00000111 %
#172
b10011000 #
b00000100 %
#173
b00011111 #
b00000011 $
b00000011 %
#174
b11000001 #
b00000111 $
b00000001 %
#175
b10101100 #
b00000010 $
b00101011 %
#176
b11101001 #
b00000000 $
b11101001 %
#177
b01011110 #
b00000101 $
b00000010 %
#178
b11000000 #
b00000110 %
#179
b00000001 #
b00000100 $
b00000000 %
#180
b10101010 #
b00001000 $
#181
b01000111 #
b00000011 $
b00001000 %
#182
b00011110 #
b00000101 $
b00000000 %
#183
b10001001 #
b00001000 $
#184
b10100001 #
b00000100 $
b00001010 %
#185
b11100011 #
b00000010 $
b00111000 %
#186
b10011100 #
b00000111 $
b00000001 %
#187
b11000001 #
#188
b00000101 #
b00000001 $
b00000010 %
#189
b00100001 #
b00001000 $
b00000000 %
#190
b10100100 #
b00000011 $
b00010100 %
#191
b11101001 #
b00000111 $
b00000001 %
#192
b01010010 #
b00000100 $
b00000101 %
#193
b10100001 #
b00000000 $
b10100001 %
#194
b01001001 #
b00000001 $
b00100100 %
#195
b01010011 #
b00101001 %
#196
b10100101 #
b00000000 $
b10100101 %
#197
b01101011 #
b01101011 %
#198
b10110001 #
b00000010 $
b00101100 %
#199
b11010010 #
b00000011 $
b00011010 %
#200
b00010011 #
b00001000 $
b00000000 %
#201
b00111011 #
b00000101 $
b00000001 %
#202
b10000100 #
b00001000 $
b00000000 %
#203
b10001010 #
#204
b00100100 #
b00000000 $
b00100100 %
#205
b10010010 #
b00000011 $
b00010010 %
#206
b01001111 #
b00001001 %
#207
b01000110 #
b00000110 $
b00000001 %
#208
b11011000 #
b00000011 %
#209
b10111011 #
b00001000 $
b00000000 %
#210
b00100100 #
b00000011 $
b00000100 %
#211
b11110000 #
b00000111 $
b00000001 %
#212
b00100011 #
b00000010 $
b00001000 %
#213
b11011100 #
b00000110 $
b00000011 %
#214
b10010000 #
b00000010 %
#215
b10000010 #
b00000100 $
b00001000 %
#216
b11000101 #
b00000001 $
b01100010 %
#217
b00010011 #
b00000101 $
b00000000 %
#218
b01010000 #
b00000011 $
b00001010 %
#219
b10001010 #
b00010001 %
#220
b10011011 #
b00000111 $
b00000001 %
#221
b11011011 #
b00000101 $
b00000110 %
#222
b10111110 #
b00000101 %
#223
b00010000 #
b00000110 $
b00000000 %
#224
b01111011 #
b00000101 $
b00000011 %
#225
b10110010 #
b00000011 $
b00010110 %
#226
b00000001 #
b00000010 $
b00000000 %
#227
b01101000 #
b00000001 $
b00110100 %
#228
b10011101 #
b00000110 $
b00000010 %
#229
b00011010 #
b00001000 $
b00000000 %
#230
b01111001 #
b00000100 $
b00000111 %
#231
b01001100 #
b00000010 $
b00010011 %
#232
b00100101 #
b00000111 $
b00000000 %
#233
b00010101 #
b00000010 $
b00000101 %
#234
b01001100 #
b00000111 $
b00000000 %
#235
b11011101 #
b00000001 %
#236
b01001110 #
b00000000 $
b01001110 %
#237
b01000000 #
b00000010 $
b00010000 %
#238
b10000101 #
b00000011 $
#239
b11101001 #
b00000100 $
b00001110 %
#240
b11011101 #
b00001000 $
b00000000 %
#241
b11010001 #
b00000011 $
b00011010 %
#242
b01111101 #
b00000111 $
b00000000 %
#243
b10100110 #
b00000001 %
#244
b00100101 #
b00000000 %
#245
b01110011 #
b00000110 $
b00000001 %
#246
b11001000 #
b00000001 $
b01100100 %
#247
b01111011 #
b00001000 $
b00000000 %
#248
b11011010 #
b00000111 $
b00000001 %
#249
b11110110 #
b00000001 $
b01111011 %
#250
b00111011 #
b00000010 $
b00001110 %
#251
b11001101 #
b00001000 $
b00000000 %
#252
b01000010 #
b00000110 $
b00000001 %
#253
b01111101 #
b00000111 $
b00000000 %
#254
b01001100 #
b00000001 $
b00100110 %
#255
b01101000 #
b00000000 $
b01101000 %
#256
b00000110 $
b00000001 %
#257
b11100010 #
b00000101 $
b00000111 %
#258
b10111110 #
b00000000 $
b10111110 %
#259
b00000110 #
b00000111 $
b00000000 %
#260
b00001100 #
b00000001 $
b00000110 %
#261
b10000000 #
b00000010 $
b00100000 %
#262
b11111011 #
b00000111 $
b00000001 %
#263
b10000111 #
b00000011 $
b00010000 %
#264
b11100001 #
b00001000 $
b00000000 %
#265
b01101111 #
b00000011 $
b00001101 %
#266
b10101010 #
b00000101 $
b00000101 %
#267
b10110110 #
b00000110 $
b00000010 %
#268
b00011110 #
b00000011 $
b00000011 %
#269
b00111110 #
b00000111 $
b00000000 %
#270
b10101001 #
b00000011 $
b00010101 %
#271
b11000001 #
b00000010 $
b00110000 %
#272
b01011111 #
b00000011 $
b00001011 %
#273
b01110100 #
b00000001 $
b00111010 %
#274
b10010010 #
b00001000 $
b00000000 %
#275
b11010110 #
b00000000 $
b11010110 %
#276
b00101110 #
b00000100 $
b00000010 %
#277
b11111111 #
b00000101 $
b00000111 %
#278
b10110011 #
b00000110 $
b00000010 %
#279
b11110100 #
b00000001 $
b01111010 %
#280
b01111000 #
b00000100 $
b00000111 %
#281
b10110000 #
b00001000 $
b00000000 %
#282
b11111001 #
b00000100 $
b00001111 %
#283
b11001101 #
b00001100 %
#284
b10001101 #
b00000001 $
b01000110 %
#285
b10111110 #
b00000110 $
b00000010 %
#286
b00011111 #
b00000011 $
b00000011 %
#287
b10111110 #
b00000000 $
b10111110 %
#288
b00010010 #
b00000110 $
b00000000 %
#289
b00111100 #
b00001000 $
#290
b11000010 #
b00000111 $
b00000001 %
#291
b01100100 #
b00000100 $
b00000110 %
#292
b11001110 #
b00000101 $
#293
b11101011 #
b00000110 $
b00000011 %
#294
b11100100 #
b00000101 $
b00000111 %
#295
b11001111 #
b00000001 $
b01100111 %
#296
b11100101 #
b00000010 $
b00111001 %
#297
b01110010 #
b00011100 %
#298
b11101101 #
b00000100 $
b00001110 %
#299
b01101100 #
b00001000 $
b00000000 %
#300
b10101000 #
b00000100 $
b00001010 %
#301
b00011000 #
b00000010 $
b00000110 %
#302
b11100001 #
b00111000 %
#303
b10110100 #
b00000110 $
b00000010 %
#304
b11101101 #
b00001000 $
b00000000 %
#305
b01000010 #
#306
b11010001 #
b00000001 $
b01101000 %
#307
b10000100 #
b00000000 $
b10000100 %
#308
b01101001 #
b00000101 $
b00000011 %
#309
b11110100 #
b00000011 $
b00011110 %
#310
b01100001 #
b00000101 $
b00000011 %
#311
b10110110 #
b00000000 $
b10110110 %
#312
b00000010 #
b00000101 $
b00000000 %
#313
b01001110 #
b00000100 $
b00000100 %
#314
b01011011 #
b00000001 $
b00101101 %
#315
b11101111 #
b00000111 $
b00000001 %
#316
b01111100 #
b00000100 $
b00000111 %
#317
b01010000 #
b00000111 $
b00000000 %
#318
b11101011 #
b00000011 $
b00011101 %
#319
b01111001 #
b00000111 $
b00000000 %
#320
b01001111 #
b00000101 $
b00000010 %
#321
b11101111 #
b00000111 %
#322
b11000010 #
b00000010 $
b00110000 %
#323
b10000000 #
b00000111 $
b00000001 %
#324
b11000101 #
b00001000 $
b00000000 %
#325
b01000111 #
b00000001 $
b00100011 %
#326
b11001000 #
b00000110 $
b00000011 %
#327
b11100100 #
b00000001 $
b01110010 %
#328
b10000110 #
b00000000 $
b10000110 %
#329
b10101101 #
b00000111 $
b00000001 %
#330
b01010111 #
b00000110 $
#331
b01100110 #
b00001000 $
b00000000 %
#332
b01100000 #
b00000100 $
b00000110 %
#333
b11110101 #
b00001111 %
#334
b01001110 #
b00000010 $
b00010011 %
#335
b10111101 #
b00001000 $
b00000000 %
#336
b11101110 #
#337
b11011000 #
b00000111 $
b00000001 %
#338
b01010011 #
b00001000 $
b00000000 %
#339
b00110011 #
b00000100 $
b00000011 %
#340
b00010110 #
b00000010 $
b00000101 %
#341
b10101011 #
b00000000 $
b10101011 %
#342
b00100011 #
b00000011 $
b00000100 %
#343
b00010000 #
b00000100 $
b00000001 %
#344
b10101010 #
b00000010 $
b00101010 %
#345
b00111010 #
b00000001 $
b00011101 %
#346
b10011000 #
b00000000 $
b10011000 %
#347
b11001110 #
b00001000 $
b00000000 %
#348
b10010110 #
b00000111 $
b00000001 %
#349
b01101100 #
b00000011 $
b00001101 %
#350
b01100000 #
b00000001 $
b00110000 %
#351
b01000101 #
b00000111 $
b00000000 %
#352
b00001000 #
b00000010 $
b00000010 %
#353
b11010010 #
b00000000 $
b11010010 %
#354
b10111110 #
b00001000 $
b00000000 %
#355
b10011100 #
b00000010 $
b00100111 %
#356
b00000101 #
b00000110 $
b00000000 %
#357
b00001101 #
b00000011 $
b00000001 %
#358
b01111101 #
b00000100 $
b00000111 %
#359
b10001010 #
b00001000 $
b00000000 %
#360
b10100100 #
b00000111 $
b00000001 %
#361
b11001100 #
b00000100 $
b00001100 %
#362
b10000111 #
b00000111 $
b00000001 %
#363
b01110000 #
b00000000 $
b01110000 %
#364
b01011111 #
b00000010 $
b00010111 %
#365
b11111001 #
b00000111 $
b00000001 %
#366
b00101010 #
b00000010 $
b00001010 %
#367
b10011100 #
b00000111 $
b00000001 %
#368
b00101010 #
b00000010 $
b00001010 %
#369
b10001100 #
b00000100 $
b00001000 %
#370
b11110100 #
b00000001 $
b01111010 %
#371
b10110011 #
b00000011 $
b00010110 %
#372
b00001101 #
b00001000 $
b00000000 %
#373
b11001000 #
b00000111 $
b00000001 %
#374
b00111001 #
b00000101 $
#375
b11111001 #
b00000100 $
b00001111 %
#376
b01000000 #
b00001000 $
b00000000 %
#377
b01011010 #
b00000000 $
b01011010 %
#378
b10110001 #
b00000001 $
b01011000 %
#379
b01010000 #
b00000101 $
b00000010 %
#380
b11000101 #
b00000100 $
b00001100 %
#381
b01101100 #
b00000000 $
b01101100 %
#382
b01011110 #
b00000001 $
b00101111 %
#383
b10000011 #
b00000011 $
b00010000 %
#384
b10100111 #
b00000000 $
b10100111 %
#385
b01010100 #
b00000011 $
b00001010 %
#386
b00101001 #
b00000100 $
b00000010 %
#387
b10110010 #
b00000111 $
b00000001 %
#388
b01001000 #
b00000000 %
#389
b00010011 #
b00000100 $
b00000001 %
#390
b10001000 #
b00000110 $
b00000010 %
#391
b11011010 #
b00000101 $
b00000110 %
#392
b10101000 #
b00000111 $
b00000001 %
#393
b11100111 #
b00001000 $
b00000000 %
#394
b11110100 #
b00000100 $
b00001111 %
#395
b11001001 #
b00000001 $
b01100100 %
#396
b01001011 #
b00000100 $
b00000100 %
#397
b10000011 #
b00001000 %
#398
b01010111 #
b00000011 $
b00001010 %
#399
b01000101 #
b00000111 $
b00000000 %
#400
b11110101 #
b00000001 $
b01111010 %
#401
b11000110 #
b00000000 $
b11000110 %
#402
b11010101 #
b00001000 $
b00000000 %
#403
b01111111 #
b00000101 $
b00000011 %
#404
b00011111 #
b00000111 $
b00000000 %
#405
b10011000 #
b00000011 $
b00010011 %
#406
b01110011 #
b00000101 $
b00000011 %
#407
b10001011 #
b00000011 $
b00010001 %
#408
b10110001 #
b00000010 $
b00101100 %
#409
b01011001 #
b00000100 $
b00000101 %
#410
b10100011 #
b00001010 %
#411
b00010111 #
b00000001 $
b00001011 %
#412
b01011011 #
b00000111 $
b00000000 %
#413
b01000011 #
b00000010 $
b00010000 %
#414
b10111010 #
b00001000 $
b00000000 %
#415
b11010100 #
b00000111 $
b00000001 %
#416
b10000110 #
#417
b10001001 #
b00000110 $
b00000010 %
#418
b11100011 #
b00000101 $
b00000111 %
#419
b00001001 #
b00000010 $
b00000010 %
#420
b10100101 #
b00000101 $
b00000101 %
#421
b11000111 #
b00000110 %
#422
b11010011 #
b00000100 $
b00001101 %
#423
b00000000 $
b11010011 %
#424
b10010011 #
b00001000 $
b00000000 %
#425
b10100101 #
b00000110 $
b00000010 %
#426
b11110100 #
b00000101 $
b00000111 %
#427
b11010110 #
b00000100 $
b00001101 %
#428
b00010110 #
b00001000 $
b00000000 %
#429
b11011001 #
#430
b00100000 #
b00000101 $
b00000001 %
#431
b11111001 #
b00001000 $
b00000000 %
#432
b10011000 #
b00000011 $
b00010011 %
#433
b01000110 #
b00000100 $
b00000100 %
#434
b10110101 #
b00000110 $
b00000010 %
#435
b11000001 #
b00000100 $
b00001100 %
#436
b11011110 #
b00000110 $
b00000011 %
#437
b10011001 #
b00000010 %
#438
b11101110 #
b00000100 $
b00001110 %
#439
b11101100 #
b00000001 $
b01110110 %
#440
b01100110 #
b00000000 $
b01100110 %
#441
b10001010 #
b00000001 $
b01000101 %
#442
b11101011 #
b00000010 $
b00111010 %
#443
b00000001 #
b00000001 $
b00000000 %
#444
b00001111 #
b00000100 $
#445
b00111010 #
b00000110 $
#446
b01011001 #
b00000000 $
b01011001 %
#447
b00101001 #
b00000101 $
b00000001 %
#448
b00100000 #
b00001000 $
b00000000 %
#449
b10000010 #
#450
b00011011 #
#451
b10000001 #
b00000100 $
b00001000 %
#452
b11101100 #
b00001110 %
#453
b01110000 #
b00000010 $
b00011100 %
#454
b11100010 #
b00000101 $
b00000111 %
#455
b01110001 #
b00000100 $
#456
b01111011 #
b00000110 $
b00000001 %
#457
b00101111 #
b00000111 $
b00000000 %
#458
b01010010 #
b00000000 $
b01010010 %
#459
b00110001 #
b00001000 $
b00000000 %
#460
b10111110 #
b00000110 $
b00000010 %
#461
b10000110 #
b00000010 $
b00100001 %
#462
b10110010 #
b00000001 $
b01011001 %
#463
b11001110 #
b00000011 $
b00011001 %
#464
b11101111 #
b00000101 $
b00000111 %
#465
b11000011 #
b00000011 $
b00011000 %
#466
b11011011 #
b00000001 $
b01101101 %
#467
b10100010 #
b00000110 $
b00000010 %
#468
b00001101 #
b00000101 $
b00000000 %
#469
b00100000 #
b00000110 $
#470
b01000100 #
b00000100 $
b00000100 %
#471
b10101110 #
b00000010 $
b00101011 %
#472
b01110000 #
b00000001 $
b00111000 %
#473
b11010011 #
b00000011 $
b00011010 %
#474
b11111100 #
b00000111 $
b00000001 %
#475
b11011010 #
b00000101 $
b00000110 %
#476
b10101011 #
b00000100 $
b00001010 %
#477
b01101110 #
b00000000 $
b01101110 %
#478
b01100110 #
b00001000 $
b00000000 %
#479
b10001000 #
b00000101 $
b00000100 %
#480
b01001101 #
b00000010 %
#481
b01101000 #
b00000010 $
b00011010 %
#482
b11011010 #
b00000000 $
b11011010 %
#483
b10000001 #
b00000110 $
b00000010 %
#484
b10001011 #
b00000000 $
b10001011 %
#485
b10100001 #
b00000110 $
b00000010 %
#486
b11101011 #
b00000000 $
b11101011 %
#487
b00111100 #
b00000001 $
b00011110 %
#488
b00000010 #
b00000010 $
b00000000 %
#489
b00110011 #
b00000011 $
b00000110 %
#490
b10011000 #
b00000110 $
b00000010 %
#491
b00111000 #
b00000000 %
#492
b00111100 #
#493
b01110101 #
b00000011 $
b00001110 %
#494
b10110001 #
b00000101 $
b00000101 %
#495
b01111001 #
b00000011 $
b00001111 %
#496
b00110010 #
b00001000 $
b00000000 %
#497
b00000100 #
b00000110 $
#498
b11010000 #
b00000000 $
b11010000 %
#499
b10000100 #
b00000001 $
b01000010 %
#500
b01111110 #
b00000010 $
b00011111 %
#501
b01000001 #
b00000011 $
b00001000 %
#502
b01001111 #
b00001000 $
b00000000 %
#503
b11001011 #
b00000010 $
b00110010 %
#504
b01100011 #
b00011000 %
#505
b00100110 #
b00000000 $
b00100110 %
#506
b01110000 #
b00000101 $
b00000011 %
#507
b01101101 #
b00001000 $
b00000000 %
#508
b00111101 #
b00000100 $
b00000011 %
#509
b00011110 #
b00000101 $
b00000000 %
#510
b10111111 #
b00000100 $
b00001011 %
#511
b00111110 #
b00000000 $
b00111110 %
#512
b10011110 #
b10011110 %
#513
b01001111 #
b00000010 $
b00010011 %
#514
b01010011 #
b00000111 $
b00000000 %
#515
b00111010 #
b00000010 $
b00001110 %
#516
b01000001 #
b00000101 $
b00000010 %
#517
b11101010 #
b00000110 $
b00000011 %
#518
b11010110 #
#519
b11101101 #
b00001000 $
b00000000 %
#520
b10111101 #
b00000000 $
b10111101 %
#521
b00010111 #
b00010111 %
#522
b11100110 #
b00000100 $
b00001110 %
#523
b00001101 #
b00000111 $
b00000000 %
#524
b00100000 #
b00000001 $
b00010000 %
#525
b11011001 #
b00000110 $
b00000011 %
#526
b00001100 #
b00000011 $
b00000001 %
#527
b00011010 #
b00000100 $
#528
b10011101 #
b00000000 $
b10011101 %
#529
b10101001 #
b00001000 $
b00000000 %
#530
b01000011 #
b00000110 $
b00000001 %
#531
b10111011 #
b00000111 $
#532
b00010100 #
b00000000 %
#533
b11110100 #
b00001000 $
#534
b00110011 #
b00000101 $
b00000001 %
#535
b10100001 #
b00001000 $
b00000000 %
#536
b11011010 #
b00000101 $
b00000110 %
#537
b10111000 #
b00000001 $
b01011100 %
#538
b00010110 #
b00000011 $
b00000010 %
#539
b01111011 #
b00000111 $
b00000000 %
#540
b10000111 #
b00000001 $
b01000011 %
#541
b10111000 #
b00000111 $
b00000001 %
#542
b01111001 #
b00000100 $
b00000111 %
#543
b11001010 #
b00000000 $
b11001010 %
#544
b00111111 #
b00000100 $
b00000011 %
#545
b01101000 #
b00000001 $
b00110100 %
#546
b01101001 #
b00000101 $
b00000011 %
#547
b11101010 #
b00000011 $
b00011101 %
#548
b00100000 #
b00000001 $
b00010000 %
#549
b00010010 #
b00000100 $
b00000001 %
#550
b11100100 #
b00000000 $
b11100100 %
#551
b00000110 #
b00000110 %
#552
b01101111 #
b00000101 $
b00000011 %
#553
b01001111 #
b00000010 %
#554
b01110000 #
b00000011 %
#555
b11111000 #
b00000000 $
b11111000 %
#556
b11011001 #
b00000100 $
b00001101 %
#557
b01101010 #
b00000110 %
#558
b10011110 #
b00000000 $
b10011110 %
#559
b11011101 #
b00000110 $
b00000011 %
#560
b01000000 #
b00000100 $
b00000100 %
#561
b00000001 #
b00000001 $
b00000000 %
#562
b11010000 #
b00000011 $
b00011010 %
#563
b11000110 #
b00000000 $
b11000110 %
#564
b00100010 #
b00000011 $
b00000100 %
#565
b00010001 #
b00000110 $
b00000000 %
#566
b11101110 #
b00001000 $
#567
b10111011 #
b00000110 $
b00000010 %
#568
b00000010 #
b00000111 $
b00000000 %
#569
b10011000 #
b00000011 $
b00010011 %
#570
b11111010 #
b00000110 $
b00000011 %
#571
b10011110 #
b00000001 $
b01001111 %
#572
b00001101 #
b00000110 %
#573
b00001011 #
b00000110 $
b00000000 %
#574
b11010000 #
b00000111 $
b00000001 %
#575
b01111101 #
b00001000 $
b00000000 %
#576
b11110110 #
b00000001 $
b01111011 %
#577
b11111101 #
b00000100 $
b00001111 %
#578
b11000010 #
b00001000 $
b00000000 %
#579
b11110011 #
b00000001 $
b01111001 %
#580
b10001011 #
b01000101 %
#581
b01010101 #
b00000011 $
b00001010 %
#582
b00101110 #
b00000001 $
b00010111 %
#583
b00010010 #
b00000111 $
b00000000 %
#584
b10001101 #
b00000010 $
b00100011 %
#585
b01000000 #
b00000101 $
b00000010 %
#586
b01001001 #
b00000100 $
b00000100 %
#587
b01010011 #
b00000110 $
b00000001 %
#588
b00000110 #
b00000000 $
b00000110 %
#589
b01001001 #
b00000011 $
b00001001 %
#590
b00101111 #
b00000001 $
b00010111 %
#591
b01101110 #
b00000011 $
b00001101 %
#592
b00010000 #
b00000001 $
b00001000 %
#593
b11001011 #
b00000000 $
b11001011 %
#594
b10111001 #
b00000011 $
b00010111 %
#595
b00100001 #
b00000111 $
b00000000 %
#596
b01100100 #
b00000110 $
b00000001 %
#597
b01101100 #
b00000111 $
b00000000 %
#598
b01011000 #
#599
b00010101 #
#600
b10100110 #
b00000100 $
b00001010 %
#601
b01001111 #
b00000100 %
#602
b01101100 #
b00000111 $
b00000000 %
#603
b11011101 #
b00000101 $
b00000110 %
#604
b11000000 #
b00000000 $
b11000000 %
#605
b10111111 #
b00000110 $
b00000010 %
#606
b11001100 #
b00000111 $
b00000001 %
#607
b01110001 #
b00000001 $
b00111000 %
#608
b10100011 #
b00000100 $
b00001010 %
#609
b11100010 #
b00000110 $
b00000011 %
#610
b11111100 #
b00000011 $
b00011111 %
#611
b00011110 #
b00000111 $
b00000000 %
#612
b10111100 #
b00000100 $
b00001011 %
#613
b00000110 #
b00000000 %
#614
b00001011 #
b00000000 $
b00001011 %
#615
b01010000 #
b00000101 $
b00000010 %
#616
b11000110 #
b00000111 $
b00000001 %
#617
b00100101 #
b00000110 $
b00000000 %
#618
b10101000 #
b00000100 $
b00001010 %
#619
b00000100 #
b00000110 $
b00000000 %
#620
b00101101 #
b00000000 $
b00101101 %
#621
b10111110 #
b00000110 $
b00000010 %
#622
b10001110 #
b00000111 $
b00000001 %
#623
b00100010 #
b00000000 $
b00100010 %
#624
b01011000 #
b00000001 $
b00101100 %
#625
b00000001 #
b00000010 $
b00000000 %
#626
b00111001 #
b00000001 $
b00011100 %
#627
b11101011 #
b00000100 $
b00001110 %
#628
b11001011 #
b00000000 $
b11001011 %
#629
b11011011 #
b00000011 $
b00011011 %
#630
b10110001 #
b00000001 $
b01011000 %
#631
b10010010 #
b01001001 %
#632
b01111111 #
b00000110 $
b00000001 %
#633
b00101000 #
b00000000 %
#634
b11010011 #
b00000001 $
b01101001 %
#635
b10101010 #
b00000010 $
b00101010 %
#636
b11000101 #
b00001000 $
b00000000 %
#637
b11110001 #
b00000011 $
b00011110 %
#638
b00010011 #
b00000010 %
#639
b01001011 #
b00001001 %
